Workbook

Sheet ERA5和其他数据源组合调研(补充算法组的数据源信息)
A1: 数据类型分类(标红的代表数据组已经下载的数据) | B1: 编号(红色编号对应算法组需要使用的数据) | C1: 算法组使用说明 | D1: 数据名称 | E1: 对应风场预测本体类别(对应禧蕾那边本体设计) | F1: 对应风场预测本体节点(对应禧蕾那边本体节点) | G1: 分辨率（时/空） | H1: 优先级 | I1: 数据格式 | J1: 是否(开源/下载/有无数据) | K1: 下载链接 | L1: 样本数据下载 | M1: 核心字段 | N1: 缺失值规则 | O1: 元数据表征 | P1: 特征维度 | Q1: 数据获取难度 | R1: 数据源优先级与获取难度评判标准 | S1: 成本/费用 | T1: 数据更新延迟 | U1: 历史数据年限 | V1: 地理覆盖范围 | W1: 用途 | X1: 备注 | Y1: 本地数据样本下载位置
A2: =INDEX(数据源对应的文献以及数据使用方法和条目需求!A:B,MATCH(B2,数据源对应的文献以及数据使用方法和条目需求!B:B,0),1) -> ERA5相关性数据 | B2: AIA-1064 | C2: 使用✅ | D2: 气象站实测ISD(风速/风向/温度/气压/湿度) | E2: 气象与环境； 相邻/上游测风站数据 | F2: 气象与环境(数据源类型-实测值)； 相邻/上游测风站数据(历史风速) | G2: 时：小时级（1h/3h，单条记录对应单次观测）；空：站点级（全球 90°S~90°N，180°W~180°E） | H2: 🔴 必需 | I2: ASCII 字符格式（含 ISD-Lite 精简 CSV 版） | J2: 开源✅ 下载✅(部分需注册) 有数据✅ | K2: 中国气象数据网：https://data.cma.cn/； ISD 全球站点：https://www.ncei.noaa.gov/pub/data/noaa | L2: 陈林老师已经完成1901-2025的数据下载（天翼云） | M2: 1. 站点元数据字段（含长度 + 规则）： USAF (6 位)：美国空军主站标识符，2013 年起首位可为字母； WBAN (5 位)：NCEI WBAN 标识符，数字 0-9； CTRY (2 位)：FIPS 国家代码（如 CN = 中国、US = 美国）； ST (2 位)：美国州代码（仅美国站点）； ICAO (4 位)：机场代码（如 ZBAA = 北京，缺失为空白 / 9999）； LAT (7 位)：纬度（千分之一度，南纬为负，缩放因子 1000）； LON (8 位)：经度（千分之一度，西经为负，缩放因子 1000）； ELEV (5 位)：海拔（米，+9999 = 缺失）； BEGIN (8 位)：起始日期（YYYYMMDD）； END (8 位)：结束日期（YYYYMMDD，99991231 = 持续更新 2. 气象要素：风速 / 风向 / 阵风、气温 / 露点、云量、海平面气压 / 站点气压、当前天气 / 能见度、分时段降水量、积雪深度、其他观测要素（如高度表设置） | N2: 1. 站点元数据缺失值： LAT=+99999、LON=+999999； ELEV=+9999（相对于平均海平面 MSL）； ICAO = 空白 / 9999； BEGIN=00000000、END=99991231（表示持续更新）； 2. 气象要素缺失值：气温 / 气压类 = 9999.9、风 / 能见度类 = 999.9、降水 = 99.99、雪深 = 999.9； | O2: 1. 数据集核心元数据：数据集 ID (DS3505)、维护机构 (NOAA 国家环境信息中心 (NCEI) + 美国空军第 14 气象中队)、数据来源 (ASOS/AWOS/SYNOP/METAR/SHIP 等地面观测数据)； 2. LAT/LON 缩放因子 1000（解码示例：latitude_deg = int (LAT)/1000.0，如 + 39900→39.900°N；longitude_deg = int (LON)/1000.0，如 - 116400→-116.400°W； 3. 时间 / 空间：时间基准 (UTC)、空间覆盖 (全球 90°S~90°N，180°W~180°E) | P2: 地理特征维度：经纬度（LAT_DEG/LON_DEG，千分之一度转换为十进制度）、海拔（ELEV，相对于平均海平面）、站点标识（USAF/WBAN/CTRY/ST/ICAO）； 气象特征维度：风要素（风速 u/v 分量、风向、最大阵风）、温湿要素（气温、露点温度、相对湿度）、气压要素（海平面气压、站点气压）、降水 / 积雪要素（降水量、雪深）、天气现象要素（雾 / 雨 / 雪 / 冰雹等）； 时空特征维度：小时级时序特征（1h/3h 分辨率）、站点级空间特征（单点实测） | Q2: ⭐⭐ 中等 | R2: 第一点：优先级评判标准（优先级用于评估数据源对风场预测项目的重要程度，分为三个等级） 🔴 必需：没有该数据无法开展风场预测或关键评估 判断依据： 1、是模型运行的核心输入数据 2、缺失该数据会导致预测系统无法正常工作 3、是风场预测的基础数据，无法用其他数据替代 4、直接影响预测结果的可用性 典型数据源示例： 1、气象站实测风速/风向 2、数字高程模型(DEM) 3、风机位置与布局图 4、风机SCADA历史数据 5、经纬度与海拔 🟡 推荐：能显著提升精度/鲁棒性但缺失时模型仍可运行 判断依据： 1、能够明显改善预测精度和模型稳定性 2、有助于提升模型的鲁棒性（抗干扰能力） 3、缺失时模型仍可运行，但性能会下降 4、属于重要的辅助数据，但不是绝对必需 典型数据源示例： 1、气象站温度/气压/湿度 2、高分辨率气象同化数据 3、边界层高度数据 4、湍流动能(TKE) 5、垂直风切变指数 🟢 可选：主要用于增强分析或专项研究，对主流程影响较小 判断依据： 1、主要用于深度分析或特定场景研究 2、对主要预测流程影响较小 3、可以用于模型优化，但不是核心需求 4、属于锦上添花的数据，优先级较低 典型数据源示例： 1、卫星散射计海面风场（仅海上风场适用） 2、卫星云图/水汽图 3、气象雷达反射率/径向速度 4、植被指数(NDVI) 5、建筑物高度与密度数据 6、天气形势分型 第二点：数据获取难度评判标准（数据获取难度用于评估获取该数据源所需付出的成本（时间、人力、资金等），分为四个等级） ⭐ 简单：公开/免费、注册即下或直接下载 判断依据： 1、数据完全公开，无需付费 2、下载流程简单，通常只需注册账号 3、可以直接通过网页或API下载 4、无需特殊申请或审批流程 5、获取成本极低，几乎无门槛 典型数据源示例： 1、ERA5再分析数据 2、DEM地形高程数据 3、地表粗糙度/土地利用数据 4、NDVI植被指数数据 ⭐⭐ 中等：需注册/申请或简单对接接口，有一定流程和配额限制 判断依据： 1、需要注册账号或提交简单申请 2、可能需要对接API接口 3、有一定的下载流程和配额限制 4、需要一定的技术能力（如API调用） 5、获取成本中等，有一定门槛但可接受 典型数据源示例： 1、气象站观测数据（部分需注册） 2、卫星数据（需注册Copernicus等平台） 3、MODIS数据（需注册NASA账号） 4、高分辨率气象预报数据（部分需注册） ⭐⭐⭐ 困难：强依赖业主/机构授权或多系统协同，沟通和审批成本高 判断依据： 1、需要向业主或相关机构申请授权 2、需要多系统协同配合 3、沟通和审批流程复杂，耗时较长 4、可能需要签署协议或合同 5、获取成本较高，需要投入较多时间和精力 典型数据源示例： 1、风机SCADA历史数据（需业主授权） 2、风机位置与布局图（需业主提供） 3、气象雷达数据（需向气象部门申请） 4、测风塔观测数据（需业主提供） ⭐⭐⭐⭐ 极难：需自建观测设备或自跑大规模模式，消耗人力+计算资源+资金 判断依据： 1、需要自己建设观测设备 2、需要自己运行大规模数值模式 3、需要大量的人力、计算资源和资金投入 4、技术门槛高，需要专业团队 5、获取成本极高，通常需要项目级投入 典型数据源示例： 1、激光雷达/声雷达测风剖面（需购买设备） 2、区域WRF/COSMO等模式输出（需自跑模式） 3、风机尾流模型输出（需自建模型和计算） | S2: 免费(部分需注册) | T2: 实时/延迟数小时 | U2: SD: 1900 年至今（具体取决于站点）； 中国气象数据网：近 10-20 年 | V2: 全球（纬度 90°S~90°N，经度 180°W~180°E），9000 + 气象站点 | W2: 1. 提供气象站实测风速 / 风向 / 温 / 压 / 湿等小时级观测数据 2. 用于风场预测模型训练、验证、订正 3. 作为风资源评估与数值模拟结果的实测基准 | X2: 1. 记录结构：变长记录（最大长度 2844 字符），包含： 控制数据段（60 字符，固定）、强制数据段（45 字符，固定）、附加数据段（0-637 字符）、备注数据段（最大 515 字符）、元素质量数据段（最大 1587 字符）； 2. 唯一站点 ID：USAF (6 位)+WBAN (5 位)（示例：723150-03812）； 3. 文件名约定：USAF-WBAN - 年份（示例：723150-03812-2023）； 4. 注意事项： ① 站点数据可能存在观测空缺（BEGIN/END 仅表示有数据时段）； ② 多源数据经纬度 / 海拔可能略有差异（非站点搬迁）； ③ 站点搬迁时分配新标识符，历史数据保留原 ID | Y2: D:\dcsk\knowledge_graph_1014\download_data\geodata\data\舟山\ISD\584770-99999-2024.gz；天翼云上存储全量数据：/home/admin/data_set/mvp_data/noaa_isd_samples
A3: =INDEX(数据源对应的文献以及数据使用方法和条目需求!A:B,MATCH(B3,数据源对应的文献以及数据使用方法和条目需求!B:B,0),1) -> 官方业务全球预报数据 | B3: AIA-1097 | C3: 使用✅ | D3: ECMWF HRES 全球预报数据（免费版 0.25°/ 商业版 < 0.1°） | E3: 气象与环境 | F3: 气象与环境 (高空风速风向 - 高精度预报（10m U/V 风分量 u10/v10）、地表气压（sp）、干球温度（2t，样本数据未包含）、大气稳定度 - blh（边界层高度，样本数据未包含）) | G3: 时：3h（验证确认符合 1-3h 要求）；空：0.25°（免费版≈28km）/<0.1°（商业版≈10km） | H3: 🟡 推荐 | I3: GRIB/NetCDF（样本为 GRIB2 格式，已成功转换为 NetCDF 验证文件） | J3: 开源❌ 下载⚠️(付费许可) 有数据✅ | K3: ECMWF HRES：https://data.ecmwf.int/forecasts/20260312/00z/ifs/0p25/oper/ | L3: ⚠️(付费许可)（免费版可获取 0.25° 分辨率数据，<0.1° 高精度数据需购买商业许可；样本数据已成功下载，路径：D:\dcsk\knowledge_graph_1014\download_data\geodata\data\ 舟山 \ECMWF\） | M3: 1. 时空元数据字段：时间步长 step（小时）、纬度 latitude（度）、经度 longitude（度）； 2. 实测存在变量：u10、v10、sp、lsm、asn、q、tcwv、rsn、sithick、sot、vsw、strd、ssr、str、ttr、vo、gh、fg10、ewss、w、d、nsss、r、t、u、v、ro、tp、sd、sf、msl、sve、svn、mucape、zos、tcc、skt、ptype、tprate、ssrd、tcw； 3. 派生变量：wind_speed_10m（√(u10²+v10²)）、sp_hpa（sp/100）； 4. 业务需求缺失变量：2t、blh | N3: 1. 时空坐标：无缺失，全球网格全覆盖（舟山区域：29.7382~30.733°N，121.9655~123.102°E）； 2. 要素缺失： ✅ 存在且无缺失：u10/v10/sp（5/5 文件完整）； ❌ 完全缺失：2t/blh（0/5 文件包含）； ✅ 派生变量：wind_speed_10m/sp_hpa 无缺失； 3. 网格无效区：统一用 NaN 标识 | O3: 1. 数据集核心元数据： 来源 (ECMWF HRES 0p25-oper)、模式 (IFS)、分辨率 (0.25° 免费版 /<0.1° 商业版)、格式 (GRIB2/NetCDF)、时区 (UTC)、文件命名规则 (YYYYMMDD000000-XXh-oper-fc.grib2)； 2. 验证结论：数据源合规、时间分辨率 3h 符合要求、空间分辨率 0.25°（免费版限制 | P3: 地理特征维度：latitude（纬度）、longitude（经度）、网格分辨率(0.25°)； 气象特征维度： ✅ 核心：近地面风场 (u10/v10/wind_speed_10m)、地表气压 (sp/sp_hpa)； ✅ 其他：lsm/asn/q/tcwv 等 30 + 气象变量； ❌ 缺失：2m 气温 (2t)、边界层高度 (blh)； 时空特征维度：时间维度（预报时效 48/54/60/66/72h）、空间维度（全球网格化 ~28km）、单要素数值维度。 | Q3: ⭐⭐ 中等 | S3: 付费 (商业使用需购买许可证；非商业科研可申请免费版，仅获取 0.25° 分辨率数据) | T3: 延迟数小时（ECMWF HRES 预报数据发布延迟约 3-6 小时，样本数据无异常延迟） | U3: 近 10-15 年（ECMWF 官方存档周期，样本数据为 20260312 预报数据，在覆盖范围内） | V3: 全球（样本数据覆盖舟山区域：纬度 29.7382~30.733°N，经度 121.9655~123.102°E，无空间偏移） | W3: 1. 业务应用：气象同化输入、近地面风场高精度预报、地表气压分析、大气稳定度评估（需补充2t/blh）； 2. 数据处理：派生10m合成风速、地表气压hPa单位转换，满足AIA-1097业务规范要求； 3. 场景适配：舟山区域气象要素提取、环境气象分析、天气系统识别，支撑相关业务化输出。 | X3: 1. 数据现状：u10/v10/sp 5/5文件完整有效，2t/blh 完全缺失（需在ECMWF下载界面补充勾选对应参数）； 2. 分辨率说明：免费版实际0.25°（≈28km），<0.1°高精度需购买ECMWF商业许可； 3. 派生字段：wind_speed_10m、sp_hpa 基于原始字段计算，符合气象行业业务规范； 4. 格式兼容：原始数据为GRIB2，已成功转换为NetCDF格式，可直接用于后续分析。 | Y3: D:\dcsk\knowledge_graph_1014\download_data\geodata\data\舟山\ECMWF
A4: =INDEX(数据源对应的文献以及数据使用方法和条目需求!A:B,MATCH(B4,数据源对应的文献以及数据使用方法和条目需求!B:B,0),1) -> WRF数据 | B4: AIA-1094 | C4: 使用✅ | D4: 区域WRF/COSMO等模式输出 | E4: 气象与环境 | F4: 气象与环境(高空风速风向-高分辨率、大气稳定度-TKE/PBL) | G4: 时：1-3h；空：1-5 km | H4: 🟡 推荐 | I4: NetCDF | J4: 模式开源✅ 结果需自跑⚠️ 有数据⚠️(需自行运行) | K4: WRF：https://www.mmm.ucar.edu/models/wrf | Q4: ⭐⭐ 中等 | S4: 高成本(需计算资源+专业知识) | T4: 自定义(需自行运行) | U4: 自定义(取决于输入数据) | V4: 自定义(取决于配置) | W4: 1. 业务应用：区域高分辨率气象预报、高空风场精细化分析、大气稳定度评估（TKE/PBL）、中小尺度天气系统模拟； 2. 科研支撑：气象物理过程研究、数据同化方案验证、极端天气事件复盘分析、模式参数优化； 3. 场景适配：复杂地形/下垫面气象要素模拟、航空/风电等行业定制化气象服务、环境气象耦合模拟输入。 | X4: 1. 数据获取：模式开源免费（WRF v4.5及以上版本），但需自行配置输入数据（如ECMWF/FNL）、调试参数并运行； 2. 成本说明：高计算资源需求（CPU/GPU+存储），需具备气象模式运行专业知识，结果精度依赖配置合理性； 3. 时空特性：时间分辨率1-3h可自定义，空间分辨率1-5km支持按需调整，覆盖范围/时间跨度取决于输入数据与运行设置； 4. 核心优势：支持并行计算、物理过程参数化方案丰富，适配从 tens of meters 到 thousands of kilometers 多尺度模拟需求。
A5: =INDEX(数据源对应的文献以及数据使用方法和条目需求!A:B,MATCH(B5,数据源对应的文献以及数据使用方法和条目需求!B:B,0),1) -> ERA5相关性数据 | B5: KG-6 | C5: 未使用❌ | D5: 卫星散射计海面风场(ASCAT OASWC12 沿海风场产品) | E5: 气象与环境 | F5: 气象与环境(高空风速风向-海上补充) | G5: 时：卫星过境（实测单次过境时间：2026-03-12 13:03:00）； 空：12.5-25 km | H5: 🟢 可选 | I5: NetCDF | J5: 开源✅ 下载✅(需注册) 有数据✅(海上区域) | K5: ASCAT：https://data.eumetsat.int/extended?query=OASWC12；Sentinel-1：https://scihub.copernicus.eu/ | L5: 需要注册账号下载(账号：wangdelei密码：Wdl2072706022) | M5: 1. 定位字段：lat（纬度，°）、lon（经度，°）、time（观测时间，UTC）； 2. 风场要素：wind_speed（风速，m s⁻¹，实测存在且字段有效）、wind_dir（风向，°，实测存在且字段有效）； 3. 质量标识：数据质量标记、有效观测标记 | N5: 1. 风要素缺失：wind_speed = 999.9、wind_dir = 999.9； 2. 空间字段缺失：lat = 999.99、lon = 999.99； 3. 无效区域标记：近海/陆地附近为缺失/掩膜值； 4. 无观测区域统一使用缺测值填充 | O5: 1. 数据集核心： 1. 数据集核心： OASWC12 海面风场产品，EUMETSAT 生产，MetOp‑B 卫星观测； 2. 实测元数据： 数据延迟 20.9 小时、空间覆盖纬度 - 89.36~89.27°N / 经度 0.01~360.00°E、仅海上有效（陆地数据为 False）； 3. 验证结论：仅数据格式标注（NetCDF/HDF5）与实测不符（实际仅 NetCDF 4. 字段元数据： - lat/lon：浮点型，单位 ° - wind_speed：浮点型，单位 m s⁻¹ - wind_dir：浮点型，单位 ° - time：UTC 卫星过境时间 5. 时空基准：时间UTC，空间全球海上网格 | P5: 地理特征维度：地理特征维度：经纬度（lat/lon，实测范围 - 89.36~89.27°N，0.01~360.00°E）、全球海上覆盖（陆地数据标记为 False）、12.5km 网格分辨率； 气象特征维度：海面风速、海面风向、风场质量标记； 时空特征维度：卫星过境单次时间、12.5 km 网格空间分辨率 | Q5: ⭐⭐ 中等 | S5: 免费(需注册) | T5: 延迟数小时 - 数天（实测单文件延迟 20.9 小时） | U5: ASCAT: 2007年至今； Sentinel-1: 2014年至今 | V5: 全球 (仅海上区域)，实测覆盖纬度 - 89.36~89.27°N，经度 0.01~360.00°E，陆地数据标记为 False | W5: 1. 提供卫星遥感海面风速/风向数据 2. 用于海上/沿海风场预测模型验证、订正 3. 作为海上背景风场参考与补充数据源 | X5: 1. 数据格式：实测为 NetCDF（NC）格式，非 HDF5 格式； 2. 结构：lat/lon/time 三维结构； 3. 唯一标识：OASWC12_20260312_130300_69953_M01.nc； 4. 注意事项：仅海上有效（陆地数据标记为 False），无陆地数据；使用前需过滤缺失值； 5. 验证结论：除格式标注外，其余元数据（分辨率 / 覆盖 / 字段 / 成本）均与实测一致 | Y5: D:\dcsk\knowledge_graph_1014\download_data\geodata\data\舟山\KG-6\OASWC12_20260312_130300_69953_M01.nc
A6: =INDEX(数据源对应的文献以及数据使用方法和条目需求!A:B,MATCH(B6,数据源对应的文献以及数据使用方法和条目需求!B:B,0),1) -> ERA5相关性数据 | B6: AIA-1081 | C6: 使用✅ | D6: 卫星云图 / 水汽图（Himawari-9 L2CLP010 云特性产品 / JAXA 生产） | E6: 气象与环境 | F6: 气象与环境(全局水平辐照度-间接、近地面微气象-云量/辐射影响) | G6: 时：10min（实测）； 空：2.22km（实测） | H6: 🟢 可选 | I6: NetCDF（实测仅为 NetCDF 格式，三维网格结构 lat/lon/time） | J6: 开源✅ 下载✅(部分需注册) 有数据✅ | K6: Himawari-8：https://www.eorc.jaxa.jp/ptree/； FY-4A：http://satellite.nsmc.org.cn/ | L6: ftp协议连接：21、主机名 (H)：ftp.ptree.jaxa.jp、用户名 (U)：tejerajorge488_gmail.com密码 (P)：SP+wari8 | M6: 1. 定位字段：latitude（degrees_north）、longitude（degrees_east）、time（UTC，实测观测时间 2026-03-12 08:00）； 2. 云 / 水汽要素：CLP（云量概率，%）、COD（云光学厚度，单位 1）、CTH（云顶高度，m）； 3. 质量标识：数据质量标记； 4. 字段单位补充：COD 标注为「单位 1」（无量纲），latitude/longitude 单位标注为 degrees_north/degrees_east | N6: 1. 云 / 水汽要素缺失：CLP=999.9、COD=999.9、CTH=99999.0（实测缺测值）； 2. 空间字段缺失：latitude=999.99、longitude=999.99； 3. 无效区域标记：舟山区域外为掩膜值；无观测区域填充缺测值； 4. 补充：缺测值字典化表述 {'CLP': 999.9, 'COD': 999.9, 'CTH': 99999.0}，便于数据过滤 | O6: 1. 数据集核心：Himawari L2CLP010 云特性产品（实测为 Himawari-9 卫星），JAXA 生产；FY-4A AGRI 云产品，CMA 生产； 2. 字段元数据： - latitude/longitude：浮点型，单位 degrees_north/degrees_east； - CLP：浮点型，单位 %；COD：浮点型，单位 1（无量纲）；CTH：浮点型，单位 m； 3. 时空基准： - 时间：UTC（实测观测时间 2026-03-12 08:00）； - 空间：亚太网格（实测 90.0~180.0°E, 0.0~60.0°N | P6: 地理特征维度：经纬度（latitude/longitude）、舟山区域（121.38~123.07°E, 29.73~30.85°N）、亚太区域（实测 90.0~180.0°E, 0.0~60.0°N）； 气象特征维度：CLP（云量概率）、COD（云光学厚度）、CTH（云顶高度）、数据质量标记； 时空特征维度：10min 单次观测（实测）、2.22km 网格空间分辨率（实测 | Q6: ⭐⭐⭐⭐ 极难 | S6: 免费(部分需注册) | T6: 近实时 / 延迟约 103.6 小时（实测） | U6: FY-4A: 2016年至今；Himawari-8: 2015年至今 | V6: 区域覆盖 (FY-4A: 中国及周边；Himawari-8/9: 亚太（实测 90.0~180.0°E, 0.0~60.0°N）；舟山区域（121.38~123.07°E, 29.73~30.85°N）) | W6: 1. 提供 CLP/COD/CTH 等卫星遥感数据，用于舟山区域近地面微气象模型验证、全局水平辐照度估算、海上 / 沿海气象背景数据补充 | X6: 1. 数据格式：NetCDF 网格数据（实测），三维结构（latitude/longitude/time 维度）； 2. 唯一标识：NC_H09_20260312_0800_L2CLP010_FLDK.02401_02401.nc、NC_H09_20260312_0810_L2CLP010_FLDK.02401_02401.nc； 3. 文件名约定：卫星代号_H09 - 日期_小时 - 产品类型_分辨率（示例：H09_20260312_0800_L2CLP010_FLDK.02401）； 4. 注意事项： - 已裁剪舟山指定区域（121.38~123.07°E, 29.73~30.85°N）； - 实测缺测值：{'CLP': 999.9, 'COD': 999.9, 'CTH': 99999.0}，使用前需过滤无效值； - 不同卫星产品分辨率 / 覆盖范围略有差异，FTP 访问需确认账号权限有效性； 5. 数据缩放规则：经纬度原始精度 0.02°（无需换算），CLP 为百分比直接使用，CTH 单位为米（无需缩放）； | Y6: D:\dcsk\knowledge_graph_1014\download_data\geodata\data\舟山\KG-7\NC_H09_20260312_0800_L2CLP010_FLDK.02401_02401.nc；阿里云全量数据：/data/hdfs/user/zaixi.tang/himawari/2025
A7: =INDEX(数据源对应的文献以及数据使用方法和条目需求!A:B,MATCH(B7,数据源对应的文献以及数据使用方法和条目需求!B:B,0),1) -> 遥感观测数据 | B7: KG-8 | C7: 未使用❌ | D7: 气象雷达反射率/径向速度 | E7: 气象与环境 | F7: 气象与环境(近地面微气象-强对流相关) | G7: 时：~6min 体扫； 空：~1 km，多高度层 | H7: 🟢 可选 | I7: 雷达 Level-II / BUFR | J7: 开源⚠️(需申请) 下载⚠️ 有数据⚠️(视区域) | K7: 中国气象数据网：https://data.cma.cn/（需专项申请） | L7: 需向气象部门提交专项申请，提供项目立项证明 + 数据使用说明，审批通过后获取 FTP/API 访问权限 | M7: 1. 定位字段：lat（纬度，°）、lon（经度，°）、time（体扫时间，UTC/BTC）、height（高度，m） 2. 雷达要素：DBZ（反射率因子，dBZ）、Vr（径向速度，m/s）、SW（谱宽，m/s） 3. 质量标识：数据质量控制标记（QC_flag）、噪声过滤标记、距离折叠标记 | N7: 1. 雷达要素缺失：DBZ=-32768、Vr=-32768、SW=-32768 2. 定位字段缺失：lat=999.99、lon=999.99、height=9999 3. 无效区域标记：雷达覆盖范围外为掩膜值，地物遮挡区域填充缺测值 | O7: 1. 数据集核心：中国气象局新一代天气雷达（CINRAD）Level-II 产品，CMA 气象探测中心生产 2. 字段元数据： - lat/lon：浮点型，单位 °；height：浮点型，单位 m - DBZ：整型，单位 dBZ；Vr/SW：浮点型，单位 m/s 3. 时空基准：时间 UTC/BTC 双基准，空间雷达站点为中心的极坐标网格（转笛卡尔坐标后 1km 分辨率） | P7: 地理特征维度：经纬度（lat/lon）、雷达覆盖区域（半径 150-230km）、垂直高度层（100m-15km） 气象特征维度：反射率因子（DBZ）、径向速度（Vr）、谱宽（SW）、强对流识别标记 时空特征维度：6min 体扫时间分辨率、1km 水平分辨率、100m-1km 垂直分辨率 | Q7: ⭐⭐ 中等 | S7: 免费（需申请审批，无数据使用费 | T7: 实时 / 延迟数分钟（业务运行雷达延迟≤5 分钟，归档数据延迟≤1 小时） | U7: 近 5-10 年 (视雷达站)（新建雷达站存档 3 年 +，骨干雷达站存档 10 年 +） | V7: 区域覆盖 (视雷达站分布)（单站覆盖半径 150-230km，沿海 / 强对流频发区站点密度高） | W7: 1. 提供气象雷达反射率 / 径向速度数据，用于强对流天气（雷暴 / 冰雹 / 短时强降水）监测预警，作为近地面微气象模型强对流过程订正数据源，辅助风场突变事件分析 | X7: 1. 记录结构：Level-II 格式含主数据段 + 质量控制段 + 标定参数段，BUFR 格式为二进制编码结构； 2. 唯一标识：雷达站号（5 位）+ 体扫时间（YYYYMMDDHHMM）+ 产品类型 + 数据级别； 3. 注意事项：数据需使用气象雷达专用解码工具（如 MATLAB 雷达工具箱、Py-ART）处理，需结合雷达站点标定文件进行精度校正，舟山区域主要覆盖雷达站为舟山雷达站（Z9510）及周边宁波（Z9507）、上海（Z9505）雷达站。
A8: =INDEX(数据源对应的文献以及数据使用方法和条目需求!A:B,MATCH(B8,数据源对应的文献以及数据使用方法和条目需求!B:B,0),1) -> 遥感观测数据 | B8: KG-9 | C8: 未使用❌ | D8: 激光雷达/声雷达测风剖面 | E8: 相邻/上游测风站数据 | F8: 相邻/上游测风站数据(历史风速-高精度风廓线、湍流强度/风切变) | G8: 时：1s-10min； 空：垂直10-300m分层 | H8: 🟡 推荐 | I8: CSV/Binary | J8: 开源❌ 下载❌ 有数据⚠️(需现场采集) | K8: 随设备厂商/业主提供 | L8: 需业主/设备方提供，无公开下载渠道 | M8: 1. 定位字段：站点编号、经度LON、纬度LAT、海拔ELEV、测量时间TIME、测量高度HEIGHT； 2. 风场要素：风速WS、风向WD、垂直风速W、湍流强度TI、风切变Shear、信噪比SNR； 3. 质量标识：QC质量标记、有效数据标记、异常值标记 | N8: 1. 定位缺失值：LON=999.999、LAT=999.999、ELEV=9999、HEIGHT=9999； 2. 风场缺失值：WS=99.99、WD=999、TI=99.99、Shear=99.99； 3. 无效标记：QC=2/3/9为异常或缺测 | O8: 1. 数据集：激光雷达/声雷达现场观测数据； 2. 字段：高度分层10~300m，时间1s~10min，单位：m/s、°、m、%； 3. 时空基准：本地时/UTC，单点站点观测 | P8: 地理特征：单点测站位置(LON/LAT/ELEV)、垂直高度层(10~300m)；气象特征：风速、风向、垂直风速、湍流强度TI、风切变、信噪比；时空特征：高频时间序列(1s~10min)、垂直分层空间特征 | Q8: ⭐⭐⭐ 困难 | S8: 高成本(需购买设备+现场部署) | T8: 实时(设备采集) | U8: 设备部署期间 | V8: 站点级(单点观测) | W8: 1. 用于高精度风廓线反演、风切变/湍流计算、风场模拟验证、风机尾流分析、风资源评估高精度输入 | X8: 1. 记录结构：按时间+垂直高度分层存储，CSV/Binary格式； 2. 唯一标识：站点编号_设备编号_起止时间； 3. 文件名约定：站点ID_设备ID_开始时间-结束时间； 4. 注意事项：数据为现场采集，无公开渠道，需厂商/业主提供；需过滤无效值、异常值、低信噪比数据；仅在设备部署期间有观测。
A9: =INDEX(数据源对应的文献以及数据使用方法和条目需求!A:B,MATCH(B9,数据源对应的文献以及数据使用方法和条目需求!B:B,0),1) -> 地理与地表信息数据 | B9: KG-10 | C9: 未使用❌ | D9: 数字高程模型 (DEM)（ASTER GDEM V003） | E9: 空间与地理地形 | F9: 空间与地理地形(地形复杂度、离地高度(风机)-海拔基准) | G9: 时：静态；空：30 m（对应经纬度分辨率 0.000277777777777778°，实测） | H9: 🔴 必需 | I9: GeoTIFF（实测为 GeoTIFF 格式，单波段栅格结构） | J9: 开源✅ 下载✅ 有数据✅ | K9: USGS：https://earthexplorer.usgs.gov/； 地理空间数据云：https://www.gscloud.cn/sources/index?pid=302； | L9: 需要注册账号下载(账号：wangdelei密码：wdl2072706022) | M9: 1. 地理坐标字段：LAT（纬度，十进制度）、LON（经度，十进制度）； 2. 高程核心字段：DEM_BAND_1（地表高程值，单位：米 (m)）； 3. 质量评估字段：NUM_BAND_1（数据质量等级 / 观测次数） | N9: 1. 无效值标识：NoData（None，按栅格文件头信息识别）； 2. 高程异常值：低于海平面（<0m）为有效海洋 / 洼地高程，非缺失值； 3. 质量字段：NUM_BAND_1=0 表示低质量数据，建议剔除 | O9: 1. 数据集核心：发布机构 (USGS/NASA/METI)、数据版本 (ASTER GDEM V003)、坐标参考系 (EPSG:4326，WGS84)； 2. 字段属性：高程单位 (米 (m))、空间分辨率 (30m=0.000277777777777778°，90m=0.000833333°)、栅格尺寸 (3601×3601 像素)； 3. 质量规则：ASTER GDEM V3 高程误差≤15m（95% 置信度），SRTM 高程误差≤16m（90% 置信度） | P9: 1. 地理特征维度：经纬度、海拔高程、站点级 / 栅格级空间位置； 2. 地形特征维度：坡度（Slope）、坡向（Aspect）、地形起伏度、离地高度（风机选址核心指标）； 3. 空间特征维度：30m 栅格精度、全球陆地区域连续覆盖 | Q9: ⭐ 简单 | S9: 免费 | T9: 静态数据(一次性) | U9: ASTER GDEM V3：2000 年 3 月～2013 年 11 月； SRTM：2000 年 2 月～2000 年 3 月 | V9: 全球陆地区域（ASTER GDEM V3：北纬 83°~ 南纬 83°；SRTM：北纬 60°~ 南纬 56°）； 覆盖舟山区域（舟山范围：121.38~123.07°E, 29.73~30.85°N） | W9: 1. 风场地形复杂度分析 2. 风机离地高度计算 3. 尾流效应模拟 4. 坡度、坡向、地形起伏度提取 | X9: 1. 数据选型：30m 精度优先选择 ASTER GDEM V3，90m 精度选择 SRTM； 2. 瓦片命名：按经纬度编码（如 ASTGTMV003_N29E121/SRTM_29_121）； 3. 适用场景：风场地形复杂度分析；风机离地高度计算；尾流效应模拟；坡度、坡向、地形起伏度提取； 4. 注意事项：极地无冰陆地、纯海洋区域无数据，需按经纬度筛选有效瓦片； 5. 舟山覆盖：是； 6. 数据格式：GTiff，单波段栅格，数据类型 int16 | Y9: D:\dcsk\knowledge_graph_1014\download_data\geodata\data\舟山\DEM 30\ASTGTMV003_N30E122\ASTGTMV003_N30E122_dem.tif
A10: =INDEX(数据源对应的文献以及数据使用方法和条目需求!A:B,MATCH(B10,数据源对应的文献以及数据使用方法和条目需求!B:B,0),1) -> 地理与地表信息数据 | B10: KG-11 | C10: 未使用❌ | D10: 地表粗糙度长度 | E10: 空间与地理地形 | F10: 空间与地理地形(下垫面特征-粗糙度) | G10: 时：年度； 空：10 m | H10: 🔴 必需 | I10: GeoTIFF（GTiff，LZW 压缩） | J10: 开源✅ 下载✅ 有数据✅ | K10: ESA WorldCover：https://livingatlas.arcgis.com/landcoverexplorer/； ESA WorldCover：https://esa-worldcover.org/en； GlobeLand30：https://www.webmap.cn/mapDataAction.do?method=globalLandCover | L10: 需要注册账号下载 | M10: 1. 地理坐标：LAT（十进制度）、LON（十进制度）； 2. 核心字段：Z0（地表粗糙度长度，单位：m）； 3. 关联字段：LULC_TYPE（土地利用类型编码，uint8，0‑11 | N10: 1. 缺失值标识：NoData=0.0（编码 0，占比 72.43%）； 2. 无效值：Z0≤0 或 Z0>0.5； 3. 云像元（编码 10）需剔除 | O10: 1. 数据集核心：发布机构 (Esri/ESA)、数据源 (ESRI 10m Annual LULC)、坐标系 EPSG:32651； 2. 字段属性：Z0 单位 (米)、分辨率 10m、栅格尺寸 61044×89013、类型 uint8； 3. 质量规则：基于 ESRI→IGBP 映射，Z0 参考 WRF‑VEGPARM.TBL | P10: 1. 地理特征：经纬度 119.76959~126.23041°E，23.970698~32.035404°N； 2. 下垫面特征：Z0 范围 0.0001‑0.5m，水域占比 42.93%； 3. 时空特征：年度更新，10m 栅格精度 | Q10: ⭐ 简单 | S10: 免费 | T10: 年度更新 | U10: WorldCover:2020/2021 年； GlobeLand30:2000/2010/2020 年； 实测数据：2024 年 | V10: 全球 (单瓦片覆盖 149,820km²，UTM 51 区)； WGS84: Lon[119.76959,126.23041], Lat[23.970698,32.035404] | W10: 1. Z₀通过 ESRI LULC→IGBP→Z0 映射推导； 2. 剔除 Z0≤0 或 > 0.5、NoData、云像元； 3. 瓦片命名：MGRS 100km 网格； 4. 有效面积 149820km² | X10: 1. 地表粗糙度长度 Z₀ 并非原生下载数据，需通过「下载 LULC 土地利用数据 + 基于 WRF 官方 VEGPARM.TBL 经验赋值表进行栅格重分类」推导得到： - 第一步：下载源 LULC 数据（ESA WorldCover 10m / GlobeLand30 30m，GeoTIFF 格式），获取 LULC_TYPE 编码； - 第二步：将 LULC_TYPE 映射至 WRF 官方 USGS/IGBP 分类体系，参考 WRF 3.9 版 VEGPARM.TBL 中 Z₀ 经验赋值表（权威来源：WRF 模式官方静态参数库 `VEGPARM.TBL`），为每类土地利用赋值 Z₀（单位：m，默认取 Z0MIN）； - 第三步：在 QGIS/Python 中执行栅格重分类，将 LULC 编码替换为对应 Z₀ 值； - 第四步：质量控制：剔除 Z₀ ≤ 0 或 Z₀ > 5 的异常值，将海洋/无数据区域标记为 NoData，最终输出 Z₀ 栅格（GeoTIFF 格式）。 2. 适配风场边界层模拟、下垫面粗糙度校正； 3. 海洋、极地无冰区域无数据，需按经纬度筛选陆地区域（剔除外海/冰雪区）。 | Y10: D:\dcsk\knowledge_graph_1014\download_data\geodata\data\舟山\LULC\51R_20240101-20241231.tif
A11: =INDEX(数据源对应的文献以及数据使用方法和条目需求!A:B,MATCH(B11,数据源对应的文献以及数据使用方法和条目需求!B:B,0),1) -> 地理与地表信息数据 | B11: KG-12 | C11: 未使用❌ | D11: 土地利用/土地覆盖(LULC) | E11: 空间与地理地形 | F11: 空间与地理地形(下垫面特征-粗糙度-LULC→z₀) | G11: 时：年度；空：10m | H11: 🔴 必需 | I11: GeoTIFF（LZW 压缩、COG 瓦片、512×512 块） | J11: 开源✅ 下载✅ 有数据✅ | K11: 同上（WorldCover/GlobeLand30 等） | L11: 需要注册账号下载 | M11: 1. 地理坐标：LAT（十进制度）、LON（十进制度），可从投影反算为 WGS84 十进制度； 2. 分类字段：LULC_TYPE（uint8 离散整数编码，0-11）、LULC_NAME（类型名称）； 3. 辅助字段：CONFIDENCE（分类置信度） | N11: 1. 缺失值标识：NoData=0.0（编码 0，占比 72.43%）； 2. 无效值：LULC_TYPE=0（NoData）、10（云）； 3. 无 99 编码 | O11: 1. 数据集核心：发布机构 (Esri/ESA)、数据源：Sentinel-2、分类体系：ESRI 10m Annual LULC、坐标系 EPSG:32651； 2. 字段属性：类型编码 uint8、分辨率 10m、栅格尺寸 61044×89013； 3. 质量规则：可映射至 IGBP 17 类，支持 Z0 推导 | P11: 1. 地理特征：经纬度、空间位置； 2. 下垫面特征：土地利用类型、地表粗糙度关联，可直接映射 Z0（符合 LULC→Z0 需求）； 3. 时空特征：年度更新、10-30m 栅格精度 | Q11: ⭐ 简单 | S11: 免费 | T11: 年度更新 | U11: WorldCover: 2020/2021年； GlobeLand30: 2000/2010/2020年 | V11: 全球 | W11: 1. 下垫面特征分析、地表粗糙度 Z₀ 推导、风场模拟、城市 / 生态监测 | X11: 1. 用于推导地表粗糙度 Z₀，基于 ESRI→IGBP→Z0 映射； 2. 分类体系：ESRI 11 类，可转 IGBP； 3. 坐标系 EPSG:32651，可转 WGS84； 4. 单瓦片覆盖 149,820 km²（中国东部 UTM 51 区）； 5. 水域占比 42.93%，有效像元占比 27.57%。 | Y11: D:\dcsk\knowledge_graph_1014\download_data\geodata\data\舟山\LULC\51R_20240101-20241231.tif
A12: =INDEX(数据源对应的文献以及数据使用方法和条目需求!A:B,MATCH(B12,数据源对应的文献以及数据使用方法和条目需求!B:B,0),1) -> 地理与地表信息数据 | B12: KG-13 | C12: 未使用❌ | D12: 植被指数(NDVI) | E12: 空间与地理地形 | F12: 空间与地理地形(下垫面特征-粗糙度-季节变化) | G12: 时：16 天 / 月度；空：10m（实测 Sentinel-2 R10m） | H12: 🟢 可选 | I12: 原生数据（JP2）、计算后输出（GeoTIFF） | J12: 开源✅ 下载✅(需注册) 有数据✅ | K12: MODIS：https://ladsweb.modaps.eosdis.nasa.gov/； Sentinel-2：https://dataspace.copernicus.eu/ | L12: Sentinel-2：账号：tejerajorge488@gmail.com 密码：!Wdl2072706022 | M12: 1. 地理坐标：LAT（十进制度）、LON（十进制度）； 2. 核心指数：NDVI（归一化植被指数，-1~1）； 3. 辅助字段：QA（MODIS 质量标识）、SCL（Sentinel-2 场景分类） | N12: 1. 缺失值：-9999（Sentinel-2 JP2），实测 NoData 像素数量 = 0； 2. 无效值：NDVI<-1 或> 1（异常值需剔除）； 3. QA（MODIS）/ SCL（Sentinel-2）字段标识云污染 / 无效观测 | O12: 1. 数据集核心：发布机构 (NASA/ESA)、传感器 (MODIS/Sentinel-2 MSI)，Sentinel-2 原生坐标系 EPSG:32651（实测），可转 WGS84； 2. 字段属性：NDVI 单位 (无)、时间分辨率 (16 天 / 月度)、空间分辨率 10m； 3. 质量规则：QA（MODIS）/ SCL（Sentinel-2）字段标识云污染 / 无效观测 | P12: 1. 地理特征：经纬度（舟山定海：29.7382~30.733°N / 121.9655~123.102°E）、空间位置； 2. 植被特征：植被覆盖度、生长季变化； 3. 时空特征：16 天 / 月度更新、10m 栅格精度（实测） | Q12: ⭐ 简单 | S12: 免费(需注册) | T12: 16 天 / 月度更新 | U12: MODIS: 2000年至今； Sentinel-2: 2015年至今 | V12: 全球 | W12: 1. 提供归一化植被指数（NDVI），反映区域植被覆盖度与季节动态变化，用于风场数值模型中地表粗糙度 Z₀ 的季节修正，区分植被区、裸地、建筑区，提升城市与近地面风场模拟的真实性与精度 | X12: 1. 植被指数（NDVI）并非原生下载数据，需通过 Sentinel-2/MODIS 原始波段计算得到： - Sentinel-2：利用红光（B04）与近红外（B08）10m 波段（EPSG:32651），按公式 NDVI = (B08 - B04)/(B08 + B04) 计算； - MODIS：利用 250m 近红外 / 红光波段计算 NDVI，或直接使用 MOD13Q1 预处理 NDVI 产品。 2. 反映植被季节变化，辅助调整地表粗糙度 Z₀ 的季节动态； 3. Sentinel-2（10m）适配舟山定海（29.7382~30.733°N）小范围精细化分析，MODIS（250m）适配大范围宏观分析 | Y12: D:\dcsk\knowledge_graph_1014\download_data\geodata\data\舟山\NDVI\S2A_MSIL2A_20240409T022531_N0510_R046_T51RVP_20240409T055950.SAFE\GRANULE\L2A_T51RVP_A045946_20240409T023525\IMG_DATA\R10m
A13: =INDEX(数据源对应的文献以及数据使用方法和条目需求!A:B,MATCH(B13,数据源对应的文献以及数据使用方法和条目需求!B:B,0),1) -> 地理与地表信息数据 | B13: KG-14 | C13: 未使用❌ | D13: 建筑物高度、密度数据与建筑轮廓数据 | E13: 空间与地理地形 | F13: 空间与地理地形(下垫面特征-障碍物) | G13: 时：静态；空：10-100 m | H13: 🟢 可选 | I13: GeoTIFF（由矢量栅格化） | J13: 开源✅ 下载✅ 有数据✅ | K13: GHSL-Built：https://ghsl.jrc.ec.europa.eu/download.php； Microsoft-OSM：https://source.coop/vida/google-microsoft-osm-open-buildings/flatgeobuf/by_country/country_iso=CHN/CHN.fgb； 建筑轮廓数据 | L13: Microsoft Building：https://github.com/microsoft/GlobalMLBuildingFootprints(数据处理脚本 + 数据获取指引)； GHSL-Built：https://ghsl.jrc.ec.europa.eu/download.php(建筑高度) | M13: 1. 地理坐标：LAT（十进制度）、LON（十进制度）； 2. 核心字段：BUILDING_HEIGHT（建筑物高度，单位：m）、BUILDING_DENSITY（建筑物密度，单位：栋 /km²）、DEM (0~21.01m)、NDVI (-1~1)、建筑掩码 (0/1)； 3. 辅助字段：CONFIDENCE（检测置信度，0~1 | N13: 1. 缺失值标识：NoData（栅格文件头标注）； 2. 无效值：BUILDING_HEIGHT=-1（无高度估计）、BUILDING_DENSITY=0（无建筑物区域），舟山数据中 BUILDING_HEIGHT 无 -1 无效值（实际为 0~50m），DENSITY=0 代表无建筑区域 | O13: 1. 数据集核心：发布机构 (EU JRC/Microsoft)、数据类型 (矢量转栅格)、坐标参考系 (EPSG:4326)； 2. 字段属性：高度单位 (米)、空间分辨率 (10m/100m)； 3. 质量规则：Microsoft 数据置信度≥0.8 为高质量，GHSL 数据精度与人口密集度正相关，筛选的舟山轮廓数据置信度≥0.8，为高质量；GHSL 高度数据精度与舟山人口密度正相关，符合描述 | P13: 1. 地理特征：经纬度、空间位置； 2. 下垫面特征：建筑物高度、密度（障碍物评估）； 3. 时空特征：静态更新、10-100m 栅格精度 | Q13: ⭐ 简单 | S13: 免费 | T13: 静态/不定期更新 | U13: GHSL: 1975/1990/2000/2015年； Microsoft: 2022年 | V13: 全球(主要城市) | W13: 1. 为风场数值模拟提供三维建筑下垫面特征数据，包括建筑高度、建筑密度、地形高程（DEM）和植被指数（NDVI），用于修正地表粗糙度参数 Z₀、识别城市障碍物分布、模拟建筑对风场的遮挡与尾流效应，提升近地面风场模拟精度，支撑城市风环境评估、台风影响分析及风机选址等应用 | X13: 1. 数据处理成果： - 已完成舟山区域建筑轮廓（Microsoft Open Buildings，2022）、建筑高度（GHSL-BUILT-H，3 arcsec≈100m）、建筑密度（由轮廓矢量计算，栋/km²）的栅格化处理； - 融合 DEM（ASTGTMV003，30m→100m）、NDVI（Sentinel-2 L2A，10m→100m）数据，生成 5 波段 GeoTIFF 输入文件：Zhoushan_WindModel_Input_100m.tif； - 最终数据分辨率 100m，坐标系 EPSG:4326，尺寸 1364×1194，覆盖舟山核心区域（LON:121.9655~123.102°，LAT:29.7382~30.733°）。 2. 验证结论： - 经 Python 代码验证，文件完整、波段数正确（5 个：DEM/NDVI/建筑掩码/高度/密度）、坐标系统一（EPSG:4326）； - DEM 高程范围 0~21.01m，符合舟山海岛/沿海平原地形特征，数值真实有效； - 建筑高度/密度/掩码数据与舟山城市分布匹配，可支撑下垫面障碍物效应模拟。 3. 模型适配性： - 可直接输入风场模型（如 WRF、CFD、WindNinja），用于： ① 基于建筑高度/密度修正地表粗糙度 Z₀； ② 基于建筑掩码标记障碍物区域，模拟风场遮挡/尾流效应； ③ 结合 DEM/NDVI 修正地形/植被对近地面风场的影响。 4. 使用限制与建议： - 原始数据为静态更新（GHSL:2015，Microsoft:2022），无法反映最新城市建设变化； - 偏远海岛数据覆盖稀疏，优先用于舟山城市/近郊风场分析； - 最终数据为 100m 分辨率，若需更高精度（如 10m），可基于原始矢量轮廓重新栅格化。 | Y13: D:\dcsk\knowledge_graph_1014\download_data\geodata\data\舟山\BUILDING-3D\BUILDING-FOOTPRINT\CHN.fgb；D:\dcsk\knowledge_graph_1014\download_data\geodata\data\舟山\BUILDING-3D\BUILDING-HEIGHT\GHS_BUILT_H_AGBH_E2018_GLOBE_R2023A_4326_3ss_V1_0_R6_C31\GHS_BUILT_H_AGBH_E2018_GLOBE_R2023A_4326_3ss_V1_0_R6_C31.tif
A14: =INDEX(数据源对应的文献以及数据使用方法和条目需求!A:B,MATCH(B14,数据源对应的文献以及数据使用方法和条目需求!B:B,0),1) -> 风电场特定数据 | B14: KG-15 | C14: 未使用❌ | D14: 风机位置与布局图 | E14: 空间与地理地形；风电场与机组状态 | F14: 空间与地理地形(离地高度(风机))； 风电场与机组状态(机组布局-风机阵列拓扑、机组气动性能-Cp/Ct曲线) | G14: 时：静态；空：单风机级 | H14: 🔴 必需 | I14: JSON/CSV/Shapefile | J14: 开源⚠️(部分公开) 下载⚠️ 有数据⚠️(多需业主提供) | K14: The Wind Power：https://www.thewindpower.net/ | L14: 1. 公开平台：注册 The Wind Power 账号，查询部分公开风电场布局数据； 2. 核心数据：需向业主提交数据使用申请，提供项目立项证明 + 保密协议，审批通过后获取文件传输权限 | M14: 1. 定位字段：风机编号（Turbine_ID）、lat（纬度，°）、lon（经度，°）、hub_height（轮毂高度，m）、tower_height（塔高，m） 2. 布局 / 性能字段：array_topology（阵列拓扑类型）、row_col_num（行列编号）、Cp_curve（功率系数曲线参数）、Ct_curve（推力系数曲线参数） 3. 质量标识：数据精度标记、坐标系统标记（WGS84 / 地方坐标系） | N14: 1. 定位 / 高度缺失：lat=999.99、lon=999.99、hub_height=999.9、tower_height=999.9 2. 布局 / 性能缺失：array_topology=“Unknown”、Cp_curve=[]、Ct_curve=[] 3. 无效区域标记：非风电场内风机点位标注为 “Invalid” | O14: 1. 数据集核心：风电场风机位置与布局数据集，来源为业主设计文件或 The Wind Power 公开数据库（经校验） 2. 字段元数据： - lat/lon：浮点型，单位 °（坐标系统 WGS84/UTM）；hub_height/tower_height：浮点型，单位 m - array_topology：字符串型；Cp/Ct 曲线：数组型（含风速 - 系数映射关系） 3. 时空基准：时间静态（以最新布局为准），空间为大地坐标系（默认 WGS84 | P14: 地理特征维度：风机经纬度（lat/lon）、轮毂高度、塔高、风电场边界范围 布局特征维度：风机阵列拓扑（行列式 / 随机式）、行列编号、风机间距 性能特征维度：Cp 曲线（功率系数 - 风速）、Ct 曲线（推力系数 - 风速 | Q14: ⭐ 简单 | S14: 需协商 (多需业主提供)（公开平台基础数据免费，高级布局数据需付费订阅） | T14: 静态数据（风机布局变更后同步更新） | U14: 当前状态（自风电场投产至今，随布局调整更新） | V14: 场站级（单风电场完整覆盖，含所有机组及场界范围） | W14: 1. 提供风机精准位置、阵列布局及气动性能数据，用于风场尾流效应模拟、机组布局优化、风资源评估、发电量计算及运维路径规划 | X14: 1. 数据格式：JSON/CSV（字段结构化存储）、Shapefile（地理空间格式，支持地图可视化） 2. 结构：单文件含所有风机信息，按风机编号唯一索引 3. 唯一标识：风电场 ID_风机布局_版本号（示例：WF_ZHOUSHAN_2026V1） 4. 注意事项：需确认坐标系统一致性，业主提供数据需与公开平台交叉校验，Cp/Ct 曲线需匹配风机型号
A15: =INDEX(数据源对应的文献以及数据使用方法和条目需求!A:B,MATCH(B15,数据源对应的文献以及数据使用方法和条目需求!B:B,0),1) -> ERA5相关性数据 | B15: KG-16 | C15: 未使用❌ | D15: 风机SCADA历史数据 | E15: 风电场与机组状态；风速本体及时序特征 | F15: 风电场与机组状态(机组运行模式-启动模式/停机/故障/降载运行/恒功率/恒转速/MPPT/限电、机组硬件状态-变桨系统-桨距角/转子-转子转速/旋转动能/偏航系统-偏航角/对风偏差角/核心部件-机舱温度)； 风速本体及时序特征(历史风速序列) | G15: 时：10min/1s； 空：单风机 | H15: 🔴 必需 | I15: CSV/数据库表 | J15: 开源❌ 下载⚠️(需授权) 有数据⚠️ | K15: 业主提供 | L15: 必须由风电场业主/运维方授权，通过运维系统导出或数据库抽取 | M15: 1. 标识字段：风机编号Turbine_ID、时间Time、场站ID；2. 气象输入：风速WS、风向WD、空气密度、温压湿；3. 运行状态：运行模式、桨距角、转子转速、发电机功率、偏航角、对风偏差、机舱温度、故障码；4. 质量字段：有效标记、数据异常标记 | N15: 1. 数值缺失：WS=99.99、WD=999、功率=99999、转速=9999.9、桨距角=999.9、温度=999.9； 2. 状态缺失：运行模式=Unknown、故障码=9999； 3. 无效标记：有效标记=0/异常标记=1表示无效数据 | O15: 1. 数据集：风机SCADA实时/历史采集数据； 2. 字段：1s/10min采样，单位m/s、°、kW、rpm、℃； 3. 时空基准：本地时间/UTC，单机组单点观测 | P15: 地理特征：单风机位置、场站范围； 机组特征：运行模式、变桨/转子/偏航/温度/故障状态； 功率特征：实时功率、MPPT、限电状态； 时序特征：1s高频/10min统计风速序列 | Q15: ⭐⭐⭐ 困难 | S15: 需协商(需业主授权) | T15: 实时/延迟数分钟 | U15: 风场运行期间(通常3-10年) | V15: 场站级(单风机) | W15: 1. 用于风场预测模型训练、功率验证、故障识别、尾流分析、风速序列拟合、运行状态识别与限电判断 | X15: 1. 记录结构：时间序列结构化存储，单风机一条记录，含运行状态、功率、气象、质量标记； 2. 唯一标识：风机ID + 起始时间 + 结束时间 + 数据版本； 3. 文件名约定：SCADA_Turbine{ID}_{YYYYMMDDHHMM}_{YYYYMMDDHHMM}.csv； 4. 注意事项：数据必须业主授权获取，含大量停机、故障、限电、异常值，使用前必须QC过滤；1s高频数据体积大，常规使用10min统计值。
A16: =INDEX(数据源对应的文献以及数据使用方法和条目需求!A:B,MATCH(B16,数据源对应的文献以及数据使用方法和条目需求!B:B,0),1) -> ERA5相关性数据 | B16: KG-17 | C16: 未使用❌ | D16: 风机功率输出数据 | E16: 风电场与机组状态 | F16: 风电场与机组状态(机组运行模式-功率输出) | G16: 时：10-15min； 空：单风机 | H16: 🔴 必需 | I16: CSV/数据库表 | J16: 开源❌ 下载⚠️ 有数据⚠️ | K16: 业主提供 | L16: 需业主/运维方授权，从SCADA/功率统计系统导出 | M16: 1. 标识字段：风机编号Turbine_ID、时间Time、场站ID； 2. 功率字段：有功功率P、无功功率Q、视在功率S、限电标记、运行状态； 3. 环境字段：风速WS、风向WD、空气密度、温度； 4. 质量标识：有效标记、异常标记、限电标记 | N16: 1. 功率缺失：P=99999、Q=99999、WS=99.99、WD=999； 2. 状态缺失：运行状态=Unknown、限电标记=Unknown； 3. 无效标记：有效标记=0、异常标记=1表示不可用 | O16: 1. 数据集：风机实测功率输出历史数据； 2. 字段：10‑15min统计间隔，单位kW、kVar、m/s、℃； 3. 时空基准：本地时间/UTC，单风机单点观测 | P16: 地理特征：单风机位置、场站范围； 功率特征：有功/无功/视在功率、限电状态、运行模式； 时序特征：10‑15min等间隔功率时序 | Q16: ⭐⭐⭐ 困难 | S16: 需协商(需业主授权) | T16: 实时/延迟数分钟 | U16: 风场运行期间(通常3-10年) | V16: 场站级(单风机) | W16: 1. 用于风功率预测模型训练、实际发电量验证、功率曲线拟合、限电分析、尾流评估、考核指标计算 | X16: 1. 记录结构：时间序列结构化存储，单风机一条记录，以功率为核心字段； 2. 唯一标识：风机ID + 起始时间 + 结束时间 + 数据版本； 3. 文件名约定：Power_Turbine{ID}_{YYYYMM}.csv； 4. 注意事项：必须业主授权获取，数据含停机/故障/限电，使用前必须过滤无效值。
A17: =INDEX(数据源对应的文献以及数据使用方法和条目需求!A:B,MATCH(B17,数据源对应的文献以及数据使用方法和条目需求!B:B,0),1) -> ERA5相关性数据 | B17: KG-18 | C17: 未使用❌ | D17: 风机尾流模型输出 | E17: 风电场与机组状态 | F17: 风电场与机组状态(尾流效应-微观流体效应) | G17: 时：1h； 空：1-5 km 网格/场内网格 | H17: 🟡 推荐 | I17: NetCDF | J17: 模式开源✅ 结果需自跑⚠️ | K17: 基于WRF/专用尾流模型生成 | L17: 需自行搭建/运行尾流模型，无直接下载渠道 | M17: 1. 标识字段：场站ID、网格lon、网格lat、高度height、时间time；2. 尾流字段：风速衰减率、尾流半径、尾流核心区、湍流强度、有效风速；3. 机组字段：风机位置、推力系数Ct、功率损失、尾流交互标记；4. 质量标识：模型收敛标记、有效网格标记 | N17: 1. 尾流缺失：风速=99.99、衰减率=99.99、Ct=99.99、功率损失=999.9；2. 空间缺失：lon=999.99、lat=999.99、height=9999；3. 无效标记：收敛标记=0、有效标记=0为无效计算 | O17: 1. 数据集：风机尾流数值模拟输出结果；2. 字段：小时级输出，单位m/s、km、%、m；3. 时空基准：UTC时间，空间为场内均匀网格 | P17: 地理特征：风电场网格lon/lat/高度、场内空间分布；尾流特征：风速衰减、尾流范围、湍流增强、功率损失、机组交互；时空特征：1h时序、场内1~5km网格分辨率 | Q17: ⭐⭐⭐⭐ 极难 | S17: 高成本(需计算资源+模式运行) | T17: 自定义(需自行运行) | U17: 自定义(取决于输入数据) | V17: 场站级(风场内) | W17: 1. 用于风场尾流效应模拟、机组间干扰分析、功率损失评估、风场布局优化、微观选址及发电量修正 | X17: 1. 记录结构：四维网格结构（时间/经度/纬度/高度），NetCDF标准格式； 2. 唯一标识：风电场ID + 模型版本 + 模拟起止时间； 3. 文件名约定：WakeModel_{WFID}_{YYYYMMDD}.nc； 4. 注意事项：无公开数据，需自行搭建尾流模型运行；依赖风机布局、地形、气象驱动数据；需检查模型收敛性，过滤非收敛网格。
A18: =INDEX(数据源对应的文献以及数据使用方法和条目需求!A:B,MATCH(B18,数据源对应的文献以及数据使用方法和条目需求!B:B,0),1) -> ERA5相关性数据 | B18: KG-19 | C18: 未使用❌ | D18: 边界层高度数据 | E18: 气象与环境 | F18: 气象与环境(大气稳定度-blh指标) | G18: 时：1h； 空：0.25° | H18: 🟡 推荐 | I18: GRIB（二进制）/NetCDF（多维数组）（当前文件：GRIB2） | J18: 开源✅ 下载✅(需注册) 有数据✅ | K18: ERA5：https://cds.climate.copernicus.eu/datasets/reanalysis-era5-single-levels?tab=download | L18: 账号：2072706022@qq.com 密码：Wdl2072706022 | M18: 1. 标识字段：时间 time（1.0h 分辨率，格式 YYYY-MM-DD HH:MM:SS）、网格 lat（0.25° 分辨率，舟山 29.5~31.0°N）、网格 lon（0.25° 分辨率，舟山 121.5~123.5°E）； 2. 核心要素字段：边界层高度 blh（单位：m，物理意义 Boundary layer height）； 3. 元数据字段：数据集 ID（ERA5 hourly data on single levels from 1940 to present）、维护机构（ECMWF）、坐标基准（WGS84 地理坐标系）； 4. 质量标识：数据质控标记（ERA5 严格质控）、有效格点标记（舟山区域格点无缺失） | N18: 1. 数值缺失：blh=NaN（GRIB 格式无显性占位符，实测缺失值占比 0.0%）； 2. 空间异常：lat/lon 超出研究区有效经纬度范围（舟山：29.5~31.0°N/121.5~123.5°E）； 3. 无效标记：blh=0（无物理意义）、blh>5000m（超出合理范围）、NaN（数据缺失）； 4. 合理范围：0~5000m | O18: 1. 元数据字段：数据集 ID（ERA5 hourly data on single levels from 1940 to present）、维护机构（ECMWF 欧洲中期天气预报中心）、坐标基准（WGS84 地理坐标系）、数据来源（ERA5 全球大气再分析数据集）； 2. 字段元数据：单位 (blh：m)、缩放因子 无（原生单位无需换算）、GRIB 版本 2； 3. 时间 / 空间：时间基准 (UTC)、空间覆盖 (全球范围格点，舟山 29.5~31.0°N/121.5~123.5°E)； 4. 数据存储结构：三维数组（time/lat/lon 维度 | P18: 地理特征维度：经纬度（LAT_DEG/LON_DEG，0.25°×0.25° 分辨率，舟山 29.5~31.0°N/121.5~123.5°E）、格点级空间特征（面状覆盖，非站点级）、无独立海拔维度（ERA5 blh 已整合海拔影响）； 气象特征维度：大气稳定度要素（边界层高度 blh）、垂直结构要素（边界层顶高度）、反映近地面大气混合程度； 时空特征维度：小时级时序特征（1.0h 分辨率）、全球格点级空间特征（0.25°×0.25°）、时间连续性（逐小时无间断，ERA5 数据特性） | Q18: ⭐ 简单 | S18: 免费(需注册CDS账号) | T18: 延迟5天 | U18: 1940年至今 | V18: 全球 | W18: 1. 风场预测模型中大气稳定度特征提取； 2. 风资源评估中大气边界层结构分析； 3. 优化风速垂直廓线模拟精度； 4. 评估近地面大气混合层对风机发电效率的影响 | X18: 1. 记录结构：三维数组（time:744, lat:7, lon:9 维度）； 2. 唯一格点 ID：纬度 (0.25° 步长)+ 经度 (0.25° 步长)（示例：29.5°N,121.5°E）； 3. 文件名约定：ERA5_blh_YYYYMMDD_HH.grib（示例：ERA5_blh_20250501_00.grib）； 4. 注意事项：① 舟山区域 blh 数值需结合当地地形高程修正（舟山平均海拔 20~100m）；② 数据经 ECMWF 严格质控无明显异常值（舟山格点无缺失）；③ 免费获取需注册 CDS 账号，数据更新延迟 5 天；④ 当前文件无损坏，可正常解析 | Y18: D:\dcsk\knowledge_graph_1014\download_data\geodata\data\舟山\KG-19\fd3bfa3939a2d7838eb69890f964143d.grib
A19: =INDEX(数据源对应的文献以及数据使用方法和条目需求!A:B,MATCH(B19,数据源对应的文献以及数据使用方法和条目需求!B:B,0),1) -> 大气状态与派生指数数据 | B19: KG-20 | C19: 未使用❌ | D19: 湍流动能(TKE，由摩擦速度/湍流应力估算) | E19: 气象与环境 | F19: 气象与环境(大气稳定度-湍流强度指标) | G19: 时：1-3h； 空：0.25°(ERA5) 或1-5km(WRF) | H19: 🟡 推荐 | I19: NetCDF | J19: 开源✅(ERA5变量或WRF输出) 下载✅/需自跑⚠️ | K19: ERA5/WRF 官网 | L19: 账号：2072706022@qq.com 密码：Wdl2072706022 | M19: 1. 标识字段：时间time（1-3h分辨率）、网格lat（0.25°(ERA5)/1-5km(WRF)分辨率）、网格lon（0.25°(ERA5)/1-5km(WRF)分辨率）； 2. 核心要素字段：摩擦速度u*（单位：m/s）、东向湍流应力τ_u（单位：N/m²）、北向湍流应力τ_v（单位：N/m²）、估算TKE（单位：m²/s²）； 3. 元数据字段：数据集ID（ERA5 hourly data on single levels from 1940 to present/WRF自定义模拟）、维护机构（ECMWF/自定义模拟团队）、坐标基准（WGS84地理坐标系）； 4. 质量标识：数据质控标记（ERA5严格质控/WRF模拟收敛标记）、有效格点标记（目标区域格点无缺失）； | N19: 1. 数值缺失：u*/τ_u/τ_v=NaN（NetCDF格式缺失值统一标识）； 2. 空间异常：lat/lon超出研究区有效经纬度范围； 3. 无效标记：u*=0（无湍流意义）、估算TKE<0（物理意义不合理）、NaN（数据缺失） | O19: 1. 数据集核心元数据：数据集 ID (ERA5 hourly data on single levels from 1940 to present/WRF自定义模拟输出)、维护机构 (ECMWF 欧洲中期天气预报中心/自定义模拟团队)、数据来源 (ERA5全球大气再分析数据集/WRF数值模拟输出)； 2. 字段元数据：单位 (u*：m/s、τ_u/τ_v：N/m²、TKE：m²/s²)、缩放因子 无（原生单位无需换算）、格式版本 (NetCDF4)； 3. 时间 / 空间：时间基准 (UTC)、空间覆盖 (全球范围格点(ERA5)/自定义区域格点(WRF)) | P19: 地理特征维度：经纬度（LAT_DEG/LON_DEG，0.25°×0.25°(ERA5)/1-5km×1-5km(WRF)分辨率）、格点级空间特征（面状覆盖，非站点级）、无独立海拔维度（近地面湍流特征）； 气象特征维度：湍流强度要素（摩擦速度u*）、湍流应力要素（τ_u/τ_v）、估算湍流动能（TKE≈0.5×u*²）、大气稳定度表征； 时空特征维度：小时级时序特征（1-3h分辨率）、全球/自定义格点级空间特征（0.25°×0.25°(ERA5)/1-5km×1-5km(WRF)）、时间连续性（逐小时无间断(ERA5)/自定义(WRF)） | Q19: ⭐~⭐⭐⭐⭐ | S19: 免费(ERA5) / 高成本(WRF) | T19: 延迟5天(ERA5) / 自定义(WRF) | U19: 1940年至今(ERA5) / 自定义(WRF) | V19: 全球(ERA5) / 自定义(WRF) | W19: 1. 风场预测模型湍流强度特征提取； 2. 风资源评估大气边界层湍流结构分析； 3. 优化风机尾流模拟中湍流耗散参数； 4. 评估湍流强度对风机发电效率与载荷的影响； | X19: 1. 记录结构：三维数组（time/lat/lon维度）； 2. 唯一格点 ID：纬度(0.25°/1-5km步长)+经度(0.25°/1-5km步长)； 3. 文件名约定：ERA5_TKE_YYYYMMDD_HH.nc(ERA5)/WRF_TKE_YYYYMMDD_HH.nc(WRF)； 4. 注意事项：① 目标区域 TKE 需由 ERA5 替代变量估算（核心公式：TKE ≈ 0.5 × u*²）；② ERA5 数据经 ECMWF 严格质控无明显异常值，WRF 数据需验证模拟收敛性；③ ERA5 免费获取需注册 CDS 账号（数据延迟 5 天），WRF 需自跑模拟（高算力成本）；④ 数据格式为 NetCDF，可通过 xarray/netCDF4 读取后处理；
A20: =INDEX(数据源对应的文献以及数据使用方法和条目需求!A:B,MATCH(B20,数据源对应的文献以及数据使用方法和条目需求!B:B,0),1) -> ERA5相关性数据 | B20: KG-21 | C20: 未使用❌ | D20: 垂直风切变指数 | E20: 风速本体及时序特征 | F20: 风速本体及时序特征(湍流强度/风切变) | G20: 时：1h (ERA5)；空：0.25° 网格 | H20: 🟡 推荐 | I20: 源数据 CSV/TXT/NetCDF； 指数为工程计算字段 | J20: 开源✅(ERA5)；下载✅ | K20: ERA5：https://cds.climate.copernicus.eu/datasets/reanalysis-era5-single-levels?tab=download | L20: 账号：2072706022@qq.com 密码：Wdl2072706022 | M20: 1. 标识字段：时间 time（1h 分辨率）、网格 lat（0.25°）、网格 lon（0.25°）、高度层 height（10m/100m）； 2. 核心要素字段：u10、v10、u100、v100（单位：m s⁻¹）、垂直风切变指数（单位：s⁻¹ 或 m/s/100m）； 3. 元数据字段：数据集 ID（ERA5 hourly data on single levels from 1940 to present）、维护机构（ECMWF 欧洲中期天气预报中心）、坐标基准（WGS84 地理坐标系）； 4. 质量标识：数据质控标记（ERA5 严格质控）、有效格点标记（目标区域无缺失）； | N20: 1. 数值缺失：缺失值：99.99 / 999.9 / NaN；缺失值占比 0.0%； 2. 空间异常：lat/lon超出目标区域、高度层缺失； 3. 无效标记：风速 < 0、风切变指数 < 0、风速 = 0、Na） | O20: 1. 数据集核心元数据：数据集 ID (ERA5 hourly data on single levels from 1940 to present)、维护机构 (ECMWF 欧洲中期天气预报中心)、数据来源 (ERA5 再分析)； 2. 字段元数据：单位 (风速：m/s、风切变指数：s⁻¹)、缩放因子 无（原生单位无需换算）、格式版本 (GRIB2)； 3. 时间 / 空间：时间基准 (UTC)、空间覆盖 (全球网格 (ERA5)) | P20: 地理特征维度：网格经纬度（LAT_DEG/LON_DEG，0.25°×0.25° 分辨率）、高度层分布（10m/100m）、网格空间特征； 气象特征维度：风速垂直梯度、垂直风切变强度、湍流强度关联表征； 时空特征维度：1h 时序特征、网格级空间特征（0.25°×0.25°）、时间连续性（逐小时无间断 (ERA5)） | Q20: ⭐⭐~⭐⭐⭐ | S20: 免费 (ERA5) | T20: 延迟 5 天 (ERA5) | U20: 1940 年至今 (ERA5) | V20: 全球(ERA5) | W20: 1. 风场预测模型垂直风切变特征提取； 2. 风资源评估风机载荷与安全工况分析； 3. 优化风速垂直廓线拟合精度； 4. 评估风切变对风机发电效率与疲劳寿命的影响； | X20: 1. 记录结构：三维数组（time/lat/lon 维度）；2. 唯一标识：网格 ID + 高度层 + 时间戳；3. 文件名约定：ERA5_Shear_YYYYMMDD_HH.nc；4. 注意事项：① 垂直风切变由多层风速计算得到（核心公式：Shear = (V₁₀₀ - V₁₀) /ln (100/10)）；② ERA5 需多层风速数据；③ 数据经质控，缺失值占比 0.0%；④ ERA5 免费需注册 CDS 账号，延迟 5 天； | Y20: D:\dcsk\knowledge_graph_1014\download_data\geodata\data\舟山\KG-20-21-22\87aa950f2c788dc9592506e5548116b8.grib
A21: =INDEX(数据源对应的文献以及数据使用方法和条目需求!A:B,MATCH(B21,数据源对应的文献以及数据使用方法和条目需求!B:B,0),1) -> ERA5相关性数据 | B21: KG-22 | C21: 未使用❌ | D21: 大气稳定度指数 | E21: 气象与环境 | F21: 气象与环境(大气稳定度-Richardson数/Monin-Obukhov长度/Pasquill稳定度分类) | G21: 时：1h (ERA5)；空：0.25° 网格 | H21: 🟡 推荐 | I21: 源数据 NetCDF/TXT； 指数为工程计算字段 | J21: ERA5/探空开源✅ 下载✅ 有数据✅ | K21: ERA5：https://cds.climate.copernicus.eu/； 探空：http://weather.uwyo.edu/upperair/sounding.html | L21: 账号：2072706022@qq.com 密码：Wdl2072706022 | M21: 1. 标识字段：时间 time（1h 分辨率）、网格 lat（0.25°）、网格 lon（0.25°）、高度层 height； 2. 核心要素字段：2 米温度（单位：K）、10 米风速（u/v 分量，单位：m/s）、地表压力（单位：Pa）、Richardson 数、Monin-Obukhov 长度、Pasquill 稳定度等级； 3. 元数据字段：数据集 ID（ERA5 hourly data on single levels from 1940 to present）、维护机构（ECMWF 欧洲中期天气预报中心）、坐标基准（WGS84 地理坐标系）； 4. 质量标识：数据质控标记（ERA5 严格质控）、有效格点标记（目标区域无缺失）； | N21: 1. 数值缺失：缺失值：NaN / 999.9；缺失占比 0.0%； 2. 空间异常：lat/lon超出目标区域、廓线高度层不连续； 3. 无效标记：温度 <100K 或>400K；NaN、风速 < 0、地表压力 < 80000Pa 或 > 110000Pa、Richardson 数无物理极值、稳定度等级超出范围（A-F）、NaN（数据缺失） | O21: 1. 数据集核心元数据：数据集 ID (ERA5 hourly data on single levels from 1940 to present)、维护机构 (ECMWF 欧洲中期天气预报中心)、数据来源 (ERA5 再分析)； 2. 字段元数据：单位 (温度：K、风速：m/s、地表压力：Pa、Monin-Obukhov 长度：m)、缩放因子 无（原生单位无需换算）、格式版本 (GRIB2)； 3. 时间 / 空间：时间基准 (UTC)、空间覆盖 (全球网格 (ERA5)) | P21: 地理特征维度：网格经纬度（LAT_DEG/LON_DEG，0.25°×0.25° 分辨率）、高度层分布（边界层）、网格空间特征；气象特征维度：温度垂直梯度、风速垂直梯度、Richardson 数、Monin-Obukhov 长度、Pasquill 稳定度分类；时空特征维度：1h 时序特征、网格级空间特征（0.25°×0.25°）、时间连续性（逐小时无间断 (ERA5)） | Q21: ⭐⭐ 中等 | S21: 免费(需注册) | T21: 延迟5天(ERA5) | U21: 1940年至今(ERA5) | V21: 全球(ERA5) | W21: 1. 风场预测模型大气稳定度分类特征提取； 2. 风资源评估边界层湍流结构分析； 3. 优化尾流模型与湍流扩散参数； 4. 评估大气稳定度对风场波动与发电量的影响； | X21: 1. 记录结构：三维数组（time/lat/lon 维度）； 2. 唯一标识：网格 ID + 时间戳； 3. 文件名约定：ERA5_Stab_YYYYMMDD_HH.nc； 4. 注意事项：① 稳定度指数由 Richardson 数、Monin‑Obukhov 长度计算；② ERA5 数据可作为输入；③ 数据经严格质控，缺失值占比 0.0%；④ 免费需注册，ERA5 延迟 5 天； | Y21: D:\dcsk\knowledge_graph_1014\download_data\geodata\data\舟山\KG-20-21-22\87aa950f2c788dc9592506e5548116b8.grib
A22: =INDEX(数据源对应的文献以及数据使用方法和条目需求!A:B,MATCH(B22,数据源对应的文献以及数据使用方法和条目需求!B:B,0),1) -> ERA5相关性数据 | B22: KG-23 | C22: 未使用❌ | D22: 对流可用位能(CAPE) | E22: 气象与环境 | F22: 气象与环境(大气稳定度-对流指标) | G22: 时：1h；空：0.25° 网格 | H22: 🟡 推荐 | I22: NetCDF/GRIB | J22: 开源✅ 下载✅ 有数据✅ | K22: ERA5：https://cds.climate.copernicus.eu/ | L22: 账号：2072706022@qq.com 密码：Wdl2072706022 | M22: 1. 标识字段：时间 time（1h 分辨率）、网格 lat（0.25° 分辨率）、网格 lon（0.25° 分辨率）； 2. 核心要素字段：对流可用位能 CAPE（单位：J/kg）； 3. 元数据字段：数据集 ID（ERA5 hourly data on single levels from 1940 to present）、维护机构（ECMWF 欧洲中期天气预报中心）、坐标基准（WGS84 地理坐标系）； 4. 质量标识：数据质控标记（ERA5 严格质控）、有效格点标记（目标区域格点无缺失）； | N22: 1. 数值缺失：缺失值：NaN；缺失占比 0.0%（NetCDF/GRIB格式缺失值统一标识）； 2. 空间异常：lat/lon超出研究区有效经纬度范围； 3. 无效标记：CAPE<0（物理意义不合理）、CIN>0（无对流抑制意义）、NaN（数据缺失） | O22: 1. 数据集核心元数据：数据集 ID (ERA5 hourly data on single levels from 1940 to present)、维护机构 (ECMWF 欧洲中期天气预报中心)、数据来源 (ERA5 全球大气再分析数据集)； 2. 字段元数据：单位 (CAPE：J/kg)、缩放因子 无（原生单位无需换算）、格式版本 (GRIB2)； 3. 时间 / 空间：时间基准 (UTC)、空间覆盖 (全球范围格点) | P22: 地理特征维度：经纬度（LAT_DEG/LON_DEG，0.25°×0.25° 分辨率）、格点级空间特征（面状覆盖，非站点级）；气象特征维度：对流不稳定指标（CAPE）、大气对流潜力表征；时空特征维度：小时级时序特征（1.0h 分辨率）、全球格点级空间特征（0.25°×0.25°）、时间连续性（逐小时无间断） | Q22: ⭐ 简单 | S22: 免费(需注册CDS账号) | T22: 延迟5天 | U22: 1940年至今 | V22: 全球 | W22: 1. 风场预测模型对流不稳定特征提取； 2. 风资源评估强对流天气风险分析； 3. 优化极端风况预测与风机安全控制； 4. 评估对流活动对风电场出力稳定性的影响； | X22: 1. 记录结构：三维数组（time/lat/lon 维度）； 2. 唯一格点 ID：纬度 (0.25° 步长)+ 经度 (0.25° 步长)； 3. 文件名约定：ERA5_CAPE_YYYYMMDD_HH.nc； 4. 注意事项：① CAPE 为 ERA5 直接输出变量，表征对流潜力（数值范围 0.00~140.62 J/kg）；② 数据经 ECMWF 严格质控无异常，缺失值占比 0.0%；③ 免费获取需注册 CDS 账号，数据延迟 5 天； | Y22: D:\dcsk\knowledge_graph_1014\download_data\geodata\data\舟山\KG-20-21-22\87aa950f2c788dc9592506e5548116b8.grib
A23: =INDEX(数据源对应的文献以及数据使用方法和条目需求!A:B,MATCH(B23,数据源对应的文献以及数据使用方法和条目需求!B:B,0),1) -> 时空上下文特征数据 | B23: KG-24 | C23: 未使用❌ | D23: 经纬度与海拔 | E23: 空间与地理地形 | F23: 空间与地理地形(经度、纬度、海拔-场址海拔基准) | G23: 时：静态；空：站点/风机级 | H23: 🔴 必需 | I23: CSV/DB(坐标表)+GeoTIFF(DEM) | J23: 开源✅(DEM) 坐标自有数据；有数据✅ | K23: DEM 数据：ASTGTM 30m 高程数据（WGS84，EPSG:4326），已覆盖舟山全域； 经纬度：从舟山研究区（121.9655~123.102°E，29.7382~30.733°N）内风机/测点位置获取，或通过地图拾取获得。 | M23: 1. 经度 Lon（十进制度）； 2. 纬度 Lat（十进制度）； 3. 海拔高度（单位：m） | N23: 1. 缺失值：无（站点级必须配置）； 2. 无效海拔：负值（近海区域需修正） | O23: 1. 数据类型：静态空间位置数据； 2. DEM坐标系：WGS84（EPSG:4326）； 3. 精度：DEM 30m，坐标GPS级 | P23: 1. 空间定位：确定风机/测点地理位置； 2. 地形基准：提供海拔高度，用于风场模型高度参照； 3. 时空特征：静态不变 | Q23: ⭐ 简单 | S23: 免费(DEM) / 自有数据(GPS) | T23: 静态数据 | U23: DEM:2000年至今； GPS：当前 | V23: 全球(DEM) / 站点级(GPS) | W23: 1. 提供风机 / 测点的精准空间定位和海拔基准 2. 作为风场模型的地形高度参照，支撑风场模拟中海拔校正、场址位置匹配，保障风场预测的空间准确性 | X23: 经纬度来源于风机 / 测点 GPS 坐标或地图拾取，确保站点级空间定位精准； 2. 海拔从 ASTGTM 30m DEM 数据（WGS84 坐标系，EPSG:4326）中提取对应点位高程，近海区域需排查并修正负值无效海拔； 3. 数据为静态，作为风场模型的基础空间基准数据，无时间变化
A24: =INDEX(数据源对应的文献以及数据使用方法和条目需求!A:B,MATCH(B24,数据源对应的文献以及数据使用方法和条目需求!B:B,0),1) -> 时空上下文特征数据 | B24: KG-25 | C24: 未使用❌ | D24: 时间特征（年、月、日、时、日序） | E24: 风速本体及时序特征 | F24: 风速本体及时序特征(时间嵌入特征) | G24: 时：与原始序列一致；空：同站点/风机 | H24: 🔴 必需 | I24: 工程计算字段（CSV/Parquet/DB 列） | J24: —（从时间戳计算）从时间戳计算） 无需外部数据源，从时间戳自动生成 | K24: — | M24: 1. 年； 2. 月； 3. 日； 4. 时； 5. 日序DayOfYear | N24: 1. 无缺失值（时间戳完整即可生成）； 2. 异常值：时间不连续、时间戳错误需清洗 | O24: 1. 特征类型：时间嵌入特征； 2. 计算方式：从datetime时间戳提取； 3. 无单位 | P24: 1. 时序特征：提供周期信息（日/月/季节/年际）； 2. 模型输入：作为机器学习/风场模型的时间维度特征； 3. 时空特征：与风速序列时间同步 | Q24: ⭐ 简单 | S24: 免费(工程计算) | T24: 实时(从时间戳提取) | U24: 无限制(取决于原始数据时间范围) | V24: 无限制(适用于所有数据) | W24: 1. 提取风速时间序列的时间嵌入特征，提供日、月、季节、年际等周期信息 2. 作为风场预测模型（机器学习 / 数值模拟）的时间维度输入，提升风速预测精度。 | X24: 无需外部下载数据源，通过工程计算从原始风速时间戳（datetime）中自动提取，与风速序列时间保持同步； 2. 提取过程中需清洗时间不连续、时间戳错误等异常值，确保特征有效性； 3. 特征无单位，实时提取生成，适用所有风场站点 / 风机的时序模拟场景
A25: =INDEX(数据源对应的文献以及数据使用方法和条目需求!A:B,MATCH(B25,数据源对应的文献以及数据使用方法和条目需求!B:B,0),1) -> ERA5相关性数据 | B25: KG-26 | C25: 未使用❌ | D25: 天气形势分型 | E25: 本体外扩展 | F25: 本体外扩展(天气形势分型-聚类特征) | G25: 时：1h(随NWP)； 空：大尺度场/站点映射 | H25: 🟢 可选 | I25: 工程计算字段 | J25: —（从 NWP 聚类得到） | K25: — | L25: 开源✅(依赖ERA5)；需聚类计算 从NWP/ERA5再分析数据聚类得到 | M25: 1. 标识字段：时间time（1h分辨率）、格点lat/lon（0.25°）； 2. 核心要素字段：天气型编号、环流类型、主导系统类型； 3. 元数据字段：数据集ID（ERA5 hourly data）、维护机构（ECMWF）、坐标基准（WGS84）； 4. 质量标识：基于ERA5严格质控，格点全覆盖无缺失 | N25: 1. 数值缺失：天气型编号=-99、NaN； 2. 空间异常：lat/lon超出29.5~31.0°N、121.5~123.5°E； 3. 无效标记：天气型编号<0或超出分类范围、时间不连续 | O25: 1. 数据集核心元数据：数据集ID（ERA5 hourly data on single levels from 1940 to present）、维护机构（ECMWF）、数据来源（ERA5再分析）； 2. 字段元数据：单位（无/分型编号）、缩放因子无、格式版本（工程计算字段）； 3. 时间/空间：时间基准UTC、空间覆盖全球格点 | P25: 地理特征维度：格点经纬度（0.25°×0.25°）、大尺度环流场空间特征、区域映射特征；气象特征维度：环流类型、主导天气系统、气压场特征、稳定度特征；时空特征维度：1h时序、大尺度空间场、时间连续性（逐小时） | Q25: ⭐⭐ 中等 | S25: 免费(需NWP数据+聚类算法) | T25: 延迟5天(取决于NWP) | U25: 1940年至今(取决于NWP数据) | V25: 全球(取决于NWP覆盖) | W25: 1. 风场预测大尺度环流背景特征输入； 2. 提升风速/风电功率预测鲁棒性； 3. 按天气型分场景建模； 4. 异常天气预警辅助 | X25: 1. 记录结构：时序+格点二维； 2. 唯一标识：格点ID+时间戳； 3. 文件名约定：WeatherType_YYYYMMDD.nc； 4. 基于ERA5温、压、风、高度场聚类得到天气型
A26: =INDEX(数据源对应的文献以及数据使用方法和条目需求!A:B,MATCH(B26,数据源对应的文献以及数据使用方法和条目需求!B:B,0),1) -> 历史与误差信息数据 | B26: KG-27 | C26: 未使用❌ | D26: 基础模型/历史预测误差 | E26: 本体外扩展 | F26: 本体外扩展(历史预测误差-MOS方法/模型误差统计) | G26: 时：按统计周期/或逐时； 空：场站/风机级 | H26: 🟡 推荐 | I26: CSV/Parquet/数据库表 | J26: —（模型内部生成） | K26: — | L26: 开源✅(模型内部生成) 模型预测输出+ERA5真值计算 | M26: 1. 标识字段：时间time（1h）、场站/格点lat/lon；2. 核心要素字段：预测风速、观测/真值风速、绝对误差、相对误差、误差符号；3. 元数据字段：模型版本、坐标基准WGS84；4. 质量标识：有效预测时段标记、异常误差过滤 1. 数值缺失：误差=999/NaN；2. 时间异常：预测时间超前/滞后超阈值；3. 无效标记：误差绝对值超合理范围、无对应真值 | N26: 1. 数值缺失：误差=999/NaN； 2. 时间异常：预测时间超前/滞后超阈值； 3. 无效标记：误差绝对值超合理范围、无对应真值 | O26: 1. 数据集核心元数据：来源为预测模型输出+ERA5真值、维护机构（项目内部）； 2. 字段元数据：单位（m/s、无维）、缩放因子无； 3. 时间/空间：时间基准UTC、空间覆盖本项目格点 | P26: 地理特征维度：场站/格点经纬度、区域空间分布特征；气象特征维度：风速误差、稳定度相关误差、天气型相关偏差；时空特征维度：逐小时误差时序、日内/周内/月内误差周期 | Q26: ⭐⭐ 中等 | S26: 免费(模型内部生成) | T26: 实时(随模型预测) | U26: 模型运行期间 | V26: 场站级(取决于模型应用范围) | W26: 1. MOS模型校正输入； 2. 预测偏差修正； 3. 模型效果评估； 4. 分场景误差学习 | X26: 1. 记录结构：时间+站点/格点二维； 2. 唯一标识：场站ID+预测时间； 3. 文件名约定：ModelError_YYYYMMDD.csv； 4. 误差由预测场与ERA5真值计算得到
A27: =INDEX(数据源对应的文献以及数据使用方法和条目需求!A:B,MATCH(B27,数据源对应的文献以及数据使用方法和条目需求!B:B,0),1) -> ERA5相关性数据 | B27: KG-28 | C27: 未使用❌ | D27: 多模式集合预报 | E27: 气象与环境 + 本体外扩展 | F27: 气象与环境 (整体气象背景场：GFS 0.25° 风场 / 气压场 / 温度场)；本体外扩展 (预测不确定性 - 集合特征：风速集合离散度 / 概率指标) | G27: 时：1h(典型)；空：0.25°（GFS 原始分辨率） | H27: 🟡 推荐 | I27: GRIB/NetCDF (原始)；CSV/Parquet (整理后) | J27: NWP 开源✅/部分付费；有数据✅ | K27: ERA5：https://cds.climate.copernicus.eu/； GFS：https://nomads.ncep.noaa.gov/； ECMWF HRES：见上 | M27: 1. 标识字段：时间 time（1h）、集合成员（GFS 集合预报成员）、lat/lon（0.25°）； 2. 核心要素字段：集合风速均值、集合离散度、风速上下限、概率指标；u10/v10（10m 风分量）、t2m（2m 气温）、sp（表面气压）、wind_speed（风速）、wind_dir（风向） 3. 元数据字段： 模式来源（GFS）、分辨率（0.25°）、坐标基准 WGS84； 4. 质量标识：集合成员完整性、异常值过滤（风速 < 0 / 离散度为负 / 时间不连续已过滤 | N27: 1. 数值缺失：风速 = 99.99/NaN；（已处理：缺失值填充 / 剔除）； 2. 空间异常：超出本项目经纬度范围； 3. 无效标记：风速 < 0、离散度为负、时间不连续；（已处理：无效值标记为 NaN 并过滤） | O27: 1. 数据集核心元数据：来源 GFS、维护机构 NCEP（美国国家环境预报中心）； 2. 字段元数据： 单位：u10/v10/wind_speed (m/s)、sp (Pa)、t2m (K)、wind_dir (°)；缩放因子无；格式 GRIB2/NetCDF； 3. 时间/空间：时间基准 UTC、空间基准全球 0.25° 格点 | P27: 地理特征维度：0.25°×0.25° 格点经纬度、大尺度气象场空间结构（GFS 全球格点→舟山区域裁剪； 气象特征维度：集合风速场、气压场、温度场、离散度 / 不确定性（u10/v10/t2m/sp/wind_speed/wind_dir）； 时空特征维度：1h 时序、集合预报时间序列、空间一致性（GFS 1h 更新频率，舟山区域空间一致性校验） | Q27: ⭐⭐ 中等 | S27: 免费(ERA5/GFS) / 付费(ECMWF HRES) | T27: 延迟5天(ERA5) / 实时(GFS) / 延迟数小时(HRES) | U27: 1940年至今(ERA5) / 近10年(GFS) / 近10-15年(HRES) | V27: 全球 | W27: 1. 风场概率预测； 2. 预测不确定性评估； 3. 多模式融合校正； 4. 极端风况风险预警； 5. 舟山区域风速 / 气温空间分布分析； | X27: 1. 记录结构：集合成员×time×lat×lon； 2. 唯一标识：模式+成员+时间+格点； 3. 文件名约定：MultiModel_YYYYMMDD.nc； 4. 支持ERA5/GFS/ECMWF多源融合输入 | Y27: D:\dcsk\knowledge_graph_1014\download_data\geodata\data\舟山\KG-28\gfs_full\gfs.t06z.pgrb2.0p25.f000
A28: =INDEX(数据源对应的文献以及数据使用方法和条目需求!A:B,MATCH(B28,数据源对应的文献以及数据使用方法和条目需求!B:B,0),1) -> ERA5相关性数据 | B28: AIA-1090 | C28: 使用✅ | D28: NOAA GSOD全球逐日汇总数据 | E28: 气象与环境； 相邻/上游测风站数据 | F28: 气象与环境(数据源类型-实测值)； 相邻/上游测风站数据(历史风速) | G28: 时：日（GMT/UTC 0000Z-2359Z 汇总）；空：站点级（全球 9000 + 站点） | H28: 🟡 推荐 | I28: ASCII/CSV/TXT（压缩包格式：tar.gz）；核心数据源：ISD/USAF DATSAV3 | J28: 开源✅ 下载✅ 有数据✅ | K28: NOAA GSOD：https://www.ncei.noaa.gov/data/global-summary-of-the-day/archive/ | L28: 陈林老师已经完成1929-2025的数据下载（天翼云） | M28: 1. 站点基础信息： STATION（站点编号，WMO/DATSAV3 格式）、DATE（观测日期，mm/dd/yyyy，GMT 基准）、LATITUDE（纬度，十进制度，南半球负值）、LONGITUDE（经度，十进制度，西半球负值）、ELEVATION（海拔，米）、NAME（站点名称）； 2. 气象要素： TEMP（日平均气温，°F×0.1）、MAX（日最高气温，°F×0.1）、MIN（日最低气温，°F×0.1）、DEWP（日平均露点，°F×0.1）、SLP（日平均海平面气压，mb×0.1）、STP（日平均站点气压，mb×0.1）、WDSP（日平均风速，knots×0.1）、MXSPD（日最大持续风速，knots×0.1）、GUST（日最大阵风，knots×0.1）、VISIB（日平均能见度，英里 ×0.1）、PRCP（日累计降水量，英寸 ×0.01）、SNDP（雪深，英寸 ×0.1）、FRSHTT（6 位天气现象标识，从左到右依次为：F 雾、R 雨、S 雪、H 冰雹、T 雷暴、T 龙卷风 / 漏斗云；1 = 发生，0 = 未发生 / 未报告）、PRCP_ATTRIBUTES（降水量属性代码，A-I 分别对应不同报告频次与数据完整性） | N28: 1. 标准缺失值：温度 / 气压类 9999.9；风 / 能见度类 999.9/999；降水量 99.99；雪深 999.9； 2. PRCP=0：确认无实测降水（含微量）； 3. PRCP_ATTRIBUTES 代码 H：报告 0 值但小时观测有降水（数据不完整）； 4. PRCP_ATTRIBUTES 代码 I：当日无任何降水报告（仍可能存在未报告降水）； 5. 缺失值含义：99.99/999.9 代表未报告 / 缺失，而非无数据；部分站点无数据时填充 999.9 而非 0 | O28: 1. 数据集核心： 发布机构 (NOAA National Centers for Environmental Information, NCEI)、数据来源 (ISD/USAF DATSAV3)、时间基准 (GMT/UTC 0000Z-2359Z)、版本 (V8)、更新频率 (观测日后 1-2 天)； 2. 字段属性： TEMP/MAX/MIN 单位 (°F×0.1)、SLP/STP 单位 (mb×0.1)、WDSP/MXSPD/GUST 单位 (knots×0.1)、VISIB 单位 (英里 ×0.1)、PRCP 单位 (英寸 ×0.01)、SNDP 单位 (英寸 ×0.1)； 3. 质量规则： 每日至少 4 次有效观测生成日数据；存在单位转换舍入误差；日极值 / 累计值可能跨日历日 | P28: 1. 地理特征维度： 全球站点分布、经纬度 / 海拔属性、站点编号唯一标识； 2. 气象特征维度： 温湿要素（气温、露点）、气压要素（海平面 / 站点气压）、风要素（平均 / 最大持续 / 阵风）、能见度要素、降水 / 积雪要素、天气现象要素（雾 F、雨 R、雪 S、冰雹 H、雷暴 T、龙卷风 / 漏斗云 T，通过 FRSHTT 6 位编码标识））； 3. 时空特征维度： 日级 GMT 汇总时序、1929 年至今长期连续时序、全球站点级空间覆盖 | Q28: ⭐⭐ 中等 | S28: 免费 | T28: 延迟1-2天 | U28: 1929 年至今（1973 年至今数据最完整） | V28: 全球 9000 + 气象站点（覆盖纬度 90°S~90°N、经度 180°W~180°E） | W28: 1. 风资源评估中历史风速/风况统计分析； 2. 气象背景场补充与测风塔数据校验； 3. 长期气候趋势分析与极端天气事件复盘； 4. 风场预测模型历史误差校准与边界条件优化； 5. 相邻/上游站点气象要素关联分析，提升风场预测精度； 6. 温压湿等气象要素与风速相关性研究。 | X28: 1. 数据属性：GSOD 为日级汇总数据，源自 ISD/USAF DATSAV3 小时观测，需每日≥4 次有效观测； 2. 文件名规范：年度.tar.gz（如 2025.tar.gz），数据基于 GMT/UTC 0000Z-2359Z 汇总； 3. 时间特性：日极值 / 累计值（降水、阵风、积雪）可能跨相邻日历日； 4. 使用限制：非美国站点数据仅限科研 / 教育，禁止商业再分发 / 出口；美国站点无此限制； 5. 数据特征：部分能见度值存在聚集（如 10 英里），因站点报告上限所致； 6. FRSHTT 编码示例：101000 表示当日有雾和雪，无雨、冰雹、雷暴、龙卷风； 7. PRCP_ATTRIBUTES 代码 A-I 用于标识降水报告频次与数据完整性，需结合 PRCP 值共同解读； 8. 部分站点能见度值存在聚集（如 10 英里），因站点报告上限所致 | Y28: 天翼云：/home/admin/data_set/mvp_data/noaa_gsd_samples
A29: =INDEX(数据源对应的文献以及数据使用方法和条目需求!A:B,MATCH(B29,数据源对应的文献以及数据使用方法和条目需求!B:B,0),1) -> ERA5相关性数据 | B29: AIA-1091 | C29: 使用✅ | D29: 中国第一代全球陆面再分析产品（CMA-RA/Land）- 大气驱动融合产品 | E29: 气象与环境；相邻/上游测风站数据 | F29: 气象与环境(数据源类型-实测值)；相邻/上游测风站数据(历史风速) | G29: 时：3h（每日 8 个时次）；空：约 34km（高斯网格 1152×576） | H29: 🔴 必需 | I29: GRIB（标准气象格点格式） | J29: 开源✅ 下载✅(需注册) 有数据✅ | K29: 中国气象数据网：https://data.cma.cn/ | M29: 1. 基础标识信息： TIME（观测时间，UTC，3h 间隔）、LATITUDE（纬度）、LONGITUDE（经度）、GRID_ID（网格编码）、PRODUCT_TYPE（大气驱动融合产品）； 2. 气象要素： 近地面要素：T2M（2 米气温）、SPFH2M（2 米比湿）、UGRD10M（10 米 U 风）、VGRD10M（10 米 V 风）、PRCP（降水率）； 关联陆面要素（配套产品）：TS（地表温度）、SOIL_T（各层土壤温度）、SOIL_M（各层土壤湿度 | N29: 1. 无统一数字缺失标记，采用 GRIB 原生缺失值标识； 2. 全球网格全域覆盖，无空间缺失区域； 3. 0 值为有效模拟结果（如无降水时 PRCP=0），非缺失； 4. 样例数据仅开放中国区域（bbox [60.0, 0.0, 160.0, 65.0]），其他区域需商业授权获取 | O29: 1. 数据集核心： 发布机构（国家气象信息中心 / 中国气象局）、数据类型（第一代全球陆面再分析数据）、核心模型（Noah 3.3 陆面模式）、同化技术（四维集合变分混合同化）； 2. 字段属性： 时间分辨率（3h）、空间分辨率（34km）、垂直结构（土壤 4 层：0-0.1/0.1-0.4/0.4-1.0/1.0-2.0m）、数据基准（UTC）； 3. 质量规则： 基于多源观测同化生成，数据质量与国际第三代再分析产品相当；500hPa 位势高度误差低于早期国外产品；更新延迟 6.5-9 小时 | P29: 1. 地理特征维度： 全球网格覆盖、34km 等分辨率分布、中国区域样例开放； 2. 气象特征维度： 近地面温湿风要素、降水要素、配套陆面状态变量（土壤温湿度、地表通量等）； 3. 时空特征维度： 3h 高频时序特征、1979 年至今连续时序、网格级空间特征、多圈层（大气 - 陆面）关联特征 | Q29: ⭐⭐ 中等 | S29: 免费（中国区域样例数据，科研/个人使用）；商业/大批量数据需授权付费 | T29: 延迟 1-2 天（观测日后 1-2 天内更新） | U29: 1979 年1月1日至今（持续更新） | V29: 全球（样例数据开放中国范围下载） | W29: 1. 风资源评估中历史风速统计与风场模拟； 2. 陆面 - 水文 - 生态模型驱动场，支撑水循环 / 碳循环模拟； 3. 长期气候变化趋势分析与极端天气事件复盘； 4. 数值预报模式初始场与边界条件补充； 5. 农业 / 新能源 / 水资源管理等跨行业专业气象服务； 6. 相邻 / 上游区域气象要素关联分析，提升局地预测精度 | X29: 1. CMA-RA 是我国首套自主全球陆面再分析产品，打破欧美产品依赖，质量与 JRA-55 等国际产品相当； 2. 产品分大气驱动融合产品（核心）与陆面产品（配套），数据格式为 GRIB，天翼云存储路径：/home/admin/data_set/mvp_data/CMA-RA； 3. 数据通过中国气象数据网注册获取，样例数据（中国区域）免费，大批量 / 商业使用需授权； 4. 2024 年升级版本 CMA-RA V1.5 分辨率提升至 10km，更新频率达逐小时； 5. 垂直方向土壤分 4 层，配套陆面产品含土壤温湿度、地表通量等约 30 个变量 | Y29: 天翼云：/home/admin/data_set/mvp_data/CMA-RA
A30: =INDEX(数据源对应的文献以及数据使用方法和条目需求!A:B,MATCH(B30,数据源对应的文献以及数据使用方法和条目需求!B:B,0),1) -> ERA5相关性数据 | B30: AIA-1088 | C30: 使用✅ | D30: 全球高空探空数据(IGRA，NOAA) | E30: 气象与环境 | F30: 气象与环境 | G30: 时：12h；空：站点级，多高度层 | H30: 🟡 推荐 | I30: TXT/NetCDF | J30: 开源✅ 下载✅ 有数据✅ | K30: NOAA IGRA：https://www.ncei.noaa.gov/products/weather-balloon/integrated-global-radiosonde-archive | Q30: ⭐⭐ 中等 | S30: 增加输入通道，特征融合 | T30: 延迟数小时 | U30: 1905年至今 | V30: 全球
A31: =INDEX(数据源对应的文献以及数据使用方法和条目需求!A:B,MATCH(B31,数据源对应的文献以及数据使用方法和条目需求!B:B,0),1) -> ERA5相关性数据 | B31: AIA-1089 | C31: 使用✅ | D31: 中国高空探空数据(CMA) | E31: 气象与环境 | F31: 气象与环境(高空风速风向-多高度层、大气稳定度) | G31: 时：12h；空：站点级，多高度层 | H31: 🟡 推荐 | I31: TXT/NetCDF | J31: 开源✅ 下载✅(需注册) 有数据✅ | K31: 中国气象数据网：https://data.cma.cn/ | Q31: ⭐⭐ 中等 | S31: 免费(需注册) | T31: 实时/延迟数小时 | U31: 近10-20年 | V31: 中国
A32: =INDEX(数据源对应的文献以及数据使用方法和条目需求!A:B,MATCH(B32,数据源对应的文献以及数据使用方法和条目需求!B:B,0),1) -> ERA5相关性数据 | B32: AIA-1072 | C32: 使用✅ | D32: NOAA NDBC海洋浮标网数据 | E32: 气象与环境 | F32: 气象与环境(高空风速风向-海上补充) | G32: 时：1h；空：浮标站点 | H32: 🟢 可选 | I32: CSV/TXT | J32: 开源✅ 下载✅ 有数据✅ | K32: NOAA NDBC：https://www.ndbc.noaa.gov/ | Q32: ⭐⭐ 中等 | S32: 免费 | T32: 实时/延迟数小时 | U32: 1970年至今 | V32: 美国近海及部分全球海域
A33: =INDEX(数据源对应的文献以及数据使用方法和条目需求!A:B,MATCH(B33,数据源对应的文献以及数据使用方法和条目需求!B:B,0),1) -> ERA5相关性数据 | B33: AIA-1073 | C33: 使用✅ | D33: ICOADS全球海洋综合数据集(全球船舶+浮标综合观测) | E33: 气象与环境 | F33: 气象与环境(高空风速风向-海上补充) | G33: 时：3h/6h；空：站点级 | H33: 🟢 可选 | I33: NetCDF/CSV | J33: 开源✅ 下载✅ 有数据✅ | K33: ICOADS：https://www.ncei.noaa.gov/products/international-comprehensive-ocean-atmosphere-data-set | Q33: ⭐⭐ 中等 | S33: 免费 | T33: 延迟数天 | U33: 1662年至今 | V33: 全球海洋
A34: =INDEX(数据源对应的文献以及数据使用方法和条目需求!A:B,MATCH(B34,数据源对应的文献以及数据使用方法和条目需求!B:B,0),1) -> 海洋气象数据 | B34: AIA-1074 | C34: 使用✅ | D34: ORAS5海洋再分析数据 | E34: 气象与环境 | F34: 气象与环境(高空风速风向-海上补充、海洋背景场) | G34: 时：1天；空：0.25° | H34: 🟢 可选 | I34: NetCDF | J34: 开源✅ 下载✅(需注册) 有数据✅ | K34: ECMWF ORAS5：https://www.ecmwf.int/en/forecasts/datasets/reanalysis-datasets/oras5 | Q34: ⭐⭐ 中等 | S34: 免费(需注册) | T34: 延迟数天 | U34: 1979年至今 | V34: 全球海洋
A35: =INDEX(数据源对应的文献以及数据使用方法和条目需求!A:B,MATCH(B35,数据源对应的文献以及数据使用方法和条目需求!B:B,0),1) -> ERA5相关性数据 | B35: AIA-1075 | C35: 使用✅ | D35: CFSR/CFSv2海洋再分析数据(NCEP海洋+大气再分析) | E35: 气象与环境 | F35: 气象与环境(高空风速风向-多源验证、整体气象背景场) | G35: 时：6h；空：0.5° | H35: 🟡 推荐 | I35: GRIB/NetCDF | J35: 开源✅ 下载✅ 有数据✅ | K35: NCEP CFSR/CFSv2：https://www.ncei.noaa.gov/products/weather-climate-models/climate-forecast-system | Q35: ⭐⭐ 中等 | S35: 免费 | T35: 延迟数天 | U35: CFSR: 1979-2010年；CFSv2: 2011年至今 | V35: 全球
A36: =INDEX(数据源对应的文献以及数据使用方法和条目需求!A:B,MATCH(B36,数据源对应的文献以及数据使用方法和条目需求!B:B,0),1) -> ERA5相关性数据 | B36: AIA-1066 | C36: 使用✅ | D36: NEXRAD天气雷达数据 | E36: 气象与环境 | F36: 气象与环境(近地面微气象-强对流相关) | G36: 时：~5-6min 体扫；空：~1 km，多高度层 | H36: 🟢 可选 | I36: 雷达 Level-II/Level-III | J36: 开源✅ 下载✅ 有数据✅ | K36: NOAA NEXRAD：https://www.ncei.noaa.gov/products/radar/next-generation-weather-radar | Q36: ⭐⭐ 中等 | S36: 免费 | T36: 实时/延迟数分钟 | U36: 1991年至今 | V36: 美国本土及部分海外
A37: =INDEX(数据源对应的文献以及数据使用方法和条目需求!A:B,MATCH(B37,数据源对应的文献以及数据使用方法和条目需求!B:B,0),1) -> ERA5相关性数据 | B37: AIA-1067 | C37: 使用✅ | D37: TDWR终端多普勒天气雷达数据(机场) | E37: 气象与环境 | F37: 气象与环境(近地面微气象-强对流相关) | G37: 时：~1min 体扫；空：~0.5 km，多高度层 | H37: 🟢 可选 | I37: 雷达 Level-II | J37: 开源✅ 下载✅ 有数据✅ | K37: NOAA TDWR：https://www.ncei.noaa.gov/products/radar/terminal-doppler-weather-radar | Q37: ⭐⭐ 中等 | S37: 免费 | T37: 实时/延迟数分钟 | U37: 1994年至今 | V37: 美国主要机场周边
A38: =INDEX(数据源对应的文献以及数据使用方法和条目需求!A:B,MATCH(B38,数据源对应的文献以及数据使用方法和条目需求!B:B,0),1) -> ERA5相关性数据 | B38: AIA-1068 | C38: 使用✅ | D38: GridRad网格化雷达数据 | E38: 气象与环境 | F38: 气象与环境(近地面微气象-强对流相关) | G38: 时：5min；空：0.02°×0.02° (~2km)，多高度层 | H38: 🟢 可选 | I38: NetCDF | J38: 开源✅ 下载✅ 有数据✅ | K38: GridRad：https://gridrad.org/ | Q38: ⭐⭐ 中等 | S38: 免费 | T38: 延迟数小时 | U38: 1995年至今 | V38: 美国本土
A39: =INDEX(数据源对应的文献以及数据使用方法和条目需求!A:B,MATCH(B39,数据源对应的文献以及数据使用方法和条目需求!B:B,0),1) -> ERA5相关性数据 | B39: AIA-1069 | C39: 使用✅ | D39: 中国气象雷达拼图数据 | E39: 气象与环境 | F39: 气象与环境(近地面微气象-强对流相关) | G39: 时：6-10min；空：1-2 km，多高度层 | H39: 🟢 可选 | I39: NetCDF/BUFR | J39: 开源⚠️(需申请) 下载⚠️ 有数据⚠️(视区域) | K39: 中国气象数据网：https://data.cma.cn/（需专项申请） | Q39: ⭐⭐⭐ 困难 | S39: 需协商(需向气象部门申请) | T39: 实时/延迟数分钟 | U39: 近5-10年(视雷达站) | V39: 中国区域
A40: =INDEX(数据源对应的文献以及数据使用方法和条目需求!A:B,MATCH(B40,数据源对应的文献以及数据使用方法和条目需求!B:B,0),1) -> 天气雷达数据 | B40: AIA-1070 | C40: 使用✅ | D40: NASA机载雷达数据 | E40: 气象与环境 | F40: 气象与环境(近地面微气象-强对流相关) | G40: 时：秒级-分钟级；空：~100m-1 km，多高度层 | H40: 🟢 可选 | I40: NetCDF/HDF5 | J40: 开源✅ 下载✅ 有数据✅(特定研究项目) | K40: NASA Airborne Radar：https://www-air.larc.nasa.gov/ | Q40: ⭐⭐⭐ 困难 | S40: 免费(需申请) | T40: 延迟数天-数周 | U40: 特定研究项目期间 | V40: 特定研究区域
A41: =INDEX(数据源对应的文献以及数据使用方法和条目需求!A:B,MATCH(B41,数据源对应的文献以及数据使用方法和条目需求!B:B,0),1) -> 天气雷达数据 | B41: AIA-1071 | C41: 使用✅ | D41: 欧洲雷达数据(OPERA/EUMETNET) | E41: 气象与环境 | F41: 气象与环境(近地面微气象-强对流相关) | G41: 时：5-15min；空：1-2 km，多高度层 | H41: 🟢 可选 | I41: BUFR/ODIM HDF5 | J41: 开源✅ 下载✅(需注册) 有数据✅ | K41: OPERA：https://www.eumetnet.eu/activities/observations-programme/current-activities/opera/；EUMETNET：https://www.eumetnet.eu/ | Q41: ⭐⭐ 中等 | S41: 免费(需注册) | T41: 实时/延迟数分钟 | U41: 2004年至今 | V41: 欧洲区域
... A46: =INDEX(数据源对应的文献以及数据使用方法和条目需求!A:B,MATCH(B46,数据源对应的文献以及数据使用方法和条目需求!B:B,0),1) -> ERA5相关性数据 | B46: AIA-1080 | C46: 使用✅ | D46: EUMETSAT METEOSAT+MetOp卫星数据 | E46: 气象与环境 | F46: 气象与环境(全局水平辐照度-间接、近地面微气象-云量/辐射影响) | G46: 时：15min；空：1-3 km | H46: 🟢 可选 | I46: NetCDF/HDF5 | J46: 开源✅ 下载✅(需注册) 有数据✅ | K46: EUMETSAT：https://www.eumetsat.int/； METEOSAT：https://www.eumetsat.int/meteosat-series； MetOp：https://www.eumetsat.int/metop-series | Q46: ⭐⭐ 中等 | S46: 免费(需注册) | T46: 实时/延迟数分钟 | U46: METEOSAT: 1977年至今； MetOp: 2006年至今 | V46: 欧洲、非洲及周边区域
A47: =INDEX(数据源对应的文献以及数据使用方法和条目需求!A:B,MATCH(B47,数据源对应的文献以及数据使用方法和条目需求!B:B,0),1) -> ERA5相关性数据 | B47: AIA-1081 | C47: 使用✅ | D47: 日本Himawari-8/9卫星数据 | E47: 气象与环境 | F47: 气象与环境(全局水平辐照度-间接、近地面微气象-云量/辐射影响) | G47: 时：10min（全盘扫描，L2/L3 级核心观测周期）；空：5km（本次下载 L2 级产品核心分辨率） | H47: 🟢 可选 | I47: NetCDF（本次下载为 L2 级标准格式） | J47: 开源✅ 下载✅(需注册) 有数据✅ | K47: JAXA Himawari：https://www.eorc.jaxa.jp/ptree/； JMA：https://www.jma.go.jp/jma/indexe.html | L47: 唐再喜老师已经完成2026-2025年全年时间分辨率10min空间分辨率5km的数据 | M47: 1. 基础标识信息： TIME（观测时间，UTC，10min 间隔）、LATITUDE（纬度）、LONGITUDE（经度）、SATELLITE（Himawari-8/9）、RESOLUTION（5km）、PRODUCT（L2 级产品类型：CLP/ARP/PAR）、LEVEL（数据级别：L2）； 2. 气象要素： CLP（云产品：云检测、云顶高度 / 温度 / 相态）、ARP（气溶胶产品：AOD、埃斯特伦指数）、PAR（光合有效辐射：400-700nm 辐射强度） | N47: 1. 无统一数字缺失标记，采用 NetCDF 原生缺失值标识； 2. 亚太全圆盘（FLDK）全域覆盖，无空间缺失区； 3. 0 值为有效观测结果（如无云区云量 = 0、无气溶胶区 AOD=0），非缺失； 4. 云掩膜规则：CLP 识别为有云区域时，对应 ARP 数据为无效 / 原生缺失（数据关联性要求 | O47: 1. 数据集核心： 发布机构（JMA 日本气象厅）、数据类型（静止气象卫星 L2 级反演产品）、卫星载荷（AHI 成像仪 16 波段）、观测模式（FLDK 全圆盘扫描）； 2. 字段属性： 时间分辨率（L2 级 10min）、空间分辨率（L2 级 5km）、数据级别（L2 级 CLP/ARP/PAR）、数据基准（UTC）； 3. 质量规则： 基于 AHI 辐射定标与几何校正，L2 级为反演产品，数据精度符合业务标准；CLP/ARP/PAR 数据存在强关联性，使用需遵守数据关联规则 | P47: 1. 地理特征维度： 亚太全圆盘覆盖（FLDK）、5km 等分辨率网格、中国及周边海域精细覆盖； 2. 气象特征维度： 云要素（CLP）、气溶胶要素（ARP）、光合有效辐射要素（PAR）、多波段反演物理量； 3. 时空特征维度： 10min 高频时序特征、2025-2026 年连续时序、5km 网格级空间特征、L2 级反演产品专属时空特征 | Q47: ⭐⭐ 中等 | S47: 免费 (科研 / 教育用途，需在 JAXA PTree 平台注册，遵守 JMA 数据使用条款) | T47: 实时/延迟数分钟 | U47: 2025-2026 年全年（本次下载数据范围）；Himawari-8/9 接力观测（2015/2016 年至今） | V47: 亚太区域（FLDK 全圆盘覆盖，含中国全境及周边海域） | W47: 1. 全局水平辐照度间接反演（基于 PAR 光合辐射）； 2. 近地面微气象分析：云量（CLP）、辐射（PAR）对近地面温湿 / 风场的影响研究； 3. 气溶胶 - 云 - 辐射耦合关系分析（CLP/ARP/PAR 联合使用）； 4. 亚太区域云系 / 气溶胶时空演变监测； 5. 气象环境快速响应分析（10min 高频数据支撑）； 6. 台风 / 暴雨等极端天气的云系 - 辐射关联研究 | X47: 1. 葵花 8/9 为 JMA 运营静止气象卫星，搭载 AHI 成像仪，8/9 号接力保障东亚 - 西太平洋数据连续性； 2. 本次下载数据为 L2 级核心产品：CLP（云）、ARP（气溶胶）、PAR（光合辐射），空间分辨率 5km、时间分辨率 10min； 3. 数据格式为 NetCDF，文件名含 FLDK（全圆盘）标识，2km 为部分产品可选分辨率； 4. 数据关联性：CLP 为掩膜，有云区域 ARP 无效，PAR 计算依赖云属性，使用需遵循关联规则； 5. 下载渠道：JAXA PTree 平台注册获取，科研 / 教育用途免费，商业使用遵守 JMA 条款； 6. L1 级最高分辨率 0.5km，L3 级为日 / 月尺度聚合产品，本次数据为 L2 级实时反演产品 7. ftp协议连接：21、主机名 (H)：ftp.ptree.jaxa.jp、用户名 (U)：tejerajorge488_gmail.com、密码 (P)：SP+wari8 | Y47: 阿里云：/data/hdfs/user/zaixi.tang/himawari/2025/
A48: =INDEX(数据源对应的文献以及数据使用方法和条目需求!A:B,MATCH(B48,数据源对应的文献以及数据使用方法和条目需求!B:B,0),1) -> ERA5相关性数据 | B48: AIA-1082 | C48: 使用✅ | D48: NASA CloudSat & CALIPSO卫星数据 | E48: 气象与环境 | F48: 气象与环境(近地面微气象-云量/辐射影响、大气稳定度) | G48: 时：卫星过境；空：1.4km×1.7km，多高度层 | H48: 🟢 可选 | I48: HDF5 | J48: 开源✅ 下载✅(需注册) 有数据✅ | K48: NASA CloudSat：https://www.cloudsat.cira.colostate.edu/； NASA CALIPSO：https://www-calipso.larc.nasa.gov/ | Q48: ⭐⭐ 中等 | S48: 免费(需注册) | T48: 延迟数天 | U48: CloudSat: 2006-2023年；CALIPSO: 2006年至今 | V48: 全球
A49: =INDEX(数据源对应的文献以及数据使用方法和条目需求!A:B,MATCH(B49,数据源对应的文献以及数据使用方法和条目需求!B:B,0),1) -> ERA5相关性数据 | B49: AIA-1056 | C49: 使用✅ | D49: ERA5单层再分析数据 | E49: 气象与环境 | F49: 气象与环境(高空风速风向-高精度预报、整体气象背景场) | G49: 时：1h；空：0.25° | H49: 🟡 推荐 | I49: NetCDF/GRIB | J49: 开源✅ 下载✅(需注册) 有数据✅ | K49: ERA5：https://cds.climate.copernicus.eu/ | Q49: ⭐ 简单 | S49: 免费(需注册CDS账号) | T49: 延迟5天 | U49: 1940年至今 | V49: 全球
A50: =INDEX(数据源对应的文献以及数据使用方法和条目需求!A:B,MATCH(B50,数据源对应的文献以及数据使用方法和条目需求!B:B,0),1) -> ERA5相关性数据 | B50: AIA-1057 | C50: 使用✅ | D50: ERA5等压面再分析数据 | E50: 气象与环境 | F50: 气象与环境(高空风速风向-高精度预报、整体气象背景场) | G50: 时：1h；空：0.25°，多等压面层 | H50: 🟡 推荐 | I50: NetCDF/GRIB | J50: 开源✅ 下载✅(需注册) 有数据✅ | K50: ERA5：https://cds.climate.copernicus.eu/ | Q50: ⭐ 简单 | S50: 免费(需注册CDS账号) | T50: 延迟5天 | U50: 1940年至今 | V50: 全球
A51: =INDEX(数据源对应的文献以及数据使用方法和条目需求!A:B,MATCH(B51,数据源对应的文献以及数据使用方法和条目需求!B:B,0),1) -> ERA5相关性数据 | B51: AIA-1065 | C51: 使用✅ | D51: CMA-RA中国再分析数据 | E51: 气象与环境 | F51: 气象与环境(高空风速风向-多源验证、整体气象背景场) | G51: 时：3h/6h；空：0.25° | H51: 🟡 推荐 | I51: NetCDF/GRIB | J51: 开源✅ 下载✅(需注册) 有数据✅ | K51: CMA-RA：http://data.cma.cn/；国家气象信息中心 | Q51: ⭐⭐ 中等 | S51: 免费(需注册) | T51: 延迟数天 | U51: 1979年至今 | V51: 中国及周边区域
A52: =INDEX(数据源对应的文献以及数据使用方法和条目需求!A:B,MATCH(B52,数据源对应的文献以及数据使用方法和条目需求!B:B,0),1) -> ERA5相关性数据 | B52: AIA-1083 | C52: 使用✅ | D52: MERRA-2再分析数据 | E52: 气象与环境 | F52: 气象与环境(高空风速风向-多源验证、整体气象背景场) | G52: 时：1h；空：0.5°×0.625° | H52: 🟡 推荐 | I52: NetCDF | J52: 开源✅ 下载✅(需注册) 有数据✅ | K52: NASA MERRA-2：https://disc.gsfc.nasa.gov/ | Q52: ⭐⭐ 中等 | S52: 免费(需注册NASA EarthData) | T52: 延迟数天 | U52: 1980年至今 | V52: 全球
A53: =INDEX(数据源对应的文献以及数据使用方法和条目需求!A:B,MATCH(B53,数据源对应的文献以及数据使用方法和条目需求!B:B,0),1) -> ERA5相关性数据 | B53: AIA-1084 | C53: 使用✅ | D53: NCEP CFSv2/CFSR大气再分析数据 | E53: 气象与环境 | F53: 气象与环境(高空风速风向-多源验证、整体气象背景场) | G53: 时：3h/6h；空：0.5625° | H53: 🟡 推荐 | I53: GRIB/NetCDF | J53: 开源✅ 下载✅(需注册) 有数据✅ | K53: JMA JRA-55：https://jra.kishou.go.jp/JRA-55/ | Q53: ⭐⭐ 中等 | S53: 免费(需注册) | T53: 延迟数天 | U53: 1958年至今 | V53: 全球
A54: =INDEX(数据源对应的文献以及数据使用方法和条目需求!A:B,MATCH(B54,数据源对应的文献以及数据使用方法和条目需求!B:B,0),1) -> ERA5相关性数据 | B54: AIA-1085 | C54: 使用✅ | D54: JMA JRA-55日本再分析数据 | E54: 气象与环境 | F54: 气象与环境(高空风速风向-海上补充、海洋背景场) | G54: 时：3h/6h（支持日 / 月汇总）；空：1.25°（TL319 谱模式≈55km，高斯网格 0.5625°） | H54: 🟢 可选 | I54: GRIB1/NetCDF（可格式转换） | J54: 开源✅ 下载✅ 有数据✅ | K54: NCAR 国际镜像：https://rda.ucar.edu/datasets/ds628.0/；日本气象厅（JMA）官网： https://jra.kishou.go.jp/JRA-55/index_en.html；UCAR气候数据指南：https://climatedataguide.ucar.edu/climate-data/jra-55 | M54: 1. 基础标识信息： TIME（观测时间，UTC）、LATITUDE（纬度，十进制度）、LONGITUDE（经度，十进制度）、LEVEL（垂直气压层 / 地面层，共 60 层）、GRID_RES（网格分辨率，1.25°/0.5625°）； 2. 气象要素： 大气三维变量：HGT（位势高度）、TMP（气温）、UGRD/VGRD（纬向 / 经向风，高空风速风向）、RH（相对湿度）、W（垂直速度）； 地表要素：T2M（2 米气温）、SPFH2M（2 米比湿）、WIND10M（10 米风场）、SLP（海平面气压）、PRES（地表气压）； 海洋 / 通量要素：PRCP（降水率）、EVAP（蒸发率）、SST（海表温度）、RAD（短波 / 长波辐射）； 土壤 / 积雪要素：SOIL_T（土壤温度）、SOIL_M（土壤含水量）、SD（雪深）、SWE（雪水当量） | N54: 1. 无统一数字缺失标记，采用 GRIB1/NetCDF 原生缺失值标识； 2. 全球全域覆盖（90°S~90°N，180°W~180°E），无空间缺失区域； 3. 0 值为有效模拟结果，PRCP=0 表示确认无降水，非缺失； 4. 降水、蒸发等诊断变量无统一缺省值，使用时需评估数据不确定性 | O54: 1. 数据集核心： 发布机构 (日本气象厅 JMA)、数据类型 (第二代全球大气再分析数据)、同化技术 (4D-Var 四维变分同化)、核心模型 (TL319 谱模式 L60 层)、产品序列 (含 JRA-55C/AMIP 配套数据集)； 2. 字段属性： 时间分辨率 (3h/6h 逐时，支持日 / 月汇总)、空间分辨率 (1.25° 经纬度网格 / TL319≈55km/0.5625° 高斯网格)、垂直结构 (60 层，模式顶 0.1hPa)、数据基准 (UTC 时间)； 3. 质量规则： 基于固定版本同化系统回算历史观测，消除模式变更影响； 卫星辐射数据采用 VarBC 变分偏差校正； 每日多频次观测融合，保证数据时空连续性 | P54: 1. 地理特征维度： 全球全域经纬度覆盖、多分辨率网格分布、55km 精细化模拟（重点优化亚太区域）、60 层垂直气压层结构； 2. 气象特征维度： 大气三维要素（温、压、风、湿）、近地表气象要素、海洋背景场要素、地表能量 / 水通量要素、土壤 / 积雪陆面要素、云量 / 臭氧等诊断要素； 3. 时空特征维度： 3h/6h 高分辨率时序、日 / 月汇总时序特征、网格级空间特征、1958 年至今长期连续时序特征、多圈层物理一致时空特征 | Q54: ⭐ 简单 | S54: 免费（科研 / 教育用途，商业使用需遵守 JMA/NCAR 使用条款） | T54: 延迟数天 | U54: 1958 年至今（2024 年起更新终止，替换为 JRA-3Q） | V54: 全球（大气/海洋/陆面，重点精细刻画亚太区域） | W54: 1. 风资源评估中海上高空风速风向补充、海洋背景场分析； 2. 数值天气预报 / 气候模式的初始场设置与边界条件补充； 3. 长期气候变化趋势分析与极端天气事件机理研究； 4. 陆面 - 水文 - 生态模型驱动场，支撑全球 / 区域水循环模拟； 5. 亚太区域大气环流特征分析，弥补海洋数据稀疏区不足； 6. 新能源（风能 / 太阳能）资源评估与潜力分析； 7. 卫星观测资料验证与数值模式模拟性能检验； | X54: 1. JRA-55 为 JMA 第二代全球再分析数据，是 JRA-25 升级版本，含 JRA-55C（仅常规观测）、JRA-55AMIP（无同化）配套产品； 2. 原生数据格式为 WMO GRIB1，NCAR RDA 支持定制子集并转换为 NetCDF 格式； 3. 时间基准为 UTC，水平分辨率核心为 1.25°，TL319 谱模式等效≈55km，垂直方向分 60 层至 0.1hPa； 4. 2024 年 1 月起数据更新终止，官方推荐替换为新一代 JRA-3Q 再分析数据； 5. 科研 / 教育用途免费使用，商业使用需遵守 JMA/NCAR 使用条款，发表成果需规范引用数据源； 6. 降水、蒸发等模式诊断变量存在不确定性，使用时需谨慎评估
A55: =INDEX(数据源对应的文献以及数据使用方法和条目需求!A:B,MATCH(B55,数据源对应的文献以及数据使用方法和条目需求!B:B,0),1) -> ERA5相关性数据 | B55: AIA-1087 | C55: 使用✅ | D55: GLDAS全球陆面数据同化系统数据 | E55: 气象与环境 | F55: 气象与环境(下垫面特征-陆面过程) | G55: 时：3h；空：0.25° | H55: 🟢 可选 | I55: NetCDF | J55: 开源✅ 下载✅(需注册) 有数据✅ | K55: NASA GLDAS：https://disc.gsfc.nasa.gov/ | Q55: ⭐⭐ 中等 | S55: 免费(需注册NASA EarthData) | T55: 延迟数天 | U55: 2000年至今 | V55: 全球陆地
A56: =INDEX(数据源对应的文献以及数据使用方法和条目需求!A:B,MATCH(B56,数据源对应的文献以及数据使用方法和条目需求!B:B,0),1) -> ERA5相关性数据 | B56: AIA-1092 | C56: 使用✅ | D56: ERA5-land陆面再分析数据 | E56: 气象与环境 | F56: 气象与环境(下垫面特征-陆面过程) | G56: 时：1h；空：0.1° | H56: 🟡 推荐 | I56: NetCDF/GRIB | J56: 开源✅ 下载✅(需注册) 有数据✅ | K56: ERA5-land：https://cds.climate.copernicus.eu/ | Q56: ⭐ 简单 | S56: 免费(需注册CDS账号) | T56: 延迟5天 | U56: 1950年至今 | V56: 全球陆地
A57: =INDEX(数据源对应的文献以及数据使用方法和条目需求!A:B,MATCH(B57,数据源对应的文献以及数据使用方法和条目需求!B:B,0),1) -> 再分析数据 | B57: AIA-1095 | C57: 使用✅ | D57: NCEP GFS全球预报历史存档数据 | E57: 气象与环境 + 本体外扩展 | F57: 气象与环境(整体气象背景场)； 本体外扩展(预测不确定性-集合特征) | G57: 时：3h/6h；空：0.25° | H57: 🟡 推荐 | I57: GRIB/NetCDF | J57: 开源✅ 下载✅ 有数据✅ | K57: NCEP GFS历史存档：https://www.ncei.noaa.gov/products/weather-climate-models/numerical-weather-prediction | Q57: ⭐⭐ 中等 | S57: 免费 | T57: 延迟数天 | U57: 近10-20年 | V57: 全球
A58: =INDEX(数据源对应的文献以及数据使用方法和条目需求!A:B,MATCH(B58,数据源对应的文献以及数据使用方法和条目需求!B:B,0),1) -> WRF数据 | B58: AIA-1094 | C58: 使用✅ | D58: NCAR CESM-CMIP5全球偏差校正WRF强迫场数据 | E58: 气象与环境 | F58: 气象与环境(高空风速风向-高分辨率、大气稳定度-TKE/PBL) | G58: 时：1-3h；空：1-5 km | H58: 🟡 推荐 | I58: NetCDF | J58: 模式开源✅ 结果需自跑⚠️ 有数据⚠️(需自行运行或获取) | K58: NCAR CESM：https://www.cesm.ucar.edu/；CMIP5：https://pcmdi.llnl.gov/mips/cmip5/ | Q58: ⭐⭐⭐⭐ 极难 | S58: DS-013-CESM | T58: 自定义(需自行运行) | U58: 自定义(取决于输入数据) | V58: 自定义(取决于配置)
A59: =INDEX(数据源对应的文献以及数据使用方法和条目需求!A:B,MATCH(B59,数据源对应的文献以及数据使用方法和条目需求!B:B,0),1) -> 官方业务全球预报数据 | B59: AIA-1097 | C59: 使用✅ | D59: IFS-HRES官方业务全球预报数据 | E59: 气象与环境 + 本体外扩展 | F59: 气象与环境(整体气象背景场)； 本体外扩展(预测不确定性-集合特征) | G59: 时：逐 3h；空：0.1°(模式水平分辨率约 9km) | H59: 🟡 推荐 | I59: GRIB/NetCDF | J59: 开源❌ 下载⚠️(付费许可) 有数据✅ | K59: ECMWF IFS-HRES：https://data.ecmwf.int/forecasts/ | L59: 已完成数据下载（阿里云） | M59: 1. 基础标识信息： MODE（模式类型：OPER/SCDA）、RUN_UTC（起报时次，00/06/12/18 UTC）、FCST_HOUR（预报时效，h）、LAT（纬度）、LON（经度）； 2. 气象要素： TEMP（温度）、RH/SPFH（湿度）、PRES/SLP（气压）、UGRD/VGRD（风场）、PRCP（降水）等标准气象变量 | N59: 1. 无统一数值缺失标记，采用 GRIB/NetCDF 原生缺失值； 2. 超出预报时效（OPER>240h、SCDA>144h）为缺失； 3. 0 值为有效预报，PRCP=0 表示无降水，非缺失 | O59: 1. 数据集核心： 发布机构（ECMWF欧洲中期天气预报中心）、数据类型（确定性高分辨率预报 HRES）、模式体系（OPER/SCDA）； 2. 字段属性： 空间分辨率≈9km/0.1°、时间分辨率逐 3h、日更 4 次（00/06/12/18 UTC）、 OPER 预报时效 0–240h（或更长）、SCDA 0–144h； 3. 质量规则： OPER 长截断（等待全球观测资料齐整后运算），观测资料完整度极高；SCDA 短截断（快速锁定观测场运算），观测完整度较高，专为 06Z/18Z 时次设计 | P59: 1. 地理特征维度： 全球全域覆盖、0.1°等分辨率经纬度网格、水平约 9km 精细化网格； 2. 气象特征维度： 温湿要素（气温、湿度）、气压要素（海平面气压 / 站点气压）、风场要素（纬向风、经向风、风速 / 风向）、降水要素（累计降水量）等全气象背景场变量； 3. 时空特征维度： 逐 3h 高分辨率时序、9km 网格级空间、每日 4 次滚动更新、多预报时效演变特征、OPER/SCDA 双模式差异化时间特征 4 次滚动更新 | Q59: ⭐⭐ 中等 | S59: 付费 (商业使用需购买许可证，非商业科研可申请专属权限) | T59: 延迟数小时 | U59: 近10-15年 | V59: 全球 | W59: 1.风资源评估中气象背景场分析与短期风场预报； 2.风场预测模型实时边界条件更新与精度优化； 3.全球 / 区域气象场演变分析与风资源关联研究； 4.临近天气调整、电力 / 航空应急调度支撑； 5.气象背景场与测风数据融合校正； 6.极端天气预判与风场影响分析。 | X59: 1.IFS-HRES 为 ECMWF 确定性高分辨率大气预报数据，包含 OPER/SCDA 双模式体系； 2.数据格式为 GRIB/NetCDF，按预报时次与时效存储，阿里云存储路径：/data/hdfs/tmp/hres/ifs/0p25/oper； 3.时间基准为 UTC，OPER 为旗舰业务产品（最高达 240h / 更长预报时效），SCDA 为短临快报产品（0-144h 预报时效）； 4.OPER 长截断，计算优先级最高，00Z/12Z 发布；SCDA 短截断，计算优先级高，06Z/18Z 发布； 5.商业使用需购买 ECMWF 许可证，遵循官方数据使用协议。 | Y59: 阿里云：/data/hdfs/tmp/hres/ifs/0p25/oper
A60: =INDEX(数据源对应的文献以及数据使用方法和条目需求!A:B,MATCH(B60,数据源对应的文献以及数据使用方法和条目需求!B:B,0),1) -> 官方业务全球预报数据 | B60: AIA-1098 | C60: 使用✅ | D60: GFS官方业务全球预报数据 | E60: 气象与环境；相邻/上游测风站数据 | F60: 气象与环境(数据源类型-实测值)； 相邻/上游测风站数据(历史风速) | G60: 时：1h；空：0.1° | H60: 🟡 推荐 | I60: GRIB/NetCDF | J60: 开源✅ 下载✅ 有数据✅ | K60: NCEP GFS：https://www.ncei.noaa.gov/products/weather-climate-models/global-forecast-system | Q60: ⭐⭐ 中等 | S60: 免费 | T60: 延迟数分钟 - 1 小时 | U60: 近40年 | V60: 全球

Sheet 数据源对应的文献以及数据使用方法和条目需求
A1: 数据类型分类 | B1: 编号 | C1: 数据名称 | D1: 分辨率（时/空） | E1: 数据使用 | F1: 对应论文与数据量需求
A2: ERA5相关性数据 | B2: AIA-1064 | C2: 气象站实测ISD(风速/风向/温度/气压/湿度) | D2: 时：1h/3h；空：站点级 | E2: 微调: 作为训练标签，优化模型在站点处的预测。 | F2: [1] (801769条, +DS-013 801769条, +DS-001 1份静态数据, +DS-002 1份静态数据, +DS-001, GPS 1份静态数据, +工程计算 801769条) [3] (10955条） [5] (8764条) [7] (1038条) [8] (8760条) [10] (52560条） [11](210432条, +DS-016 1315200条, +GPS坐标 1份静态数据) [15] (1440条, +DS-013 1440条） [16] (34560条) [17] (210240条) [18] (744条) [19] (1492条) [20] (8760条) [21] (1201条) [22] (12120条) [23] (7776条) [24] (6539条) [25] (2908条) [26] (144条, +DS-005 36条, +DS-019 896条, +DS-014b 1份静态数据) [27] (5000条) [28] (708条, +DS-006 744条, +DS-013 744条, +DS-017 721条, +DS-008 3份静态剖面数据) [29] (1458条) [30] (8372条) {34} (108条, +AIA-1057 4条, +KG-12 1份静态数据, +KG-15 1份静态数据, +NEW-001 1份静态数据, +NEW-003 1份静态数据, +NEW-004 12条)) {39} (676条) {42} (60192条) {43} (3137条) {45} (2928条, +KG-10 1份静态数据, +KG-11 1份静态数据 {50} (52560条, +AIA-1098 365条, +AIA-1094 52560条, +KG-10 1份静态数据) {51} (2592条) {52} (8759条) {53} (70080条, +KG-24 1份静态数据, +KG-25 70080条) {56} (6696条, +KG-25 6696条) {57} (60条, +KG-17 60条) {58} (26280条) {59} (365条) {60} (576条, +AIA-1095 48条, +NEW-010 144条, +KG-16 576条) {61} (17520条) {63} (4464条) {64} (720条) {67} (8760条) {70} (2400~2800条) {72} (11802条) {77} (11946240条, +KG-12 1份静态数据, +AIA-1056 1份静态数据, +AIA-1094 17246040条) {78} (11640条) {83} (26280条, +AIA-1094 26280条) {86} (1208880条, +AIA-1083 297840条) {93} (87600条, +AIA-1064 105120条) {95} (2390条, +AIA-1064 2390条) {96} (1000条, +AIA-1064 1000条) {98} (856080条, +AIA-1064 1048800条) {99} (33216条, +AIA-1064 33216条) {102} (2600条, +AIA-1064 2600条) {117} (35040条, +AIA-1057 35040条, +AIA-1097 8760条) {123} (262800条, +AIA-1056 262800条, +KG-25 262800条) {127} (280320条, +AIA-1057 560640条)
E3: 后处理: 用模型预测与实测值的差作为目标，训练校正器。 | F3: [15] (1440条, +DS-013 1440条） {38} (103512条, +NEW-001 103512条) {92} (13870条, +AIA-1095 13870条)
E4: 增加输入通道 | F4: {93} (105120条, +AIA-1064 87600条) {95} (2390条, +AIA-1064 2390条) {96} (1000条, +AIA-1064 1000条) {98} (1048800条, +AIA-1064 856080条) {99} (33216条, +AIA-1064 33216条) {102} (2600条, +AIA-1064 2600条)
E5: 预测精度对比基线 | F5: {116} (8760条, +AIA-1094 78840条, +AIA-1097 8760条, +KG-10 1份静态数据) {124} (3600条, +AIA-1094 720条, +AIA-1056 60条, +AIA-1057 60条, +KG-10 1份静态数据, +KG-12 1份静态数据) {126} (27864条, +AIA-1072 18576条, +AIA-1094 46440条, +AIA-1056 46440条, +KG-10 1份静态数据, +KG-11 1份静态数据)
E6: 计算大气稳定度的底层数据 | F6: {121} (17520条, +KG-9 26280条, +AIA-1056 26280条, +AIA-1057 26280条, +AIA-1094 26280条)
A7: 官方业务全球预报数据 | B7: AIA-1097 | C7: <0.1°气象同化数据(6通道) | D7: 时：1-3h；空：0.1°(~10 km) | E7: 增加输入通道: 插值到0.25°后与ERA5通道拼接。 | F7: {97} (702条, +AIA-1056 702条)
E8: 特征融合: 设计独立编码器，提取高分辨率特征并与主干融合。
E9: 条件注入 | F9: {116} (8760条, +AIA-1094 78840条, +AIA-1064 8760条, +KG-10 1份静态数据) {120} (288条, +AIA-1056 144条, +AIA-1088 12条)
E10: 微调 | F10: {128} (11680条, +AIA-1056 57000条, +AIA-1057 57000条, +KG-25 68680条)
A11: WRF数据 | B11: AIA-1094 | C11: 区域WRF/COSMO等模式输出 | D11: 时：1-3h；空：1-5 km | E11: 增加输入通道: 将WRF预测作为额外通道。 | F11: [1] (801769条, +DS-009, DS-016 801769条, +DS-001 1份静态数据, +DS-002 1份静态数据, +DS-001, GPS 1份静态数据, +工程计算 801769条) [14] (40704条, +DS-018 40704条) [15] (1440条, +DS-009 1440条) [28] (744条, +DS-006 744条, +DS-017 721条, +DS-015 708条, +DS-008 3份静态剖面数据) [31] (105120条, +KG-16 105120条, +KG-17 105120条) {83} (26280条, +AIA-1064 26280条)
E12: 特征融合: WRF特征作为独立分支。
E13: 条件注入: 若WRF提供模式不确定性，可作为条件注入。 | F13: [26](36条, +DS-019 896条, +DS-009 144条, +DS-014b 1份静态数据)
E14: 提取高分辨率预报风速结合功率曲线，用于评估单一确定性模型的坡道事件预测能力 | F14: {41} (6条, +KG-17 105120条, +NEW-001 72条, +NEW-002 17520条)
E15: 后处理: 校正模型输出。 | F15: {75} (35040条, +AIA-1095 35040条, +KG-16 35040条, +KG-10 1份静态数据, +KG-11 1份静态数据, +KG-15 1份静态数据)
E16: 预测精度对比基线 | F16: {115} (7300条, +KG-9 327767条, +KG-6 52560条, +AIA-1056 52560条) {121} (26280条, +KG-9 26280条, +AIA-1056 26280条, +AIA-1057 26280条, +AIA-1064 17520条)
E17: 核心预测变量 | F17: {116} (78840条, +AIA-1097 8760条, +AIA-1064 8760条, +KG-10 1份静态数据) {118} (175200条, +AIA-1056 175200条, +AIA-1057 175200条, +AIA-1083 8760条, +KG-25 175200条) {124} (720条, +AIA-1064 3600条, +AIA-1056 60条, +AIA-1057 60条, +KG-10 1份静态数据, +KG-12 1份静态数据) {126} (46440条, +AIA-1072 18576条, +AIA-1064 27864条, +AIA-1056 46440条, +KG-10 1份静态数据, +KG-11 1份静态数据)
A18: ERA5相关性数据 | B18: KG-6 | C18: 卫星散射计海面风场 | D18: 时：卫星过境；空：12.5-25 km / 500m-1km | E18: 增加输入通道: 插值后作为海洋表面风输入。
E19: 特征融合: 提取海面风特征，与陆地风特征融合。 [作为空间风场分布的验证标签，用于定性评估各参数化方案模拟的尾流影响范围] | F19: [26](1份静态数据, +DS-005 36条, +DS-019 896条, +DS-009 144条)
E20: 作为输入变量 | F20: {115} (52560条, +KG-9 327767条, +AIA-1056 52560条, +AIA-1094 7300条)
A21: 遥感观测数据 | B21: KG-7 | C21: 卫星云图/水汽图 | D21: 时：10-15min；空：2-8 km | E21: 设计CNN分支处理图像，提取云量、水汽等特征，与主干融合。
A22: 遥感观测数据 | B22: KG-8 | C22: 气象雷达反射率/径向速度 | D22: 时：~6min 体扫；空：~1 km，多高度层 | E22: 设计CNN/RNN分支处理雷达数据立方体，提取强对流特征。
A23: 遥感观测数据 | B23: KG-9 | C23: 激光雷达/声雷达测风剖面 | D23: 时：1s-10min；空：垂直10-300m分层 | E23: 将垂直风廓线作为3D特征输入，或提取关键层次特征与主干融合。 | F23: [28] (721条, +DS-006 744条, +DS-013 744条, +DS-015 708条, +DS-008 3份静态剖面数据)
E24: [模型训练与测试真值] | F24: {115} (327767条, +KG-6 52560条, +AIA-1056 52560条, +AIA-1094 7300条) {119} (8496条, +AIA-1056 1416条, +AIA-1057 1416条, +AIA-1086 59条, +AIA-1072 1416条, +AIA-1070 23条)
E25: 模型评估实测真值 | F25: {121} (26280条, +AIA-1056 26280条, +AIA-1057 26280条, +AIA-1094 26280条, +AIA-1064 17520条) {125} (105120条, +AIA-1072 105120条, +AIA-1094 105120条, +AIA-1056 8760条, +AIA-1057 8760条, +KG-25 105120条, +KG-10 1份静态数据, +KG-12 1份静态数据)
A26: 地理与地表信息数据 | B26: KG-10 | C26: 数字高程模型(DEM) | D26: 时：静态；空：30/90 m | E26: 作为静态通道直接输入模型。 | F26: [1] (1份静态数据, +DS-009, DS-016 801769条, +DS-013 801769条, +DS-002 1份静态数据, +DS-001, GPS 1份静态数据, +工程计算 801769条) {45} (1份静态数据, +KG-11 1份静态数据, +AIA-1064 2928条 {48} (1份静态数据, +AIA-1098 2924条, +AIA-1094 2385984条, +KG-16 2385984条)
E27: 作为边界特征输入 | F27: {46} (1份静态数据, +AIA-1098 365条, +AIA-1094 35040条, +KG-16 35040条, +KG-17 35040条) {50} (1份静态数据, +AIA-1098 365条, +AIA-1094 52560条, +NEW-001 52560条) {75} (1份静态数据, +AIA-1095 35040条, +AIA-1094 35040条, +KG-16 35040条, +KG-11 1份静态数据, +KG-15 1份静态数据)
E28: 用于构建CFD流体动力学仿真的38km×25km三维复杂地形计算域模型 | F28: {71} (1份静态数据, +KG-12 1份静态数据, +011 3000条)
E29: 特征融合 | F29: {116} (1份静态数据, +AIA-1094 78840条, +AIA-1097 8760条, +AIA-1064 8760条) {124} (1份静态数据, +AIA-1094 720条, +AIA-1064 3600条, +AIA-1056 60条, +AIA-1057 60条, +KG-12 1份静态数据) {125} (1份静态数据, +KG-9 105120条, +AIA-1072 105120条, +AIA-1094 105120条, +AIA-1056 8760条, +AIA-1057 8760条, +KG-25 105120条, +KG-12 1份静态数据) {126} (1份静态数据, +AIA-1072 18576条, +AIA-1064 27864条, +AIA-1094 46440条, +AIA-1056 46440条, +KG-11 1份静态数据)
A30: 地理与地表信息数据 | B30: KG-11 | C30: 地表粗糙度长度 | D30: 时：年度；空：10-30 m | E30: 作为静态通道直接输入模型。 | F30: {45} (1份静态数据, +KG-10 1份静态数据, +AIA-1064 2928条, {75} (1份静态数据, +AIA-1095 35040条, +AIA-1094 35040条, +KG-16 35040条, +KG-10 1份静态数据, +KG-15 1份静态数据)
E31: 特征融合 | F31: {126} (1份静态数据, +AIA-1072 18576条, +AIA-1064 27864条, +AIA-1094 46440条, +AIA-1056 46440条, +KG-10 1份静态数据)
A32: 地理与地表信息数据 | B32: KG-12 | C32: 土地利用/土地覆盖(LULC) | D32: 时：年度；空：10-30 m | E32: 增加输入通道: One-hot编码或类别索引作为输入。 | F32: [1] (1份静态数据, +DS-009, DS-016 801769条, +DS-013 801769条, +DS-001 1份静态数据, +DS-001, GPS 1份静态数据, +工程计算 801769条)
E33: 条件注入: 若LULC用于定义区域类型，可作为条件。
E34: 作为WRF中尺度模型的地表静态物理特征输入 | F34: {34} (1份静态数据, +AIA-1057 4条, +KG-15 1份静态数据, +NEW-001 1份静态数据, +NEW-002 108条, +NEW-003 1份静态数据, +NEW-004 12条) {71} (1份静态数据, +KG-10 1份静态数据, +011 3000条) {77} (1份静态数据, +AIA-1056 1份静态数据, +AIA-1094 17246040条, +AIA-1064 11946240条)
E35: 特征融合 | F35: {124} (1份静态数据, +AIA-1094 720条, +AIA-1064 3600条, +AIA-1056 60条, +AIA-1057 60条, +KG-10 1份静态数据) {125} (1份静态数据, +KG-9 105120条, +AIA-1072 105120条, +AIA-1094 105120条, +AIA-1056 8760条, +AIA-1057 8760条, +KG-25 105120条, +KG-10 1份静态数据)
A36: 地理与地表信息数据 | B36: KG-13 | C36: 植被指数(NDVI) | D36: 时：16天/或月度；空：250m/10m | E36: 作为动态通道（随时间变化）输入模型。
A37: 地理与地表信息数据 | B37: KG-14 | C37: 建筑物高度与密度数据 | D37: 时：静态；空：10-100 m | E37: 作为高分辨率静态通道输入模型。
A38: 风电场特定数据 | B38: KG-15 | C38: 风机位置与布局图 | D38: 时：静态；空：单风机级 | E38: 增加输入通道: 作为二值掩码或距离图输入。 | F38: [26](896条, +DS-005 36条, +DS-009 144条, +DS-014b 1份静态数据) {61} (17520条)
E39: 图神经网络: 将风机作为图节点。
E40: 用于提供WRF风电场参数化方案(Fitch和EWP)的机位与气动特性设置 | F40: {34} (1份静态数据, +AIA-1057 4条, +KG-12 1份静态数据, +NEW-001 1份静态数据, +NEW-002 108条, +NEW-003 1份静态数据, +NEW-004 12条)
E41: 特征融合: 提取尾流特征进行融合。 | F41: {75} (1份静态数据, +AIA-1095 35040条, +AIA-1094 35040条, +KG-16 35040条, +KG-10 1份静态数据, +KG-11 1份静态数据)
A42: ERA5相关性数据 | B42: KG-16 | C42: 风机SCADA历史数据 | D42: 时：10min/1s；空：单风机 | E42: 微调: 作为轮毂高度风速标签。 | F42: [6](2160条) [12] (105120条) {54} (129600条) {55} (9000条) {82} (49104条, +AIA-1095 308条, +AIA-1088 528条) {84} (10920条) {95} (2448条, +KG-16 2448条) {96} (1000条, +KG-16 1000条) {101} (39312条, +KG-16 39312条)
E43: 后处理: 校正模型输出。 | F43: {46} (35040条, +AIA-1098 365条, +AIA-1094 35040条, +KG-10 1份静态数据, +KG-17 35040条) {47} (1221条) {48} (2385984条, +AIA-1098 2924条, +AIA-1094 2385984条, +KG-10 1份静态数据) {49} (8640条) {60} (576条, +AIA-1095 48条, +NEW-010 144条, +AIA-1064 576条) {66} (6912条) {68} (7308条) {69} (6000条) {73} (16000条) {74} (1200条) {75} (35040条, +AIA-1095 35040条, +AIA-1094 35040条, +KG-10 1份静态数据, +KG-11 1份静态数据, +KG-15 1份静态数据)
E44: 图神经网络: 作为节点观测值。
E45: 经SSA和EEMD二次分解去噪后，提取历史滞后项作为预测模型的基础输入与目标标签 | F45: {32} (80640条, +KG-17 80640条) {36} (8640条) {37} (63408条) {40} (6912条)
E46: 作为LightGBM预测模型的核心输入特征，同时作为风速预测任务的真实目标标签 | F46: {33} (52560条, +KG-17 52560条)
E47: 经小波变换(WT)去噪提取近似信号并结合自相关分析后，提取特定的风速滞后项作为SVM预测模型的核心输入与目标标签 | F47: {44} (1440条, +NEW-001 1440条)
E48: 增加输入通道 | F48: {79} (6000条) {87} (17856条) {88} (8760条) {89} (720条) {90} (144条) {95} (2448条, +KG-16 2448条) {96} (1000条, +KG-16 1000条) {101} (39312条, +KG-16 39312条)
A49: ERA5相关性数据 | B49: KG-17 | C49: 风机功率输出数据 | D49: 时：10-15min；空：单风机 | E49: 后处理: 建立风速-功率关系，校正预测。 | F49: [14] (40704条, +DS-013 40704条, +DS-018 40704条) {46} (35040条, +AIA-1098 365条, +AIA-1094 35040条, +KG-10 1份静态数据, +KG-16 35040条) {57} (60条, +AIA-1064 60条)
E50: 条件注入: 若功率反映风况，可作为条件。
E51: 作为LightGBM风机发电功率预测任务的真实输出标签 | F51: {33} (52560条, +KG-16 52560条)
E52: 作为定量评估区域风电坡道事件的真实基准与验证气象模式预测能力的标签 | F52: {41} (105120条, +AIA-1094 6条, +NEW-001 72条, +NEW-002 17520条)
A53: ERA5相关性数据 | B53: KG-18 | C53: 风机尾流模型输出 | D53: 时：1h；空：1-5 km 网格/场内网格 | E53: 增加输入通道: 尾流效应场作为额外输入。 | F53: {91} (127800条, +AIA-1094 4500条)
E54: 特征融合: 提取尾流特征进行融合。
A55: ERA5相关性数据 | B55: KG-19 | C55: 边界层高度数据 | D55: 时：1h；空：0.25° | E55: 增加输入通道 : 作为关键垂直尺度参数输入模型。
A56: 大气状态与派生指数数据 | B56: KG-20 | C56: 湍流动能(TKE) | D56: 时：1-3h；空：0.25°(ERA5) 或1-5km(WRF) | E56: 增加输入通道 : 作为表征湍流强度的变量输入模型。
A57: ERA5相关性数据 | B57: KG-21 | C57: 垂直风切变指数 | D57: 时：10min(测风塔)/1h(ERA5)；空：塔点/网格 | E57: 增加输入通道 : 作为关键动力参数输入模型。
A58: ERA5相关性数据 | B58: KG-22 | C58: 大气稳定度指数 | D58: 时：1h(ERA5 输入)/12h(探空)；空：网格/探空站 | E58: 增加输入通道: 作为物理参数输入。
E59: 条件注入: 若用于区分稳定/不稳定状态，可作为条件
A60: ERA5相关性数据 | B60: KG-23 | C60: 对流可用位能(CAPE) | D60: 时：1h；空：0.25° | E60: 增加输入通道 : 作为对流潜势的输入。
A61: 时空上下文特征数据 | B61: KG-24 | C61: 经纬度与海拔 | D61: 时：静态；空：站点/风机级 | E61: 增加输入通道: 作为静态地理特征。 | F61: [1] (1份静态数据, +DS-009, DS-016 801769条, +DS-013 801769条, +DS-001 1份静态数据, +DS-002 1份静态数据, +工程计算 801769条) {53} (1份静态数据, +AIA-1064 70080条, +KG-25 70080条)
E62: 条件注入: 若用于区域划分，可作为条件。 | F62: [11] (1份静态数据, +DS-009 210432条, +DS-016 1315200条)
A63: 时空上下文特征数据 | B63: KG-25 | C63: 时间特征（年、月、日、时、日序） | D63: 时：与原始序列一致；空：同站点/风机 | E63: 增加输入通道 : 作为周期性编码（如sin/cos）输入。 | F63: [1] (801769条, +DS-009, DS-016 801769条, +DS-013 801769条, +DS-001 1份静态数据, +DS-002 1份静态数据, +DS-001, GPS 1份静态数据) {53} (70080条, +AIA-1064 70080条, +KG-24 1份静态数据) {56} (6696条, +AIA-1064 6696条)
E64: 条件注入 : 作为时间条件注入模型。
E65: 特征融合 | F65: {118} (175200条, +AIA-1094 175200条, +AIA-1056 175200条, +AIA-1057 175200条, +AIA-1083 8760条) {123} (262800条, +AIA-1064 262800条, +AIA-1056 262800条) {125} (105120条, +KG-9 105120条, +AIA-1072 105120条, +AIA-1094 105120条, +AIA-1056 8760条, +AIA-1057 8760条, +KG-10 1份静态数据, +KG-12 1份静态数据) {128} (68680条, +AIA-1056 57000条, +AIA-1057 57000条, +AIA-1097 11680条)
A66: ERA5相关性数据 | B66: KG-26 | C66: 天气形势分型 | D66: 时：1h(随NWP)；空：大尺度场/站点映射 | E66: 条件注入 : 将分型结果（one-hot或索引）作为条件向量注入模型
A67: 历史与误差信息数据 | B67: KG-27 | C67: 基础模型/历史预测误差 | D67: 时：按统计周期/或逐时；空：场站/风机级 | E67: 增加输入通道: 将过去N小时的误差序列作为输入通道。
E68: 特征融合: 提取误差特征进行融合。
A69: ERA5相关性数据 | B69: KG-28 | C69: 多模式集合预报 | D69: 时：1h(典型)；空：0.25°/0.1° 等 | E69: 增加输入通道: 将各模式的预测作为一组通道。 | F69: [28] (744条, +DS-013 744条, +DS-017 721条, +DS-015 708条, +DS-008 3份静态剖面数据)
E70: 特征融合: 提取集合统计特征（均值、方差）进行融合 | F70: [9](496条, +DS-001 1份静态数据, +DS-013 1488条, +DS-018 525888条)
E71: 条件注入:可作为边界条件输入 | F71: [28] (744条, +DS-013 744条, +DS-017 721条, +DS-015 708条, +DS-008 3份静态剖面数据)
A72: ERA5相关性数据 | B72: AIA-1090 | C72: NOAA GSOD全球逐日汇总数据 | D72: 时：日；空：站点级
A73: ERA5相关性数据 | B73: AIA-1091 | C73: 中国地面气象观测数据(CMA) | D73: 时：1h/3h；空：站点级 | E73: 作为唯一时间序列输入驱动EMD与LMD双重模态分解、奇偶序列分离提取，以及由PSO优化的SVM与SCNs进行多模型融合多步预测 | F73: {76} (576条)
A74: ERA5相关性数据 | B74: AIA-1088 | C74: 全球高空探空数据(IGRA，NOAA) | D74: 时：12h；空：站点级，多高度层 | E74: 后处理: 校正模型输出。 | F74: {82} (528条, +AIA-1095 308条, +KG-16 49104条)
A75: ERA5相关性数据 | E75: 模型评估实测真值 | F75: {120} (12条, +AIA-1097 288条, +AIA-1056 144条)
A76: ERA5相关性数据 | B76: AIA-1089 | C76: 中国高空探空数据(CMA) | D76: 时：12h；空：站点级，多高度层
A77: ERA5相关性数据 | B77: AIA-1072 | C77: NOAA NDBC海洋浮标网数据 | D77: 时：1h；空：浮标站点 | E77: 模型评估实测真值 | F77: {119} (1416条, +AIA-1056 1416条, +AIA-1057 1416条, +AIA-1086 59条, +KG-9 8496条, +AIA-1070 23条) {126} (18576条, +AIA-1064 27864条, +AIA-1094 46440条, +AIA-1056 46440条, +KG-10 1份静态数据, +KG-11 1份静态数据)
E78: 特征融合 | F78: {125} (105120条, +KG-9 105120条, +AIA-1094 105120条, +AIA-1056 8760条, +AIA-1057 8760条, +KG-25 105120条, +KG-10 1份静态数据, +KG-12 1份静态数据)
A79: ERA5相关性数据 | B79: AIA-1073 | C79: ICOADS全球海洋综合数据集(全球船舶+浮标综合观测) | D79: 时：3h/6h；空：站点级
A80: 海洋气象数据 | B80: AIA-1074 | C80: ORAS5海洋再分析数据 | D80: 时：1天；空：0.25°
A81: ERA5相关性数据 | B81: AIA-1075 | C81: CFSR/CFSv2海洋再分析数据(NCEP海洋+大气再分析) | D81: 时：6h；空：0.5°
A82: ERA5相关性数据 | B82: AIA-1066 | C82: NEXRAD天气雷达数据 | D82: 时：~5-6min 体扫；空：~1 km，多高度层
A83: ERA5相关性数据 | B83: AIA-1067 | C83: TDWR终端多普勒天气雷达数据(机场) | D83: 时：~1min 体扫；空：~0.5 km，多高度层
A84: ERA5相关性数据 | B84: AIA-1068 | C84: GridRad网格化雷达数据 | D84: 时：5min；空：0.02°×0.02° (~2km)，多高度层
A85: ERA5相关性数据 | B85: AIA-1069 | C85: 中国气象雷达拼图数据 | D85: 时：6-10min；空：1-2 km，多高度层
A86: 天气雷达数据 | B86: AIA-1070 | C86: NASA机载雷达数据 | D86: 时：秒级-分钟级；空：~100m-1 km，多高度层 | E86: 模型评估实测真值 | F86: {119} (23条, +AIA-1056 1416条, +AIA-1057 1416条, +AIA-1086 59条, +KG-9 8496条, +AIA-1072 1416条)
A87: 天气雷达数据 | B87: AIA-1071 | C87: 欧洲雷达数据(OPERA/EUMETNET) | D87: 时：5-15min；空：1-2 km，多高度层
A88: ERA5相关性数据 | B88: AIA-1076 | C88: 中国风云系列气象卫星数据 | D88: 时：5-15min；空：0.5-4 km
A89: ERA5相关性数据 | B89: AIA-1077 | C89: NASA MODIS卫星数据 | D89: 时：1-2天；空：250m-1 km
A90: ERA5相关性数据 | B90: AIA-1078 | C90: ESA Sentinel系列卫星数据 | D90: 时：1-5天；空：10m-1 km | E90: 提取海面风速与风向，作为GIS风能制图及下游ANFIS-BAT预测模型的时序输入特征与目标标签 | F90: {35} (54条, +NEW-001 486条)
A91: ERA5相关性数据 | B91: AIA-1079 | C91: NOAA GOES+JPSS卫星数据 | D91: 时：5-15min；空：0.5-2 km
A92: ERA5相关性数据 | B92: AIA-1080 | C92: EUMETSAT METEOSAT+MetOp卫星数据 | D92: 时：15min；空：1-3 km
A93: ERA5相关性数据 | B93: AIA-1081 | C93: 日本Himawari-8/9卫星数据 | D93: 时：10min；空：0.5-2 km
A94: ERA5相关性数据 | B94: AIA-1082 | C94: NASA CloudSat & CALIPSO卫星数据 | D94: 时：卫星过境；空：1.4km×1.7km，多高度层
A95: ERA5相关性数据 | B95: AIA-1056 | C95: ERA5单层再分析数据 | D95: 时：1h；空：0.25° | E95: 后处理 | F95: {77} (1份静态数据, +KG-12 1份静态数据, +AIA-1094 17246040条, +AIA-1064 11946240条) {97} (702条, +AIA-1097 702条)
E96: 特征融合 | F96: {115} (52560条, +KG-9 327767条, +KG-6 52560条, +AIA-1094 7300条) {123} (262800条, +AIA-1064 262800条, +KG-25 262800条)
E97: 条件注入 | F97: {118} (175200条, +AIA-1094 175200条, +AIA-1057 175200条, +AIA-1083 8760条, +KG-25 175200条) {119} (1416条, +AIA-1057 1416条, +AIA-1086 59条, +KG-9 8496条, +AIA-1072 1416条, +AIA-1070 23条) {124} (60条, +AIA-1094 720条, +AIA-1064 3600条, +AIA-1057 60条, +KG-10 1份静态数据, +KG-12 1份静态数据) {125} (8760条, +KG-9 105120条, +AIA-1072 105120条, +AIA-1094 105120条, +AIA-1057 8760条, +KG-25 105120条, +KG-10 1份静态数据, +KG-12 1份静态数据) {126} (46440条, +AIA-1072 18576条, +AIA-1064 27864条, +AIA-1094 46440条, +KG-10 1份静态数据, +KG-11 1份静态数据)
E98: 预测精度对比基准 | F98: {120} (144条, +AIA-1097 288条, +AIA-1088 12条)
E99: 核心预测变量 | F99: {121} (26280条, +KG-9 26280条, +AIA-1057 26280条, +AIA-1094 26280条, +AIA-1064 17520条) {128} (57000条, +AIA-1057 57000条, +AIA-1097 11680条, +KG-25 68680条)
A100: ERA5相关性数据 | B100: AIA-1057 | C100: ERA5等压面再分析数据 | D100: 时：1h；空：0.25°，多等压面层 | E100: 条件注入 | F100: {34} (4条, +KG-12 1份静态数据, +KG-15 1份静态数据, +NEW-001 1份静态数据, +NEW-002 108条, +NEW-003 1份静态数据, +NEW-004 12条) {118} (175200条, +AIA-1094 175200条, +AIA-1056 175200条, +AIA-1083 8760条, +KG-25 175200条) {119} (1416条, +AIA-1056 1416条, +AIA-1086 59条, +KG-9 8496条, +AIA-1072 1416条, +AIA-1070 23条) {124} (60条, +AIA-1094 720条, +AIA-1064 3600条, +AIA-1056 60条, +KG-10 1份静态数据, +KG-12 1份静态数据) {125} (8760条, +KG-9 105120条, +AIA-1072 105120条, +AIA-1094 105120条, +AIA-1056 8760条, +KG-25 105120条, +KG-10 1份静态数据, +KG-12 1份静态数据)
...

Sheet 气象站(舟山定海)数据字段
A1: 字段名 | B1: 物理量 | C1: 官方定义 | D1: 通俗解释 | E1: 示例值 | F1: 数据类型 | G1: 单位
A2: col_0 | B2: 原始 ISD 记录行 | C2: 由 NOAA NCEI 发布的固定宽度 Integrated Surface Dataset (ISD) 记录，包含多个编码组（类似 SYNOP 的分节），用于描述地面气象观测。 | D2: 原始的 NOAA ISD 文本记录，一整行未拆分的观测报文，里面按固定位置和代码组包含站号、时间、温度、气压、风、云等多种要素的编码值。通常只在需要重新解码或溯源时使用。 | E2: 0260584770999992024010100004+30033+122117FM-12+003799999V0203201N001019999999N007000199+00581+00111103041ADDAA106000091AA212000091AA324000091AY101021AY201021KA1120M+01131KA2120N+00431MA1999999102581MD1210181+9999MW1051OD139900801999REMSYN12458477 | F2: 字符串
A3: col_1 | B3: 解码代码组 1（站点/报文元信息相关） | C3: 从原始 ISD/SYNOP 风格报文中解析出的第 1 个中间代码组，其具体物理含义依 WMO 306 号代码表及站点元数据而定。 | D3: 从原始报文中拆出来的第 1 个代码组，多用于站点编号、报文类型或质量控制等，中间解析结果，一般不直接作为物理量分析。 | E3: 04957 | F3: 字符串
A4: col_2 | B4: 解码代码组 2（报文分段/质量标志相关） | C4: 依据 WMO 地面观测编码规则，从报文中拆分得到的第 2 个中间代码组，通常包含报文分段标识或质量标志等信息。 | D4: 从报文中拆出的第 2 个代码组，通常和报文分段或质量标志等有关，属于编码格式内部字段。 | E4: /3201 | F4: 字符串
A5: col_3 | B5: 解码代码组 3（温度相关） | C5: 根据 WMO 代码表，从报文中的气温或相关要素编码解出的一组中间数值，其具体物理含义取决于完整解码实现。 | D5: 与气温或相关要素有关的解码数值代码组，需结合完整 WMO/SYNOP 解码规则才能得到具体物理量（例如 1 位或 2 位表示符号、后几位表示十分之一度等）。 | E5: 10058.0 | F5: 字符串
A6: col_4 | B6: 解码代码组 4（露点/湿度相关） | C6: 可能与露点温度或湿度指标有关的中间数值代码组，来源于地面报文的相应字段。 | D6: 可能与露点温度或湿度指示有关的代码组，中间结果，尚未转换为直接物理单位。 | E6: 20011.0 | F6: 字符串
A7: col_5 | B7: 解码代码组 5（气压相关） | C7: 很可能对应本站或海平面气压的编码形式，经过初步解码后得到的中间数值组。 | D7: 可能与本站气压或海平面气压编码有关的代码组，中间解析值。 | E7: 30258.0 | F7: 字符串
A8: col_6 | B8: 解码代码组 6（气压变化/高度表设定相关） | C8: 从报文中与气压变化趋势或高度表设定有关的部分解出的一组中间数值。 | D8: 可能表示气压变化趋势或配平气压设置等的代码组，需要结合完整代码表才能转换为物理量。 | E8: 40304.0 | F8: 字符串
A9: col_7 | B9: 解码代码组 7（降水/天气相关） | C9: 通常用于表示降水量、降水时段或现在/过去天气现象的 WMO 编码字段，经解码后的中间数值组。 | D9: 常用于表示降水量、降水时段或现在/过去天气现象等的代码组，中间解析值。 | E9: 52018.0 | F9: 字符串
A10: col_8 | B10: 解码代码组 8（云/低云底高度相关） | C10: 与总云量或低云云底高度编码相关的中间数值组，出现在类似 SYNOP 的地面天气报文中。 | D10: 与云量、云底高度或云系类型相关的中间代码组。 | E10: 60002.0 | F10: 字符串
A11: col_9 | B11: 解码代码组 9（云量/云底高度类别） | C11: 用于表示云量或云底高度类别的中间数值或分类代码组。 | D11: 用于表示云量等级或云底高度类别等的代码组。 | E11: 70500 | F11: 字符串
A12: col_10 | B12: 解码代码组 10（能见度相关） | C12: 可能按照 WMO 规则编码水平能见度或相关等级的中间代码组。 | D12: 可能编码能见度数值或能见度等级的代码组，中间解析结果。 | E12: 333.0 | F12: 字符串
A13: col_11 | B13: 解码代码组 11（气温/最高-最低温相关） | C13: 与气温、最高气温或最低气温等要素的编码形式有关的中间代码组。 | D13: 与气温或极端温度有关的代码组，尚未直接换算到摄氏度/华氏度。 | E13: 10113.0 | F13: 字符串
... A30: minute | B30: 观测分钟（UTC） | C30: UTC 下观测时间的分钟（00–59）。 | D30: 观测时刻的分钟数（0–59，UTC），通常为整点观测时的 0 分。 | E30: 0 | F30: 整数
A31: lat_deg | B31: 站点纬度 | C31: 站点的大地纬度，单位为十进制度，北纬为正、南纬为负。 | D31: 站点的地理纬度，采用十进制度表示，北纬为正、南纬为负。 | E31: 30.033 | F31: 浮点数 | G31: 度
A32: lon_deg | B32: 站点经度 | C32: 站点的大地经度，单位为十进制度，东经为正、西经为负。 | D32: 站点的地理经度，采用十进制度表示，东经为正、西经为负。 | E32: 122.117 | F32: 浮点数 | G32: 度
A33: datetime_utc | B33: 观测时间（UTC） | C33: 完整的 UTC 观测日期和时间，通常采用带时区偏移的 ISO-8601 时间戳格式。 | D33: 完整的观测时间（UTC），采用类 ISO-8601 格式的日期时间字符串，包含年月日、时分和时区偏移信息，便于时间序列分析。 | E33: 2024-01-01 00:00:00+00:00 | F33: 日期时间 | G33: UTC 时间戳

Sheet 数据字段映射
A1: 字段名称 | B1: 内容 | C1: 详情
A2: col_0 | B2: raw_ISD_file_line | C2: 直接来自 NOAA ISD 原始数据文件中每条观测记录的整行文本（固定宽度记录），未拆分。
A3: col_1 | B3: col_0 | C3: 由解析器从 `col_0` 的原始报文中按 WMO/ISD 规则拆出的第 1 个代码组（站点/报文元信息相关），本质上是 `col_0` 的子串或其解码结果。
A4: col_2 | B4: col_0 | C4: 由解析器从 `col_0` 的原始报文中拆出的第 2 个代码组（报文段/质量标志相关），来自 `col_0` 的子串解码。
A5: col_3 | B5: col_0 | C5: 由解析器从 `col_0` 中温度相关的编码字段解码得到的第 3 个代码组，中间数值，来源于 `col_0`。
A6: col_4 | B6: col_0 | C6: 由解析器从 `col_0` 中露点/湿度相关编码字段解码得到的第 4 个代码组，中间数值，来源于 `col_0`。
A7: col_5 | B7: col_0 | C7: 由解析器从 `col_0` 中气压相关编码字段解码得到的第 5 个代码组，中间数值，来源于 `col_0`。
A8: col_6 | B8: col_0 | C8: 由解析器从 `col_0` 中气压变化/高度表设定等编码字段解码得到的第 6 个代码组，中间数值，来源于 `col_0`。
A9: col_7 | B9: col_0 | C9: 由解析器从 `col_0` 中降水/天气现象相关编码字段解码得到的第 7 个代码组，中间数值，来源于 `col_0`。
A10: col_8 | B10: col_0 | C10: 由解析器从 `col_0` 中云量/云底高度相关编码字段解码得到的第 8 个代码组，中间数值，来源于 `col_0`。
A11: col_9 | B11: col_0 | C11: 由解析器从 `col_0` 中云量或云底高度类别相关编码字段解码得到的第 9 个代码组，中间数值，来源于 `col_0`。
A12: col_10 | B12: col_0 | C12: 由解析器从 `col_0` 中能见度或能见度等级相关编码字段解码得到的第 10 个代码组，中间数值/类别，来源于 `col_0`。
... A33: datetime_utc | B33: year+month+day+hour+minute | C33: 通过字段 `year`、`month`、`day`、`hour` 和 `minute` 拼接并指定时区为 UTC 构造出的完整时间戳（ISO-8601 风格字符串）。

Sheet 数据源调研详情
A1: 数据源ID | B1: 数据源名称 | C1: 对应本体节点 | D1: 提供数据 | E1: 数据源 | F1: 格式 | G1: 空间分辨率 | H1: 时间分辨率 | I1: 是否开源 | J1: 是否可下载 | K1: 数据可用性 | L1: 下载链接 | M1: 更新频率 | N1: 历史数据年限 | O1: 地理覆盖范围
A2: DS-001 | B2: DEM地形高程数据 | C2: 地形复杂度（主要），离地高度(风机)（辅助——提供场址海拔基准） | D2: elevation：地面海拔高度（ 这是地面相对海平面的高度，非风机离地高度 AGL） | slope：坡度（地形复杂度的一部分） | aspect：坡向（地形复杂度的一部分） | terrain_ruggedness：地形粗糙指数（地形复杂度） | E2: SRTM V3, ASTER GDEM, ALOS World 3D | F2: GeoTIFF | G2: 30m/90m | H2: 静态 | I2: 是 | J2: 是（需注册部分数据源） | K2: 有数据 | L2: SRTM：https://earthexplorer.usgs.gov/ （需注册USGS账号） | ASTER GDEM：https://earthexplorer.usgs.gov/ （需注册USGS账号） | ALOS World 3D：https://www.eorc.jaxa.jp/ALOS/en/dataset/aw3d30/aw3d30_e.htm （最新版本v4.1，2024年4月更新） | Google Earth Engine（ALOS）：https://developers.google.com/earth-engine/datasets/catalog/JAXA_ALOS_AW3D30_V4_1 | 地理空间数据云（国内镜像）：https://www.gscloud.cn/sources/index?pid=302 （SRTM、ASTER GDEM V3等） | M2: 一次性（静态数据） | N2: SRTM: 2000年；ASTER: 2009年；ALOS: 2014-2021年 | O2: 全球
A3: DS-002 | B3: 地表粗糙度/土地利用数据 | C3: 粗糙度 | D3: roughness_length：粗糙度长度 z₀（直接对应""粗糙度""） | landcover：土地利用类型（用于估算粗糙度） | E3: ESA WorldCover, GlobeLand30, MODIS Land Cover | F3: GeoTIFF | G3: 10m~30m | H3: 年度更新 | I3: 是 | J3: 是 | K3: 有数据 | L3: ESA WorldCover：https://esa-worldcover.org/en （10m分辨率，年度更新，需注册ESA账号）(Wdl_123456、!Wdl123456) | Google Earth Engine（ESA WorldCover）：https://developers.google.com/earth-engine/datasets/catalog/ESA_WorldCover_v200 | GlobeLand30：https://www.globeland30.org/ （30m分辨率，中国主导） | MODIS Land Cover：https://ladsweb.modaps.eosdis.nasa.gov/ （MCD12Q1产品） | 地理空间数据云（土地覆盖专题）：https://www.gscloud.cn/sources/index?pid=1 （包含GLC30、ESA WorldCover等） | M3: 年度 | N3: WorldCover: 2020/2021年；GlobeLand30: 2000/2010/2020年 | O3: 全球
A4: DS-003 | B4: NDVI植被指数数据 | C4: 粗糙度（季节变化） | D4: NDVI：归一化植被指数（用于动态调整粗糙度） | E4: MODIS MOD13Q1, Sentinel-2 | F4: GeoTIFF | G4: 250m~10m | H4: 16天/月度 | I4: 是 | J4: 是（需注册） | K4: 有数据 | L4: MODIS MOD13Q1：https://ladsweb.modaps.eosdis.nasa.gov/ （250m分辨率，16天合成，需注册NASA账号） | Google Earth Engine（MODIS NDVI）：https://developers.google.com/earth-engine/datasets/catalog/MODIS_061_MOD13Q1 | Sentinel-2 NDVI：https://dataspace.copernicus.eu/ （10m分辨率，需注册Copernicus账号） | Google Earth Engine（Sentinel-2）：https://developers.google.com/earth-engine/datasets/catalog/COPERNICUS_S2_SR_HARMONIZED | 地理空间数据云（MODIS产品）：https://www.gscloud.cn/sources/index?pid=305 （国内镜像） | M4: 16天/月度 | N4: MODIS: 2000年至今；Sentinel-2: 2015年至今 | O4: 全球
A5: DS-004 | B5: 建筑物高度密度数据 | C5: 障碍物 | D5: building_height：建筑物高度（对应""障碍物""的高度） | building_density：建筑物密度（对应""障碍物""的分布） | E5: GHSL-Built, WSF3D, 微软建筑足迹 | F5: GeoTIFF | G5: 10~100m | H5: 静态 | I5: 是 | J5: 是 | K5: 有数据 | L5: GHSL-Built：https://ghsl.jrc.ec.europa.eu/download.php （全球建筑物高度和密度，100m分辨率） | Google Earth Engine（GHSL）：https://developers.google.com/earth-engine/datasets/catalog/JRC_GHSL_P2016_BUILT_LDSMT_GLOBE_V1 | 微软建筑足迹（Microsoft Building Footprints）：https://github.com/microsoft/GlobalMLBuildingFootprints （全球建筑轮廓矢量数据，需转换为栅格） | WSF3D：https://download.geoservice.dlr.de/WSF3D/ （DLR全球3D建筑数据，需注册） | M5: 不定期更新 | N5: GHSL: 1975/1990/2000/2015年；Microsoft: 2022年 | O5: 全球(主要城市)
A6: DS-005 | B6: ERA5再分析数据 | C6: 高空风速风向、高层等压面气象、地表气压、测站气压、大气稳定度、相对湿度、比湿、干球温度、露点温度、近地面微气象(tp/tcc)、数据源类型(NWP预报) | D6: u100/v100（高空风速风向） | w（垂直风速分量，用于复杂地形抬升/下沉气流分析）← V4.4新增 | 10fg（10米阵风风速，用于偏航控制与极值预测）← V4.4新增 | u@850hPa/v@850hPa（高层等压面气象） | sp（地表气压） | msl（海平面气压） | t2m（干球温度） | d2m（露点温度） | blh（边界层高度，用于稳定度） | sshf/slhf（感热通量/潜热通量，用于精细化热力稳定度刻画）← V4.4新增 | tp（总降水量，累积值需差分转瞬时率） | sf/icing（降雪量/结冰指数，判断叶片结冰严重掉电场景）← V4.4新增 | tcc（总云量，0-1） | cape（对流可用位能，用于稳定度） | E6: ERA5 | F6: NetCDF / GRIB | G6: 0.25° (~25km) | H6: 逐小时 | I6: 是 | J6: 是（需注册CDS账号） | K6: 有数据 | L6: https://cds.climate.copernicus.eu/ | M6: 延迟5天 | N6: 1940年至今 | O6: 全球
A7: DS-006 | B7: NWP预报 | C7: 高空风速风向（预报）、数据源类型(NWP预报) | D7: UGRD/VGRD@100m：100米高度风速分量（对应""高空风速风向（预报）""） | UGRD/VGRD@850hPa：850hPa等压面风速（对应""高层等压面气象""） | E7: GFS/NCEP | F7: GRIB2 | G7: 0.25° (~25km) | H7: 逐3h/6h | I7: 是 | J7: 是（无需注册） | K7: 有数据 | L7: https://nomads.ncep.noaa.gov/ | M7: 每日4次 | N7: 近10年 | O7: 全球
A8: DS-007 | B8: ECMWF HRES高分辨率预报 | C8: 高空风速风向（高精度预报）、数据源类型(NWP预报) | D8: u/v@100m：100米高度风速分量（对应""高空风速风向（高精度预报）""） | u/v@850hPa：850hPa等压面风速（对应""高层等压面气象""） | E8: ECMWF HRES | F8: GRIB / NetCDF | G8: 0.1° (~10km) | H8: 逐1h/3h | I8: 否（商业数据） | J8: 需付费（商业使用需购买许可证） | K8: 有数据 | L8: https://www.ecmwf.int/en/forecasts/accessing-forecasts | M8: 每日2次 | N8: 近10-15年 | O8: 全球
A9: DS-008 | B9: 高空探空数据 | C9: 高空/三维气象剖面、大气稳定度 | D9: 各气压层温度（温度廓线） | 各气压层湿度（湿度廓线） | 各气压层风速风向 | E9: 探空站数据（Wyoming大学） | F9: TXT / CSV | G9: 站点 | H9: 逐12h（每日2次，通常为00UTC和12UTC） | I9: 是 | J9: 是（无需注册） | K9: 有数据 | L9: http://weather.uwyo.edu/upperair/sounding.html | M9: 每日2次 | N9: 近50年 | O9: 站点级
A10: DS-009 | B10: 气象站观测数据 | C10: 测站气压、相对湿度、干球温度、数据源类型(实测值) | D10: station_pressure：测站气压（直接测量），单位：Pa或hPa | relative_humidity：相对湿度（直接测量），单位：% | dry_bulb_temperature：干球温度（直接测量），单位：K或℃ | wind_speed_10m：10米高度风速，ISD字段WIND_SPD | wind_direction_10m：10米高度风向，ISD字段WIND_DIR | E10: 中国气象数据网, ISD/NCEI | F10: CSV / TXT（ISD格式） | G10: 站点 | H10: 逐小时/3小时 | I10: 是 | J10: 是（部分需注册） | K10: 有数据 | L10: 中国气象数据网：https://data.cma.cn/ | ISD全球站点：https://www.ncei.noaa.gov/pub/data/noaa | M10: 实时/延迟数小时 | N10: ISD: 1901年至今；中国气象数据网: 近10-20年 | O10: 全球(ISD) / 中国(气象数据网)
A11: DS-011 | B11: 卫星云图/水汽图 | C11: 全局水平辐照度（间接） | D11: VIS通道（可见光反射率，0-1） | IR通道（红外亮温，K） | WV通道（水汽辐射，K） | 可用于反演辐照度 | E11: FY-4A, Himawari-8 | F11: HDF5 / NetCDF | G11: 2~8km | H11: 逐10~15min | I11: 是 | J11: 是（需注册部分数据源） | K11: 有数据 | L11: FY-4A（中国）：http://satellite.nsmc.org.cn/ | Himawari-8（日本）：https://www.eorc.jaxa.jp/ptree/ | M11: 实时 | N11: FY-4A: 2016年至今；Himawari-8: 2015年至今 | O11: 区域覆盖(FY-4A: 中国及周边；Himawari-8: 亚太)
A12: DS-012 | B12: 气象雷达数据 | C12: 近地面微气象（组合概念，间接贡献）—— 通过雷达径向速度反演低层风场，辅助识别强对流天气对风速高频波动分量的影响 | D12: dBZ：反射率（分贝Z，表征降水粒子强度） | V_r：径向速度（雷达指向方向的风速分量，m/s） | E12: 气象雷达（中国气象数据网） | F12: Level-II / BUFR | G12: ~1km，多高度层 | H12: 逐6min体扫 | I12: 需申请 | J12: 需申请 | K12: 需申请（视区域） | L12: 中国气象数据网：https://data.cma.cn/（需专项申请） | M12: 自定义 | N12: 近5-10年(视雷达站) | O12: 区域覆盖(视雷达站分布)
A13: DS-013 | B13: WRF/COSMO区域模式 | C13: 高空风速风向（高分辨率）、数据源类型(NWP预报) | D13: u/v：三维风速分量（m/s） | T：温度（K） | P：气压（Pa） | Q：比湿（kg/kg） | TKE：湍流动能（m²/s² 或 J/kg） | PBL height：边界层高度（m） | E13: WRF/COSMO | F13: NetCDF | G13: 1~5km（可自定义） | H13: 逐1h~3h | I13: 是（WRF开源） | J13: 可运行（需自行部署WRF模式） | K13: 需自行运行 | L13: https://www.mmm.ucar.edu/models/wrf | M13: 自定义 | N13: 自定义(取决于输入数据) | O13: 自定义(取决于配置)
A14: DS-014b | B14: 卫星遥感风场数据（海上风场适用） | C14: 高空风速风向（海上场景补充） | D14: sea_surface_wind_speed：海面风速（m/s） | wind_direction：风向（°） | E14: ASCAT散射计, Sentinel-1 SAR | F14: NetCDF / HDF5 | G14: 12.5~25km（散射计）/ 500m~1km（SAR） | H14: 不定期（卫星过境时） | I14: 是 | J14: 是（需注册） | K14: 有数据（海上区域） | L14: ASCAT散射计：https://osi-saf.eumetsat.int/ | Sentinel-1 SAR：https://scihub.copernicus.eu/ | N14: ASCAT: 2007年至今；Sentinel-1: 2014年至今 | O14: 全球（仅海上区域）
A15: DS-015 | B15: 测风塔观测数据 | C15: 空间相对位置（通过GPS计算）、动态气象（气温、气压、风向）、历史风速 | D15: 各高度层温度（动态气象-气温） | 气压（动态气象-气压） | 各高度层风向（动态气象-风向） | 各高度层风速（历史风速） | E15: 测风塔（风场业主提供） | F15: CSV / TXT | G15: 单塔多层 | H15: 10分钟 | I15: 否（商业数据） | J15: 需授权（风场业主提供） | K15: 需获取 | M15: 实时(设备采集) | N15: 设备部署期间 | O15: 站点级(单点观测)
A16: DS-016 | B16: 气象站观测数据（相邻站） | C16: 空间相对位置（通过GPS计算）、动态气象（气温、气压、风向）、历史风速 | D16: temperature：温度 | pressure：气压 | wind_direction：风向 | wind_speed：风速 | E16: ISD/NCEI | F16: CSV / TXT | G16: 站点 | H16: 逐小时 | I16: 是 | J16: 是 | K16: 有数据 | L16: https://www.ncei.noaa.gov/pub/data/noaa | N16: ISD: 1901年至今 | O16: 全球
A17: DS-017 | B17: LiDAR/SoDAR测风数据 | C17: 历史风速（高精度风廓线） | D17: ws：各高度层风速（m/s） | wd：各高度层风向（°） | TI：湍流强度（无量纲） | CNR/SNR：载噪比/信噪比（dB） | E17: LiDAR/SoDAR设备（设备厂商/业主提供） | F17: CSV / Binary | G17: 10~300m（垂直分辨率） | H17: 逐1s~10min | I17: 否（商业设备） | J17: 需购买设备 | K17: 需现场采集 | M17: 实时(设备采集) | N17: 设备部署期间 | O17: 站点级(单点观测)
A18: DS-018 | B18: 风机SCADA实测数据 | C18: 机组运行模式（启动模式、停机、故障、降载运行、恒功率、恒转速、MPPT、限电） | 变桨系统（桨距角） | 转子（转子转速、旋转动能） | 偏航系统（偏航角、对风偏差角） | 历史风速序列 | D18: turbine_status：机组运行模式（0-7状态码） | is_curtailed：限电标识（ 极其重要，用于剔除""高风速低功率""的异常调度数据） | active_power_limit：有功功率限值（调度指令下达的功率上限） | pitch_angle：桨距角（°） | rotor_speed：转子转速（rpm） | yaw_angle：偏航角（°） | yaw_error：对风偏差角（°） | nacelle_temperature：机舱温度（°C） | ambient_temperature：环境温度（°C） | wind_speed：风速（m/s） | wind_direction：风向（°） | active_power：有功功率（kW） | reactive_power：无功功率（kVar） | E18: SCADA系统（风场业主提供） | F18: CSV / 数据库 | G18: 单风机 | H18: 10分钟 / 1秒 | I18: 否（商业数据） | J18: 需授权（风场业主提供） | K18: 需获取 | M18: 实时/延迟数分钟 | N18: 风场运行期间(通常3-10年) | O18: 场站级(单风机)
A19: DS-019 | B19: 风机设备参数与布局图 | C19: 机组布局（风机阵列拓扑）、离地高度(风机) | D19: hub_height：轮毂高度 AGL（对应""离地高度(风机)""，当前主流 100-120m） | turbine_locations：风机经纬度坐标（机组布局） | layout_map：风机布局图（风机阵列拓扑） | rated_power：额定功率（kW） | rotor_diameter：转子直径（m） | cp_curve：功率系数曲线（风速-功率转换核心参数） | ct_curve：推力系数曲线（尾流模型计算核心参数） | E19: The Wind Power数据库, 风场业主提供 | F19: JSON / CSV / Shapefile | G19: 矢量数据（精确坐标） | H19: 静态 | I19: 部分公开 | J19: 部分可下载 | K19: 需从业主获取 | L19: https://www.thewindpower.net/ | M19: 静态数据 | N19: 当前状态 | O19: 场站级
A20: GPS坐标 | B20: GPS坐标 | C20: 经度、纬度 | D20: longitude：经度（°，-180~180，东经为正） | latitude：纬度（°，-90~90，北纬为正）
A21: 工程计算 | B21: 工程计算 | C21: 时间嵌入特征、低频趋势分量、高频波动分量、爬坡事件特征、湍流强度/风切变、时序稳定性指数 | D21: year, month, day, hour, day_of_year：时间特征（从时间戳提取） | 低频趋势分量：从历史风速序列分解（EMD、小波分解） | 高频波动分量：从历史风速序列分解 | 爬坡事件特征：差分计算/滑动窗口（一阶/二阶差分或最大变化率） | 湍流强度/风切变：从多层风速计算 | 时序稳定性指数：从历史风速序列计算统计指标（如变异系数）
A22: DS-005/DS-006(聚类) | B22: 天气形势分型 | C22: 本体外扩展（间接关联气象与环境整体） | D22: weather_pattern_type：天气模式类型（categorical，int 0-N） | F22: 工程计算字段
A23: 模型输出(MOS) | B23: 基础模型/历史预测误差 | C23: 本体外扩展（后处理校正环节） | D23: forecast_error：预测误差（m/s） | bias：偏差（m/s，系统性误差） | rmse：均方根误差（m/s） | mae：平均绝对误差（m/s） | F23: CSV/Parquet/数据库表
A24: DS-005/DS-006/DS-007 | B24: 多模式集合预报 | C24: 气象与环境（整体气象背景场）；本体外扩展（预测不确定性-集合特征） | D24: member_i_forecast：各成员预报量（第i个成员的预报结果） | ensemble_mean：集合平均（所有成员预报的平均值） | ensemble_std：集合标准差（所有成员预报的标准差，反映预测不确定性） | F24: GRIB/NetCDF（原始）或CSV/Parquet（整理后） | G24: 0.25°/0.1° 等 | H24: 1h（典型）

Sheet ERA5数据和其他数据源组合调研
B1: 数据名称 | C1: 对应风场预测本体类别(对应禧蕾那边本体设计) | D1: 对应风场预测本体节点(对应禧蕾那边本体节点) | E1: 分辨率(时/空)-粒度 | F1: 数据格式 | G1: 是否(开源、下载、有无数据) | H1: 下载链接 | I1: 下载链接和可用性验证(链接有效性、国内气象同化数据专项检查、数据可用性) | J1: 主要提供字段以及解释说明 | K1: 元数据表征 | L1: 对应数据源ID(数据源详细信息) | M1: 优先级 | N1: 数据获取难度 | O1: 数据源优先级与获取难度评判标准 | P1: 成本/费用 | Q1: 数据更新延迟 | R1: 历史数据年限 | S1: 地理覆盖范围 | T1: 数据质量说明 | U1: 数据使用 | V1: 如何与基础模型结合 | W1: 数据量需求 | X1: 预期效果
A2: 地面观测​ | B2: 1. 气象站实测风速 | C2: 气象与环境；相邻/上游测风站数据 | D2: 气象与环境(数据源类型-实测值)；相邻/上游测风站数据(历史风速) | E2: 时：1h/3h；空：站点级 | F2: CSV/TXT（ISD 格式） | G2: 开源✅ 下载✅(部分需注册) 有数据✅ | H2: NOAA NCEI ISD-Lite：https://www.ncei.noaa.gov/pub/data/noaa/isd-lite/；ISD 全球站点：https://www.ncei.noaa.gov/pub/data/noaa | I2: NOAA NCEI ISD-Lite：有效、精度准确、数据可用 | J2: col_0,col_1,col_2,col_3,col_4,col_5,col_6,col_7,col_8,col_9,col_10,col_11,col_12,col_13,col_14,col_15,col_16,col_17,col_18,col_19,col_20,source_id,usaf,wban,year,month,day,hour,minute,lat_deg,lon_deg,datetime_utc | K2: [变量名: wind_speed_10m] [单位: m/s] [数据类型: float32] [文件格式: CSV/TXT] [字段说明: ISD字段WIND_SPD] [空间分辨率: 站点级] [时间分辨率: 1h/3h] | L2: DS-009, DS-016 | M2: 🔴 必需 | N2: ⭐⭐ 中等 | O2: 第一点：优先级评判标准（优先级用于评估数据源对风场预测项目的重要程度，分为三个等级） 🔴 必需：没有该数据无法开展风场预测或关键评估 判断依据： 1、是模型运行的核心输入数据 2、缺失该数据会导致预测系统无法正常工作 3、是风场预测的基础数据，无法用其他数据替代 4、直接影响预测结果的可用性 典型数据源示例： 1、气象站实测风速/风向 2、数字高程模型(DEM) 3、风机位置与布局图 4、风机SCADA历史数据 5、经纬度与海拔 🟡 推荐：能显著提升精度/鲁棒性但缺失时模型仍可运行 判断依据： 1、能够明显改善预测精度和模型稳定性 2、有助于提升模型的鲁棒性（抗干扰能力） 3、缺失时模型仍可运行，但性能会下降 4、属于重要的辅助数据，但不是绝对必需 典型数据源示例： 1、气象站温度/气压/湿度 2、高分辨率气象同化数据 3、边界层高度数据 4、湍流动能(TKE) 5、垂直风切变指数 🟢 可选：主要用于增强分析或专项研究，对主流程影响较小 判断依据： 1、主要用于深度分析或特定场景研究 2、对主要预测流程影响较小 3、可以用于模型优化，但不是核心需求 4、属于锦上添花的数据，优先级较低 典型数据源示例： 1、卫星散射计海面风场（仅海上风场适用） 2、卫星云图/水汽图 3、气象雷达反射率/径向速度 4、植被指数(NDVI) 5、建筑物高度与密度数据 6、天气形势分型 第二点：数据获取难度评判标准（数据获取难度用于评估获取该数据源所需付出的成本（时间、人力、资金等），分为四个等级） ⭐ 简单：公开/免费、注册即下或直接下载 判断依据： 1、数据完全公开，无需付费 2、下载流程简单，通常只需注册账号 3、可以直接通过网页或API下载 4、无需特殊申请或审批流程 5、获取成本极低，几乎无门槛 典型数据源示例： 1、ERA5再分析数据 2、DEM地形高程数据 3、地表粗糙度/土地利用数据 4、NDVI植被指数数据 ⭐⭐ 中等：需注册/申请或简单对接接口，有一定流程和配额限制 判断依据： 1、需要注册账号或提交简单申请 2、可能需要对接API接口 3、有一定的下载流程和配额限制 4、需要一定的技术能力（如API调用） 5、获取成本中等，有一定门槛但可接受 典型数据源示例： 1、气象站观测数据（部分需注册） 2、卫星数据（需注册Copernicus等平台） 3、MODIS数据（需注册NASA账号） 4、高分辨率气象预报数据（部分需注册） ⭐⭐⭐ 困难：强依赖业主/机构授权或多系统协同，沟通和审批成本高 判断依据： 1、需要向业主或相关机构申请授权 2、需要多系统协同配合 3、沟通和审批流程复杂，耗时较长 4、可能需要签署协议或合同 5、获取成本较高，需要投入较多时间和精力 典型数据源示例： 1、风机SCADA历史数据（需业主授权） 2、风机位置与布局图（需业主提供） 3、气象雷达数据（需向气象部门申请） 4、测风塔观测数据（需业主提供） ⭐⭐⭐⭐ 极难：需自建观测设备或自跑大规模模式，消耗人力+计算资源+资金 判断依据： 1、需要自己建设观测设备 2、需要自己运行大规模数值模式 3、需要大量的人力、计算资源和资金投入 4、技术门槛高，需要专业团队 5、获取成本极高，通常需要项目级投入 典型数据源示例： 1、激光雷达/声雷达测风剖面（需购买设备） 2、区域WRF/COSMO等模式输出（需自跑模式） 3、风机尾流模型输出（需自建模型和计算） | P2: 免费(部分需注册) | Q2: 实时/延迟数小时 | R2: ISD: 1901年至今；中国气象数据网: 近10-20年 | S2: 全球(ISD) / 中国(气象数据网) | T2: 高精度(实测值，需质控) | U2: 微调, 后处理校正​ | V2: 微调: 作为训练标签，优化模型在站点处的预测。 | W2: 1000-10000高质量配对 | X2: 直接修正模型在站点位置的系统偏差，显著提升站点预测精度。
I3: ISD 全球站点：有效、精度准确、数据可用 | V3: 后处理: 用模型预测与实测值的差作为目标，训练校正器。 | W3: <10000
B4: 2. 气象站实测风向 | C4: 气象与环境；相邻/上游测风站数据 | D4: 气象与环境(风向角、正弦分量、余弦分量)；相邻/上游测风站数据(动态气象-风向) | E4: 时：1h/3h；空：站点级 | F4: CSV/TXT（ISD 格式） | G4: 开源✅ 下载✅ 有数据✅ | H4: NOAA NCEI ISD-Lite：https://www.ncei.noaa.gov/pub/data/noaa/isd-lite/；ISD 全球站点：https://www.ncei.noaa.gov/pub/data/noaa | J4: col_0,col_1,col_2,col_3,col_4,col_5,col_6,col_7,col_8,col_9,col_10,col_11,col_12,col_13,col_14,col_15,col_16,col_17,col_18,col_19,col_20,source_id,usaf,wban,year,month,day,hour,minute,lat_deg,lon_deg,datetime_utc | K4: [变量名: wind_direction_10m] [单位: °] [值域: 0-360] [数据类型: float32] [文件格式: CSV/TXT] [字段说明: ISD字段WIND_DIR] [空间分辨率: 站点级] [时间分辨率: 1h/3h] | L4: DS-009, DS-016 | M4: 🔴 必需 | N4: ⭐⭐ 中等 | P4: 免费(部分需注册) | Q4: 实时/延迟数小时 | R4: ISD: 1901年至今；中国气象数据网: 近10-20年 | S4: 全球(ISD) / 中国(气象数据网) | T4: 高精度(实测值，需质控) | U4: 微调, 增加输入通道​ | V4: 微调: 作为多任务学习的附加目标。 | W4: 1000-10000高质量配对 | X4: 改善风向预测，来间接提升风速预测的物理一致性。
V5: 增加输入通道: 若基础模型未使用风向，可直接加入。 | W5: 与ERA5原始数据集相当
B6: 3. 气象站温度/气压/湿度 | C6: 气象与环境；相邻/上游测风站数据 | D6: 气象与环境(测站气压、干球温度、相对湿度、空气密度)；相邻/上游测风站数据(动态气象-气温/气压) | E6: 时：1h/3h；空：站点级 | F6: CSV/TXT（ISD 格式） | G6: 开源✅ 下载✅ 有数据✅ | H6: NOAA NCEI ISD-Lite：https://www.ncei.noaa.gov/pub/data/noaa/isd-lite/；ISD 全球站点：https://www.ncei.noaa.gov/pub/data/noaa | J6: col_0,col_1,col_2,col_3,col_4,col_5,col_6,col_7,col_8,col_9,col_10,col_11,col_12,col_13,col_14,col_15,col_16,col_17,col_18,col_19,col_20,source_id,usaf,wban,year,month,day,hour,minute,lat_deg,lon_deg,datetime_utc | K6: [变量名: temperature/pressure/relative_humidity] [单位: K或℃/Pa或hPa/%] [数据类型: float32] [文件格式: CSV/TXT] [字段说明: ISD格式 TMP/SLP/DEW] [空间分辨率: 站点级] [时间分辨率: 1h/3h] | L6: DS-009, DS-016 | M6: 🟡 推荐 | N6: ⭐⭐ 中等 | P6: 免费(部分需注册) | Q6: 实时/延迟数小时 | R6: ISD: 1901年至今；中国气象数据网: 近10-20年 | S6: 全球(ISD) / 中国(气象数据网) | T6: 高精度(实测值，需质控) | U6: 增加输入通道, 特征融合​ | V6: 增加输入通道: 若基础模型未使用，可直接加入。 | W6: 与ERA5原始数据集相当 | X6: 帮助模型校正近地面层的气象状态，改善热力效应引起的风速变化预测。
V7: 特征融合: 作为独立分支输入，与主干特征融合。 | W7: 取决于新分支的复杂度和融合策略
A8: 高分辨率数值产品​ | B8: 4. <0.1°气象同化数据（6通道） | C8: 气象与环境 | D8: 气象与环境(高空风速风向-高精度预报、地表气压、干球温度、大气稳定度-blh) | E8: 时：1-3h；空：0.1°(~10 km) | F8: GRIB/NetCDF | G8: 开源✅ 下载✅ 有数据✅ | H8: ECMWF HRES：https://cds.climate.copernicus.eu/datasets/reanalysis-era5-single-levels?tab=download | I8: ECMWF HRES：有效、精度准确、数据可用 | J8: u100,v100(m/s), t2m(K), sp(Pa), d2m(K), blh(m),"100米高度风速分量u100和v100（东西向和南北向，单位米/秒）、2米高度温度t2m（开尔文）、地表气压sp（帕斯卡）、2米高度露点温度d2m（开尔文）、边界层高度blh（米）。这些是再分析数据（如ERA5）在100米高度（接近风机轮毂高度）的关键参数，u100和v100可直接用于风机功率计算，blh反映大气边界层结构，影响风场垂直分布。" | K8: [变量名: u100/v100/t2m/sp/d2m/blh] [单位: m/s/K/Pa/K/K/m] [数据类型: float32] [文件格式: GRIB/NetCDF] [空间分辨率: 0.1°] [数据维度: (time,lat,lon)] [时间分辨率: 1-3h] | L8: DS-007 | M8: 🟡 推荐 | N8: ⭐⭐ 中等 | P8: 付费(商业使用需购买许可证) | Q8: 延迟数小时 | R8: 近10-15年 | S8: 全球 | T8: 高精度(ECMWF HRES，商业级质量) | U8: 增加输入通道, 特征融合​ | V8: 增加输入通道: 插值到0.25°后与ERA5通道拼接。 | W8: 与ERA5原始数据集相当 | X8: 提供更精细的初始场，改善模型对中小尺度天气系统的捕捉能力。
V9: 特征融合: 设计独立编码器，提取高分辨率特征并与主干融合。 | W9: 取决于新分支的复杂度和融合策略
B10: 5. 区域WRF/COSMO等模式输出 | C10: 气象与环境 | D10: 气象与环境(高空风速风向-高分辨率、大气稳定度-TKE/PBL) | E10: 时：1-3h；空：1-5 km | F10: NetCDF | G10: 模式开源✅ 结果需自跑⚠️ 有数据⚠️(需自行运行) | H10: WRF：https://www.mmm.ucar.edu/models/wrf | I10: WRF：模式开源、有测试数据(数据覆盖2008年，不具备时效性) | J10: u,v(m/s,3D), T(K), P(Pa), Q(kg/kg), TKE, PBL height,"三维风速分量u和v（米/秒）、温度T（开尔文）、气压P（帕斯卡）、比湿Q（千克/千克，表示水汽含量）、湍流动能TKE、边界层高度PBL height。这些是数值天气预报（NWP）模式的三维输出，提供完整的大气状态信息，TKE表征湍流强度，PBL height反映大气稳定度和混合层深度，对风场预测至关重要。" | K10: [变量名: u/v/T/P/Q/TKE/PBL] [单位: m/s/K/Pa/kg/kg/m²/s²/m] [数据类型: float32] [文件格式: NetCDF] [空间分辨率: 1-5km] [数据维度: (time,z,lat,lon)] [时间分辨率: 1-3h] | L10: DS-013 | M10: 🟡 推荐 | N10: ⭐⭐⭐⭐ 极难 | P10: 高成本(需计算资源+专业知识) | Q10: 自定义(需自行运行) | R10: 自定义(取决于输入数据) | S10: 自定义(取决于配置) | T10: 中等-高精度(取决于模式配置和输入数据质量) | U10: 增加输入通道, 特征融合, 条件注入​ | V10: 增加输入通道: 将WRF预测作为额外通道。 | W10: 与ERA5原始数据集相当 | X10: 引入高分辨率动力学过程信息，提升对局地环流（如海陆风、山谷风）的预测。
V11: 特征融合: WRF特征作为独立分支。 | W11: 取决于新分支的复杂度和融合策略
V12: 条件注入: 若WRF提供模式不确定性，可作为条件注入。 | W12: 1w-5w个
A13: 遥感观测​ | B13: 6. 卫星散射计海面风场 | C13: 气象与环境 | D13: 气象与环境(高空风速风向-海上补充) | E13: 时：卫星过境；空：12.5-25 km / 500m-1km | F13: NetCDF/HDF5 | G13: 开源✅ 下载✅(需注册) 有数据✅(海上区域) | H13: ASCAT：https://osi-saf.eumetsat.int/；Sentinel-1：https://dataspace.copernicus.eu/ | I13: ASCAT：有效、精度准确、数据可用 | J13: sea_surface_wind_speed(m/s), wind_direction(°),"海面风速（米/秒）和风向（度）。用于海上风电场或近海风场的补充数据源。海面风场数据通常来自卫星观测或海洋再分析数据，对于海上风电场的功率预测和风资源评估非常重要，因为海面粗糙度低，风场特征与陆地差异显著。" | K13: [变量名: sea_surface_wind_speed/wind_direction] [单位: m/s/°] [数据类型: float32] [文件格式: NetCDF/HDF5] [数据产品: ASCAT L2] [空间分辨率: 12.5-25km] [时间分辨率: 卫星过境] | L13: DS-014b | M13: 🟢 可选 | N13: ⭐⭐ 中等 | P13: 免费(需注册) | Q13: 延迟数小时-数天 | R13: ASCAT: 2007年至今；Sentinel-1: 2014年至今 | S13: 全球(仅海上区域) | T13: 中等精度(卫星反演，需验证) | U13: 增加输入通道, 特征融合​ | V13: 增加输入通道: 插值后作为海洋表面风输入。 | W13: 与ERA5原始数据集相当 | X13: 大幅改善海上及近海区域的风场初始条件精度。
I14: Sentinel-1：有效、精度准确、数据可用 | V14: 特征融合: 提取海面风特征，与陆地风特征融合。 | W14: 取决于新分支的复杂度和融合策略
B15: 7. 卫星云图/水汽图 | C15: 气象与环境 | D15: 气象与环境(全局水平辐照度-间接、近地面微气象-云量/辐射影响) | E15: 时：10-15min；空：2-8 km | F15: HDF5/NetCDF | G15: 开源✅ 下载✅(部分需注册) 有数据✅ | H15: FY-4A：http://satellite.nsmc.org.cn/portalsite/Data/DataView.aspx?SatelliteType=1&SatelliteCode=FY4A#；Himawari-8：https://www.eorc.jaxa.jp/ptree/ | I15: 第一个链接需要付费， 第二个链接无效 | J15: VIS 反射率(0-1), IR 亮温(K), WV 辐射(K),"可见光（VIS）反射率（0-1无量纲）、红外（IR）亮温（开尔文）、水汽（WV）辐射（开尔文）。这些是卫星遥感数据：VIS反射率反映云量和地表反照率；IR亮温反映云顶温度和地表温度；WV辐射反映大气中上层水汽含量。卫星数据可用于识别天气系统、云量变化，间接影响风场预测，特别是在复杂天气条件下。" | K15: [变量名: VIS/IR/WV] [含义: 可见光反射率/红外亮温/水汽辐射] [单位: 0-1/K/K] [数据类型: uint16/float32] [文件格式: HDF5/NetCDF] [空间分辨率: 2-8km] [时间分辨率: 10-15min] | L15: DS-011 | M15: 🟢 可选 | N15: ⭐⭐ 中等 | P15: 免费(部分需注册) | Q15: 实时/延迟数分钟 | R15: FY-4A: 2016年至今；Himawari-8: 2015年至今 | S15: 区域覆盖(FY-4A: 中国及周边；Himawari-8: 亚太) | T15: 高精度(卫星观测，需反演处理) | U15: 特征融合​ | V15: 设计CNN分支处理图像，提取云量、水汽等特征，与主干融合。 | W15: 取决于新分支的复杂度和融合策略 | X15: 改善与对流、云物理过程相关的风速突变预测。
B16: 8. 气象雷达反射率/径向速度 | C16: 气象与环境 | D16: 气象与环境(近地面微气象-强对流相关) | E16: 时：~6min 体扫；空：~1 km，多高度层 | F16: 雷达 Level-II / BUFR | G16: 开源⚠️(需申请) 下载⚠️ 有数据⚠️(视区域) | H16: 中国气象数据网：https://data.cma.cn/（需专项申请） | I16: 需要注册申请 | J16: dBZ(反射率), V_r(径向速度,m/s),"雷达反射率dBZ（分贝Z，表征降水粒子强度）和径向速度V_r（米/秒，雷达指向方向的风速分量）。天气雷达数据用于监测强对流天气、降水系统，这些天气现象会显著影响风场，导致风速突变、风向变化和湍流增强，对风电场安全运行和功率预测有重要影响。" | K16: [变量名: dBZ/V_r] [含义: 反射率/径向速度] [单位: dBZ/m/s] [数据类型: float32] [文件格式: Level-II/BUFR] [空间分辨率: ~1km] [时间分辨率: 6min体扫] | L16: DS-012 | M16: 🟢 可选 | N16: ⭐⭐⭐ 困难 | P16: 需协商(需向气象部门申请) | Q16: 实时/延迟数分钟 | R16: 近5-10年(视雷达站) | S16: 区域覆盖(视雷达站分布) | T16: 高精度(雷达观测，需VAD/VVP反演) | U16: 特征融合​ | V16: 设计CNN/RNN分支处理雷达数据立方体，提取强对流特征。 | W16: 取决于新分支的复杂度和融合策略 | X16: 极大提升对雷暴、飑线等强对流天气下阵风的短临预测能力。
B17: 9. 激光雷达/声雷达测风剖面 | C17: 相邻/上游测风站数据 | D17: 相邻/上游测风站数据(历史风速-高精度风廓线、湍流强度/风切变) | E17: 时：1s-10min；空：垂直10-300m分层 | F17: CSV/Binary | G17: 开源❌ 下载❌ 有数据⚠️(需现场采集) | H17: 随设备厂商/业主提供 | J17: ws(m/s), wd(°), TI(湍流强度), CNR/SNR,"风速ws（米/秒）、风向wd（度）、湍流强度TI（无量纲，通常为风速标准差与平均风速的比值）、载噪比CNR或信噪比SNR（分贝）。这些是测风塔或激光雷达（LiDAR）的实测数据，提供高精度的风廓线信息。TI是风电场功率预测和疲劳载荷评估的关键参数，CNR/SNR反映数据质量。" | K17: [变量名: ws/wd/TI/CNR/SNR] [单位: m/s/°/无量纲/dB/dB] [数据类型: float32] [文件格式: CSV/Binary] [空间分辨率: 垂直10-300m分层] [时间分辨率: 1s-10min] | L17: DS-017 | M17: 🟡 推荐 | N17: ⭐⭐⭐⭐ 极难 | P17: 高成本(需购买设备+现场部署) | Q17: 实时(设备采集) | R17: 设备部署期间 | S17: 站点级(单点观测) | T17: 高精度(专业设备，高时空分辨率) | U17: 特征融合​ | V17: 将垂直风廓线作为3D特征输入，或提取关键层次特征与主干融合。 | W17: 取决于新分支的复杂度和融合策略 | X17: 精准改善垂直风切变、低空急流等垂直结构的预测。
A18: 地理与地表信息​ | B18: 10. 数字高程模型（DEM） | C18: 空间与地理地形 | D18: 空间与地理地形(地形复杂度、离地高度(风机)-海拔基准) | E18: 时：静态；空：30/90 m | F18: GeoTIFF | G18: 开源✅ 下载✅ 有数据✅ | H18: USGS：https://earthexplorer.usgs.gov/；地理空间数据云：https://www.gscloud.cn/sources/accessdata/aeab8000652a45b38afbb7ff023ddabb?pid=302 | I18: USGS:可以下载，地理空间数据云:可以下载 | J18: elevation(m), slope(°), aspect(°), terrain_ruggedness,"海拔高度（米）、坡度（度，地形倾斜角度）、坡向（度，坡面朝向，0度为北）、地形崎岖度（无量纲指数，反映地形复杂程度）。地形数据影响局地风场：海拔影响风速（通常随高度增加而增大），坡度和坡向影响风向和风速加速效应，地形崎岖度影响湍流和风切变，是风场数值模拟的重要输入。" | K18: [变量名: elevation/slope/aspect/terrain_ruggedness] [单位: m/°/°/m] [说明: elevation为场址海拔非AGL] [数据类型: float32/int16] [文件格式: GeoTIFF] [坐标系: WGS84] [空间分辨率: 30m/90m] [时间特性: 静态] | L18: DS-001 | M18: 🔴 必需 | N18: ⭐ 简单 | P18: 免费 | Q18: 静态数据(一次性) | R18: SRTM: 2000年；ASTER: 2009年；ALOS: 2014-2021年 | S18: 全球 | T18: 高精度(卫星/航测，全球覆盖) | U18: 增加输入通道​ | V18: 作为静态通道直接输入模型。 | W18: 数百到数千个样本（用于微调相关层） | X18: 使模型显式学习地形对气流（爬坡、绕流、峡谷效应）的影响。
B19: 11. 地表粗糙度长度 | C19: 空间与地理地形 | D19: 空间与地理地形(下垫面特征-粗糙度) | E19: 时：年度；空：10-30 m | F19: GeoTIFF | G19: 开源✅ 下载✅ 有数据✅ | H19: ESA WorldCover：https://esa-worldcover.org/en；GlobeLand30：http://data.casearth.cn；https://www.tianditu.gov.cn | I19: 第一个链接可以下载，第二个可以下载，第三个是以API形式 | J19: roughness_length z₀(m), landcover,"粗糙度长度z₀（米，表征地表对风的摩擦阻力）和土地覆盖类型（如草地、森林、城市等）。粗糙度长度是风廓线模型的关键参数，不同下垫面（如水面、草地、森林、城市）的粗糙度差异很大，直接影响近地面风速分布和风切变。landcover提供定性的地表类型信息。" | K19: [变量名: roughness_length z₀] [单位: m] [值域: 0.0001-2.0] [数据类型: float32] [文件格式: GeoTIFF] [空间分辨率: 10-30m] [获取方式: 从landcover查表] [时间特性: 年度更新] | L19: DS-002 | M19: 🔴 必需 | N19: ⭐ 简单 | P19: 免费 | Q19: 年度更新 | R19: WorldCover: 2020/2021年；GlobeLand30: 2000/2010/2020年 | S19: 全球 | T19: 中等精度(从LULC查表转换，需验证) | U19: 增加输入通道​ | V19: 作为静态通道直接输入模型。 | W19: 数百到数千个样本（用于微调相关层） | X19: 改善模型对地表摩擦效应的表征，提升近地面风速预测精度。
B20: 12. 土地利用/土地覆盖（LULC） | C20: 空间与地理地形 | D20: 空间与地理地形(下垫面特征-粗糙度-LULC) | E20: 时：年度；空：10-30 m | F20: GeoTIFF | G20: 开源✅ 下载✅ 有数据✅ | H20: ESA WorldCover：https://esa-worldcover.org/en；GlobeLand30：https://www.globeland30.org/；https://www.tianditu.gov.cn | I20: 第一个链接可以下载，第二个链接无效，第三个是以API形式 | J20: landcover_class(分类0-200),"土地覆盖分类（0-200的整数分类代码，如0-11为IGBP分类，不同数值代表不同地表类型如常绿针叶林、落叶阔叶林、草地、农田、城市等）。标准化的土地覆盖分类可用于自动提取粗糙度参数，支持大规模风场模拟和预测。" | K20: [变量名: landcover_class] [类型: categorical] [编码范围: ESA分类0-200] [数据类型: uint8] [文件格式: GeoTIFF] [空间分辨率: 10-30m] [时间特性: 年度更新] | L20: DS-002 | M20: 🔴 必需 | N20: ⭐ 简单 | P20: 免费 | Q20: 年度更新 | R20: WorldCover: 2020/2021年；GlobeLand30: 2000/2010/2020年 | S20: 全球 | T20: 高精度(卫星分类，ESA/中国标准) | U20: 增加输入通道, 条件注入​ | V20: 增加输入通道: One-hot编码或类别索引作为输入。 | W20: 与ERA5原始数据集相当 | X20: 区分不同下垫面的热力和动力特性，改善局地微气候预测。
V21: 条件注入: 若LULC用于定义区域类型，可作为条件。 | W21: 1w-5w个
B22: 13. 植被指数（NDVI） | C22: 空间与地理地形 | D22: 空间与地理地形(下垫面特征-粗糙度-季节变化) | E22: 时：16天/或月度；空：250m/10m | F22: GeoTIFF | G22: 开源✅ 下载✅(需注册) 有数据✅(海上区域) | H22: MODIS：https://ladsweb.modaps.eosdis.nasa.gov/；Sentinel-2：https://dataspace.copernicus.eu/ | I22: 第一个链接可以下载，第二个链接无效，第三个是以API形式 | J22: NDVI(-1~1),"归一化植被指数（Normalized Difference Vegetation Index，取值范围-1到1，正值表示植被覆盖，值越大植被越茂盛）。NDVI反映植被生长状况和季节变化，植被高度和密度影响地表粗糙度，进而影响风场。NDVI的季节变化可用于动态调整粗糙度参数，提高风场预测精度。" | K22: [变量名: NDVI] [单位: 无量纲] [值域: -1.0~1.0] [数据类型: float32] [文件格式: GeoTIFF] [空间分辨率: 250m(MODIS)/10m(S2)] [时间特性: 16天合成] | L22: DS-003 | M22: 🟢 可选 | N22: ⭐ 简单 | P22: 免费(需注册) | Q22: 16天/月度更新 | R22: MODIS: 2000年至今；Sentinel-2: 2015年至今 | S22: 全球 | T22: 高精度(卫星观测，MODIS/S2标准产品) | U22: 增加输入通道​ | V22: 作为动态通道（随时间变化）输入模型。 | W22: 与ERA5原始数据集相当 | X22: 捕捉植被季节性变化对地表粗糙度和热通量的影响。
B23: 14. 建筑物高度与密度数据 | C23: 空间与地理地形 | D23: 空间与地理地形(下垫面特征-障碍物) | E23: 时：静态；空：10-100 m | F23: GeoTIFF（由矢量栅格化） | G23: 开源✅ 下载✅ 有数据✅ | H23: GHSL-Built：https://ghsl.jrc.ec.europa.eu/download.php；Microsoft Building：https://github.com/microsoft/GlobalMLBuildingFootprints | I23: GHSL-Bui1t:两个链接都有效，精度准确，数据可用 | J23: building_height(m), building_density(%),"建筑物高度（米）和建筑物密度（百分比，单位面积内建筑物覆盖比例）。城市或复杂地形区域的建筑物会产生显著的障碍效应和尾流，影响局地风场。建筑物高度和密度数据用于评估城市风场特征，对于城市周边或复杂地形风场的功率预测非常重要。" | K23: [变量名: building_height/building_density] [单位: m/%] [值域: 0-100] [数据类型: float32] [文件格式: GeoTIFF] [空间分辨率: 10-100m] [时间特性: 静态] | L23: DS-004 | M23: 🟢 可选 | N23: ⭐ 简单 | P23: 免费 | Q23: 静态/不定期更新 | R23: GHSL: 1975/1990/2000/2015年；Microsoft: 2022年 | S23: 全球(主要城市) | T23: 中等精度(卫星/航测，城市区域较准确) | U23: 增加输入通道​ | V23: 作为高分辨率静态通道输入模型。 | W23: 数百到数千个样本（用于微调相关层） | X23: 显著改善城市及风电场内建筑群导致的尾流和湍流效应预测。
A24: 风电场特定数据​ | B24: 15. 风机位置与布局图 | C24: 空间与地理地形；风电场与机组状态 | D24: 空间与地理地形(离地高度(风机))；风电场与机组状态(机组布局-风机阵列拓扑、机组气动性能-Cp/Ct曲线) | E24: 时：静态；空：单风机级 | F24: JSON/CSV/Shapefile | G24: 开源⚠️(部分公开) 下载⚠️ 有数据⚠️(多需业主提供) | H24: The Wind Power：https://www.thewindpower.net/ | I24: 有效，但是需要收费 | J24: turbine_lat/lon, hub_height, rated_power, cp_curve, ct_curve, layout_map,"风机经纬度坐标、轮毂高度（米）、额定功率（千瓦或兆瓦）、功率系数曲线cp_curve（Cp-λ曲线，反映风机在不同叶尖速比下的功率提取效率）、推力系数曲线ct_curve（Ct-λ曲线，反映风机推力特性）、布局图layout_map（风机在风电场内的空间分布）。这些是风机的物理参数和布局信息，用于将风场数据转换为功率输出，cp_curve和ct_curve是风机气动性能的核心，layout_map用于计算尾流效应。" | K24: [变量名: turbine_lat/lon/hub_height/rated_power/cp_curve/ct_curve] [单位: °/m/kW/曲线/曲线] [说明: hub_height为AGL轮毂高度=离地高度(风机),主流100-120m] [数据类型: float64/float32] [文件格式: JSON/CSV/Shapefile] [数据类型: 矢量] [时间特性: 静态] | L24: DS-019 | M24: 🔴 必需 | N24: ⭐⭐⭐ 困难 | P24: 需协商(多需业主提供) | Q24: 静态数据(一次性) | R24: 当前状态 | S24: 场站级 | T24: 高精度(工程参数，精确坐标) | U24: 增加输入通道, 图神经网络融合​ | V24: 增加输入通道: 作为二值掩码或距离图输入。 | W24: 与ERA5原始数据集相当 | X24: 让模型明确知晓预测目标点，并学习风机间的尾流干扰。
V25: 图神经网络: 将风机作为图节点。 | W25: 1w-5w个图快照
B26: 16. 风机SCADA历史数据 | C26: 风电场与机组状态；风速本体及时序特征 | D26: 风电场与机组状态(机组运行模式-启动模式/停机/故障/降载运行/恒功率/恒转速/MPPT/限电、机组硬件状态-变桨系统-桨距角/转子-转子转速/旋转动能/偏航系统-偏航角/对风偏差角/核心部件-机舱温度)；风速本体及时序特征(历史风速序列) | E26: 时：10min/1s；空：单风机 | F26: CSV/数据库表 | G26: 开源❌ 下载⚠️(需授权) 有数据⚠️ | H26: 业主提供 | J26: wind_speed, wind_direction, rotor_speed, pitch_angle, yaw_angle, turbine_status, is_curtailed, active_power_limit, nacelle_temperature, ambient_temperature,"风速、风向、转子转速（转/分或弧度/秒）、桨距角（度，叶片与旋转平面的夹角）、偏航角（度，机舱朝向与风向的夹角）、风机状态（如运行、停机、故障等）、是否限电is_curtailed（布尔值）、有功功率限值（千瓦）、机舱温度（摄氏度）、环境温度（摄氏度）。这些是风机的实时运行数据，反映风机的实际运行状态和性能。桨距角和偏航角影响功率输出效率，风机状态和限电信息用于数据质量控制和异常检测，温度数据可用于评估风机热状态和性能衰减。" | K26: [变量名: wind_speed/rotor_speed/pitch_angle/yaw_angle/turbine_status/is_curtailed/active_power_limit/nacelle_temperature] [单位: m/s/rpm/°/°/int/bool/kW/°C] [值域: turbine_status为0-7] [数据类型: float32/int/bool] [文件格式: CSV/DB] [空间分辨率: 单风机] [时间分辨率: 10min] | L26: DS-018 | M26: 🔴 必需 | N26: ⭐⭐⭐ 困难 | P26: 需协商(需业主提供) | Q26: 实时/延迟数分钟 | R26: 风场运行期间(通常3-10年) | S26: 场站级(单风机) | T26: 高精度(实测值，需质控和异常值处理) | U26: 微调, 后处理校正, 图神经网络融合​ | V26: 微调: 作为轮毂高度风速标签。 | W26: 1000-10000高质量 | X26: 提供风机轮毂高度的风速信息，直接优化对发电有直接影响的风速预测。
V27: 后处理: 校正模型输出。 | W27: 数百到数千个样本（校正器训练）
V28: 图神经网络: 作为节点观测值。 | W28: 1w-5w个图快照
B29: 17. 风机功率输出数据 | C29: 风电场与机组状态 | D29: 风电场与机组状态(机组运行模式-功率输出) | E29: 时：10-15min；空：单风机 | F29: CSV/数据库表 | G29: 开源❌ 下载⚠️ 有数据⚠️ | H29: 业主提供 | J29: active_power(kW), reactive_power(kVar),"有功功率（千瓦，实际输出的电能）和无功功率（千乏，用于维持电网电压和频率）。这是风机的实际功率输出数据，是风电场功率预测的目标变量。有功功率直接反映风能转换为电能的效率，无功功率反映风机的电网支撑能力。" | K29: [变量名: active_power/reactive_power] [单位: kW/kVar] [数据类型: float32] [文件格式: CSV/DB] [空间分辨率: 单风机] [时间分辨率: 10min/15min] | L29: DS-018 | M29: 🔴 必需 | N29: ⭐⭐⭐ 困难 | P29: 需协商(需业主提供) | Q29: 实时/延迟数分钟 | R29: 风场运行期间(通常3-10年) | S29: 场站级(单风机) | T29: 高精度(实测值，需识别限电/故障) | U29: 后处理校正, 条件注入​ | V29: 后处理: 建立风速-功率关系，校正预测。 | W29: 数百到数千个样本（校正器训练） | X29: 使风速预测更贴合实际发电效益，优化预测的经济价值。
V30: 条件注入: 若功率反映风况，可作为条件。 | W30: 1w-5w个
B31: 18. 风机尾流模型输出 | C31: 风电场与机组状态 | D31: 风电场与机组状态(尾流效应-微观流体效应) | E31: 时：1h；空：1-5 km 网格/场内网格 | F31: NetCDF | G31: 模式开源✅ 结果需自跑⚠️ 有数据⚠️(需自行运行) | H31: 基于WRF/专用尾流模型生成 | J31: wake_loss(%), wake_field(m/s deficit), wake_direction(°),"尾流损失（百分比，上游风机对下游风机造成的功率损失比例）、尾流场（米/秒亏缺，风速减少量）、尾流方向（度，尾流传播方向）。尾流效应是风电场内风机相互影响的主要机制，上游风机的尾流导致下游风机风速降低和湍流增强，显著影响整体发电量。wake_loss用于评估尾流影响程度，wake_field提供详细的尾流风速分布，wake_direction反映尾流的方向性特征。" | K31: [变量名: wake_loss/wake_field/wake_direction] [单位: %/m/s/°] [值域: wake_loss为0-100] [数据类型: float32] [文件格式: NetCDF] [空间分辨率: 网格1-5km] [时间分辨率: 逐小时] | L31: DS-013(尾流模块) | M31: 🟡 推荐 | N31: ⭐⭐⭐⭐ 极难 | P31: 高成本(需计算资源+模式运行) | Q31: 自定义(需自行运行) | R31: 自定义(取决于输入数据) | S31: 场站级(风场内) | T31: 中等精度(模型输出，需验证) | U31: 增加输入通道, 特征融合​ | V31: 增加输入通道: 尾流效应场作为额外输入。 | W31: 与ERA5原始数据集相当 | X31: 引入流体力学规律，提升风电场内空间风速分布预测的物理合理性。
V32: 特征融合: 提取尾流特征进行融合。 | W32: 取决于新分支的复杂度和融合策略
A33: 大气状态与派生指数​ | B33: 19. 边界层高度数据 | C33: 气象与环境 | D33: 气象与环境(大气稳定度-blh指标) | E33: 时：1h；空：0.25° | F33: NetCDF/GRIB | G33: 开源✅ 下载✅(需注册) 有数据✅(海上区域) | H33: ERA5：https://cds.climate.copernicus.eu/ | I33: ERA5:有效，精度准确，数据可用 | J33: blh(m),"边界层高度（米，Planetary Boundary Layer Height）。边界层高度是大气边界层的顶部高度，反映大气稳定度和垂直混合强度。边界层高度高通常表示对流活跃、混合强烈，风速垂直分布较均匀；边界层高度低表示稳定层结，可能出现低空急流和强风切变。blh是风场预测和大气稳定度评估的重要参数。" | K33: [变量名: blh] [单位: m] [值域: 0-5000] [数据类型: float32] [数据源变量: ERA5变量boundary_layer_height] [文件格式: NetCDF/GRIB] [空间分辨率: 0.25°] [时间分辨率: 1h] | L33: DS-005(ERA5 blh) | M33: 🟡 推荐 | N33: ⭐ 简单 | P33: 免费(需注册CDS账号) | Q33: 延迟5天 | R33: 1940年至今 | S33: 全球 | T33: 中等精度(NWP输出，需验证) | U33: 增加输入通道​ | V33: 作为关键垂直尺度参数输入模型。 | W33: 与ERA5原始数据集相当 | X33: 改善混合层内风速垂直分布和日变化特征的预测。
B34: 20. 湍流动能（TKE） | C34: 气象与环境 | D34: 气象与环境(大气稳定度-湍流强度指标) | E34: 时：1-3h；空：0.25°(ERA5) 或1-5km(WRF) | F34: NetCDF | G34: 开源✅(ERA5变量或WRF输出) 下载✅/需自跑⚠️ | H34: ERA5/WRF 官网 | J34: tke(m²/s² 或 J/kg),"湍流动能（Turbulent Kinetic Energy，单位平方米/秒²或焦耳/千克）。TKE表征大气湍流的强度，反映风速和风向的脉动程度。高TKE值表示强湍流，会导致风机载荷增大、功率波动增强；低TKE值表示平稳风场。TKE是评估风场质量和风机疲劳载荷的重要参数，也是风场数值模拟的关键变量。" | K34: [变量名: tke] [单位: m²/s²或J/kg] [数据类型: float32] [获取方式: WRF直接输出或ERA5多层风速派生] [文件格式: NetCDF] | L34: DS-005/DS-013 | M34: 🟡 推荐 | N34: ⭐~⭐⭐⭐⭐ | P34: 免费(ERA5) / 高成本(WRF) | Q34: 延迟5天(ERA5) / 自定义(WRF) | R34: 1940年至今(ERA5) / 自定义(WRF) | S34: 全球(ERA5) / 自定义(WRF) | T34: 中等精度(派生变量，需验证) | U34: 增加输入通道​ | V34: 作为表征湍流强度的变量输入模型。 | W34: 与ERA5原始数据集相当 | X34: 提升对湍流引起的风速脉动和短期波动的预测能力。
B35: 21. 垂直风切变指数 | C35: 风速本体及时序特征 | D35: 风速本体及时序特征(湍流强度/风切变) | E35: 时：10min(测风塔)/1h(ERA5)；空：塔点/网格 | F35: 源数据 CSV/TXT/NetCDF；指数为工程计算字段 | G35: 开源❌(测风塔)、ERA5✅；下载⚠️ | H35: 测风塔数据(业主)；ERA5：https://cds.climate.copernicus.eu/ | I35: ERA5:有效，精度准确，数据可用 | J35: wind_shear_exponent α(由多高度风速计算),"风切变指数α（无量纲，由多高度风速数据通过幂律或对数律拟合得到）。风切变指数反映风速随高度的变化率，α值越大表示风速随高度增加越快。典型值：中性层结约0.1-0.2，稳定层结可大于0.3，不稳定层结可小于0.1。风切变指数用于外推不同高度的风速，是风资源评估和功率预测的重要参数。" | K35: [变量名: wind_shear_exponent α] [单位: 无量纲] [值域: 0.1-0.5] [计算公式: α=ln(v₂/v₁)/ln(z₂/z₁)] [计算方法: 从多层风速计算] [源数据格式: CSV/TXT/NetCDF] | L35: DS-015/DS-005 | M35: 🟡 推荐 | N35: ⭐⭐~⭐⭐⭐ | P35: 免费(ERA5) / 需协商(测风塔) | Q35: 延迟5天(ERA5) / 实时(测风塔) | R35: 1940年至今(ERA5) / 测风期间(测风塔) | S35: 全球(ERA5) / 站点级(测风塔) | T35: 高精度(测风塔) / 中等精度(ERA5派生) | U35: 增加输入通道​ | V35: 作为关键动力参数输入模型。 | W35: 与ERA5原始数据集相当 | X35: 直接改善对风剪切，这一影响风机载荷和发电的关键因素的预测。
B36: 22. 大气稳定度指数（如里查逊数） | C36: 气象与环境 | D36: 气象与环境(大气稳定度-Richardson数/Monin-Obukhov长度/Pasquill稳定度分类) | E36: 时：1h(ERA5 输入)/12h(探空)；空：网格/探空站 | F36: 源数据 NetCDF/TXT；指数为工程计算字段 | G36: ERA5/探空开源✅ 下载✅ 有数据✅ | H36: ERA5：https://cds.climate.copernicus.eu/；探空：http://weather.uwyo.edu/upperair/sounding.html | I36: ERA5:有效，精度准确，数据可用 | J36: Ri、L、Pasquill 类别(由温度/风廓线计算),"理查森数Ri（Richardson Number，无量纲，反映大气稳定度，Ri>0稳定，Ri<0不稳定）、Monin-Obukhov长度L（米，表征大气稳定度，L<0不稳定，L>0稳定，|L|越小稳定度效应越强）、Pasquill稳定度类别（A-F分类，A最不稳定，F最稳定，由温度梯度和风速计算）。这些是大气稳定度参数，稳定度影响风速垂直分布、湍流强度和边界层结构，是风场预测的关键因子。不同稳定度条件下，风廓线和功率输出差异显著。" | K36: [变量名: Richardson数Ri/M-O长度L/Pasquill分类] [单位: 无量纲/m/categorical] [值域: Pasquill分类A-F] [计算方法: 从温度+风廓线计算] [源数据格式: NetCDF/TXT] | L36: DS-005/DS-008 | M36: 🟡 推荐 | N36: ⭐⭐ 中等 | P36: 免费(需注册) | Q36: 延迟5天(ERA5) / 实时(探空) | R36: 1940年至今(ERA5) / 近50年(探空) | S36: 全球(ERA5) / 站点级(探空) | T36: 中等精度(派生计算，需验证) | U36: 增加输入通道, 条件注入​ | V36: 增加输入通道: 作为物理参数输入。 | W36: 与ERA5原始数据集相当 | X36: 区分稳定/不稳定边界层，显著改善夜间低空急流、白天对流混合等不同状态下的风速预测。
V37: 条件注入: 若用于区分稳定/不稳定状态，可作为条件。 | W37: 数千到数万个样本（训练注入机制）
B38: 23. 对流可用位能（CAPE） | C38: 气象与环境 | D38: 气象与环境(大气稳定度-对流指标) | E38: 时：1h；空：0.25° | F38: NetCDF/GRIB | G38: 开源✅ 下载✅ 有数据✅ | H38: ERA5：https://cds.climate.copernicus.eu/ | I38: ERA5:有效，精度准确，数据可用 | J38: cape(J/kg),"对流有效位能（Convective Available Potential Energy，单位焦耳/千克）。CAPE反映大气中对流发展的潜势，高CAPE值表示强对流天气可能，会导致风速突变、风向变化、强湍流和极端天气事件。CAPE是评估强对流天气对风电场影响的重要指标，用于极端天气预警和功率预测的不确定性评估。" | K38: [变量名: cape] [单位: J/kg] [值域: 0-5000+] [数据类型: float32] [数据源变量: ERA5变量CAPE] [文件格式: NetCDF/GRIB] [空间分辨率: 0.25°] [时间分辨率: 1h] | L38: DS-005(ERA5 cape) | M38: 🟡 推荐 | N38: ⭐ 简单 | P38: 免费(需注册CDS账号) | Q38: 延迟5天 | R38: 1940年至今 | S38: 全球 | T38: 中等精度(NWP输出，需验证) | U38: 增加输入通道​ | V38: 作为对流潜势的输入。 | W38: 与ERA5原始数据集相当 | X38: 提升对强对流天气可能引发的极端阵风的预警能力。
A39: 时空上下文特征​ | B39: 24. 经纬度与海拔 | C39: 空间与地理地形 | D39: 空间与地理地形(经度、纬度、海拔-场址海拔基准) | E39: 时：静态；空：站点/风机级 | F39: CSV/DB(坐标表)+GeoTIFF(DEM) | G39: 开源✅(DEM) 坐标自有数据；有数据✅ | H39: DEM 同 DS-001；坐标来自业主/GPS | J39: latitude, longitude, elevation,"纬度（度，-90到90，北纬为正）、经度（度，-180到180，东经为正）、海拔高度（米，相对于海平面的高度）。地理位置信息用于数据匹配、坐标系转换、计算太阳辐射和日变化特征。纬度影响季节变化和气候带特征，经度影响时区和日变化相位，海拔影响大气压力和温度，进而影响风场特征。" | K39: [变量名: latitude/longitude/elevation] [单位: °/°/m] [数据类型: float64] [数据来源: 从GPS/DEM获取] [文件格式: CSV/DB(坐标表)+GeoTIFF(DEM)] [时间特性: 静态] | L39: DS-001, GPS | M39: 🔴 必需 | N39: ⭐ 简单 | P39: 免费(DEM) / 自有数据(GPS) | Q39: 静态数据(一次性) | R39: DEM: 2000年至今；GPS: 当前 | S39: 全球(DEM) / 站点级(GPS) | T39: 高精度(GPS精确坐标；DEM见DS-001) | U39: 增加输入通道, 条件注入​ | V39: 增加输入通道: 作为静态地理特征。 | W39: 数百到数千个样本（用于微调相关层） | X39: 让模型学习地理位置和海拔的气候学背景与系统性偏差。
V40: 条件注入: 若用于区域划分，可作为条件。 | W40: 1w-5w个
B41: 25. 时间特征（年、月、日、时、日序） | C41: 风速本体及时序特征 | D41: 风速本体及时序特征(时间嵌入特征) | E41: 时：与原始序列一致；空：同站点/风机 | F41: 工程计算字段（CSV/Parquet/DB 列） | G41: —（从时间戳计算） | H41: — | J41: year, month, day, hour, day_of_year,"年份、月份、日期、小时、一年中的第几天（1-365/366）。时间信息用于构建时间特征，捕捉风场的季节变化、日变化和周期性特征。day_of_year可用于表示季节周期（如正弦/余弦编码），hour用于表示日周期，这些时间特征对风电场功率预测模型的性能有重要影响，因为风场具有明显的季节和日变化规律。" | K41: [变量名: year/month/day/hour/day_of_year] [数据类型: int] [值域: month(1-12), day(1-31), hour(0-23), day_of_year(1-366)] [处理建议: 可sin/cos编码] [文件格式: 工程计算字段(CSV/Parquet/DB列)] | L41: 工程计算 | M41: 🔴 必需 | N41: ⭐ 简单 | P41: 免费(工程计算) | Q41: 实时(从时间戳提取) | R41: 无限制(取决于原始数据时间范围) | S41: 无限制(适用于所有数据) | T41: 高精度(精确时间戳) | U41: 增加输入通道, 条件注入​ | V41: 增加输入通道: 作为周期性编码（如sin/cos）输入。 | W41: 与ERA5原始数据集相当 | X41: 让模型捕捉风速的季节性、月相和日变化规律。
V42: 条件注入: 作为时间条件注入模型。 | W42: 数千到数万个样本（训练注入机制）
B43: 26. 天气形势分型 | C43: 本体外扩展 | D43: 本体外扩展(天气形势分型-聚类特征) | E43: 时：1h(随NWP)；空：大尺度场/站点映射 | F43: 工程计算字段 | G43: —（从 NWP 聚类得到） | H43: — | J43: weather_pattern_type(聚类类别),"天气模式类型（通过聚类分析得到的天气形势分类，如高压控制型、低压系统型、锋面型等）。天气模式分类用于识别大尺度天气形势，不同天气模式下的风场特征差异显著。通过将当前天气条件归类到历史相似天气模式，可以利用历史数据中的模式-功率关系来改进预测，这是一种基于天气分型的预测方法。" | K43: [变量名: weather_pattern_type] [类型: categorical] [值域: int 0-N] [生成方法: K-means/SOM聚类ERA5/GFS大尺度场] [典型分类数: 5-20类] [文件格式: 工程计算字段] | L43: DS-005/DS-006(聚类) | M43: 🟢 可选 | N43: ⭐⭐ 中等 | P43: 免费(需NWP数据+聚类算法) | Q43: 延迟5天(取决于NWP) | R43: 1940年至今(取决于NWP数据) | S43: 全球(取决于NWP覆盖) | T43: 中等精度(聚类结果，需验证分类有效性) | U43: 条件注入​ | V43: 将分型结果（one-hot或索引）作为条件向量注入模型。 | W43: 数千到数万个样本（训练注入机制） | X43: 帮助模型关联大尺度环流背景与局地风场的统计关系。
A44: 历史与误差信息​ | B44: 27. 基础模型历史预测误差 | C44: 本体外扩展 | D44: 本体外扩展(历史预测误差-MOS方法/模型误差统计) | E44: 时：按统计周期/或逐时；空：场站/风机级 | F44: CSV/Parquet/数据库表 | G44: —（模型内部生成） | H44: — | J44: forecast_error, bias, rmse, mae 等,"预测误差（实际值与预测值的差值）、偏差bias（系统性误差，预测值的平均偏差）、均方根误差RMSE（Root Mean Square Error，反映预测误差的总体水平）、平均绝对误差MAE（Mean Absolute Error，反映预测误差的平均幅度）等误差指标。这些是预测性能评估指标，用于量化预测模型的准确性。bias反映系统性偏差，RMSE和MAE反映预测精度，这些指标用于模型优化、MOS（Model Output Statistics）校正和预测不确定性评估。" | K44: [变量名: forecast_error/bias/rmse/mae] [单位: m/s] [数据类型: float32] [统计方式: 按时段/天气类型统计] [方法标识: MOS方法] [文件格式: CSV/Parquet/数据库表] | L44: 模型输出(MOS) | M44: 🟡 推荐 | N44: ⭐⭐ 中等 | P44: 免费(模型内部生成) | Q44: 实时(随模型预测) | R44: 模型运行期间 | S44: 场站级(取决于模型应用范围) | T44: 中等精度(统计误差，需持续更新) | U44: 增加输入通道, 特征融合​ | V44: 增加输入通道: 将过去N小时的误差序列作为输入通道。 | W44: 与ERA5原始数据集相当 | X44: 让模型学习自身误差的自相关性和系统性偏差模式，实现自校正。
V45: 特征融合: 提取误差特征进行融合。 | W45: 取决于新分支的复杂度和融合策略
B46: 28. 多模式集合预报 | C46: 气象与环境 + 本体外扩展 | D46: 气象与环境(整体气象背景场)；本体外扩展(预测不确定性-集合特征) | E46: 时：1h(典型)；空：0.25°/0.1° 等 | F46: GRIB/NetCDF(原始)；CSV/Parquet(整理后) | G46: NWP 开源✅/部分付费；有数据✅ | H46: ERA5：https://cds.climate.copernicus.eu/；GFS：https://nomads.ncep.noaa.gov/；ECMWF HRES：见上 | I46: ERA5，GFS:有效，精度准确，数据可用 | J46: 各成员 member_i_forecast，ensemble_mean, ensemble_std,"各成员预报member_i_forecast（集合预报中第i个成员的单独预报结果）、集合平均ensemble_mean（所有成员预报的平均值，通常比单个成员预报更准确）、集合标准差ensemble_std（所有成员预报的标准差，反映预测不确定性）。集合预报通过多个略有差异的初始条件或物理参数运行多个预报，提供预测的概率分布。ensemble_mean作为确定性预报，ensemble_std量化预测不确定性，可用于风险评估和概率预测。集合预报是提高风电场功率预测精度和可靠性的重要方法。" | K46: [变量名: member_i_forecast/ensemble_mean/ensemble_std] [含义: 各成员预报量/集合均值/集合标准差] [数据类型: float32] [文件格式: GRIB/NetCDF(原始)或CSV/Parquet(整理后)] [数据维度: (time,lat,lon,member)] [时间分辨率: 1h] | L46: DS-005/DS-006/DS-007 | M46: 🟡 推荐 | N46: ⭐⭐ 中等 | P46: 免费(ERA5/GFS) / 付费(ECMWF HRES) | Q46: 延迟5天(ERA5) / 实时(GFS) / 延迟数小时(HRES) | R46: 1940年至今(ERA5) / 近10年(GFS) / 近10-15年(HRES) | S46: 全球 | T46: 高精度(多模式集成，降低不确定性) | U46: 增加输入通道, 特征融合​ | V46: 增加输入通道: 将各模式的预测作为一组通道。 | W46: 与ERA5原始数据集相当 | X46: 降低单一模式的不确定性，提高预测的稳健性和可靠性。
V47: 特征融合: 提取集合统计特征（均值、方差）进行融合。 | W47: 取决于新分支的复杂度和融合策略

Sheet 文献列表
A1: 论文ID | B1: DOI | C1: ERA5数据是否是数据源之一 | D1: 论文题目 | E1: 发表年份 | F1: 开源状态/代码链接 | G1: 空间分辨率 | H1: 时间分辨率 | I1: 风场高度/离地 | J1: 海拔高度与地形 | K1: 气象与环境输入 | L1: 有无传感器输入 | M1: 数据集与特征工程处理方法 | N1: 数据集链接 | O1: 空间与地理地形输入 | P1: 近地面微气象与局部扰动输入 | Q1: 时空关联与历史序列特征 | R1: 目标输出形态 | S1: 核心算法基线 | T1: 物理机制融合点 | U1: 损失函数 | V1: 性能提升幅度 | W1: 业务映射 | X1: 算法分类
A2: 2 | D2: High-resolution wind speed forecast system coupling numerical weather prediction and machine learning for agricultural studies — a case study from South Korea | E2: 2022年，发表于 International Journal of Biometeorology | F2: 未开源代码（文献末尾注明代码不适用 / Not applicable） | G2: 单机级预测 点尺度（注：文献使用了100m × 100m 的高分辨率网格预报场，但最终落脚于对104个农业气象站单点位置的风速进行精确降尺度预测） | H2: 短期（预测未来48小时，逐小时分辨率） | I2: 10m（注：文献的核心任务是将数值模式 10m 高度的风速，降尺度预测到离地 3m 高度的近地面微风速） | J2: 涵盖 低海拔沿海 / 中海拔（研究覆盖韩国全境，特别对比了内陆区域与沿海区域，发现内陆区域的预测精度高于沿海区域） | K2: 6个NWP预报气象变量（注：原文明确从高分辨率数值模式 KMAPP 的表面数据中提取了6个预报变量作为降尺度模型的输入特征，具体包括：10米高度风速的 u 分量、10米高度风速的 v 分量、气温、相对湿度、海平面气压，以及向下短波辐射） | L2: 有（注：使用了 104 个自动农业观测站（AAOS）的实测风速数据；这些站点位于农场和果园，测量的离地 3m 高度每小时平均风速被用作机器学习建模的目标标签和性能评估基准） | M2: 严格质控、区间过采样与后向消除特征筛选（注：在数据清洗阶段，按照韩国气象局标准剔除了仪器位移超150m、位置不当或缺失/零值率超10%的测站数据 ；针对低风速数据偏态分布易导致过拟合的问题，按 1m/s 的区间进行了均匀数据量的“过采样” ；最后，使用后向消除法（backward elimination）基于验证集 RMSE，将初始的48个候选特征精简至最终的18个 ） | N2: 提供官方数据库入口链接（注：文末 Data Availability 声明部分明确给出了数据获取网址。气象观测数据可从 weather.rda.go.kr 下载，空间地形数据可从 egis.me.go.kr 和 soil.rda.go.kr 获取，KMAPP 预报数据需向韩国国家气象科学研究所 www.nims.go.kr 申请。代码未开源） | O2: 多维度地理与地表静态属性（注：模型显式输入了11个空间特征。涵盖由 DEM 计算得出的地形坡度（南/北和东/西分量）和地形曲率（南/北和东/西分量），从土地覆盖图中提取的1个特征，从农业适宜性地图中提取的3个特征（排水等级、地貌、土壤亚类），以及测站自身的经度、纬度和海拔信息） | P2: 未提及（注：文献完全未提及局部垂直风切变或局部地形引发的尾流扰动等微尺度物理特征输入。作者在局限性讨论中更明确承认，由于依赖数值天气预报的近地面风速，模型未考虑混合层以下的湍流动能（turbulent kinematic energy），导致对极端高风速预测表现不佳） | Q2: 仅保留月份时间周期编码（注：未提及使用目标站点过去的历史风速序列作为滞后项，也未引入相邻或上游站点的空间传播特征。时间维度上最初考虑了年、月、日、时四个特征，但经过后向消除法特征筛选后，最终仅保留了“月份（month）”这一单项时间编码特征） | R2: 单点多步确定性预报及高分辨率区域网格预报（注：系统旨在输出未来48小时、逐小时的3米高度确定性风速标量值。模型既可针对104个农业测风站进行单点时间序列预测，也具备在韩国全境 460万个 100m×100m 高分辨率网格点上进行空间网格推演的能力，不涉及概率区间预测） | S2: 经典机器学习算法对比传统物理风廓线法（注：本文验证了三种机器学习回归器：随机森林（RF）、支持向量回归（SVR）和极限学习机（ELM）作为降尺度的核心算法。用于对比的 Baseline 基线模型包括：原生的 KMAPP 模式预报场，以及传统的物理对数风廓线法（LOG）和幂律法（POW）） | T2: 纯数据驱动，未涉及物理机制融合（注：本文虽然在标题中写了“耦合数值天气预报（NWP）”，但其本质是将 NWP（KMAPP 模型）输出的 10米风速、气压、温度等气象场参数，加上高程、坡度、土地覆盖等地理特征直接作为机器学习（RF、SVR、ELM）的输入特征进行黑盒映射。机器学习模型内部并未显式定制物理约束损失函数。文章只是将纯数据驱动的 ML 模型与传统的物理学经验公式（对数风廓线 LOG 和幂律 POW）进行了平行的基线对比实验，证明了数据驱动拟合的效果优于直接套用物理公式） | U2: 均方根误差RMSE（注：文献未提及在模型目标函数中添加额外的物理约束项。在模型的特征剔除选择（后向消除法）以及超参数优化调参（如决定 RF 的 500 棵树、SVR 的 gamma/cost 参数）过程中，均是直接基于验证集上的均方根误差（RMSE）来进行反馈优化的） | V2: 最佳模型 RF 的 RMSE < 0.8 m/s，MAE 约为 0.5 m/s（注：根据原文给出的明确数值，在 48 小时的预测中，表现最好的随机森林（RF）模型的 RMSE 小于 0.8 m/s，而用于对比的传统气象学物理风廓线方法（LOG 和 POW）的 RMSE 均大于 1.4 m/s，同组表现最差的机器学习模型 ELM 的 RMSE 也在 1.1 m/s 以上） | W2: 解决了气象局常规预报高度（10米）与近地面农业实际需求高度（3米）不匹配的空间降尺度痛点（注：世界气象组织规定的标准测风高度为 10 米，但该高度的风速往往无法直接用于农业。作者在结论中强调，该系统成功实现了向 3 米高度的高精度降尺度预报，输出的 100米级高分辨率近地面风速能够直接指导农药喷洒日程安排、花粉传播评估、农作物倒伏预测以及林冠蒸散量估算，填补了气象预报与精细化农业管理之间的业务鸿沟） | X2: 树模型与集成学习，支持向量机类，前馈神经网络
A3: 3 | B3: 10.1016/j.knosys.2013.11.015 | C3: 否 | D3: Optimal parameters selection for BP neural network based on particle swarm optimization: A case study of wind speed forecasting | E3: 2014年（2013年投稿并在线发表）；刊源为 Knowledge-Based Systems，通常该期刊属于中科院1区/Q1 | F3: 未提供直接的代码下载链接 | G3: 点尺度（注：基于酒泉和玉门单个气象观测站的历史风速序列进行单点预测，未涉及具体风机实体或风电场拓扑） | H3: 日平均与6小时分辨率(注:实验包含两套时间尺度，一套是酒泉的日平均风 速，另一套是玉门的6小时采样风速;预测任务通过输入维度 N 决定，例如输入前 N 天数据 来预测当前天的风速) | I3: 仅提到数据来自酒泉和玉门气象观测，并探讨了风速对海拔和地形的依赖性，但并未具体标注测风仪或预测目标的高度 | J3: 内陆复杂地形（河西走廊） （注：研究区域位于中国甘肃省河西走廊西端，文中强调风速受地形（terrain）和海拔（elevation）影响较大，具有间歇性和波动性；酒泉地区总面积达 191,342 km2） | K3: 历史风速（注：原文明确指出人工神经网络模型“除了风速历史数据外，不需要多余的信息（no need for excess information other than wind speed history）”，其输入层的节点仅代表过去历史的日平均或6小时平均风速值，完全未引入温度、气压、风向等其他气象变量数据） | L3: 未提及具体传感器名称。原文仅表述为从四个站点“采样”的数据（sampled from the four sites），并未明确提及使用了测风塔（Mast）、激光雷达（LiDAR）或 SCADA 系统等物理硬件名称 | M3: Min-Max归一化与横/纵向重采样构造（注：在数据预处理阶段，采用了极值线性变换将输入输出数据严格缩放至 [-1, 1] 区间，并在预测后进行反归一化；在特征工程切分上，创新性地提出了“横向数据选择（Lateral data selection）”和“纵向数据选择（Longitudinal data selection）”两种重构训练/测试集的方法。全文未提及异常值剔除或VMD/小波等频域分解方法） | N3: 未提及（注：全局扫描正文，文章仅说明使用了中国甘肃酒泉（2001-2006年每日）和玉门（2001-2006年每6小时）的实测平均风速数据，未提供任何开源下载链接、GitHub 地址或官方数据库入口） | O3: 未提及（注：本文模型输入全为一维纯时间序列数据，未显式输入高程DEM、地表粗糙度等空间静态物理特征） | P3: 未提及（注：全文完全未提及湍流动能(TKE)、局部垂直风切变或局部地形引发的尾流扰动等微尺度物理特征输入） | Q3: 多步历史风速滞后序列与纵向时间周期关联（注：模型在输入层显式采用了目标站点过去的历史风速序列作为滞后项（如确定最佳滞后项为 Lag = 5）。此外，虽然没有引入相邻站点的空间传播特征，但通过其提出的“纵向数据选择”方法，将同一天或同一小时的数据提取成子集进行重组训练，隐式引入了风速的月度或日内时间周期关联特征） 。 | R3: 单点单步确定性预测（注：模型的输出层严格设定为 1 个节点，即基于历史滑动窗口数据，输出特定气象站点未来下一个时间步（如未来1天或未来6小时）的风速确定性标量预报值，不输出概率区间或网格面预报） | S3: 提出 IS-PSO-BP 混合模型（注：本文提出的创新模型为结合了“输入参数选择(Input parameter Selection)”与“粒子群优化(PSO)”的 BP 神经网络（即 IS-PSO-BP）。用于严格对比的 Baseline 基线模型包括传统的基础 BP 神经网络（BPNN）以及经典的 ARIMA 时间序列模型） | T3: 纯数据驱动，未涉及物理机制融合（注：本文提出的是结合了输入参数选择（IS）和粒子群优化算法（PSO）的反向传播（BP）神经网络模型 。模型完全依靠风速时间序列数据进行黑盒非线性映射，利用 PSO 算法及混沌搜索去全局优化神经网络的权重和偏置 ，全文未在特征输入、网络架构或损失函数中融合任何空气动力学方程、温度/气压等多变量气象学定律或物理约束 | U3: MSE均方误差（注：原文明确说明，在BP网络计算全局误差以及在PSO算法中评估粒子适应度时，选用均方误差 (MSE) 作为目标性能函数，计算公式依赖纯数学映射的误差平方，未提及添加任何物理约束损失项） | V3: MAPE 最低达到 15.51% / MSE 降低至 0.17（注：原文明确给出了绝对对比数值。在酒泉日均风速预测测试中（Table 4），提出的 IS-PSO-BP 模型的 MAPE 为 15.51%、MSE 为 0.17，优于对比的 ARIMA(2,1,3) 基线模型（MAPE 19.55%，MSE 0.18）和基础 BP 模型（MAPE 21.10%，MSE 0.22）；在波动更剧烈的玉门 6 小时风速预测中（Table 5），IS-PSO-BP 的 MAPE 为 21.02%、MSE 为 3.67，大幅优于基础 BP 模型的 MAPE 35.19%、MSE 9.42 ） | W3: 解决了黑盒神经网络中因输入参数（滞后时长/数据切割方式）盲目主观选择而导致预测极不稳定的痛点（注：作者在研究中发现，盲目增加历史输入天数反而会导致极差的预测结果（甚至出现过拟合）。该系统最大的工程价值在于，它证明了“纵向数据切割法（longitudinal data selection）”比常规的横向滑动切割更有效，并通过算法自动定死了最佳历史参考天数（如5天），使得模型能够真正学习到风速波动的频率特征，而不是像 ARIMA 那样只能平滑地输出一条接近均值的直线，这极大增强了风电场短期调度的可靠性 ） | X3: 优化算法增强,前馈神经网络
A4: 4
A5: 5 | B5: 10.1016/j.apenergy.2015.01.038 | C5: 否 | D5: The study and application of a novel hybrid forecasting model – A case study of wind speed forecasting in China | E5: 2015年；刊源为 Applied Energy。该期刊通常被认为属于中科院1区/JCR Q1分区 | F5: 未提供直接的代码链接 | G5: 点尺度(注:研究对象为甘肃省内的四个特定风电场站点，即张掖站、武威站 酒泉站和马山站，而非网格化数据场) | H5: 短期（论文使用了约六年的日平均风速数据进行建模。） | I5: 未明确说明 | J5: 内陆风电场区域(注:研究区域覆盖中国西北部甘肃省的四个站点，文中强 调这些区域因其独特的“地理特征"拥有领先的风能资源，但未给出具体的海拔高度数值或对复 杂地形的分类描述) | K5: 纯历史风速（注：原文明确指出仅使用了中国甘肃省四个风电场（武威、酒泉、张掖、马鬃山）的“日平均风速序列（daily average wind speed series）”作为基础输入，未引入温度、气压、风向等任何其他气象变量数据） | L5: 未明确提及具体传感器名称 （注：文中提到数据是直接从四个站点“采样”（sampled）得到的实测日平均风速序列，但在描述数据来源时，未出现测风塔（Mast）、激光雷达（LiDAR）或风机 SCADA 等具体传感器的术语） | M5: 小波包变换（WPT）分解去噪与相空间重构（PSR）（注：在数据处理阶段，首先使用小波包变换（WPT）将原始风速序列分解为不同频率的子序列，并直接剔除随机性最强的最高频子序列（HH2）以达到滤波去噪目的；随后，采用相空间重构（PSR）技术中的 C-C 方法，对保留下来的各子序列进行处理以确定模型的最佳输入形式。数据集被划分为约 75% 训练集、25% 验证集和 25% 测试集） | N5: 未提及（注：全局扫描正文及参考文献，文中仅说明数据采集自甘肃省的四个特定风电场，但完全未提供任何可供下载的数据开源链接、GitHub 地址或官方数据库入口） 。 | O5: 未提及（注：模型输入完全依赖一维的纯时间序列数据，未显式输入高程DEM、地表粗糙度等空间静态物理特征） | P5: 未提及（注：全文完全未提及湍流动能(TKE)、局部垂直风切变或局部地形引发的尾流扰动等微尺度物理特征） | Q5: 历史风速滞后序列（注：模型通过 C-C 方法计算出“延迟时间（delay time）”和“嵌入维数（embedding dimension）”，借此将目标站点过去的历史风速序列转化为滞后项输入（Lag variables）。文中未引入月份/小时等时间周期编码；同时，作者在引言中明确提到了空间相关性模型（Spatial correlation models）需要多个站点的测量值会增加复杂度和成本，但在本文提出的模型中并未引入相邻或上游站点的空间传播特征） | R5: 单点确定性预测（注：模型最终针对四个特定风电场输出未来的日平均风速确定性标量预测值。该预测值是由WPT分解后保留的各个低/中频子序列的预测值直接叠加求和而得，不涉及概率区间预测或区域网格预测） | S5: 提出 WPT-LSSVM-PSOSA 混合模型（注：本文提出的核心创新模型是结合了小波包变换（WPT）、最小二乘支持向量机（LSSVM）以及基于模拟退火改良的粒子群算法（PSOSA）。用于对比的 Baseline 基线模型包括：经典 ARIMA 模型、单一 LSSVM 模型、LSSVM-PSOSA 模型，以及采用传统小波变换的 WT-LSSVM-PSOSA 模型） | T5: 纯数据驱动，未涉及物理机制融合（注：本文构建的混合预测模型（WPT-LSSVM-PSOSA）完全依赖于一维历史风速时间序列数据进行非线性映射。尽管该研究极具创新性地引入了相空间重构理论（Phase Space Reconstruction）并利用 C-C 方法计算序列的最佳延迟时间和嵌入维数，同时使用小波包变换（WPT）对序列进行了信号分解，但这些均属于纯数学统计与信号处理范畴的数据特征工程，全文未在网络输入、架构或损失函数中显式融合任何空气动力学偏微分方程、多变量气象定律等流体力学物理机制 。） | U5: MSE均方误差（注：在 LSSVM 模型中，利用 PSOSA 算法寻优其核心参数（c 和 σ2 ）时，明确将验证集上的均方误差（MSE）定义为粒子的适应度函数（fitness function）进行直接优化；而 LSSVM 本身的优化目标也是基于误差平方项，全文未提及添加任何物理约束项） | V5: RMSE 降低了 6.59% 至 12.54%（注：原文在表 10（Table 10）中明确给出了所提出的 WPT-LSSVM-PSOSA 模型相较于同组表现最好的基线模型（WT-LSSVM-PSOSA）的误差下降具体百分比。在中国西北的四个风电场（Site 1至 Site 4）测试中，其 RMSE 分别降低了 8.77%、7.71%、12.54% 和 6.59%；对应的 MAE 分别降低了 6.12%、9.86%、12.39% 和 6.68% 。） | W5: 解决了特征输入极其依赖人工主观试错，以及高精度寻优模型运算耗时过长的工程落地痛点（注：作者在研究中强调，通过引入相空间重构（C-C方法）自动判定输入数据的最佳回溯长度，大幅减少了个人主观特征选择对预测精度的负面影响 ；更具工程业务价值的是，由于融合了带有退火机制的粒子群优化（PSOSA），模型仅需极少迭代进化（20次）即可逼近 200 次迭代的同等最优预测精度，CPU 计算耗时大幅缩减。这使得该系统能够极其轻易地部署在风电场的高性能计算机并行架构中，为防范电网崩溃和降低系统备用容量提供实时、高效的短期决策支撑 。） | X5: 分解-预测混合框架，优化算法增强，支持向量机类
A6: 6 | B6: 10.1016/j.rser.2014.12.012 | C6: 否 | D6: Combined forecasting models for wind energy forecasting: A case study in China | E6: 2015年（2014年投稿并在线发表）；刊源为 Renewable and Sustainable Energy Reviews。该期刊是能源领域的顶级期刊，通常属于中科院1区/JCR Q1分区 | F6: 未提供直接的代码下载链接 | G6: 点尺度 （注：研究对象明确为承德地区的三个特定风机站点，数据采集点直接关联至具体风机位置，而非网格化的空间预报场 ） | H6: 每小时（注：文献使用了三个风机从 2010 年 4 月 5 日至 2011 年 4 月 24 日的每小时风速数据；预测任务设定为利用过去 20 天（480 个数据点）的序列，预测未来 10 天（240 个数据点）的每小时风速值 ） | I6: 未明确说明 | J6: 内陆风场区域（承德地区） （注：研究区域位于河北省东北部，地理坐标为东经 115°15′40″–119°11′50″，北纬 40°11′10″–42°14′00″；文中提到风能资源集中在围场、丰宁和平泉县，并特别指出丰宁县部分地区由于无风力障碍物，非常适合建设风电场） | K6: 纯历史风速（注：原文明确指出仅使用了中国承德地区三台风机的“逐小时风速数据（hourly wind speed）”进行建模 ，未引入温度、气压、风向等任何其他气象变量数据）。 | L6: 有 （注：明确使用了来自三个风机的每小时实测风速数据（hourly average wind speed data of three wind turbines）；虽然未列出传感器型号，但数据源属于物理站点的观测数据） | M6: Min-Max归一化与系统误差后处理修正（注：在 BP 神经网络的数据预处理阶段，使用极值线性变换公式将输入变量归一化 ；在特征工程方面，针对 SVM 模型因系统性误差经常出现低估的情况，在预测结果后统一加上了 4.0895 m/s 的均值修正项（Data post-processing technique） 。全文未提及频域分解方法） | N6: 未提及（注：全局扫描正文、结论及致谢部分，仅提及研究数据来自中国承德地区的三个风机，完全未提供任何开源下载链接、GitHub 地址或官方数据库入口 ）。 | O6: 未提及（注：虽然文章在“研究区域（Study area）”部分对承德地区的地形（如无风路障碍物）进行了文字描述 ，但其构建的所有预测模型输入层全为一维的纯时间序列数据，未显式输入高程 DEM、地表粗糙度等空间静态物理特征） | P6: 未提及（注：全文完全没有提及湍流动能 (TKE)、局部垂直风切变或由于地形/风机引起的尾流扰动等微尺度物理特征 ） | Q6: 多步历史风速滞后序列（注：模型高度依赖目标站点自身的历史风速滞后项。例如：BP 模型使用过去30天（共720小时）的数据作为输入矩阵预测未来风速，混合卡尔曼滤波 (HKF) 模型使用过去 10 个小时的数据作为滞后输入 。各风机之间独立进行预测，明确未引入相邻或上游气象站点的空间传播特征，也未显式输入月份/小时等时间周期编码）。 | R6: 单点多步确定性预测（注：模型最终针对 3 个独立的风机节点，基于已有的历史时序数据，输出未来 10 天、逐小时（共计 240 个时间步）的风速确定性标量预报值，不涉及概率区间预测或网格面预报 ） | S6: 提出无负约束理论（NNCT）与启发式算法赋权的组合预测模型（注：本文的创新点在于打破了传统的“权重必须为正”的限制，提出了无负约束理论组合模型（TCM-NNCT），以及利用混沌粒子群算法（CPSO-CM-NNCT）和遗传算法（GA-CM-NNCT）来智能寻找最佳权重。用于对比的 Baseline 基线模型包括：传统的正权重组合模型，以及 5 个独立的底层子模型：ARIMA、ARCH、BP 神经网络、SVM 和 HKF ） | T6: 纯数据驱动，未涉及物理机制融合（注：本文是一篇极其纯正的“纯数据驱动-时间序列组合预测”文章。模型完全依赖一维历史风速序列数据，底层的五个子模型（ARIMA、ARCH、BP、SVM、HKF）均为经典的统计学或机器学习黑盒模型。顶层的组合策略更是纯粹的数学权重优化（基于无负约束理论和混沌粒子群算法计算最小误差平方和），全文未在特征输入或损失函数中引入任何气象动力学方程、温度/气压等多变量特征，也未显式融合任何流体力学物理约束） | U6: SSE误差平方和/MSE（注：无论是在传统的组合方法中，还是在 CPSO 和 GA 等智能优化算法计算适应度（fitness value）寻找最优组合权重时，均明确采用了预测输出与实际值之间的误差平方和（SSE）作为唯一的目标优化函数；各底层模型自身也以均方误差映射为主，未提及添加任何物理机制约束项 ） | V6: 组合优化后 SSE 与 MSE 均取得绝对数值上的显著降低（注：原文在表 9（Table 9）等核心评估结果中明确给出了绝对对比数值。以 3 号风机（Wind turbine 3）为例，在所有的单体基线模型中，表现最好的 ARCH 模型的 SSE（误差平方和）为 589.366 (m/s)²，MSE 为 0.1012 m/s；而本文提出的基于 CPSO 算法优化的五模型集成架构（CPSO-CM-NNCT），将其 SSE 进一步降低至 552.634 (m/s)²，MSE 降低至 0.098 m/s，且整体精度和稳定性均优于传统的“简单非负权重组合模型”与“GA 遗传算法组合模型”） | W6: 打破了传统组合预测中“权重必须为正”的思想钢印，并解决了预测高波动性对并网安全的致命威胁（注：作者在结论与实验分析中深刻指出，传统集成学习强制要求“权重必须在 之间且为正”往往会导致部分子模型失效（权重被赋为0）。本文放开约束，对预测趋势与实际序列相反的子模型赋予负权重（范围扩展至 [-2, 2]），反而大幅提高了预测精度。同时，研究明确证实了遗传算法（GA）在权重寻优时表现出的高波动性对电网安全是“致命的（lethal for grid security）”，而混沌粒子群算法（CPSO）展现出的极强鲁棒性，使其非常适合用于中国大型风电场的短期稳定调度需求） | X6: 集成方法，优化算法增强
A7: 7 | B7: 10.1177/0958305X18787258 | C7: 否 | D7: Prediction of wind speed using a new Grey-extreme learning machine hybrid algorithm: A case study | E7: 2019年（2018年在线发表）；刊源为 Energy & Environment。该期刊通常属于 JCR Q3/Q4 分区或中科院 4 区 | F7: 未提供直接的代码链接 | G7: 点尺度 （注：研究对象为伊朗赞詹省省会赞詹市，文中明确给出了该城市的地理坐标为北纬 36°40′、东经 48°29′，并未提及任何基于网格的空间分辨率） | H7: 日分辨率及 24 小时频率预测 （注：Grey ELM 混合算法模型采用了 2013-2015 年间的 8 个变量的日数据（daily data）进行长期预测研究；同时利用 Homer 软件分析了 10 年间的平均风速以获得 24 小时内的风速变化频率预测） | I7: 未明确说明 | J7: 山脉南部的寒冷半干旱气候区 （注：赞詹市位于伊朗首都德黑兰西北 298 公里处，地理位置在 Qaflankuh 山脉以南约 20 公里，气候特征为寒冷半干旱，夏季炎热干燥，冬季寒冷湿润） | K7: 8个气象与环境变量（注：原文明确指出使用了伊朗赞詹市（Zanjan）的八个历史变量数据作为模型输入：TMAX（最高温度）、TMIN（最低温度）、VP（水汽压）、RHMIN（最低相对湿度）、RHMAX（最高相对湿度）、WINDSPEED（风速）、SUNSHINE HOURS（日照时数）和 PERCIPITATION（降水量） , , ） | L7: 未明确提及具体传感器名称 （注：研究使用了最高温、最低温、蒸气压、最小相对湿度、最大相对湿度、风速、日照时数和降水量共 8 个气象变量作为输入，虽然这些属于物理观测数据，但文中并未列出测风塔、气象站或特定传感器硬件的名称） | M7: 累加生成操作（AGO）与 归一化（注：研究采用了灰色系统理论中的 GM(1,1) 模型。首先对原始时间序列执行累加生成操作（AGO）以降低数据的随机性并提取潜在的整体规律；接着将新序列归一化到 区间后输入极限学习机（ELM）进行训练；预测完成后，通过逆累加生成操作（IAGO）还原成原始风速序列的预测值 , , ） | N7: 未提及（注：全局扫描正文，仅交代了数据采集自伊朗赞詹市的两个时间段（2013–2016 年的长期预测数据和 2005–2015 年用于 Homer 软件的 24 小时预测数据），未提供任何开源下载链接、GitHub 地址或官方数据库入口 , , ） | O7: 未提及（注：文章在“Study area（研究区域）”中描述了赞詹市的坐标（36°40'N–48°29'E）和周边的山脉地理位置，但在其构建的算法模型输入层中，完全没有显式输入高程 DEM、地表粗糙度等空间静态物理特征 , ） | P7: 未提及（注：全文完全未提及湍流动能 (TKE)、局部垂直风切变或局部地形引发的尾流扰动等微尺度物理特征 ） | Q7: 单点本地时间序列，无空间传播关联（注：模型使用了目标城市自身的多变量日常时间序列。虽然借助 Homer 软件详细分析了逐小时的风速变动频率，但 Grey-ELM 核心模型并未显式表征相邻或上游气象站点的空间连带效应，属于孤立的单点时间序列挖掘 , , ） | R7: 单点确定性预报及逐时频率预测（注：一方面，Grey-ELM 预测模型输出未来的风速标量值；另一方面，文章创新性地借助 Homer 软件输出了未来 24 小时内不同特定时段（如第1小时、第14小时等）风速上升或下降变化的具体百分比频率图，不涉及概率区间或区域网格预测 | S7: 提出 Grey-ELM 混合算法（注：本文提出的创新模型结合了灰色系统理论模型（Grey model, GM(1,1)）与人工神经网络中的极限学习机（ELM）。用于对比的 Baseline 基线模型包括：普通的 ELM 算法，以及另外三种神经网络组合算法（NN+SFLA混洗蛙跳算法、NN+GA遗传算法、NN+SA模拟退火算法） | T7: 纯数据驱动，未涉及物理机制融合（注：本文提出的 Grey ELM 混合算法完全基于数学统计与机器学习。它利用灰色系统理论（GM(1,1)模型）对包含风速、温度、湿度等 8 个气象变量的时间序列进行累加生成操作（AGO）以降低数据的随机性与不确定性，随后输入极限学习机（ELM）进行黑盒非线性映射预测。全文未在模型特征、网络架构或损失函数中显式融入任何空气动力学偏微分方程或流体力学物理约束） | U7: MSE均方误差（注：在极限学习机（ELM）内部求取输出权重时采用了广义伪逆矩阵的方法（隐式基于最小化平方误差）；在模型验证与基线对比阶段，明确将均方误差（MSE）以及决定系数（R2）作为核心评估指标，全文未提及添加任何物理学约束惩罚项 | V7: MSE 降低至 0.000987，R² 提升至 0.99376（注：原文在结论与表格中明确给出了绝对对比数值。在 1038 个样本的测试集中，本文提出的 Grey-ELM 模型的 MSE 为 0.000987，相较于未经过灰色理论处理的普通 ELM 算法（MSE 为 0.00720）取得了极大幅度的绝对数值下降，且拟合优度 R² 从 0.98075 提升到了 0.99376。同时，该混合算法在绝对误差上也优于同组横评的 NN+SFLA、NN+GA、NN+SA 等深度学习组合基线模型） | W7: 克服了原始数据采集存在的随机不确定性，并实现了风速日内变动频率的精细化预测（注：作者指出，风速预测常受制于仪器误差、数据缺失等不确定性，Grey 理论的引入成功将不规则的时间序列平滑为了有规律的数据，直接提升了模型的抗噪能力。此外，该研究最具工程应用价值的一点是，结合 Homer 软件详细分析并预测了风电场一天 24 小时内不同时间段“风速变化的频率分布（如第X小时最频繁的变化是下降/上升Y个单位）”，这对于风电场在日内的微观灵活调度极具实操指导价值） | X7: 分解-预测混合框架，规则系统与灰色理论
A8: 8 | B8: 10.1051/e3sconf/202017301004 | C8: 否 | D8: Forecasting Wind Speed using Artificial Neural Networks – A Case Study of a Potential Location of Saudi Arabia | E8: 2020年；刊源为 ICACER 2020 (International Conference on Advanced Clean Energy Research) | F8: 未提供直接的代码下载链接 | G8: 点尺度 （注：研究对象为沙特阿拉伯的特定地理位置凯苏马，并未涉及网格化的预报场或空间粒度描述） | H8: 每小时（注：使用了 13 年间的每小时平均风速数据；实证研究中提取了 8760 个样本用于训练和测试，其中 7008 个样本用于训练，1752 个样本用于测试和验证） | I8: 未提及具体高度 | J8: 沙漠地形 （注：研究区域沙特阿拉伯基本为沙漠地带，夏季炎热，冬季寒冷；文中提到凯苏马是一个潜在的风资源开发点，但在具体实验中，海拔（elevation）是作为神经网络的一个输入属性（attribute）而非研究的地形背景） | K8: 历史风速、地温与相对湿度（注：原文在描述模型输入层时明确指出，输入层数据集的独特属性可以包含风速（wind speed）、地温（earth temperature）以及相对湿度（relative humidity）作为气象与环境特征 。） | L8: 有 （注：明确使用了“实测风速数据”（measured wind speed data），并将其作为模型训练的主要输入变量和验证效率的目标值；尽管文中未列出测风塔或传感器的具体型号，但数据来源于该地区的长期气象观测记录） | M8: 未提及复杂特征工程，仅进行基础数据集划分（注：文章仅说明将沙特阿拉伯 Qaisumah 地区长达 13 年（1970-1982年）的 8760 条每小时平均数据按比例划分成了 7008 条训练集和 1752 条测试/验证集。全文未提及任何数据清洗、异常值处理、归一化或 VMD 等频域分解方法 。） | N8: 未提及（注：全局扫描正文及参考文献，文中仅说明该历史长期风速数据来源于 1986 年出版的《沙特阿拉伯王国风能图集》（参考文献17），但完全未提供任何开源下载链接、GitHub 地址或官方数据库入口 。） | O8: 海拔高度（注：原文在描述人工神经网络（ANN）的输入层架构时，明确将“海拔（elevation）”与气象参数一并列入该数据集的独特输入属性（unique attribute）中 。） | P8: 未提及（注：全文侧重于宏观的长时间尺度测风数据拟合，完全未提及湍流动能 (TKE)、局部垂直风切变或局部地形引发的尾流扰动等微尺度物理特征 。） | Q8: 单点本地历史序列，无空间传播关联（注：模型在方法论上仅使用了目标观测点（Qaisumah）过去的历史实测风速作为主要输入变量（滞后项）来预测未来情况。文章明确是一个“个案研究（case-study）”，没有引入相邻或上游站点的空间连带效应，也未显式提取月份/小时等时间周期编码作为特征 。） | R8: 单点确定性预测（注：模型针对沙特 Qaisumah 这一单一潜在选址区域，利用测量数据预测出确定性的风速标量值，以论证 ANN 模型的有效性，不涉及概率区间预测或多点网格预测 。） | S8: 提出基于 LM 反向传播算法的两层前馈神经网络，无对比基线模型（注：本文提出使用带有 29 个隐藏神经元的两层前馈多层感知器（MLP）人工神经网络进行预测。非常值得注意的是，该论文仅用真实值验证了自身算法的有效性，并没有设置任何对比基线模型（Baseline）。作者在结论的最后一句明确承认：将目前的结果与文献中可用的其他模型进行对比，是“未来的工作（Future work）” 。） | T8: 纯数据驱动，未涉及物理机制融合（注：本文构建的是非常传统的前馈多层感知机（MLP）人工神经网络。模型完全依靠输入的数据进行黑盒非线性映射，利用 Levenberg-Marquardt 反向传播算法更新权重。全文未在网络拓扑或损失函数中显式融入任何气象学动力学方程、对数风廓线或流体力学等物理约束条件） | U8: MSE均方误差（注：在使用 Levenberg Marquardt 反向传播算法映射输入值和目标值时，明确将均方误差（MSE）以及平均绝对百分比误差（MAPE）作为计算预测精度和评估误差的核心指标，未提及添加任何物理学约束惩罚项 。） | V8: 未进行基线对比，仅报告绝对预测误差（MSE: 0.0912，MAPE: 6.65%）（注：这是一篇早期的应用型验证论文，原文完全没有设置任何 Baseline 基线模型（如 ARIMA 或传统机器学习算法）进行平行对比。作者在结论中明确声明：“与文献中其他模型的对比将包含在未来的工作中”。在测试集中，当该人工神经网络隐藏层神经元设定为 29 个时达到最佳性能，绝对误差数值为均方误差（MSE）0.0912，平均绝对百分比误差（MAPE）6.65%） | W8: 初步验证了利用黑盒神经网络对沙漠潜在风力资源点进行高精度并网负荷调度预测的可行性（注：作者指出，风速预测对于并网可再生能源系统的设计、运行以及调节电网负荷至关重要。该研究通过实证表明，针对沙特阿拉伯 Qaisumah 这种常年干旱的沙漠气候潜在风能点，纯神经网络模型能够将预测 MAPE 控制在 10% 以下（6.65%），达到了业内公认的“高预测精度”标准，为该地区未来的风电场选址与电网负载规划提供了早期的纯数据驱动参考依据） | X8: 前馈神经网络
A9: 9 | B9: 10.1016/j.seta.2022.101995 | C9: 否 | D9: A multi-scale model for day-ahead wind speed forecasting: A case study of the Houhoku wind farm, Japan | E9: 2022年；刊源为 Sustainable Energy Technologies and Assessments。该期刊通常属于 JCR Q1/Q2 分区 | F9: 未提供直接的代码下载链接 | G9: 多尺度网格 （注：中尺度 WRF 域包含三层嵌套，分辨率分别为 6.0 km、1.5 km 和最高 500 m；微观尺度的 CFD 模型 OpenFOAM 则进一步将分辨率提升至 100 m 和 50 m 的精细网格 ） | H9: 1 小时采样及输出频率 （注：WRF 模型输出的时间步长恒定为 1 小时，用于验证的涡轮机观测数据同样为 1 小时的时间间隔；预测目标是提前一天的日前预测，WRF 每日冷启动运行 30 小时，前 6 小时作为起旋期 ） | I9: 85m(文献明确指出研究对象的轮毂高度为 85 m) | J9: 山地复杂地形 （注：研究区域位于日本丰北（Houhoku）风电场，属于典型的多山崎岖地带，森林覆盖率约 66%；文中展示了包含 12 个风机位置的详细海拔图，并强调该地形会导致风况高度波动且难以被普通中尺度模型捕捉） | K9: 水平风速、风向、垂直风速与湍流动能（注：原文明确指出在耦合微尺度模型时，提取了由中尺度气象预报模型（WRF）输出的四个关键变量：水平风速（horizontal wind speed）、风向（direction）、垂直风速（vertical speed）以及湍流动能（TKE）作为 OpenFOAM 模型的初始/边界条件输入） | L9: 有 （注：使用了由 Clean Energy Factory 公司提供的 12 台风机的质量受控机舱（nacelle）风速观测数据，时间跨度为 2015 年至 2019 年，用于验证物理耦合模型及统计对比模型的预测精度） | M9: Cressman插值、VMD频域分解与卡尔曼滤波校正（注：在构建多尺度核心模型时，使用了 Cressman 插值算法将 500m 分辨率的 WRF 输出转化为微尺度边界条件；但在构建用作对比的 VMD-LSTM 深度学习基线时，显式使用了变分模态分解（VMD）将历史风速特征分解为子模态并进行了独立归一化；同时还单独采用了卡尔曼滤波（Kalman filter）作为后处理消除系统误差） | N9: 未提及真实测风开源链接（注：文中虽说明地形高程数据使用了公开的 GMTED2010 和 3弧秒分辨率的 SRTM 数据集，但核心的风电场测风数据由日本 Clean Energy Factory 公司提供，正文及附录中未给出对应的开源下载地址或代码 GitHub 库） | O9: 高精度数字高程模型（DEM）（注：显式输入了空间静态地形特征。文中明确采用了分辨率高达 3弧秒 的 SRTM 地形高程数据，将其投影转换为 UTM 坐标系后，用于生成 OpenFOAM 极高分辨率（50m/100m）的三维近地面几何计算网格） | P9: 湍流动能(TKE)与湍流耗散率(ϵ)（注：这是首次在我们精读的文献中显式引入微尺度物理场。该模型求解 RANS 方程，并利用标准 k−ϵ 湍流模型，不仅从 WRF 承接了湍流动能 TKE，还在边界条件中显式设定并计算了湍流耗散率（Epsilon），以捕获复杂山区地形产生的局部流体扰动） | Q9: 历史风速序列滞后项（深度学习基线专属）与物理流场隐式空间传播（注：在这篇文献中，“时空处理”分为两套逻辑。深度学习对比模型（VMD-LSTM）极其依赖历史时间序列，显式使用了过去5天（120个时间步）的风速数据作为滞后项输入（Lag variables）；而提出的核心多尺度流体物理模型，则摒弃了纯历史时序特征，完全依靠 3D 微尺度流场网格自动捕捉风电场内不同发电机之间的物理空间动力学关联） | R9: 单机级多步确定性日前预测（注：目标系统输出风电场内 12 台具体风机的轮毂高度处（85米）、未来24小时内逐小时（日前，day-ahead）的风速确定性标量预报值，不输出概率区间） | S9: 提出 WRF-OpenFOAM 多尺度耦合动力学模型（注：本文的核心创新是“气象中尺度+流体力学微尺度”的物理降尺度耦合模型。用于对比的 Baseline 基线模型不仅包括未耦合的单体 WRF 模式（WRF500），还跨界对比了纯数据驱动的 VMD-LSTM 深度学习组合模型，以及经典的 Kalman Filter 后处理算法） | T9: 耦合中尺度数值天气预报(NWP)与微尺度计算流体力学(CFD)的正向物理推演（注：这是一篇极其硬核的纯物理流体力学交叉论文。模型完全基于大气物理与空气动力学方程，将 WRF 中尺度气象模型的输出作为 OpenFOAM 微尺度模型的初始和边界条件，通过直接求解带有标准 k−ϵ 湍流模型的雷诺平均纳维-斯托克斯 (RANS) 偏微分方程，来模拟微尺度下的真实风场与湍流物理动态，而非依赖数据黑盒映射 ） | U9: 流体收敛残差与MSE均方误差（注：对于本文提出的核心物理流体动力学模型（CFD），其优化并不采用神经网络的损失函数，而是以流体方程稳态计算残差小于 10 −4 作为收敛目标；但原文明确说明，在训练其作为对照组的 VMD-LSTM 基线模型时，采用的是均方误差（MSE）作为唯一的损失函数） | V9: 相较于传统 WRF，冬季 RMSE 降低 36.43%，夏季 RMSE 降低 23.27%（注：原文在结论部分明确给出了绝对对比百分比。相较于仅使用中尺度 WRF 模型的预测结果（WRF-alone/WRF500），表现最好的 50 米高分辨率微尺度耦合模型（WRF_OF050）在冬季测试中使 12 台风机的平均 ME、MAE 和 RMSE 分别改善了 93.08%、40.64% 和 36.43%；夏季的改善幅度分别为 83.44%、30.25% 和 23.27% 。同时，作者证明其针对随机误差的降低能力也优于 VMD-LSTM 与 Kalman filter 等后处理算法 ） | W9: 解决了复杂山区地形下，传统中尺度气象模型无法精准提供“单台风机级别”轮毂高度日前预报的痛点（注：作者在研究动机和结论中深刻指出，日本的大部分风电场位于地形复杂的山区，传统 NWP 模型因空间分辨率过粗（如 500 米级以上）会完全忽略局部地形的剧烈起伏效应。该耦合模型成功实现了针对特定风机位置的高分辨率（50 米级）三维空间降尺度预报，大幅消除了系统性高估误差，且计算时效满足“日前预报（day-ahead）”的需求，为复杂地形风电场的精细化并网调度提供了强大的业务级工具 ） | X9: 数值天气预报，计算流体动力学
A10: 10 | B10: 10.1016/j.physa.2019.123383 | C10: 否 | D10: Artificial Neural Network based computing model for wind speed prediction: A case study of Coimbatore, Tamil Nadu, India | E10: 2020年（2019年在线发表）；刊源为 Physica A: Statistical Mechanics and its Applications，通常属于 JCR Q2/中科院 2-3 区 | F10: 未提供直接的代码下载链接 | G10: 点尺度 （注：研究针对特定地理坐标点进行，位置为印度泰米尔纳德邦哥印拜陀（Coimbatore）的 Palladam，具体地理坐标为北纬 10°59′25.8″，东经 77°17′10.9″ ） | H10: 超短期 （文献指出数据采集频率为每 10 分钟一次（每天 144 个数据点）） | I10: 65m(该模型的核心任务是利用 50m、63m 和 48m 高度的观测数据来预测 65m 高度处的风速) | J10: 黑土平原 （注：研究区域位于哥印拜陀的黑土平原地区；文中使用了 WGS84 大地坐标系统标注位置，但未明确给出具体的海拔高度数值） | K10: 50米高度风速与48米/63米高度风向（注：原文明确指出模型的输入参数（Factors）为 50米高度的风速（m/s），以及 63米和 48米高度的风向角（相对于正北的度数），完全未引入温度、气压等其他气象环境变量 ） | L10: 有 （注：明确使用了物理传感器的实测数据，包括安装在 50 米高度的风速计（Anemometer）以及分别安装在 63 米和 48 米高度的风向标（Wind Vane）） | M10: 随机数据划分、标准化重缩放与可视化分箱操作（注：研究收集了 52560 条分钟级数据，并基于相对数量按 70% 训练集和 30% 测试集进行了随机划分分配；在 MLPNN 网络架构的特征工程中，明确使用了标准化（Standardized）重缩放方法；特别地，针对分类回归（CATREG）模型中出现的负值问题，采用了“等百分位可视化分箱工具（visual binning tool with equal percentiles）”将预测风速和实际风速分类处理 ） | N10: 未提及（注：全局扫描正文及致谢部分，文中仅说明该真实风场数据是由 Suzlon Energy Limited (Palladam) 公司提供，并未附上任何开源下载链接、GitHub 地址或官方数据库入口 ） | O10: 未提及（注：尽管文章在“材料与方法”部分描述了数据采集站的具体经纬度位置（纬度 10°59'25.8''，经度 77°17'10.9''，WGS84 坐标系），但在神经网络和回归模型的实际输入层设计中，完全没有显式输入这些地理坐标或高程 DEM、地表粗糙度等物理特征 ）。 | P10: 未提及（注：全文完全没有提及湍流动能 (TKE)、垂直风切变物理方程或局部地形引起的尾流扰动等微尺度物理特征 ） | Q10: 未提及（注：这是一个非常重要的特征！ 本文实质上构建的是一个同一时间点上的“垂直空间推演模型”而非典型的时间序列预测模型。它是利用底层（50米/48米/63米）的风速和风向瞬时数据，去映射预测同一时刻 65米高度的风速。模型完全没有提及使用过去的历史风速时间滞后项（Lag variables），也未引入时间周期编码或相邻气象站点的空间传播特征 ）。 | R10: 单点确定性高度推演标量值（注：模型输出层的节点数为 1，具体输出形态为预测出的 65 米高度处的单点风速确定性数值（m/s），不涉及概率区间预测或区域网格预测 ）。 | S10: 提出多层感知机（MLPNN）、径向基函数网络（RBFNN）与分类回归（CATREG）的横向对比（注：本文并未提出全新的网络拓扑架构，而是将三种现有的纯数据驱动算法用于此特定的高度降尺度/推演任务进行横向横评。最终实验证明，在这三者中，MLPNN（多层感知机）给出了最小的误差并被认为是表现最好的模型 ） | T10: 未融合物理机制/纯数据驱动（注：本文提出使用多层感知机神经网络 (MLPNN)、径向基函数神经网络 (RBFNN) 和分类回归 (CATREG) 建立预测模型 。模型完全依靠输入的 50 米高度风速以及 48 米、63 米高度的风向特征，对 65 米高度的目标风速进行黑盒非线性映射预测 ，全文未在网络设计或损失函数中融合对数风廓线、计算流体力学 (CFD) 等任何气象学或物理学方程 ） | U10: 平方和误差（Sum of squares）（注：在 MLPNN 模型的网络自动架构参数表中，明确使用了平方和（Sum of squares）作为优化网络权重的误差函数（Error function）；同时 CATREG 方法的数学原理也是最小化响应变量与预测变量之间的平方差之和。在最终性能评估阶段则使用了均方误差（MSE） ） | V10: 未给出直接提升百分比，最佳模型 MLPNN 测试 MSE 为 195.417（注：原文未提供基线对比的百分比幅度，仅给出了绝对误差数值。在实测对比中，表现最好的 MLPNN 模型的测试 Error 为 195.417，MSE 为 0.025，决定系数 R² 达到 0.977 ；在绝对数值上显著优于作为对比的 RBFNN 模型（测试 Error 0.477，MSE 3853.775）以及首度被引入该领域的分类回归 CATREG 模型（Error 0.041）） | W10: 验证了跨高度风速推演的可行性，以降低风电场年度发电量预测的经济风险（注：作者在结论中深刻指出，仅仅做到“统计学上的匹配”对风能应用来说是不够的，因为哪怕是仅仅 1% 的预测不确定性，也会在年度能源预测中产生极高的经济偏差 。该模型利用较低高度（50米）的风况数据精准推算目标轮毂高度（65米）的风速，极大降低了风电场微观选址与并网调度时的经济预估风险 ） | X10: 前馈神经网络，基础基准与回归类
A11: 11 | B11: 10.1016/j.energy.2015.10.026 | C11: 否 | D11: Wind-speed prediction and analysis based on geological and distance variables using an artificial neural network: A case study in South Korea | E11: 2015年；刊源为 Energy。该期刊通常属于中科院 1 区/JCR Q1 分区 | F11: 未提供直接的代码链接 | G11: 点尺度 （注：研究基于分布在韩国全境的 469 个自动气象站（AWS）的特定坐标点数据；实证部分具体使用了 12 个平原站、9 个海岸站和 8 个山地站的单点观测值，未涉及网格化空间预报场） | H11: 每小时（注：文献使用了 1997 年至 2012 年间的每小时实测风速数据作为基础；ANN 模型的训练期为 2007-2011 年，测试验证期为 2012 年 1 月 1 日至 3 月 31 日，均保持每小时一次的数据频次） | I11: 未提及具体高度 | J11: 平原、里亚斯海岸及复杂山地 （注：研究将韩国地形划分为三大类：平原（如西海岸的礼唐平原）、海岸（强调具有曲折海岸线和约 2500 个岛屿的典型里亚斯特征）以及山地（横跨半岛东部的太白山脉）；山地站点如五台山（Guryongryung）的海拔高达 1015.1 米） | K11: 周边参考站的历史风速（注：原文在描述人工神经网络（ANN）模型构建时明确说明，输入层（Input Layer）仅包含两个参考站点（Reference sites）的风速数据，完全未引入温度、气压、风向等其他气象变量作为输入 | L11: 有 （注：明确使用了来自 469 个自动气象站（AWS）的物理观测数据，包含各站点的经纬度、海拔高度和实时测量的每小时风速） | M11: 按年份划分训练/测试集与人为地理分类（注：研究收集了1997-2012年的风速数据，并在分析前将其人为划分为三大地理类别（平原、海岸、山区）。在模型训练的具体特征处理层面，仅简单将 2007-2011 年的数据作为训练集，2012 年的数据作为无监督测试集，全文未提及使用归一化、异常值处理或 VMD 频域分解等复杂特征工程处理方法 ）。 | N11: 未提及具体获取链接（注：文中说明了 469 个自动气象站（AWS）的全部数据均由韩国气象厅（KMA）提供，但在正文和参考文献中均未提供任何可供下载的开源网址链接、GitHub 地址或直接访问的官方数据库网页入口 ） | O11: 未提及（仅作为评估分类依据，非模型输入）（注：这是一个极易产生幻觉的点！虽然文章的主旨是研究“地理特征（平原/海岸/山地）”和“距离”对预测精度的影响，并采集了海拔和经纬度，但这些空间静态物理特征并没有被显式输入到 ANN 的网络计算中。ANN 的输入层只吃纯风速数据，地理和距离因素仅用于事后的误差归因分析和分组讨论 ）。 | P11: 未提及（注：全文完全没有提及湍流动能 (TKE)、局部垂直风切变或局部地形引发的尾流扰动等微尺度物理特征输入 ） | Q11: 相邻气象站点的空间连带/传播特征（注：这是一篇非常典型的基于“空间关联映射”的研究（类似 MCP 测量-相关-预测法）。模型没有使用目标站点自身的历史风速滞后项，也没有引入时间周期编码，而是完全依靠周边 2 个相邻测风站（参考站）同一时间的风速数据作为特征输入，去推演目标站点的风速表现，高度依赖空间传播关联效应 ）。 | R11: 单点确定性空间推演预测（注：模型的输出层为1个节点，即根据相邻参考站的输入，输出目标气象站点（Target site）对应的风速确定性标量值，不涉及概率区间预测或区域网格预测 ）。 | S11: 使用标准多层感知机（MLP）进行地貌适应性横评，无对比基线模型（注：本文未提出创新的深度学习拓扑架构，直接使用了带有 Levenberg-Marquardt 反向传播算法的三层前馈神经网络。特别注意：本文未设置诸如 SVR、ARIMA 等常规算法作为 Baseline 进行对比，其所有的性能实验均是在不同地貌（平原、山地、海岸）和不同距离的测风站组合之间进行的内部横向规律对比 ） | T11: 纯数据驱动，未涉及物理机制融合（注：本文构建的是经典的多层感知机前馈神经网络（ANN） 。该模型完全依靠周边两个参考气象站的历史风速数据作为输入，去黑盒映射预测目标站点的风速 。虽然文章在其标题和结论中深度探讨了平原、海岸、山地等地质地形特征以及气象站间距离对预测精度的影响，但这仅仅是对预测输出结果（相关系数）进行的外部统计学事后分析，全文并未在网络结构、特征输入层或损失函数中显式融入任何空气动力学、数值天气预报（NWP）或流体力学等物理约束方程 ） | U11: 未明确命名具体的公式名称（注：隐式为均方误差等，原文仅提到性能目标）（注：文章仅明确说明使用了 Levenberg-Marquardt 反向传播算法进行训练，并设定了具体的“训练性能目标（performance goal of training）为 0.0005”，但并未在正文或公式中明文提及是均方误差（MSE）还是误差平方和（SSE），也未提及添加任何物理约束项 ） | V11: 未进行基线模型对比，仅报告目标预测的相关系数（最好结果为 0.7438）（注：这是一篇聚焦于“空间气象站关联性评估”的应用型研究，原文完全没有设置任何其他的 Baseline 基线模型（如 ARIMA、SVR 等）进行平行误差对比，也没有报告常规的 RMSE 或 MAE 数值 。作者仅给出了实际测风数据与 ANN 模拟数据之间的相关系数（Correlation coefficient）来衡量精度。结果显示，表现最好的内陆平原地区（Plain #1）相关系数最高达到 0.7438，而受海洋气候和复杂地形影响强烈的海岸与山区，其相关系数普遍极低（甚至低至 0.1973） ） | W11: 揭示了利用周边气象站推测目标地风速时的空间地形限制，为国家级风电场宏观选址提供了“避坑指南”（注：作者在研究动机中提到，韩国早年曾因选址前未充分评估风速波动特征，导致郁陵岛风力发电系统运行仅60天便因发电不足而停电失败 。该研究通过全韩国规模的测风站关联分析，向工程界证明了一个极具业务价值的残酷真相：在推演未知地点风速时，距离近并不等于风速相关性高，复杂山地和海岸线的地形气候对风速关联性的破坏极大。因此，仅仅依靠周边气象站和普通神经网络，无法在全国范围内提供绝对稳定的风能评估，必须引入更多能补偿地质气候效应的变量 ） | X11: 前馈神经网络
A12: 12 | B12: 10.1080/15567036.2011.551915 | C12: 否 | D12: An Analysis of Wind Speed Prediction Using Artificial Neural Networks: A Case Study in Manjil, Iran | E12: 2012年；刊源为 Energy Sources Part A: Recovery, Utilization & Environmental Effects。该期刊通常属于 JCR Q3/Q4 分区 | F12: 未提供直接的代码下载链接 | G12: 点尺度 （注：研究对象明确为伊朗的曼吉尔气象站（Manjil station），属于针对特定单点观测站的研究，未涉及网格化空间预报场） | H12: 每月平均每日（注：文献使用的输入变量和输出预测目标均为“每月平均每日”数值，包括月平均每日气温、相对湿度、蒸气压以及月平均每日风速） | I12: 未提及 | J12: 未提及 （注：研究区域确定为伊朗的曼吉尔（Manjil），但提供的资料中未明确提及该区域的具体海拔高度数值或地形特征描述） | L12: 有 （注：明确使用了来自曼吉尔气象站（Manjil station）的测量数据（measured data），包括气温、相对湿度和蒸气压，用于神经网络模型的训练与测试）
A13: 13 | B13: 10.1016/j.enconman.2021.114002 | C13: 否 | D13: A deep learning-based evolutionary model for short-term wind speed forecasting: A case study of the Lillgrund offshore wind farm | E13: 2021年，发表于 Energy Conversion and Management | F13: 未提及 | G13: 点尺度 （注：研究针对 Lillgrund 海上风电场的特定风机进行，实证案例选取了编号为 D8 和 B8 的两台风机作为观测点，并未涉及网格化气象场或空间预报分辨率） | H13: 短期（注：SCADA 系统以 10 分钟的时间间隔收集风电场信息；研究设定了两个预测时长：提前 10 分钟预测和提前 1 小时预测 ） | I13: 未明确说明（注：文献指出在该研究区域，轮毂高度处的平均风速约为 8.5 m/s；由于数据来源于风机 SCADA 系统，预测和验证的对象均为风机轮毂高度处的实时风速 ） | J13: 海上浅水区域 （注：研究区域位于波罗的海（Baltic Sea）内的 Oresund 浅滩，距离瑞典海岸 7 公里，水深在 4 至 8 米之间；地形特征为典型的海上环境，文中还分析了该区域风速分布的强各向异性特征） | K13: 风速与风向（注：原文在特征输入阶段明确对比了两种系统架构：第一种仅使用单一的风速序列作为输入；第二种为了评估风向属性对预测系统的影响，同时输入了风速和风向两个变量，但随后的统计实验结果表明，额外增加风向数据并没有显著提升预测精度 。） | L13: 有 （注：明确使用了监控和数据采集系统（SCADA），通过风机自带的物理传感器实时获取风速和风向数据，数据采集频率为每 10 分钟一次） | M13: 进化分解（ED）算法与自编码器特征提取（注：本文没有使用常规的 VMD 或小波变换，而是提出了一种新型的进化分解方法（ED）。该方法首先利用自编码器（Autoencoder）提取输入数据的通用抽象特征，然后按月、周、日三个层次将风速时间序列分解为重组的子序列以提升学习效果 。整个数据集被划分为 80%训练集、10%验证集和10%测试集，并使用了 K折交叉验证 。） | N13: 未提及（注：全局扫描正文及致谢部分，文中仅说明数据来源于 Vattenfall 项目提供的瑞典 Lillgrund 海上风电场 SCADA 数据，但并未提供可供公开下载的数据集链接、GitHub 仓库或官方数据库网页入口 。） | O13: 未提及（注：尽管文章在案例分析部分描述了 Lillgrund 海上风电场的地理特征（如距离海岸 7 公里、水深 4-8 米等）及风机排布图 ，但在实际构建 Bi-LSTM 深度学习模型的输入层时，完全没有显式输入这些物理位置坐标或高程 DEM 等空间静态特征，模型依然是纯时间序列驱动的 。） | P13: 未提及（注：全文完全没有提及将湍流动能 (TKE)、局部垂直风切变或海平面尾流效应等微尺度物理参数作为模型的特征输入 。） | Q13: 单点本地历史滞后序列与多层级时间周期分解关联（注：模型极其依赖目标风机（D8、B8）自身的历史时序数据。通过 Bi-LSTM 捕捉序列的前向和后向依赖关系 ；同时，借助 ED 算法隐式提取了“月、周、日”的时间周期层级特征 ，并在后续实验中按四季（春、夏、秋、冬）进行了周期性分组实验 。但两台风机的预测是相互独立的，未引入相邻海上风机间的空间传播或尾流连带特征 。） | R13: 单点短期/超短期确定性预测（注：模型分别针对特定风机节点，基于 10 分钟分辨率的数据，输出未来 10 分钟（超短期）和未来 1 小时（短期）的风速确定性标量预报值，不输出概率区间预测或海上风电场全域网格预报 。） | S13: 提出 ED-HGNDO-BiLSTM 混合深度学习进化模型（注：本文提出了一种将进化分解 (ED)、混合广义正态分布优化 (HGNDO) 与双向长短期记忆网络 (Bi-LSTM) 相结合的创新并行架构 。用于极其详尽对比的 Baseline 基线模型不仅包括 4 种常规网络（FFNN、ANFIS、PNN、NAR）、经过网格搜索调参的单体 LSTM 和 Bi-LSTM，还包括另外 7 种基于不同元启发式算法（如 CMAES、DE、WOA、SCA 等）优化的 Bi-LSTM 变体 。） | T13: 未融合物理机制/纯数据驱动（注：本文提出的是基于深度学习与仿生进化算法的混合架构（ED-HGNDO-BiLSTM）。模型完全依赖于瑞典波罗的海海上风电场的历史风速数据进行黑盒非线性映射预测。它引入了进化分解（ED）来拆解时间序列，并利用混合广义正态分布优化算法（HGNDO）来对双向 LSTM 网络（Bi-LSTM）进行智能超参数寻优。通篇未在特征工程、网络结构或损失函数中显式融入任何气象物理动力学方程、数值天气预报或微尺度流体力学约束 ） | U13: RMSE 与 引入训练时长惩罚项的复合适应度函数（注：在使用自编码器进行分解评估以及底层神经网络评估时主要依赖均方根误差（RMSE） ；值得注意的是，在利用 HGNDO 算法进行超参数寻优时，专门构建了一个包含测试集 RMSE (f 1 ​ ) 与 训练耗时惩罚项 (f 2 ​ ) 的复合适应度函数（以防模型架构过于复杂导致计算成本过高），未提及添加物理学方程约束项 。） | V13: 相较于表现最好的对比模型，RMSE 降低了 4.13% 至 31.03% 不等（注：原文在评估 B8 风机未来一小时风速预测结果时，给出了极其明确的改善百分比数值。提出的 ED-HGNDO-BiLSTM 模型相较于同组表现最好的混合基线模型（HGNDO-BiLSTM）改善了 4.13%；而相较于标准的 BiLSTM-grid 和 LSTM-grid，RMSE 分别降低了 10.34% 和 11.72%；对比传统的浅层神经网络（如 NAR）则取得了高达 31.03% 的显著降幅 ） | W13: 打破了深度学习在实际工程落地时极度依赖“人工主观试错调参”的效率瓶颈与性能天花板（注：作者在研究动机中深刻指出，LSTM 等深层网络在实际应用时，由于超参数极其敏感且极难手动寻优，严重制约了预测模型的可靠性。该模型通过内嵌自动化、带有局部快速搜索（NM）能力的仿生调参系统，不仅完全免除了人工调参的时间成本，还通过并行计算与“将训练耗时加入惩罚函数（Loss）”的设计，大幅加快了训练速度，极大增强了大规模海上风电场短期日前/日内调度的经济可行性 ） | X13: 循环神经网络，分解-预测混合框架，优化算法增强
A14: 14 | B14: 10.1016/j.ijepes.2014.07.008 | C14: 否 | D14: A novel heuristic method for wind farm power prediction: A case study | E14: 2014年，发表于 Electrical Power and Energy Systems | F14: 未提及 | G14: 点尺度 （注：研究对象明确为 Summerside 风电场及其内部的 4 台 3 MW 涡轮机，模型针对每台风机独立建模后进行总和，而非基于特定水平网格分辨率的预报场） | H14: 1 小时与 20 分钟 （注：短期预测（Short-term）采用 1 小时时间间隔预测未来 36 小时，超短期预测（Very short-term）采用 20 分钟时间间隔；同时提到在线 SCADA 系统具有每 10 分钟记录一次数据的能力） | I14: 未提及具体高度 | J14: 未提及 （注：研究区域确认为加拿大的 Summerside 风电场，文中提到模型考虑了“地理条件”等环境因素，但并未给出该区域的具体海拔数值或地形复杂程度的定性描述） | K14: 风速、风向、温度、湿度与气压（注：原文明确说明将数值天气预报（NWP）模型提供的未来气象参数以及 SCADA 系统测量的历史气象数据作为神经网络的输入，具体变量包含了风速、风向、温度、空气湿度和气压 ） | L14: 有 （注：明确使用了来自在线监控和数据采集系统（SCADA）的实测数据，内容包括风机的功率输出、风速以及设备可用性记录，用于模型的训练及超短期功率预测） | M14: 基础时间窗口切分与节点结构重组（注：原文未提及使用归一化、异常值处理或频域分解（如VMD、小波变换）等复杂的特征工程方法，仅是将时间序列数据按特定滑动窗口分配到神经网络的 81 个输入节点中进行构建 ） | N14: 提供官方气候数据库与风机设备网址（注：在文献末尾的参考文献部分，作者给出了加拿大国家气候数据与信息档案馆的网址 <http://www.climate.weatheroffice.gc.ca>，以及设备商 Vestas 的网址，但并未提供专门打包好的开源代码或直接的 GitHub 仓库 ） | O14: 未提及（注：尽管文章在摘要中泛泛提到了“考虑环境因素（如地理条件、风速等）”，但在模型实际构建的 81 个特征输入节点中，完全没有显式输入高程 DEM、地理坐标或表面粗糙度等具体的空间静态物理特征 ） | P14: 未提及（注：全文完全没有提及将湍流动能(TKE)、局部垂直风切变或风机间的尾流效应等微尺度物理参数作为模型的特征输入） | Q14: 多步历史滞后序列与未来NWP预报序列，无空间传播特征（注：该模型极度依赖时间序列特征，其 81 个输入节点中明确包含了过去 48 小时的风速、温度、气压和湿度历史值（Lag variables），以及未来 24 小时的 NWP 预测值。但模型是对风场内的每台风机进行“独立的 ICA-NN 黑盒预测”然后再汇总，完全未引入相邻风机间的空间连带或尾流传播特征 ） | R14: 单机级累加的多步确定性功率预测（注：模型为加拿大 Summerside 风电场的 4 台风机建立独立的预测黑盒，最终累加输出整个风电场未来 36 小时、按 1 小时（短期）或 20 分钟（超短期）为分辨率的确定性输出功率（Power）标量值，不涉及概率区间预测 ）。 | S14: 提出 ICA-NN 混合启发式神经网络，无自身数据集的直接平行对比基线（注：本文提出了一种利用帝国竞争算法（ICA，Imperialist Competitive Algorithm）来全局优化多层感知机（MLP）神经网络连接权重的创新模型。非常特殊的是，作者并未在自己的数据集上运行诸如 ARIMA、SVM 等 Baseline 进行严格对比，而是直接将自身跑出的 RMSE 误差百分比与“其他独立文献中跑其他数据集的误差数值”进行了比较，并坦诚指出这种跨数据集的对比并不完全公平 ） | T14: 未融合物理机制/纯数据驱动（注：本文虽然在输入端强依赖于数值天气预报（NWP）输出的温度、风速、风向、湿度和气压等多变量气象数据，但其核心模型是基于多层感知机（MLP）的人工神经网络。原文明确指出该模型是为每台风机构建了一个“ICA-NN 黑盒（black box）”来进行输入特征与输出功率之间的非线性映射 。网络使用纯数学的均方误差（MSE）作为目标函数 ，并通过帝国竞争算法（ICA）全局寻优权重，全文未在网络中显式融入任何气象物理学定律或空气动力学方程 ） | U14: MSE均方误差（注：原文明确给出了均方误差（MSE）的公式，并将其严格定义为帝国竞争算法（ICA）在搜索优化神经网络权重时的成本函数（Cost function）/目标函数，未提及添加任何物理学约束惩罚项 ） | V14: 未进行同数据集平行基线对比，测试给出的绝对 RMSE 分别为 7.1%（12h）与 11.8%（24h）（注：作者在原文中坦诚指出，由于该方法融合了 NWP 数据，与文献中其他单纯依靠统计数据的模型在不同数据集上进行横评是“不公平的（cannot be fair in comparison position）” 。因此仅报告了该模型自身的绝对误差：3小时、6小时、12小时、24小时和 36小时的预测 RMSE 分别为 3.7%、5.2%、7.1%、11.8% 和 17.2% 。相较于文献 中报告的 12小时（14%）和 24小时（17%）的误差，在绝对数值上表现出了显著优势 ） | W14: 实现了“单机级别独立建模”，完美解决了风电场部分风机处于检修或停机状态下的整场发电量精准预估痛点（注：作者在研究动机中强调，很多过往研究只将整个风电场视为单一整体进行预测。而本文通过为每一台独立风机构建预测黑盒，赋予了风电场操作员极大的业务调度自由度——当农场内有部分风机正处于大修或维护期（Maintenance and Overhaul periods）时，系统能够直接剔除停机设备，精准预估剩余可用机组的发电量，极大保障了发电企业在解除管制电力市场（deregulated market）中参与实时竞价的安全性 ） | X14: 优化算法增强，前馈神经网络
A15: 15 | B15: 10.1016/j.apenergy.2022.118777 | C15: 否 | D15: A short-term wind speed prediction method utilizing novel hybrid deep learning algorithms to correct numerical weather forecasting | E15: 未提及具体期刊，年份约 2021-2022 年 | F15: 未提及 | G15: 多尺度嵌套网格，最高 0.5 km（注：WRF 模型包含三个嵌套域，其水平分辨率分别为 4.5 km (d01)、1.5 km (d02) 和 0.5 km (d03)） | H15: 10 分钟（注：WRF 模拟的时间分辨率设定为 10 分钟；验证所用的观测数据亦是从 1 分钟分辨率的原始数据中每 10 分钟提取一次，每个变量包含 1440 条数据） | I15: 80 米（注：实测数据采集自气象塔离地 80 米高度处，文中明确指出该高度被视为风力发电机组的轮毂高度（wind turbine hub）） | J15: 科罗拉多州 Boulder 南部的 Flatirons 校区（原 NWTC）（注：研究区域位于北纬 39.9106°，西经 105.2347°，处于 Flatirons 校区的西缘；文中提供了该地点的地理坐标，但未直接给出该地点的具体海拔高度数值） | K15: 数值模式多层嵌套预报变量与历史风速（注：原文明确说明，首先从 WRF 数值预报模式的不同嵌套网格（外层 d02 和内层 d03）中提取了风速、风向、气压、温度、相对湿度等变量；随后利用皮尔逊相关系数（PCC）进行特征筛选降维，最终选定 d02 和 d03 的风速、d02 和 d03 的风向，并将它们与真实的历史风速共同作为后续深度学习模型的基础输入）。 | L15: 有（注：明确使用了来自气象塔（meteorological tower）的实测数据作为校正标签和验证基准，传感器采集的变量包括风速、风向和温度） | M15: 皮尔逊相关系数筛选（PCC）与 CEEMDAN 频域分解（注：特征工程分为两步：第一步用 PCC 计算各气象变量与“WRF预报误差”之间的相关性以剔除冗余特征；第二步采用自适应噪声完备集合经验模态分解（CEEMDAN）将筛选出的输入特征和历史风速序列统一分解为 8 个具有不同频率的本征模态函数（IMFs）。数据集最终按 70% 训练集、15% 测试集和 15% 验证集进行划分） | N15: 提供美国国家可再生能源实验室(NREL)官方数据链接（注：全局扫描参考文献与正文，文中在介绍风电场测风塔数据来源时，明确提供了 NREL NWTC M2 测风塔真实测量数据的开源获取 DOI 链接：http://dx.doi.org/10.5439/1052222） | O15: 未提及（注：尽管文章提及了 WRF 模式的嵌套网格分辨率（d01为4.5km，d02为1.5km，d03为0.5km）以及测风塔的经纬度坐标，但在其构建的核心深度学习混合预测模型（CNN-BLSTM）输入层中，完全未显式输入高程 DEM 或地表粗糙度等静态空间物理特征）。 | P15: 未提及（注：全文完全没有提及将湍流动能(TKE)、局部垂直风切变或局部地形引发的尾流效应等微尺度物理参数提取并输入到深度学习网络中） | Q15: 目标站点历史风速滞后序列与 WRF 嵌套网格空间特征联合输入（注：模型不仅显式输入了目标站点的历史实测风速序列作为时间滞后项，而且创新地同时提取了 WRF 外部网格（d02）和内部网格（d03）的气象特征。算法利用 CNN 同步提取这些不同模态/网格序列间隐藏的“非线性空间相关特征（spatial correlation features）”，再通过 Bi-LSTM 叠加注意力机制提取时间相关特征。模型针对单点运作，未引入其他相邻真实物理测风站的数据）。 | R15: 单点多步确定性误差预测与风速修正（注：这是一个典型的残差/误差修正架构。深度学习网络并不直接输出预测风速，而是预测 WRF d03 预报风速与实际风速之间的“误差（Error）”。随后将该误差补偿回 WRF 的原始预报值中，最终输出目标测风塔未来 10、20、30、50 分钟（单步与多步）高度为 80 米的确定性风速标量预测值，不输出概率区间） | S15: 提出 WRF-PCC-CEEMDAN-CNN-BLSTM-AMGS 误差修正深度学习混合模型（注：本文的创新点是利用高度杂交的深度学习模型对传统 NWP（WRF）的物理预报进行误差纠正。用于对比的 Baseline 基线模型包含了单体模型（BP, SVM, CNN, LSTM, BLSTM）以及一系列分解后的消融组合模型（CEEMDAN-BP, CEEMDAN-SVM, CEEMDAN-CNN, CEEMDAN-LSTM, CEEMDAN-BLSTM, CEEMDAN-CNN-BLSTM, CEEMDAN-BLSTM-AM）以验证各模块的有效性） | T15: 纯数据驱动，未涉及物理机制融合（注：本文虽然在前端利用数值天气预报（WRF）大模型解算了流体动力学和热力学方程以获取初始气象场 ，但其核心构建的误差修正模型（CNN-BLSTM-AM）完全是一个纯数据驱动的黑盒。它仅将 WRF 不同嵌套网格（d02, d03）输出的风速、风向、气压、温度等作为特征变量输入进行非线性映射 ，全文并未在深度学习网络内部、拓扑结构或损失函数中显式融入任何空气动力学偏微分方程或物理约束条件 ） | U15: 未明确指代网络底层的损失函数（注：隐式为回归误差，原文侧重于评估指标）（注：在模型参数设定表中，明确指出各子模态网络使用了 Adam 优化器，并指出利用网格搜索算法（GS）基于模型精度（MAE, RMSE, MAPE）来遍历并优选超参数组合，但通篇未在正文或公式中明文使用“损失函数”或“目标函数”这类字眼来单独定义神经网络反向传播的物理学或数学约束项） | V15: 相较于未修正的物理预测，RMSE 降低了 93.93%（单步测试误差仅为 0.1309 m/s）（注：原文在摘要与结果部分明确给出了具体百分比：与未经过深度学习修正的 WRF 原始输出相比，该修正模型的 MAE、MAPE 和 RMSE 分别大幅下降了 94.13%、91.75% 和 93.93% 。同时，在与其余 11 种深度学习基线模型的横向对比中，本模型单步预测 RMSE 为 0.1309 m/s，在绝对数值上直接优于同组表现最好的基线模型 CEEMDAN-AM-BLSTM（其 RMSE 为 0.2112 m/s） ） | W15: 完美弥补了传统物理气象大模型（NWP）在实际工程中存在巨大固有系统偏差的痛点（注：作者在研究动机中深刻指出，WRF 等气象物理模型受制于物理方案和输入边界的不确定性，其原始预测风速往往存在高达 12m/s 的巨大误差 。该模型通过利用深度学习挖掘 WRF 外部嵌套网格（Outer domains）对内部网格气象变量的时空耦合影响，成功实现了极其精准的超短期（10~50分钟）风速残差预测与修正，为现代电网调度部门优化电网系统提供了极其可靠的业务支撑 ） | X15: 数值天气预报，卷积神经网络，循环神经网络，分解-预测混合框架
A16: 16 | B16: 10.1016/j.enconman.2018.10.068 | C16: 否 | D16: A novel combined model based on echo state network for multi-step ahead wind speed forecasting: A case study of NREL | E16: 2019年（2018年10月在线发表），发表于 Energy Conversion and Management | F16: 未提及 | G16: 点尺度 （注：研究对象为美国科罗拉多州 NWTC 的 M2 测量塔，属于针对特定单点地理坐标的研究，其坐标为北纬 39° 54′ 38.34″，西经 105° 14′ 5.28″ (WGS84)） | H16: 1 分钟 （注：传感器每 2 秒采集一次数据，并记录每 1 分钟的平均值；实验使用了 2011 年 11 月 1 日至 11 月 8 日共 8 天的数据，开展了 1 步、2 步和 3 步的前向多步预测） | I16: 20米、50米和80米 （注：文献利用了 M2 测风塔在 20m、50m 和 80m 三个不同离地高度的实时风速数据作为案例研究，以验证所提组合模型的有效性和通用性） | J16: 平均海拔 1855 米 （注：研究区域位于美国科罗拉多州的国家风力技术中心，海拔较高（1855m），拥有丰富的风能资源；文中强调了风速的随机性、波动性和非线性特征，但未将“复杂地形”作为专门的输入变量进行建模） | K16: 纯历史风速（注：原文明确指出仅选用了美国国家可再生能源实验室 (NREL) M2 测风塔 20m、50m 和 80m 三个不同高度的分钟级历史风速序列作为实验输入，完全未引入温度、气压、风向等其他气象变量数据） | L16: 有 （注：明确使用了来自 M2 测风塔（M2 measuring tower）的物理传感器实测数据，该塔测量并记录了 2m, 5m, 10m, 20m, 50m 和 80m 六个不同高度层的风速与风向信息） | M16: 奇异谱分析（SSA）去噪与滚动窗口数据切分（注：在预处理阶段，首先应用奇异谱分析（SSA）对原始风速信号进行分解和重构，以消除数据中的强噪声部分；在特征集构造上，明确采用了一种带有滑动窗口的“数据划分机制（Data set division mechanism/Rolling prediction mechanism）”，为多步预测构建动态的特征输入与输出向量对） | N16: 未提及（注：文中明确说明数据集采自 NREL 的 M2 测风塔，但全局扫描正文、附录及致谢部分，并未给读者提供任何直接的开源数据下载链接、GitHub 代码仓库地址或直达的官方数据库网页入口） | O16: 未提及（注：这是一个极易产生幻觉的测试点。尽管文章在 4.1 节介绍数据集时，详细给出了 M2 测风塔的具体经纬度坐标（北纬 39°54′，西经 105°14′）和海拔高度（1855m），但在其实际构建的所有神经网络和组合模型中，完全没有将这些静态地理坐标作为特征节点显式输入，模型吃进去的依然是一维纯数值） | P16: 未提及（注：全文完全没有提及将湍流动能 (TKE)、局部垂直风切变或风机间尾流扰动等微尺度物理参数提取作为模型的特征输入） | Q16: 单点本地历史风速多步滞后序列（注：模型极度依赖目标站点自身的历史时间序列特征。在所有实验中，明确设定输入数据的时间步长（窗口长度）为 8 作为滞后项（Lag variables = 8）。作者在引言中论述“空间相关性算法会增加数据的计算成本和复杂性”，因此本模型刻意未引入相邻或上游测风站点的空间连带特征，也未显式输入时间周期编码） | R16: 单点多步确定性预测（注：模型针对 20m、50m 和 80m 三个独立的测量高度，基于 1 分钟分辨率的数据，输出未来 1 步、2 步和 3 步（即未来 1 到 3 分钟）的风速确定性标量预报值，不输出概率区间或空间网格预测） | S16: 提出基于多混合子模型与回声状态网络（ESN）集成的双层组合模型 NCFM（注：本文提出了一种创新的架构：底层先用四个混合模型（SSA-QPSO-ESN, SSA-NARX, SSA-cycling CBP, SSA-QPSO-LSSVM）进行初次预测，顶层再将这四个中间预测结果作为输入，送入回声状态网络（ESN）进行最终的结果融合输出。用于严谨对比的 Baseline 基线模型除了上述 4 种子模型外，还包含了另外 6 个经典的单体 AI 模型：CBP, LSSVM, ESN, ELM, GRNN 和 BP） | T16: 未融合物理机制/纯数据驱动（注：本文提出了一种完全基于纯数据驱动的新型组合预测模型（NCFM） 。模型仅仅使用了历史风速这一单一时间序列数据（来自 NREL 测风塔） ，通过奇异谱分析（SSA）进行信号去噪，然后输入到四个底层的混合黑盒网络（ESN, NARX, CBP, LSSVM）中进行初步预测 。文章最核心的创新是利用回声状态网络（ESN）去非线性地“集成”这四个底层模型的预测结果 。作者在引言中明确将物理方法（PMs）排除在外，通篇未在输入层或损失函数中融入任何气象物理参数、流体力学方程或空间地形约束 ） | U16: 误差平方和（注：局部算法底层隐式定义）（注：文中在介绍底层构件 LSSVM 的数学原理时，明确给出其成本函数（Cost function）是由权重惩罚项和预测回归误差的平方项组成的；但在描述顶层系统结构时，并未定义一个包含物理学约束惩罚项的全局深度学习损失函数，仅以 NMSE、MAE 等纯误差衡量指标作为验证反馈） | V16: 相较于表现最好的底层混合基线模型，单步至三步预测的 MAPE 分别改善了 38.67%、37.63% 和 64.56%（注：原文在第 5.1 节中明确给出了具体的误差改善百分比数值。与四个底层混合模型中表现最佳的 ESN+QPSO 模型相比，本文提出的顶层 ESN 组合模型在 1步、2步和 3步预测上的 MAPE 分别提升了 38.67%、37.63% 和 64.56% ；而在与传统单体基线模型（如 BP 神经网络）的大横评中，单步预测的 MAPE 甚至平均降低了高达 86.74% ） | W16: 解决了传统单一 AI 模型在面对强非线性风速波动时极易陷入局部最优与预测失稳的痛点，为智能电网的短期多步调度提供了极具鲁棒性的技术支撑（注：作者在研究动机与结论中深刻指出，风速极其强烈的随机性和间歇性会导致单一预测模型根本无法完整捕获时间序列中的非线性分量，进而导致并网传输过程中的能量损耗与调度失效 。该系统通过史无前例地将“回声状态网络 (ESN)”作为顶层融合器，突破了传统“简单线性加权组合”的瓶颈，以极其强大的动态非线性能力集成了各家底层网络之长，彻底克服了单体人工智能算法不稳定的工程缺陷，极其契合智能微电网对多步（Multi-step）提前预警与调峰的严苛需求 ） | X16: 集成方法，循环神经网络，优化算法增强，前馈神经网络，支持向量机类
A17: 17 | B17: 10.1016/j.renene.2018.05.093 | C17: 否 | D17: Research on a Combined Model Based on Linear and Nonlinear Features - A Case Study of Wind Speed Forecasting | E17: 2019年（2018年在线发表），发表于 Renewable Energy | F17: 未提及 | G17: 点尺度 （注：研究对象明确为山东蓬莱风电场区域内的四个特定站点（Site 1, 2, 3, 4），数据采集直接针对站点位置，而非空间网格预报场） | H17: 10分钟 （注：文献使用了 10 分钟间隔的风速数据进行验证。预测任务被设定为单步（10分钟）、三步（30分钟）和五步（50分钟）的前向预测） | I17: 未提及 | J17: 沿海风电场区域 （注：研究区域位于中国山东省蓬莱市，属于沿海地带。文中强调了风速序列具有高度的波动性、不稳定性以及线性和非线性并存的特征，但未提供具体的海拔数值，也未将地形作为特定的模型输入变量） | K17: 纯历史风速（注：原文明确说明，实验验证所使用的是中国山东蓬莱风电场4个站点的 10 分钟间隔原始风速数据集。虽然引言提及传统物理模型会使用温度和气压，但本文构建的模型输入仅为历史风速序列数据 ， ） | L17: 有 （注：明确使用了来自风电场的实测原始风速数据集（Original wind-speed series），并指明这些数据具有高度不稳定性和噪声特征。为了便于预测，研究在预处理阶段使用了奇异谱分析（SSA）技术对原始观测数据进行去噪处理） | M17: 奇异谱分析（SSA）去噪与纵向数据选择划分（注：在数据预处理阶段，应用奇异谱分析（SSA）对高度不稳定和嘈杂的原始风速序列进行分解和去噪过滤 ， ；此外，在特征集构造上，采用了“纵向数据选择（longitudinal data selection procedure）”方法，不仅构建了多步滑动窗口，还将数据切分为“日间（diurnal）”和“夜间（nightly）”子集分别进行训练和实验 ， ） | N17: 未提及（注：全局扫描正文、附录及致谢部分，仅交代数据来自中国山东省蓬莱的风电场，并未提供任何开源下载链接、GitHub 代码仓库地址或官方数据库网页访问入口 ， ）。 | O17: 未提及（注：这是一个极易产生幻觉的测试点。尽管文章在图 4（Fig. 4）中绘制了山东蓬莱及 4 个站点的地图地理分布，但在其实际构建的神经网络与组合预测模型中，完全没有将经纬度、高程 DEM 或地表粗糙度等静态空间物理特征显式作为输入节点 ， ） | P17: 未提及（注：全文完全没有提及将湍流动能 (TKE)、局部垂直风切变或局部地形引起的尾流扰动等微尺度物理特征提取作为模型输入） | Q17: 单点本地历史多步滞后序列与昼夜周期划分（注：模型极度依赖各单点的历史时间序列滞后项进行多步预测；虽然没有显式将“时间编号”作为独立特征列输入，但通过人为的数据预处理将序列物理划分为“日间”和“夜间”子集分别独立建模，隐式引入了日内的时间周期特性以应对风速的昼夜差异 ， 。未引入相邻气象站点的空间传播关联特征）。 | R17: 单点多步确定性预测（注：系统针对 4 个具体测风站点，独立输出未来 1 步（10分钟）、3 步（30分钟）和 5 步（50分钟）的确定性风速标量预报值，最长测试了未来 24 步（4小时）的衰减情况，不涉及概率区间或区域网格预测 ， ） | S17: 提出基于 AFSA-ACO 优化的线性和非线性特征组合模型（注：本文提出使用一种改良的新型启发式算法（人工鱼群与蚁群混合算法，AFSA-ACO），结合无负约束理论（TCM-NNCT）来动态融合两个线性模型（ARIMA, ES）和四个非线性神经网络（BPNN, ENN, GRNN, WNN）。用于极其详尽平行对比的 Baseline 不仅包含了这 6 个独立的底层单体算法 ，还包括了采用其他优化算法（BFGS, PSO, ACO）加持的集成组合模型 ） | T17: 纯数据驱动，未涉及物理机制融合（注：本文提出了一种基于线性和非线性特征的组合预测模型。该模型完全依赖于中国山东某风电场的 10 分钟间隔历史风速时间序列数据 。底层利用 ARIMA、指数平滑（ES）等传统模型提取线性特征，利用 BPNN、GRNN、WNN、ENN 神经网络提取非线性特征 ，顶层则使用创新改进的人工鱼群-蚁群优化算法（AFSA-ACO）进行组合权重寻优 。通篇未在输入层、网络拓扑或目标函数中显式融入任何气象学偏微分方程、数值天气预报或流体力学物理约束 ） | U17: MSE/SSE（均方误差与误差平方和）（注：在如 BP 神经网络等底层子模型的反向传播学习中，明确定义了均方误差（MSE）最小化作为训练目标 ；而在顶层传统及改进的无负约束理论组合模型（TCM-NNCT）中，则是以最小化预测误差的平方和（SSE）作为目标函数，来寻找各子模型的最佳组合权重，全文未提及添加任何物理学方程约束惩罚项 ， ） | V17: 相较于各大基线模型，平均 MAPE 误差降低了 4.88% 至 58.22% 不等（注：原文在第 5.1 节中极其明确地给出了平均 MAPE 的相对误差下降百分比（DREindex）。在单步预测场景中，该组合模型相较于单体的 BPNN、ENN、GRNN、WNN、ARIMA 和 ES 模型，其 MAPE 分别显著改善了 4.8832%、37.4302%、29.3375%、52.5424%、14.6667% 和 56.2927% 。在覆盖多步预测的横评中，其最大平均 MAPE 误差降幅高达 58.2239%，最小降幅为 4.8832% ） | W17: 完美克服了真实风电场中风速同时具备强烈“线性”与“非线性”复杂波动，导致单一算法极易在多步预报中失效的工程痛点（注：作者在研究动机与结论中深刻指出，自然界的风速交织着线性趋势与非线性随机波动，任何单一预测模型都会存在无法兼顾的死角 。该架构以一种“包罗万象”的工程哲学，分别派专职算法去捕获风速的线性和非线性分量，再通过强大的仿生算法进行权重统筹，在高达 24 步（即未来4小时）的超短期多步预测中展现出极强的鲁棒性，为风电并网的实时规划和系统管理提供了高稳定性的决策支撑 ） | X17: 优化算法增强，集成方法，自回归/滑动平均类，指数平滑类，前馈神经网络，循环神经网络
A18: 18 | B18: 10.1109/iciset.2016.7856485 | C18: 否 | D18: Short Term Wind Speed Forecasting Using Artificial Neural Network: A Case Study | E18: 2016年或之后，未提及具体期刊 | F18: 未提及 | G18: 点尺度 （注：研究针对特定地理坐标点进行，具体位置为泰国巴吞他尼府亚洲理工学院环境资源与发展学院能源大楼的自动测风监测站，坐标为北纬 14.07960°，东经 100.61270°） | H18: 每小时（注：数据采样间隔为 1 小时，记录 2016 年 1 月整月的每小时平均风速；预测任务设定为提前 24 小时的日前预测，输入层包含对应过去 30 天数据的 30 个神经元） | I18: 未提及 （注：原文表述数据来自“能源大楼（Energy field building）的自动测风监测站”，但并未明确说明风速仪安装的具体离地高度或预测目标高度） | J18: 海拔 14 米 （注：研究区域位于泰国巴吞他尼府，文中明确指出测风站的海拔高度为平均海平面以上 14 米（altitude: 14m above mean sea level）） | K18: 纯历史风速（注：原文明确说明神经网络的输入节点代表过去30天的风速数据，完全未引入温度、气压、风向等其他气象变量作为模型输入 ） | L18: 有 （注：明确使用了来自 AIT 能源领域自动测风监测站（automatic wind monitoring station）的物理传感器数据，包括 2016 年 1 月期间测得的 0.04m/s 至 4.04 m/s 范围内的风速观测值） | M18: 简单随机数据划分（注：原文未提及使用归一化、异常值处理或频域分解（如VMD、小波变换）等任何复杂的特征工程方法，仅说明使用 MATLAB 的 nntool 工具将数据集简单地随机划分为 60% 训练集、20% 验证集和 20% 测试集 ） | N18: 未提及（注：文中说明测风数据由位于泰国巴吞他尼府的亚洲理工学院（AIT）能源领域的自动测风站采集，并在致谢中感谢了实验室主管提供数据，但全文未给出任何开源下载链接、GitHub 代码库地址或官方数据库网页入口 ） | O18: 未提及（注：这是一个防幻觉的测试点。尽管文章交代了测风站的具体经纬度坐标（纬度:14.07960N, 经度:100.61270E）和海拔高度（14m），但在人工神经网络的 30 个输入层节点中，完全没有显式输入这些空间静态物理特征参数 ） | P18: 未提及（注：全文完全没有提及将湍流动能(TKE)、局部垂直风切变或局部地形引起的尾流扰动等微尺度物理特征作为模型输入） | Q18: 单点同维历史多步滞后序列（注：模型极度依赖单点的历史时间序列。其数据输入构造非常原始，输入层包含 30 个神经元，这 30 个节点代表过去 30 天同一时间的风速历史滞后项（Lag variables = 30）。模型没有显式输入月份/小时等时间周期编码，也明确未引入相邻气象站点的空间传播特征 ） | R18: 单点确定性短期预测（注：该人工神经网络输出层的 1 个神经元对应目标预测日的特定单小时风速。模型对选定的1月1日、11日、22日和31日这四天，循环输出未来 24 小时逐小时的确定性风速标量预测值，不涉及概率区间预测 ） | S18: 提出使用标准前馈反向传播人工神经网络（ANN），无对比基线模型（注：本文仅建立了一个结构为 30-20-1 的三层 Levenberg-Marquardt 前馈反向传播人工神经网络进行验证，完全没有设置 ARIMA、SVR 或 LSTM 等任何 Baseline 模型进行对比。作者在结论中也坦诚指出，将此方法与支持向量机（SVM）、决策树和随机森林等其他方法进行对比，是未来的研究工作 ） | T18: 未融合物理机制/纯数据驱动（注：本文构建的是极其基础的前馈反向传播人工神经网络（ANN）。模型完全依赖于泰国亚洲理工学院（AIT）测风站过去30天的纯历史单变量风速数据，进行黑盒非线性映射以预测未来24小时的风速 。利用 Levenberg-Marquardt 算法进行训练，全文未在网络拓扑、特征输入或损失函数中显式融入任何气象偏微分方程或流体力学等物理约束条件 ） | U18: MSE均方误差（注：原文明确指出，在神经网络训练期间，连接权重和偏置的更新是为了减少输出误差的均方值（Mean Square Error, MSE），未提及在目标函数中添加任何物理学方程约束惩罚项 ） | V18: 未进行基线模型对比，仅报告绝对预测误差（MAPE 最低为 1.1%，最高为 13.7%）（注：这是一篇非常早期的基础应用型验证论文，原文完全没有设置任何 Baseline 基线模型（如 ARIMA 或其他传统机器学习算法）进行平行横评。作者仅给出了该模型在 2016 年 1 月的四个特定测试场景（1日、11日、22日和31日）下的绝对误差，其平均绝对百分比误差（MAPE）分别为 1.1%、13.7%、5.1% 和 4.08% ，以此声明该纯黑盒模型具有较高的预测精度）。 | W18: 初步验证了利用基础黑盒神经网络进行短期日前风速预报，以辅助电力系统平抑间歇性并降低电网不平衡罚款的可行性（注：作者在研究动机中明确指出，风速的强烈随机性和间歇性给风电并网同步带来了巨大挑战 。该研究通过实证表明，单纯依靠历史时间序列的 ANN 模型能将大多数测试场景的短期预测 MAPE 控制在 10% 以下（如 1.1% 甚至 4.08%），这对于提高局部电力系统的高效管理，以及让发电方在能源市场交易中提前预警、减少电量不平衡所带来的罚单（imbalance charges and fines）具有直接的实操指导意义 ） | X18: 前馈神经网络
A19: 19 | B19: 10.1109/icsitech.2015.7407784 | C19: 否 | D19: An artificial neural network hybrid with wavelet transform for short-term wind speed forecasting: A preliminary case study | E19: 2015年，发表于 2015 International Conference on Science in Information Technology (ICSITech) | F19: 未提及 | G19: 点尺度 （注：研究对象明确为 ABEI 气象站，属于针对特定地理位置的单点观测研究，未涉及任何网格化空间分辨率或预报场设置） | H19: 每小时（Hourly） （注：数据采样间隔为 1 小时，研究使用了 2010 年 1 月和 2 月共两个月（1420 个目标点）的每小时数据进行建模；预测任务设定为提前 1 小时（1-hour ahead）的短期预测） | I19: 未提及 （注：原文仅说明数据源自 ABEI 气象站，但在描述数据集划分、模型输入（Lag 1 和 Lag 2）及预测结果时，并未明确标注风速计的具体安装高度，也未提及 10m 高度或轮毂高度等参数） | J19: 未提及 （注：研究区域确定为美国爱达荷州阿伯丁（Aberdeen, Idaho），但文中未给出该站点的具体海拔高度数值，也未对地形特征（如复杂地形、平原或山地）进行强调或详细描述） | K19: 纯历史风速（注：原文明确指出，未考虑未来风速与温度、湿度等其他气象参数的相关性，模型的预测仅仅基于历史风速数据 。） | L19: 有 （注：明确使用了来自 ABEI 气象站的物理观测数据，包含两个月的历史风速记录，用于人工神经网络与小波变换混合模型的开发与性能评估） | M19: 离散小波变换（DWT）分解与 ACF/PACF 特征筛选（注：在数据预处理阶段，使用离散小波变换（DWT）将原始风速信号分解为近似组件（低频）和细节组件（高频）以降低随机性 。此外，创新性地使用自相关函数（ACF）和偏自相关函数（PACF）来统计筛选最佳的输入变量，避免了传统神经网络构建时盲目的试错过程 。数据集被按 50%、25% 和 25% 的比例严格划分为训练集、测试集和验证集 。） | N19: 未提及（注：文中说明使用了来自美国爱达荷州 ABEI 气象站可在互联网上获取的公开数据，但全局扫描正文及参考文献，并未提供任何可直接访问的开源下载链接、GitHub 代码库地址或官方数据库网页入口 。） | O19: 未提及（注：模型架构完全依赖于一维纯时间序列，没有显式输入高程 DEM、地表粗糙度等空间静态物理特征节点 。） | P19: 未提及（注：全文完全没有提及将湍流动能 (TKE)、局部垂直风切变或局部地形引发的尾流扰动等微尺度物理特征提取为模型输入 。） | Q19: 单点本地历史滞后序列（注：模型极度依赖单点自身的时间序列。通过 ACF 和 PACF 的定量分析，模型明确筛选出与未来风速高度相关的“过去 2 个时间步（Lag 1 和 Lag 2）”的历史序列作为网络输入 。未显式引入月份/小时等时间周期编码，也明确未引入相邻气象站点的空间传播特征 。） | R19: 单点单步确定性短期预测（注：该人工神经网络输出层的 1 个节点对应未来时刻的单步风速，具体形态为：使用前两个时刻的风速值作为输入，输出目标测风站未来 1 小时（1-hour ahead）的风速确定性标量预测值，不涉及概率区间预测 。） | S19: 提出 WT-ANN 混合神经网络模型（注：本文提出的核心创新模型是离散小波变换（DWT）与前馈神经网络的混合算法 。用于进行平行对比的 Baseline 基线模型是使用了相同学习算法、相同输入特征数和隐藏层的“常规神经网络（regular neural network）” 。） | T19: 未融合物理机制/纯数据驱动（注：本文提出的是结合离散小波变换（DWT）和前馈人工神经网络（ANN）的混合预测模型 。原文明确指出，该预测仅仅基于历史风速数据，并没有考虑未来风速与其他天气参数（如温度、湿度等）的关联 。通篇未在特征工程、网络拓扑或损失函数中显式融入任何气象物理学定律或流体力学方程 ） | U19: MSE均方误差（注：原文明确说明，在使用 Levenberg-Marquardt 算法（LMA）更新网络权重以进行反向传播训练时，旨在最小化的定义误差函数通常为均方误差（MSE） 。全文未提及添加任何物理学方程约束惩罚项。） | V19: 未给出对比百分比，测试集绝对均方误差（MSE）从 5.50105 降低至 2.693995（注：原文在表 1（Table I）和表 2（Table II）中给出了极其明确的绝对误差数值 。在使用相同的学习算法、输入变量数量和隐藏层结构下，未引入小波变换的常规神经网络（Regular ANN）在测试集上的 MSE 为 5.50105，而本文提出的基于小波变换的混合神经网络将其测试集 MSE 绝对数值降至 2.693995 。同时，衡量拟合优度的回归因子（Regression, R）也从 0.744412 提升到了 0.780041 ） | W19: 解决了传统风速预测神经网络在构建时极度依赖人工“主观试错（trial-and-error）”来选择输入特征的工程落地痛点（注：作者指出，风速本身具有高度波动性和不确定性，而很多过往研究在选择神经网络的输入特征时完全依赖用户经验 。该模型最大的业务价值在于，它引入了自相关函数（ACF）和偏自相关函数（PACF）等统计学工具来客观、自动地选定最佳滞后时间步（lags）作为输入，彻底摒弃了耗时且盲目的“试错法”，为短期日前/日内风速预测提供了更加系统化和自动化的建模参考 ） | X19: 分解-预测混合框架，前馈神经网络
A20: 20 | B20: 10.1016/j.epsr.2023.109502 | C20: 否 | D20: Learning based short term wind speed forecasting models for smart grid applications: An extensive review and case study | E20: 2023年，发表于 Electric Power Systems Research | F20: 未提供代码链接 | G20: 点尺度 （注：研究对象为印度西北部焦特布尔（Jodhpur）的具体站点，地理坐标明确标注为北纬 26.23890°，东经 73.02430°；文中未涉及任何网格化的空间分辨率设定） | H20: 每小时（Hourly） （注：数据集包含一整年的 8760 个样本，对应每小时一次的采样频次；研究主要关注短期预测（Short-term forecasting），旨在辅助智能网格的运营和调度决策） | I20: 未提及具体高度 | J20: 印度西北部内陆区域 （注：站点位于焦特布尔（Jodhpur），属于气候多变的内陆环境；研究特别分析了季节性（春、夏、季风、秋、冬）对模型精度的影响，但未提及具体海拔数值或复杂地形特征） | K20: 风速、气压、湿度、温度与露点（注：原文在案例研究（Case study）部分明确指出，该预测系统的数据集包含了这 5 个具体的气象特征变量，作为模型的基础输入进行多变量评估 ） | L20: 无 （注：研究明确指出数据是“从 DarkSky 收集的（collected from DarkSky）”，这属于二次气象数据服务，而非直接利用现场测风塔（Mast）或风机 SCADA 系统的原始传感器实测信号；虽然提及站点处安装有苏司兰风机，但实验数据并非直接取自该物理硬件） | M20: 缺失值处理与归一化（MinMax Scaling）（注：在“Simulation methodology”步骤中，提到识别缺失数据并使用归一化方法将所有数据点重缩放至 的统一尺度。此外，在“未来研究方向（8.1节）”中，作者明确承认本次案例研究未使用任何复杂的分解或去噪预处理模型（如 VMD、小波变换等）来处理数据的不确定性 ） | N20: 提供外部气象 API 数据库网址（注：原文明确说明案例研究的一年期数据集采集自 DarkSky，并在参考文献 中给出了具体的开发者网址链接：https://darksky.net/dev ） | O20: 未提及（注：尽管文章说明了印度焦特布尔（Jodhpur）风电场站点的具体经纬度坐标（北纬 26.23890，东经 73.02430），但在其构建和评估的 41 个学习模型中，并未显式将任何地形、高程等空间静态物理特征作为输入变量传入网络层 ） | P20: 未提及（注：全文完全没有提及将湍流动能 (TKE)、局部垂直风切变或尾流扰动等微尺度流体力学物理特征提取作为模型输入） | Q20: 单点多变量历史滞后序列与人工季节性时间周期划分（注：所有模型高度依赖目标焦特布尔站点的历史单点气象数据，无相邻站点的空间传播连带输入。但在实验验证阶段，为了探究时间周期关联，人为地将全年的数据按“春、夏、季风、秋、冬”五个季节子集进行了物理隔离与分别测试 ） | R20: 单点确定性短期预测（注：系统旨在针对该单一风电站点输出确定性的风速标量预测值。虽然在文献综述中提到了概率区间预测模型，但在本篇的 41 种算法横评实践中，仅进行了点预测和确定性误差评估 ） | S20: 进行 41 种现存学习算法的终极大横评，无单一提出的绝对创新模型（注：这是一篇极其罕见的“暴力基线测试（Benchmark）”文章。它将现存的 41 种算法分为五大阵营（线性回归类、传统机器学习、深度学习、集成学习、概率学习），并在同一数据集上进行了平行的横向对抗。最终得出的反直觉结论是：在当前中等数据量下，支持向量回归 (SVR) 综合误差表现最好、算力成本适中，甚至打败了 LSTM、GRU 和 TCN 等极为复杂的深度学习模型 ） | T20: 未融合物理机制/纯数据驱动（注：本文是一篇极具规模的综述与实证横评大作。在其印度焦特布尔风电场案例研究（Case Study）所实际运行的 41 种预测算法中，包含线性模型、机器学习、深度学习、集成学习及概率回归模型。这些模型完全依赖于风速、温度、露点、湿度和气压这 5 个气象特征的纯历史数据进行黑盒非线性映射 。作者并未在这些底层网络拓扑结构或损失函数中显式植入任何流体力学物理定律、计算流体力学（CFD）方程或物理先验约束 ） | U20: MSE 均方误差与最小二乘残差平方和（注：在评估各类深度学习网络（如 CNN, RNN, LSTM, GRU, Bi-LSTM）的统一超参数表（Table 7）中，损失函数明确全部设定为 mse；在线性模型和其他机器学习底层推导中也广泛使用最小化残差平方和，全文未在损失函数中添加任何物理学约束惩罚项 ） | V20: 正文未给出直接绝对误差数值，明确指出 SVR（支持向量回归）综合表现最佳（注：由于本文是针对 41 种现有数据驱动算法的大型横向基线测试，正文并未像提出单一创新模型的论文那样列出具体的误差降低百分比，而是明确声明具体的 MAE、RMSE 及 R 2 数值均放置于“附加说明文件（Supplementary document）”中 。但在统计学与结论部分，作者明确指出：综合预测精度与计算时间成本（CPU compilation time），SVR（支持向量回归）在单输入特征（春、夏、秋及全年）和多输入特征（夏、秋及全年）测试下均优于其他深度学习与集成算法 ） | W20: 解决了智能电网在实际应用中面对海量黑盒算法“盲目选型”的痛点，为最优储能定容与电力市场竞价提供了详实的算法推荐参考（注：作者在探讨业务应用落地时深刻指出，仅仅追求算法架构的复杂性是没有意义的，深度学习模型往往因为参数过多、需要海量数据而在计算时效上表现糟糕。该横评研究证实，在微电网调度、最优储能规模测算（Sizing problems）、能源市场竞价策略规划（Bidding strategies）以及备用容量估算（Reserve sizing）的真实业务中，计算开销适中且能捕捉季节数据非线性波动的传统 SVR 模型，往往比极度耗时的复杂深度学习模型更具工程实操可行性 ） | X20: 支持向量机类，基础基准与回归类，循环神经网络，树模型与集成学习，分位数回归，贝叶斯方法
A21: 21 | B21: 10.1016/j.apenergy.2018.05.043 | C21: 否 | D21: Time-series prediction of wind speed using machine learning algorithms: A case study Osorio wind farm, Brazil | E21: 2018年，发表于 Applied Energy | F21: 未提及 | G21: 点尺度 （注：研究对象明确为巴西 Osorio 风电场所在的特定地理位置，坐标为南纬 29.92°、西经 50.31°，未涉及网格化空间预报场） | H21: 5、10、15 和 30 分钟间隔 （注：模型分别针对 5-min、10-min、15-min 和 30-min 四种不同的数据采样间隔进行了训练与精度验证） | I21: 未提及具体高度 （注：原文虽然提到 Osorio 风电场使用的风机转子直径为 70m，且指出风速会随高度变化，但在描述用于实验的实测数据集时，未明确标注风速采集点具体的离地高度） | J21: 巴西南部沿海平坦区域（临近 Osorio 市） （注：研究区域位于里奥格兰德州（Rio Grande do Sul），靠近海岸。文中强调该风电场拥有良好的风能潜力和基础设施连接，但未提及具体的海拔高度数值） | K21: 纯历史风速（注：原文在引言及方法论部分明确指出，为了避免气象站的高昂测量成本，本研究的模型仅基于已知的实测历史风速数据进行预测，未引入温度、气压、太阳辐射或湿度等其他气象变量作为输入 。） | L21: 有 （注：文献明确使用了“实测风速数据”（measured wind speed data）作为时间序列预测的输入，并说明预测是基于已知的过去观测值来预测未来值；虽然未列出具体传感器型号，但数据来源于风电场现场的物理观测记录） | M21: 滑动时间窗口构造与简单数据切分（注：在数据处理阶段，根据设定的时间延迟参数将一维时间序列转化为输入输出矩阵（例如使用过去的 4 个时间步来预测未来值），并将 1201 个数据点严格按 70% 训练集和 30% 测试集进行切分。全文未提及使用归一化、异常值处理或如小波变换/VMD 等复杂的频域分解预处理方法 。） | N21: 未提及（注：全局扫描正文及参考文献，文中仅说明数据集采集自巴西的 Osorio 风电场，但并未给读者提供任何直接的开源数据下载链接、GitHub 代码仓库地址或官方数据库访问入口 。） | O21: 未提及（注：这是一个典型的防幻觉测试点。尽管文章在第2节“案例研究”中明确给出了 Osorio 风电场的具体经纬度坐标（纬度 −29.92°，经度 −50.31°），但在其实际构建的所有纯时间序列预测网络中，完全没有将这些静态空间物理坐标显式作为输入节点 。） | P21: 未提及（注：全文完全没有提及将湍流动能 (TKE)、局部垂直风切变或局部地形引发的尾流扰动等微尺度流体力学特征提取作为模型输入 。） | Q21: 单点本地历史多步滞后序列（注：模型极度依赖单点自身的历史时间序列。文中明确采用自回归过程（autoregressive process），将目标站点过去的风速值作为输入变量（即滞后项 Lag variables）来预测未来。未显式引入月份或小时等时间周期编码，也明确未引入相邻气象站点的空间传播特征 。） | R21: 单点多步确定性短期预测（注：系统分别针对 5分钟、10分钟、15分钟和 30分钟 这四种不同的时间尺度，输出未来的确定性风速标量预报值。文中同时探讨了“迭代法”与“直接法”两种多步超前预测（multi-step ahead prediction）输出策略，不涉及概率区间或区域网格预测 。） | S21: 首次引入 GMDH 网络并进行 9 种机器学习算法大横评（注：本文的创新点是首次将 GMDH（数据处理组合方法）神经网络引入风速时间序列预测中。文中未设定单一的 Baseline，而是将 GMDH 与另外 8 种算法（MLFFNN, SVR, FIS, ANFIS-FCM, ANFIS-SC, ANFIS-GP, ANFIS-PSO, ANFIS-GA）在同一数据集上进行了平行的全面横向对比 。） | T21: 未融合物理机制/纯数据驱动（注：本文是一篇极其纯粹的数据驱动预测大横评。作者在第1.1节的“知识空白与创新点”中明确强调，许多其他研究高度依赖气温、气压、相对湿度、太阳辐射等气象特征和经纬度地理数据，这需要额外部署复杂的测量设施；而本文的预测**“仅仅基于已知风速测量值的历史数据（predicted only based on known values of measured wind speed data）”**。模型通过 MLFFNN、SVR、FIS、ANFIS 及首次引入该领域的 GMDH 神经网络进行纯黑盒时间序列映射，通篇完全未涉及任何物理空气动力学方程或气象降尺度推演 ） | U21: 误差平方和（SSE）与 ϵ-不敏感损失函数（注：由于是多模型横评，不同底层算法采用了不同的目标函数。例如 GMDH 的数学推导明确以最小化预测输出与实际数据差异的平方和（Square of difference）为目标；SVR 则使用带有正则化惩罚项的 ϵ-不敏感损失函数。全局均未提及添加任何包含物理学方程的约束项 。） | V21: 未提供直接对比百分比，但报告了极低的绝对预测误差（如 5分钟间隔预测 RMSE 为 0.0120 m/s）（注：由于本文主要是7种不同算法（及多种优化变体）平行评测，原文未计算相对于某一最差基线的总体提升百分比，而是原样给出了各模型的极致拟合数据。在 5分钟超短期预测中，多层前馈神经网络（MLFFNN）表现出极高的绝对精度，测试集 RMSE 为 0.0120 m/s，相关系数 R 高达 0.9999；而在 15分钟和 30分钟的稍长预测中，支持向量回归（SVR）、粒子群优化的自适应神经模糊系统（ANFIS-PSO）及数据处理分组方法神经网络（GMDH）也都达到了相关系数 R > 0.98 的绝对高精水平 ） | W21: 摆脱了风电场日常预报对高昂/复杂多元气象观测设施的强依赖，为电网极短临调度提供了低成本的高效工具（注：作者在研究动机中深刻指出，预测模型的输入变量越多，需要配套的气象硬件设施就越昂贵且容易出故障。该研究证明了在巴西 Osorio 大型风电场中，哪怕只利用过去单纯的风速标量序列，通过优选适合的机器学习算法（特别是 GMDH 和仿生优化的 ANFIS），依然能够实现极高精度的 5~30 分钟超短期预报，这极其务实地满足了风电系统在机组启停决策（unit commitment decision）、实时负载平衡和储能容量优化等场景下的高频调度需求 ） | X21: 前馈神经网络，集成方法
A22: 22 | B22: 10.1049/iet-rpg.2015.0010 | C22: 否 | D22: Hybrid forecasting model-based data mining and genetic algorithm-adaptive particle swarm optimisation: a case study of wind speed time series | E22: 2016年，发表于 IET Renewable Power Generation | F22: 未提及 | G22: 点尺度 （注：研究对象明确为中国华东地区山东省蓬莱市的四个特定风电场站点，即 Site 1、Site 2、Site 3 和 Site 4，并未涉及网格化空间预报分辨率） | H22: 10 分钟 （注：风速数据是以 10 分钟为基准进行采集的（gathered on a 10 min basis）；每个站点选取了 3030 个观测值，其中前 3000 个作为训练样本，剩余 30 个作为测试样本） | I22: 未提及 | J22: 华东沿海风电场区域 （注：研究覆盖中国东部（eastern China）的多个风电场，具体案例位于山东省蓬莱市；文中提供的地图显示该区域为沿海地带，但未提及具体的海拔高度数值） | K22: 纯历史风速（注：原文明确说明仅使用从中国山东省蓬莱市收集的以10分钟为间隔的风速时间序列数据进行模型训练与预测，在模型输入层未引入温度、气压、风向等任何其他气象变量 ） | L22: 有 （注：明确使用了来自四个站点的“观测值”（observation values）和“原始风速时间序列”（raw wind speed time series）；虽然文中未列出测风塔或传感器的具体名称，但数据来源于物理站点的实时记录） | M22: 集合经验模态分解（EEMD）去噪重构（注：在数据预处理阶段，使用 EEMD 方法将极具波动性的原始风速时间序列分解为多个独立的本征模态函数（IMFs）和一个残差序列。其核心操作是直接剔除具有最高频率的第一个 IMF（当作纯噪声），然后将剩余序列重新聚合成一组新的平滑风速数据以供预测使用 ） | N22: 未提及（注：全局扫描全文，文中仅说明数据采集自中国山东蓬莱的四个测风站点（图3），但完全未提供任何开源数据下载链接、GitHub 代码仓库地址或直达的官方数据库入口 ） | O22: 未提及（注：这是一个典型的防幻觉测试点。尽管文章在配图中画出了研究区域的地图，但在小波神经网络（WNN）的实际特征构建过程中，完全没有将高程DEM、地表粗糙度或测风站经纬度等空间静态物理特征显式输入到网络节点中 ） | P22: 未提及（注：全文完全没有提及将湍流动能(TKE)、局部垂直风切变或局部地形引起的尾流扰动等微尺度物理特征作为模型特征输入 ） | Q22: 单点本地历史序列映射（注：模型极度依赖单点的历史时间序列。它利用一维的历史风速时序数据输入小波神经网络进行非线性映射，并没有引入相邻或周边气象站点的空间连带传播特征，也未显式引入月份/小时等时间周期编码 ） | R22: 单点确定性短期预测（注：系统针对四个选定的具体测风站点，基于 10 分钟分辨率的数据，输出未来的确定性风速标量预测值。在实验测试阶段，模型对测试集中的 30 个连续时间步（即未来 300 分钟）进行了标量预报验证，不涉及概率区间预测 ） | S22: 提出 E-GA-APSO-WNN 深度混合模型与大规模基线横评（注：本文提出了一种“预处理 + 仿生寻优 + 神经网络”的集成架构。为了验证其优越性，进行了极度详尽的对比：除了与自身变体（如单体WNN、未去噪的 GA-APSO-WNN、E-WNN 等）进行消融对比外，还与传统的 BP 神经网络、径向基函数（RBF）网络、广义回归神经网络（GRNN）、模糊网络（Fuzzy net）以及支持向量机（SVM）进行了全面横评 ） | T22: 未融合物理机制/纯数据驱动（注：本文提出的是基于集合经验模态分解（EEMD）、遗传算法-自适应粒子群优化（GA-APSO）以及小波神经网络（WNN）的混合预测模型 。模型完全依赖中国山东蓬莱四个站点的纯历史风速时间序列数据进行黑盒非线性映射 ，利用 EEMD 进行去噪预处理，并通过 GA-APSO 智能寻优网络参数，通篇未在输入特征、网络拓扑或目标函数中显式融入任何气象动力学定律或流体力学物理约束 ） | U22: 适应度函数（Fitness values）与纯数学误差衡量（注：在运用 GA-APSO 仿生算法智能寻找小波神经网络（WNN）的最优初始权重时，明确计算粒子的“适应度值（fitness values）”作为唯一的优化驱动力（本质是预测误差的数学映射）；全篇模型无论是训练还是评估阶段，均未提及添加任何带有流体力学或物理机制的约束惩罚项 ） | V22: 未提供提升百分比，但报告了极优的绝对误差下降（如 Site 1 测试中 MAPE 降至 1.56%）（注：原文未直接计算相对误差下降百分比，而是原样给出了详尽的绝对对比数值。在 Site 1 测试点中，本文提出的 E-GA-APSO-WNN 最终模型的 MAE、MAPE 和 MSE 分别降至 0.074、1.56% 和 0.0102 。相较于未经过去噪处理与复杂寻优的单体基线模型 WNN（其 MAE 为 0.3241，MAPE 为 5.26%，MSE 为 0.1616） ，以及同组用于横评的 BP、SVM、RBF 等传统单体模型 ，在绝对误差数值上实现了极其显著的大幅度降低 ） | W22: 完美攻克了风速原始噪声干扰以及深度网络智能调参极易陷入局部最优的工程落地痛点（注：作者在引言中明确指出，风速本身因气象因素影响充满了随机波动与噪声，且用于参数寻优的传统 PSO 算法存在收敛慢、极易陷入局部最优（local minimum）的致命工程缺陷 。本研究引入 EEMD 有效剔除了最高频噪声以避免模态混叠 ，并通过融入遗传算法（GA）的交叉变异特性重塑了粒子群算法，使得智能电网在进行短期风速预测和可靠性调度（grid reliability）时，能够依赖一个真正做到全局参数最优、抗噪能力极强的高精度黑盒系统 ） | X22: 分解-预测混合框架，优化算法增强，前馈神经网络
A23: 23 | B23: 10.1016/j.renene.2022.10.123 | C23: 否 | D23: An innovative combined model based on multi-objective optimization approach for forecasting short-term wind speed: A case study in China | E23: 2022年，发表于 Renewable Energy | F23: 未提及 | G23: 点尺度 （注：研究对象明确为中国山东蓬莱风电场内的三个特定站点，即 Site 1、Site 2 和 Site 3，通过对这些单点位置的历史观测序列进行预测验证，不涉及网格化空间分辨率设定） | H23: 10 分钟 （注：数据集的时间步长为 10 分钟，采样时间段为 2011 年 6 月 1 日至 6 月 18 日；模型任务设定为单步、两步和三步的前向预测，分别对应未来 10 分钟、20 分钟和 30 分钟的风速情况） | I23: 未提及 （注：原文在描述蓬莱风电场的数据集以及附录展示的 30 组原始数据对比表时，仅统称为“原始风速数据 / Raw wind speed data”，未明确标注具体的传感器安装高度或轮毂高度） | J23: 未提及具体数值 （注：研究区域位于中国山东省蓬莱市，文中提到该地具有“优越的地理条件”和充足的风能资源，但未给出该区域的具体海拔数值或详细的地形分类特征描述） | K23: 纯历史风速（注：原文明确说明案例研究所使用的是中国山东蓬莱风电场的 10 分钟间隔原始风速数据集，虽然在文献综述中提到了物理模型会使用温度和地形信息，但本文提出的模型仅基于历史风速数据序列进行预测，未引入其他气象变量作为输入 ） | L23: 有 （注：明确使用了来自蓬莱风电场现场的“原始风速数据集”（original wind speed dataset），该数据作为实证模拟的训练样本（前 2160 个值）和测试样本（后 432 个值），属于典型的物理站点传感器实测序列） | M23: CEEMDAN 频域分解与去噪重构（注：在数据预处理阶段，采用了自适应噪声完备集合经验模态分解（CEEMDAN）技术，将极具随机性和波动性的原始风速时间序列分解为多个本征模态函数（IMFs）和一个残差序列，以消除高频噪声信号，然后再进行重构预测。数据集按前 2160 个样本作为训练集、后 432 个样本作为测试集进行了简单的序列划分 ） | N23: 未提及（注：全局扫描全文及附录，文中仅在附录中给出了 30 个数据点的示例表格，并说明原始数据来自山东蓬莱测风站，但完全没有提供完整的开源数据集下载链接、GitHub 代码仓库地址或官方数据库访问入口 ） | O23: 未提及（注：尽管文章在配图（Fig. 1）中展示了山东省蓬莱市的地理位置映射，但在实际构建的所有预测模型输入特征计算中，完全没有显式引入高程 DEM、地表粗糙度或具体的经纬度等空间静态物理特征参数 ） | P23: 未提及（注：全文完全没有提及将湍流动能(TKE)、局部垂直风切变或局部地形引发的尾流扰动等微尺度流体力学物理特征提取作为模型输入 ） | Q23: 单点历史风速多步滞后序列（注：模型极度依赖单点自身的历史时间序列特征。在多步预测的实验设置中明确指出，系统以“前 5 个风速数据”作为输入（即滞后项 Lag variables = 5），来预测下一个时间点的风速。模型没有引入相邻或上游气象站点的空间传播关联特征，也未显式输入月份/小时等时间周期编码 ） | R23: 单点多步确定性短期预测（注：系统针对特定的单一风电站点，基于 10 分钟分辨率的风速数据，输出未来 1 步（10分钟）、2 步（20分钟）和 3 步（30分钟）的确定性风速标量预测值，本文中的多步预测是通过将上一步的输出迭代作为下一步的输入来实现的，不涉及概率区间预测 ） | S23: 提出 CEEMDAN-GWO 优化加权组合模型并进行极度详尽的消融/横评（注：本文提出使用灰狼优化算法（GWO）来动态分配并集成 5 种底层单一预测模型（ARIMA, BPNN, FTDNN, GRNN, LSTM）权重的创新架构。其对比的 Baseline 规模极大，包含三个维度：一是 5 种底层单体算法；二是 5 种采用 CEEMDAN 预处理的单一网络组合；三是采用其他 4 种不同频域分解方法（EMD, EEMD, SSA, VMD）与 GWO 加权融合的混合模型 ）。 | T23: 未融合物理机制/纯数据驱动（注：本文提出的是一种完全基于纯历史风速数据驱动的深度混合预测系统。该系统利用中国蓬莱风电场的 10 分钟间隔数据，前端使用 CEEMDAN 进行数据去噪预处理，底层利用 ARIMA、BPNN、FTDNN、GRNN 和 LSTM 五种单体模型进行黑盒映射预测，顶层则引入灰狼优化算法（GWO）进行动态组合权重寻优。作者在文献综述中明确指出物理方法（NWP）计算耗时且不擅长短临预测，因此本文通篇未在网络输入、拓扑结构或目标函数中融入任何气象动力学方程或流体力学约束 ） | U23: 纯数学误差与统计学损失映射（未明确特定单一全局方程）（注：在 BPNN 等底层神经网络的反向传播数学推导中，提到了基于预测误差梯度的连接权重更新（隐式使用MSE）；在 Diebold-Mariano (DM) 检验统计推断中，明确定义了预测误差的损失函数 Ω ~ ；灰狼算法（GWO）则通过误差评估寻优，但通篇未提及在损失函数或目标函数中添加任何物理学、空气动力学方程的约束惩罚项 ） | V23: 相较于同组最佳的混合基线模型，平均单步预测 MAPE 改善了 68.03%（注：原文在表 7（Table 7）中极其明确地给出了基于 MAPE 误差计算的具体改善率（Improvement ratio）百分比。相较于五种混合基线模型中表现最好的 CEEmdan-ARima，本文提出的 CEEmdan-GWO 组合模型在单步、两步和三步的平均预测中，MAPE 分别改善了 68.03%、36.17% 和 17.20%；若直接与传统的单体 LSTM 模型进行横向对比，其单步平均误差改善率甚至高达 85.55% ） | W23: 极大地克服了单一模型固有缺陷与原始风速高频噪声叠加导致的预测失稳痛点（注：作者在研究动机中深刻指出，风速本身具备极强的随机性和间歇性，许多传统研究直接使用原始数据或单一模型，导致预测结果精度极差。该系统利用极其严谨的“前端频域去噪 + 后端多模型仿生加权融合”组合拳，彻底规避了单一算法的局限性，实现了极具鲁棒性的短期多步（Multi-step）预报，为风力发电站的可靠、安全运行以及并网调度提供了高效的工程决策支撑 ） | X23: 优化算法增强，集成方法
A24: 24 | B24: 10.1016/j.energy.2015.08.039 | C24: 否 | D24: A hybrid wind speed forecasting model based on phase space reconstruction theory and Markov model: A case study of wind farms in northwest China | E24: 2015年，发表于 Energy | F24: 未提及 | G24: 点尺度 （注：研究对象为中国西北地区特定风电场的站点数据。文中明确区分了案例一的 Site A, B, C, D 以及案例二的 Site E, F, G, H，所有预测和验证均基于这些站点的单点观测序列，而非网格化空间预报场） | H24: 日分辨率与 10 分钟分辨率 （注：案例一使用日平均风速（daily mean wind speed），执行提前一天的日前预测，测试期为 182 天；案例二使用 10 分钟平均风速（10 min average wind speed），执行提前 10 分钟的超短期预测，测试样本量为 72 个） | I24: 未提及具体高度 | J24: 中国西北地区风场 （注：研究背景明确设定在中国西北地区（northwest China）的风电场。） | K24: 纯历史风速（注：原文明确说明，模型仅采用中国西北地区风电场的日平均和 10 分钟平均历史风速时间序列作为基础输入，未引入温度、气压、风向等任何其他气象变量 ） | L24: 有 （注：明确使用了来自风电场现场的观测风速（observed wind speeds）和实测序列（measurement data）。数据集被划分为训练集（用于获取模型参数）、验证集（用于选择最优参数）和测试集（用于评估预测能力）） | M24: 相空间重构（C-C方法）与 FCM 误差状态聚类（注：在数据预处理阶段，放弃了传统的主观滞后项选择，而是使用 C-C 相空间重构方法基于相关积分来自动计算并提取原始序列的最佳延迟时间和嵌入维数，以此确定最佳输入形式；此外，还创新性地使用模糊 C 均值（FCM）算法对初次预测产生的残差序列进行聚类，以划分不同的误差状态区间供马尔可夫模型进行修正 ） | N24: 未提及（注：全局扫描正文及参考文献，文中仅说明数据来自中国西北地区的四个风电场（Data set A-H），但完全未提供任何开源数据下载链接、GitHub 代码仓库地址或官方数据库访问入口 ） | O24: 未提及（注：模型输入层完全基于一维时间序列的重构，没有显式输入测风站的具体经纬度、高程 DEM 或地表粗糙度等空间静态物理特征 ） | P24: 未提及（注：全文完全没有提及将湍流动能(TKE)、局部垂直风切变或风机尾流效应等微尺度流体力学物理特征提取作为模型输入 ） | Q24: 单点本地历史多步滞后序列（注：高度依赖单点自身的时间序列。模型通过 C-C 方法严格计算出每个数据集特定的嵌入维数（m）和延迟时间（t）来重构历史序列作为输入 ），完全没有引入相邻或上游气象站点的空间传播关联特征，也未显式输入月份/小时等时间周期编码 ） | R24: 单点确定性预测（注：针对选定的西北地区风电场，输出未来单步的确定性风速标量预测值。系统分别在“日平均（提前一天预报）”和“10分钟平均（提前10分钟预报）”两种不同时间尺度的数据集上进行了独立建模与验证，不涉及概率区间或区域网格预测 ） | S24: 提出 C-LSSVM-PSOGSA 混合误差修正模型与多模型横评（注：本文提出了一种复杂的“相空间重构 + PSOGSA 仿生优化 LSSVM + 马尔可夫(Markov)误差修正”的复合集成架构。用于详尽对比的 Baseline 包含了传统的时间序列模型与神经网络：ARIMA、GRNN、BPNN、RBF、Elman，以及消融了误差修正模块的单体 LSSVM-PSO 和 LSSVM-PSOGSA 模型 ） | T24: 未融合物理机制/纯数据驱动（注：本文提出的是一种纯数据驱动的混合智能预测架构（C-LSSVM-PSOGSA）。该模型完全依赖于中国西北风电场的纯历史风速时间序列数据。前端通过相空间重构（C-C 方法）自动确定数据的延迟时间和嵌入维数，核心预测器使用最小二乘支持向量机（LSSVM）并结合引力粒子群（PSOGSA）算法进行黑盒参数寻优，最后利用马尔可夫链（Markov）对残差序列进行后处理修正。通篇未在输入特征、网络架构或损失函数中显式融入任何气象动力学方程、计算流体力学（CFD）或数值天气预报（NWP）物理约束） | U24: 最小二乘结构风险与适应度函数（注：在底层预测器最小二乘支持向量机（LSSVM）的数学推导中，其回归问题被转化为包含误差变量二次方与权重惩罚项的约束二次优化问题（本质即最小化平方误差）；而在顶层的引力搜索与粒子群混合算法（PSOGSA）进行寻优时，则通过计算粒子的“适应度值（fitness value）”来进行位置更新，通篇未提及在目标函数中添加任何物理学先验方程作为约束惩罚项 ） | V24: 相较于最佳传统单体模型，日均预测 MAPE 最高提升 21.71%，10分钟预测 RMSE 最高降低 39.87%（注：原文在结论与对比表格中极其详实地给出了提升百分比。在日均风速预测（Case 1）中，该组合模型相比表现最好的单体基线模型，其 MAPE 的改善幅度在四个数据集中分别为 3.9505%、14.0670%、13.8640% 和 21.7100%；在 10 分钟级别的超短期预测（Case 2 数据集 E）中，其相较于传统 RBF 神经网络，RMSE 更是大幅降低了 39.8706%） | W24: 打破了模型输入严重依赖“人工主观试错”的工程瓶颈，并利用残差挖掘突破了单体黑盒的精度天花板（注：作者在研究动机中深刻指出，传统方法在确定网络输入特征（滞后阶数）时往往依赖个人经验或偏自相关函数（PACF），主观性极强。该系统利用 C-C 理论实现了输入形式的“全自动客观决策”，并通过极具创造性的“马尔可夫误差修正机制”榨干了预测残差中的最后一点非线性信息。这不仅提升了算法的自动化落地能力，也为大规模风电网降低备用容量成本、制定极其重要的发电机组维护计划（Generator Maintenance Scheduling）提供了高精度的决策支撑） | X24: 支持向量机类，优化算法增强，（传统统计与时间序列模型）其他统计模型
... A61: 61 | B61: 10.1016/j.apenergy.2019.114259 | C61: 否 | D61: Probabilistic spatiotemporal wind speed forecasting based on a variational Bayesian deep learning model | E61: 2020年，发表于 Applied Energy | F61: 未开源代码 | G61: 网格分辨率（注：文献的核心是将风机或站点的空间位置映射为网格结构（embedding turbines into a grid space）以便提取时空特征。其中，案例1提取了304个风力发电机重构为 26 × 12 的空间网格；案例2在更大范围内提取了400个站点并重构为 20 × 20 的网格） | H61: 1小时（注：模型输入与输出的时间步长均为1小时（The time step is one hour）。预测跨度为：利用过去3小时（previous 3-h）的历史空间气象变量，预测未来3小时（3 h-ahead）的风速时间序列） | I61: 未提及具体高度（注：文中通篇仅说明使用了风力发电机（wind turbines）或相关站点（sites）的风速、风向等气象数据，但完全没有提及这些数据测量或预测所对应的具体离地高度（如 10m 或轮毂高度）） | J61: 未提及具体海拔与地形特征（注：文中仅给出了两个案例研究区域的确切经纬度坐标范围（案例1为 105.00°W-105.34°W, 41.30°N-41.90°N；案例2为 W97°-W107°, N33°-N43°），但完全没有涉及任何具体的海拔高度数值，也未对当地的地貌特征（如平原、山地）做出任何物理形态的客观描述） | K61: 风速、风向、温度、地表气压、露点、相对湿度、可降水量（注：原文在案例1中明确选取了网格内的风速、风向、温度（K）和地表气压（Pa）作为输入；在案例2中明确选取了风速、风向、温度（°C）、露点、相对湿度和可降水量作为输入。此外，明确将风向与对应的风速转换为“风速向量（wind speed vector）”作为历史变量一同输入） | L61: 未明确提及具体物理观测设备名称（注：文中使用了美国国家可再生能源实验室(NREL)提供的风力发电机(wind turbines)和站点(sites)的多变量气象数据，并将其作为“观测到的风速值（observed wind speed values）”进行预测对比，但通篇未提及测风塔、风速计、雷达等具体的独立物理气象观测传感器名称） | M61: 空间网格映射转换与缺失值填充（注：文中完全未提及使用VMD分解、归一化或异常值剔除等常见时序预处理方法。其核心的特征工程是将离散分布的真实风力发电机/测风站坐标，通过坐标转换映射重构为规则的空间二维网格矩阵（案例1为 26×12 的网格，案例2为 20×20 的网格），并将没有风机实体的空缺位置统一填充为 -1 数据，以将原始数据转化为适用于图像识别的 3D 张量形态） | N61: 有（注：全局扫描后，文中在第 4.A 节详细给出了两个案例所用美国 NREL 官方公开数据集的具体获取网址。案例1链接为：https://www.nrel.gov/grid/wind-toolkit.html ；案例2链接为：https://maps.nrel.gov/nsrdb-viewer/ ） | O61: 未提及（注：文中虽将气象站点映射为空间二维网格（grid space）并保留了相对经纬度拓扑关系，但通篇完全未显式提取或输入高程 DEM、地表粗糙度或大规模地形分类等空间静态物理特征参与建模） | P61: 未提及（注：全文完全没有涉及湍流动能(TKE)、局部垂直风切变、局部地形引起的尾流扰动等微尺度物理特征的输入）。 | Q61: 时空联合历史序列输入（注：在时间关联上，使用了过去 3 小时（previous 3-h）的历史空间气象序列作为滞后项（Lag variables）预测未来；在空间关联上，由于将站点嵌入了网格，模型通过 3D CNN 和 ConvGRU 架构中的卷积算子（convolution operator *）显式且联合地捕捉了整个区域网格内相邻站点的空间连带关联特性。但文中未提及显式引入月份/小时等时间周期编码） | R61: 区域网格多步概率与区间预测（注：该模型并非单纯的点预测标量输出，而是基于网格结构，一次性输出整个区域内所有站点未来 3 小时（3 h-ahead）风速的概率密度分布（PDF），并在实验结果中展示了其提供的 70% 和 95% 置信度的连续预测区间（prediction intervals）） | S61: 提出变分贝叶斯时空神经网络 STNN-VB（注：文中提出结合 ConvGRU 和 3D CNN 并引入变分推断的 STNN-VB 模型。为了进行验证，选用的 Baseline 基线模型涵盖了点预测模型：Persistence (PR)、Lasso Regression (LR)、ANN、LSTM、CNN，以及概率预测模型：高斯过程回归 GPR 和隐马尔可夫模型 HMM） | T61: 未融合物理机制/纯数据驱动（注：本文提出的是基于变分贝叶斯与时空神经网络结合的概率预测模型（STNN-VB）。模型通过将风力发电机坐标映射为二维网格矩阵，直接利用 ConvGRU 和 3D CNN 等深度学习图像识别算子对多站点气象数据进行纯黑盒的时空特征映射，并通过变分推断（Variational Bayesian inference）计算参数的概率密度。通篇未显式融合任何气象学流体方程、物理约束损失函数或风廓线定律 ）。 | U61: 最大化证据下界 ELBO / 平方损失加KL散度（注：变分贝叶斯推断的优化目标为最大化证据下界（ELBO）。在具体近似计算时，该函数由两部分组成：第一部分是预测的误差平方损失项，第二部分是防止过拟合的 KL 散度正则化项（近似为对变分参数的 L2 正则化），通篇未提及添加物理约束项） | V61: 相较于表现较优的 CNN 基线模型，平均 RMSE 在两个案例中分别降低了 4.10% 和 14.1%（注：原文在第 4.C 节和结论中明确给出了具体的对比百分比 。在绝对误差数值方面，以提前1小时（1-h）预测为例，本文提出的 STNN-VB 模型在案例1和案例2中的测试集 RMSE 分别低至 1.714 m/s 和 0.226 m/s，明显优于 CNN 基线的 1.826 m/s 和 0.311 m/s，以及 LSTM 基线的 1.832 m/s 和 0.292 m/s ）。 | W61: 解决了传统独立点预测模型无法同时量化“空间与时间”双重维度预测不确定性的痛点，为风电场整体并网调度提供了多维度的风险评估边界（注：作者在引言和结论中重点强调，精准的概率预报不仅需要关注单个目标站点，还要关注整个风电场区域的时空不确定性 。该模型能够在时间和空间层面上同时提供有效的风速置信区间和概率密度分布（PDF），切实保障了电网面对极端气象波动时的安全稳定运行 ）。 | X61: 循环神经网络、卷积神经网络、时空模型、贝叶斯方法
A62: 62
A63: 63 | B63: 未提及 | C63: 否 | D63: Wind Speed Forecasting Using an Echo State Network with Nonlinear Output Functions | E63: 未提及 | F63: 未开源代码 | G63: 点尺度（注：文献未涉及大范围的网格预报数据，而是针对位于内华达州里诺地区（Reno, NV area）的气象站单点位置进行多变量输入的时间序列预测建模 ） | H63: 10分钟（注：研究使用了2016年1月的数据，数据时间间隔为10分钟（a time interval of ten minutes）。在实验中，训练集（Ltrain）的长度被设定为200，测试集（Ltest）的长度为100（即对应测试集的预测跨度为100个10分钟间隔） ） | I63: 未提及具体高度（注：文中通篇仅说明使用了气象站提供的风速和风向（wind speed and direction）数据，完全没有提及所使用的测风设备所处的具体离地高度数值 ） | J63: 未提及具体海拔高度与地形特征（注：文中仅说明了数据收集自内华达州里诺地区（Reno, NV area），完全没有涉及当地确切的海拔高度数值，也未对周边地形特征做出任何客观的物理描述 ） | K63: 湿度、空气温度、平均阵风风速与风向、露点、风速与风向（注：原文明确指出，案例研究中作为网络输入的变量包括由内华达州交通部路网气象站提供的湿度、空气温度、平均阵风风速和风向、露点，以及风速和风向 ） | L63: 有（注：使用了内华达州交通部路网气象系统（RWIS）实际采集的气象数据，输入到网络中的具体观测变量包含：湿度（Humidity）、空气温度（air temperature）、平均阵风风速与风向（average gust speed and direction）、露点（dew point），以及风速和风向 ） | M63: 数据集划分与非线性读出状态构建（注：文中完全未提及数据清洗、异常值剔除或如VMD等频域分解方法。在特征处理上，主要是通过几何级数或多变量多项式（如内部状态的平方、乘积等）来重构非线性的读出状态函数向量（read-out vector）以降低网络计算量 。此外，数据被划分为长度为200的训练集（Ltrain）和长度为100的测试集（Ltest），并明确说明实验中的权重矩阵初始分配“没有缩放（with no scaling）” ） | N63: 未提及（注：全局扫描全文，文中仅指出数据获取自内华达州交通部路网气象信息系统（RWIS）的公共记录 ，但完全未提供具体的开源下载链接、GitHub地址或官方数据库的网页入口）。 | O63: 未提及（注：文中仅提及观测数据收集自内华达州的里诺地区（Reno, NV area） ，完全没有显式输入高程DEM、地表粗糙度或大规模地形分类等空间静态物理特征进行预测建模）。 | P63: 未提及（注：全文完全没有涉及湍流动能(TKE)、局部垂直风切变、局部地形引起的尾流扰动或低层微气候参数等微尺度物理特征的输入）。 | Q63: 单点历史隐式状态与输出反馈输入（注：由于回声状态网络（ESN）本质是一种离散时间的循环神经网络（RNN） ，模型通过内部状态矩阵 x(t) 和输出反馈矩阵 T⋅y(t) 显式利用了上一个时间步的内部历史状态和预测输出结果来更新当前状态 ；属于纯单点预测，完全未引入显式的月份/小时等时间周期编码，也未融合相邻气象站的空间连带传播特征）。 | R63: 单点多步标量预测（注：模型在测试集上连续输出未来 100 个 10分钟间隔（Ltest = 100）的风向和风速的绝对标量预测值 ，未使用概率区间预测形态）。 | S63: 提出基于非线性输出函数的非线性回声状态网络 N-ESN（注：文中提出了两种 N-ESN 变体：基于几何级数的 N-ESN 和基于内部状态非线性关系的 N-ESN 。用于对比的基线 Baseline 模型为经典的回声状态网络（classic ESN） ）。 | T63: 未融合物理机制/纯数据驱动（注：本文提出的是一种具有非线性输出函数的回声状态网络（N-ESN）。模型仅通过构建内部隐状态的几何级数（geometric series）或多项式非线性关系（nonlinear relations）来重构网络的非线性读出状态向量，并利用递归最小二乘算法（RLS）进行黑盒权重参数更新 。其本质仍是基于历史气象观测数据的纯数学/统计维度的映射，通篇完全未显式融合任何流体力学方程、气象物理定律、风廓线公式或带有物理约束项的损失函数）。 | U63: 递归最小二乘算法（RLS）（注：文中在训练输出权重矩阵时，并未采用常规的 MSE 梯度下降，而是明确使用了递归最小二乘（RLS）算法，利用前一次估计的误差来逐步改进下一次的权重收敛 ；在模型测试评估阶段则使用归一化均方根误差（NRMSE）和归一化平均绝对误差（NMAE）作为指标 ；未提及添加任何物理约束项）。 | V63: 风速预测的 NMAE 降低了 58%，NRMSE 降低了 53%（注：原文在第 IV-C 节给出了非常明确的对比百分比与绝对误差数值。在风速预测任务中，本文提出表现最好的“基于非线性关系状态的 N-ESN 模型”测试集 NMAE 为 1.6%、NRMSE 为 0.106；相较于传统的经典 ESN 基线模型（NMAE 3.8%, NRMSE 0.228），其 NMAE 显著降低了 58%，NRMSE 改善了 53% 。此外，在风向预测上，该模型的 NMAE 和 NRMSE 也分别比基线 ESN 降低了 39% 和 49% ）。 | W63: 缓解了风电场因风况突变导致的系统发电计划与能源调度困难，同时克服了传统深度神经网络计算资源消耗过大的痛点（注：作者在引言和结论中明确指出，风速和风向的极度多变性导致风力发电功率无法被提前准确获知，这给风电场的系统规划与电网调度（system scheduling and energy dispatching）带来了巨大困难 。该研究通过降维重构内部状态，在大幅提升预测精度的同时，显著降低了模型的计算负荷（computational load）与收敛时间 ，极其适合对计算效率要求苛刻的短临风电业务场景）。 | X63: 其他专门网络
A64: 64 | B64: 10.1016/j.enconman.2018.04.099 | C64: 否 | D64: Ensemble empirical mode decomposition based adaptive wavelet neural network method for wind speed prediction | E64: 2018年，发表于 Energy Conversion and Management | F64: 未开源代码 | G64: 点尺度（注：文献未涉及任何大范围网格预报数据，而是仅针对位于印度梅拉曼代（Melamandai）的单一点位风电场进行风速时间序列的预测建模 ） | H64: 原始10分钟，重采样为1小时（注：原始测量数据为2015年4月1日至4月30日期间采集的10分钟级样本（10min samples），随后在建模前将其平均转换为1小时（averaged over 1-h）分辨率的时间序列数据。预测跨度为单步提前（one-step ahead）预测 ） | I64: 未提及具体高度（注：文中通篇仅说明使用了风电场风速计（wind farm anemometer）收集的原始风速时间序列数据，完全没有提及该测风设备或预测目标所处的具体离地高度数值 ） | J64: 未提及具体海拔高度与地形特征（注：文中仅以图文说明了研究站点位于印度南部的泰米尔纳德邦梅拉曼代（Melamandai, TamilNadu, India），但通篇完全没有涉及该站点确切的海拔高度数值，也未对周边的地形地貌（如山地、平原或粗糙度）做出任何客观的物理描述 ） | K64: 历史风速（注：原文明确指出该模型为纯统计模型，仅使用从印度南部风电场风速计实际收集的历史风速时间序列数据（wind speed time-series data）作为基础输入，不依赖数值天气预报（NWP）输入，也完全未提及温度、气压等其他气象变量。文中明确在“未来工作”中才计划纳入风向、温度、气压和湿度等变量）。 | L64: 有（注：明确使用了安装在印度梅拉曼代站点的物理风速计（anemometer）实际采集的长达一个月的历史风速时间序列数据，将其进行 EEMD 降噪分解后，作为 AWNN 神经网络的训练输入与真实对比标签 ） | M64: 均值重采样与 EEMD 降噪重构（注：首先将原始10分钟采样间隔的风速序列求平均，转换为1小时（1-h）分辨率的数据；随后使用集合经验模态分解（EEMD）将时间序列分解为有限数量的本征模态函数（IMFs）和一个残差（Residue）；为了去噪，模型直接剔除最高频的第一个分量（first IMF），并将剩余的 IMFs 和残差相加，重构出无噪声的新数据供网络训练。通篇未提及使用归一化（Normalization/MinMax）操作）。 | N64: 有（注：文中在第4节说明数据来自印度泰米尔纳德邦 Melamandai 的测风站点，并在参考文献 中明确给出了印度国家风能研究所（NIWE）的官方数据库网址：niwe.res.in）。 | O64: 未提及（注：文中仅通过地图和文字指出了研究站点位于印度南部的泰米尔纳德邦 Melamandai，但完全没有显式输入高程 DEM、地表粗糙度或大规模地形分类等空间静态物理特征进行预测建模）。 | P64: 未提及（注：全文完全没有涉及湍流动能(TKE)、局部垂直风切变、局部地形引起的尾流扰动等微尺度物理特征的输入）。 | Q64: 单点历史序列输入（注：在构建自适应小波神经网络（AWNN）时，提取了目标站点过去的历史风速样本序列以预测未来风速，属于纯单点时间序列关联。文中完全未引入显式的月份/小时等时间周期编码，也没有融合周边相邻气象站点的空间连带传播特征）。 | R64: 单点单步标量预测（注：文中明确指出提出的是一个用于“单步提前（one-step ahead）”风速预测的有效方法，即直接输出单一站点未来 1 小时对应的一个风速绝对标量值，未使用概率区间或区域网格预测形态）。 | S64: 提出混合预测模型 EEMD-AWNN（注：文中提出了基于集合经验模态分解与自适应小波神经网络（以 Mexican hat 为母小波）结合的 EEMD-AWNN 混合模型。用于全面对比的 Baseline 基线包含两大阵营：个体模型（Persistence、BPNN、RBFNN、ENN、GRNN、WNN）以及基于 EEMD 分解的混合模型（EEMD-BPNN、EEMD-RBFNN、EEMD-ENN、EEMD-GRNN））。 | T64: 未融合物理机制/纯数据驱动（注：本文明确强调其提出的是一种纯粹基于统计的预测模型（statistical-based model），并在引言与贡献部分特意说明“无需利用数值天气预报（NWP）的输入” 。模型仅依靠集合经验模态分解（EEMD）对原始风速信号进行滤波降噪，随后利用自适应小波神经网络（AWNN）对历史序列进行纯数学维度的黑盒映射。通篇未显式融合任何流体力学物理定律、气象学约束方程或对数风廓线等物理机制）。 | U64: 均方误差 MSE（注：原文在阐述 AWNN 模型的标准反向传播（BP）算法训练时，明确指出其首要目标是最小化均方误差（Mean Square Error, MSE），并将基于梯度的E 作为成本函数（cost function）来更新平移、膨胀系数及网络权重，未提及添加任何物理约束项）。 | V64: 相较于表现最好的复杂混合基线模型，RMSE 提升了 31.78%，MAE 提升了 27.06%（注：原文在表4和表5中给出了明确的绝对对比数值与百分比。提出的 EEMD-AWNN 模型测试集绝对误差达到极低水平：RMSE 为 0.5249 m/s，MAE 为 0.4176 m/s 。在与表现最好的复杂混合基线 EEMD-BPNN 对比时，其 RMSE 提升了 31.7829%，MAE 提升了 27.0655%；若相较于表现最好的单一基线模型 WNN，其 RMSE 则大幅提升了 58.3505% ）。 | W64: 克服了纯风速信号极强的随机波动性，为智能电网与虚拟电厂（VPP）提供了兼具高精度与低计算负担的短临并网调度工具（注：作者在引言和结论中反复强调，风能固有的高度间歇性使得风电并网的常规运营变得极其复杂 。该研究通过 EEMD 消除高频物理噪声，并在 AWNN 中采用自适应学习率，切实为虚拟电厂和智能电网的运营者提供了一种能够快速收敛且高度准确的风速预测手段，极具短期供需平衡规划的业务实操价值 ）。 | X64: 分解 - 预测混合框架、前馈神经网络
A65: 65 | B65: 10.1007/s00521-020-05141-w | C65: 否 | D65: A permutation entropy-based EMD–ANN forecasting ensemble approach for wind speed prediction | E65: 2021年，发表于 Neural Computing and Applications | F65: 未开源代码 | G65: 点尺度（注：文献未涉及大范围的网格预报数据，而是针对西班牙阿尔赫西拉斯湾（The Bay of Algeciras, Spain）单一气象监测站（a weather monitoring station）的数据作为案例进行风速预测研究） | H65: 1小时（注：模型考虑了不同预测跨度，包括提前 1、2、8、24 小时（ph = 1, 2, 8, 24 ahead），以及8小时和24小时平均值，并具体给出了短期 1 小时（1 h）和中期 24 小时（24 h）预测的相关系数评估） | I65: 未提及具体高度（注：文中通篇仅说明了预测目标为风速（wind speed），完全没有提及该气象站监测风速或模型预测所对应的具体离地高度数值） | J65: 未提及具体海拔高度与地形特征（注：文中仅说明了研究的案例区域为西班牙的阿尔赫西拉斯湾（The Bay of Algeciras, Spain），完全没有涉及当地具体的海拔高度数值或对海湾地形特征的客观物理描述） | K65: 风速（注：文献片段的核心任务是风速预测（wind speed prediction），引言中提及了风速和风向是影响空气污染物的重要因素，但就模型基础输入而言，当前片段未明确提及除历史风速外的其他气象变量 ）。 | L65: 有（注：明确说明了实验数据库的数据是从真实的气象监测站（weather monitoring station）实际收集而来的，用于后续 EMD-PE-ANN 混合模型的训练与预测） | M65: EMD分解与排列熵（PE）降维预处理（注：文中提出将经验模态分解（EMD）作为数据预处理方法，并结合基于信息的排列熵（Permutation Entropy, PE）方法，通过减少需要被预测的分解组件数量，来显著降低计算成本和预测风险 ）。 | N65: 未提及（注：文中仅说明研究的案例数据库收集自西班牙阿尔赫西拉斯湾的一个气象监测站（weather monitoring station），片段中未提供任何开源下载链接或官方数据库入口 ）。 | O65: 未提及（注：文中仅指出了案例研究区域为西班牙阿尔赫西拉斯湾（The Bay of Algeciras, Spain），完全未显式提及输入高程DEM、地表粗糙度等空间静态物理特征 ）。 | P65: 未提及（注：提供的文献片段中完全未涉及湍流动能(TKE)、局部垂直风切变或尾流扰动等微尺度物理特征的输入 ）。 | Q65: 单点历史序列（注：由于模型依赖经验模态分解（EMD）预处理，可以确定其使用了目标站点的历史风速时间序列作为预测基础，但片段中未具体说明使用的滞后项（Lag variables）步长，也未提及引入时间周期编码或融合周边站点的空间连带效应 ）。 | R65: 单点多步标量与平均值预测（注：模型针对单一监测站，输出了多种预测跨度的结果，包括提前1、2、8、24小时的风速预测值（ph = 1, 2, 8, 24 ahead），以及8小时和24小时的风速平均值（8-h and 24-h average） ）。 | S65: 提出基于排列熵的 EMD-ANN 混合集成模型（注：文中提出结合经验模态分解（EMD）、排列熵（PE）与人工神经网络（ANN）的集成学习方法（EMD-PE-ANN）；用于对比的 Baseline 基线模型明确为单一的人工神经网络模型（single ANN models） ）。 | T65: 纯数据驱动，未涉及物理机制融合（注：本文明确指出其研究背景是对“数据驱动方法（Data-driven approaches）”的应用探讨 。提出的模型仅结合了经验模态分解（EMD）、排列熵（PE）与人工神经网络（ANN），依靠对历史数据的分解降维与黑盒特征映射来进行风速预测 。文献片段中完全未显式提及融入任何气象学、流体力学物理定律或物理约束函数）。 | U65: 未提及（注：当前提供的摘要与引言片段中，未涉及模型训练优化的具体损失函数（如MSE），仅在实验结果评估部分提及使用了相关系数（correlation coefficient）进行模型性能比对 ）。 | V65: 提前24小时预测的相关系数显著提升至 0.807（注：由于提供的文献片段未给出 RMSE 或 MAE 等绝对误差数值，仅给出了相关系数对比。原文明确指出：在提前 1 小时的短临预测中，提出的 EMD-PE-ANN 模型相关系数为 0.981，优于单一 ANN 基线的 0.929；而在提前 24 小时的预测中，该模型相关系数达到 0.807，大幅超越了单一 ANN 模型的 0.503 ）。 | W65: 克服了传统模型随预测跨度增加而性能急剧恶化的痛点，并为大气污染扩散建模提供了关键气象输入（注：作者在引言中特别强调，风速及风向是影响空气污染物（如 CO、PM10 和 SO2）浓度的核心因素 。该混合模型不仅通过排列熵（PE）显著降低了计算成本 ，还在中长期预测视界下维持了高准确率，这对提升空气质量预警与污染建模极具实际工程价值 ）。 | X65: 分解 - 预测混合框架、前馈神经网络
A66: 66 | B66: 10.1016/j.eswa.2022.118419 | C66: 否 | D66: A deep-learning wind speed interval forecasting architecture based on modified scaling approach with feature ranking and two-output gated recurrent unit | E66: 2023年，发表于 Expert Systems With Applications | F66: 未开源代码 | G66: 点尺度（注：文献未涉及网格预报场数据，而是分别针对中国山东蓬莱风电场与土耳其某风电场这两个单点风电场（real wind farm）的风速时间序列进行预测建模 , ） | H66: 10分钟（注：实验所使用的八个不同季节的数据集的时间分辨率均为 10 分钟（resolution as ξ = 10 minutes）。其中每个数据集包含 1728 条数据，并按照 3:1 的比例划分为训练集和测试集 ） | I66: 未提及具体高度（注：文中通篇仅说明使用了风电场的真实数据（real wind farm data）和观测风速（observed wind speed），完全没有提及风速数据对应的具体测风设备或预测目标的离地高度数值 , , ） | J66: 未提及具体海拔与地形特征（注：文中仅说明了数据分别收集自中国山东的蓬莱风电场（Penglai wind farm, Shandong, China）以及土耳其的一个风电场（a Turkish wind farm），完全没有涉及两地确切的海拔高度数值，也没有对周围的真实地形地貌进行任何客观的物理形态描述 ） | K66: 历史风速（注：原文明确仅使用目标风电场的历史风速数据（historical time points wind speeds）作为模型的基础输入，通篇完全未提及风向、温度、边界层高度、气压等其他气象变量 ）。 | L66: 有（注：使用了来自中国山东蓬莱风电场和土耳其风电场实际采集的真实风速观测数据（real wind farm data / observed wind speed），作为特征排序（FR）模块的输入与深层门控循环单元（GRU）区间预测的真实对比目标 , , ） | M66: 改进的缩放方法（MSA）与 RReliefF 特征排序（注：在特征工程层面，模型首先使用基于 RReliefF 的特征排序（Feature Ranking, FR）模块评估历史风速序列的预测重要性权重，自适应剔除冗余特征，期间提及将特征映射到 0 到 1 之间（mapped into 0–1）；在数据构建层面，提出改进的缩放方法（Modified Scaling Approach, MSA），通过对目标风速的上下界进行不对称缩放（scaling up and down）来直接生成区间值的训练标签 ）。 | N66: 未提及（注：全局扫描正文、附录，文中仅说明使用了中国山东蓬莱风电场和土耳其某风电场的真实数据进行实验，完全未提供任何开源下载链接、GitHub 地址或官方数据库入口 ）。 | O66: 未提及（注：文中仅提及数据来自中国山东和土耳其的风电场，完全未显式输入高程 DEM、地表粗糙度或大规模地形分类等空间静态物理特征进行预测建模 ） | P66: 未提及（注：全文完全没有涉及湍流动能(TKE)、局部垂直风切变、局部地形引起的尾流扰动等微尺度物理特征的输入）。 | Q66: 单点历史序列滞后项输入（注：在特征提取阶段，明确将过去连续的 m 个历史时间点风速作为候选特征池（candidate features pool），并在实验参数中设置为从过去 24 个滞后时间点中筛选出最重要的 6 个特征作为输入。属于纯单点预测，未显式引入月份/小时等时间周期编码，也未融合相邻或上游气象站点的空间传播特征 ）。 | R66: 单点区间预测（注：模型采用了双输出门控循环单元（Two-output GRU），直接输出单一风电场未来风速预测区间的下界和上界绝对标量值 ）。 | S66: 提出结合特征排序、双输出GRU与改进缩放方法的区间预测架构 FS-GRU-MSA（注：用于对比的 Baseline 基线模型非常丰富，包含了朴素模型（Naive model），以及底层采用 BP 神经网络但结合了不同区间构建策略的模型：基于正态分布的误差分布法、Bootstrap 法、核密度估计法（KDE），以及三种传统的缩放方法（SA1, SA2, SA3） ）。 | T66: 未融合物理机制/纯数据驱动（注：本文提出的是完全基于数据驱动的深度学习风速区间预测架构（FS-GRU-MSA）。模型主要依赖改进的缩放方法（MSA）直接生成区间训练标签，利用 RReliefF 算法进行特征排序（FR）以剔除冗余的历史风速特征，并通过双输出门控循环单元（GRU）进行非线性的黑盒特征映射 。通篇未在网络结构设计或损失函数优化中显式融合任何气象学原理、流体力学方程或物理定律约束 ）。 | U66: 均方误差（MSE）与多目标帕累托前沿寻优（注：在深度学习 GRU 网络的参数更新中，明确采用了均方误差公式 作为损失函数结合 Adam 优化器进行训练；而在优化构建区间的缩放参数 α1 ,α2 ​ 时，使用了带约束的多目标草蜢优化算法（MoGOAC），以覆盖率（PICP）和区间平均宽度（PINAW）为优化目标。未提及添加物理约束项 ）。 | V66: 相较于各类基线模型，CWC 平均提升了 4.07% 至 97.76%；相较于未引入 GRU 的消融模型，CWC 和 AD 进一步分别提升了 17.0% 和 30.97%（注：原文在结论与表10、表11中给出了明确的平均提升百分比。在覆盖宽度准则（CWC）上，提出的 MSA 方法较其他传统的区间构建与缩放基线模型（如核密度估计、Bootstrap等）平均提升了 4.07% 到 97.76% 。此外，相较于采用浅层网络（FR-BPNN-MSA）的最佳基线，进一步嵌入深度学习 GRU 后，其 CWC 再次提升了 17.0%，反映区间偏离程度的累积偏差（AD）也大幅改善了 30.97% ）。 | W66: 解决了传统确定性点预测无法有效量化风能不确定性，以及现有区间预测模型过度依赖严格统计假设（如假设误差服从正态分布）且预测质量低下的痛点（注：作者在引言和结论中明确强调，仅提供单一风速值的预测不足以应对风电间歇性给电网带来的挑战 。该研究无需预设误差的概率分布假设，能为风力发电系统的安全规划、日常运营以及并网生产调度（production scheduling）提供更为可靠的未来风力波动上下界限 ）。 | X66: 循环神经网络、优化算法增强、分位数回归
A67: 67 | B67: 10.1016/j.egyr.2021.08.196 | C67: 否 | D67: A reliable and cost-effective planning framework of rural area hybrid system considering intelligent weather forecasting | E67: 2021年，发表于 Energy Reports | F67: 未开源代码 | G67: 点尺度（注：文献未涉及大范围的网格预报场，而是针对伊朗锡斯坦和俾路支斯坦省（Sistan & Balouchestan province of Iran）的某个特定偏远地区（remote area）进行单点微电网系统的容量优化与气象预测） | H67: 1小时（注：文献在混合系统的仿真与成本测算中使用了全年 8760 小时（t=8760）的计算步长，并且在实际案例评估阶段，明确给出了1月1日至1月7日共 168 小时（168 h）的逐小时（hourly）负荷与风光发电量分布预测） | I67: 20米（注：文中在第2节给出了计算轮毂高度风速（wind speed at hub height）的风切变公式，并在表2（Table 2）的混合系统参数列表中明确规定了风机安装塔筒的高度（H (m)）为 20 米） | J67: 未提及具体海拔高度（注：文中仅说明了研究区位于伊朗锡斯坦和俾路支斯坦省，并提及该研究省份存在多风地区和沙漠（windy areas and deserts in the under-study province），但通篇完全没有涉及当地的具体海拔高度数值） | K67: 太阳辐射、风速、环境温度（注：原文明确指出，为了解决偏远地区气象数据难以获取的问题，模型采用了智能气象预测方案来估算太阳辐射（solar radiation）、风速（wind speed）和环境温度（ambient temperature），并将这三个变量作为系统优化的基础气象输入）。 | L67: 有（注：文中指出使用往年的历史天气观测数据来训练预测模型，并提到现实中气象设备（meteorological devices）可能存在故障，或受洪水、风暴影响产生异常数据（outlier or noise data），但全文未明确交代具体使用了多少个地面气象站或测风塔以及设备的具体型号） | M67: 模糊C均值（FCM）聚类剔除异常值（注：文中明确提出了一种预处理聚类技术，即使用模糊C均值（Fuzzy c-means, FCM）算法。其目的是为了应对由洪水、风暴或气象设备故障引起的极端异常/噪声数据（outlier or noise data），在进入神经模糊推理系统（ANFIS）学习前，先通过该聚类技术将异常历史数据剥离剔除，通篇未提及VMD频域分解或MinMax归一化）。 | N67: 未提及（注：全局扫描全文及致谢/利益冲突声明部分，文中仅说明案例研究的数据来源于伊朗锡斯坦和俾路支斯坦省（Sistan & Balouchestan province of Iran），但完全未提供任何相关数据集的开源下载链接、GitHub 地址或官方数据库网页入口）。 | O67: 未提及（注：文中仅提及该研究省份存在多风区域和沙漠（windy areas and deserts），并在计算风机发电量时设定了20米的塔筒高度（H=20m）以及0.25的风切变系数（wind shear coefficient），但完全没有显式输入高程 DEM、地表粗糙度或大规模地形分类等空间静态特征作为预测模型的输入矩阵）。 | P67: 未提及（注：全文完全没有涉及湍流动能(TKE)、局部垂直风切变、局部地形引起的尾流扰动等微尺度物理特征的输入）。 | Q67: 单点历史日前气象数据输入（注：文中在训练迭代气象预测模型时，明确使用往年特定时间间隔的历史日前气象数据（historical day-ahead weather data）来让系统进行学习；属于纯单点预测，完全未提及融合相邻或上游气象站点的空间传播连带特征，也未展示引入具体的月份/小时等周期编码）。 | R67: 单点单值连续标量预测（注：在气象预测阶段，ANFIS-FCM 模型针对单一目标地区直接输出未来具体时刻太阳辐射、温度和风速的绝对标量预测值（单位分别为 W/m2、◦C 和 m/s），未使用概率或区间预测形态）。 | S67: 提出气象预测模型 ANFIS-FCM 与系统容量优化模型 MVO（注：本文包含两个层面的算法对比。在气象预测阶段，提出了基于模糊C均值的自适应神经模糊推理系统（ANFIS-FCM），其对比的基线模型包括传统的人工神经网络（ANN）和径向基函数网络（RBF）；在微电网系统容量优化阶段，提出了多元宇宙优化算法（MVO），对比基线包括 GOA、GWO、DA 和 SSA 等元启发式算法）。 | T67: 未融合物理机制/纯数据驱动（注：本文在预测风速、太阳辐射和环境温度时，采用的是基于模糊C均值的自适应神经模糊推理系统（ANFIS-FCM）。该模型仅依靠对往年历史气象数据的模糊聚类去噪与神经网络黑盒映射进行迭代训练，通篇未在气象预测底层网络中显式融合任何流体力学定律或定制物理约束损失函数。文中的风切变指数与风机功率计算公式均属于后续微电网规划阶段的系统外部物理建模，而非机器学习算法内部的物理机制融合） 。 | U67: 预测误差阈值控制与优化目标函数 ACS（注：针对 ANFIS 气象预测训练，文中说明通过训练使“定义的误差小于预期的阈值（defined error becomes less than our intended threshold）”，并在事后评估时采用均方误差（MSE）和均方根误差（RMSE）进行对比；针对上层的微电网优化，其核心目标函数被定义为最小化系统年化成本（ACS），并通过惩罚或过滤机制满足最大供电中断概率（LPSPmax）的条件约束，未提及在预测网络中添加流体力学物理约束项）。 | V67: 在风速预测中，RMSE 降低至 1.63155，MSE 降低至 2.66197（注：原文在表1（Table 1）中给出了明确的绝对对比数值，由于未提供具体提升百分比，此处原样摘录：在风速预测任务中，提出的 ANFIS-FCM 模型的 RMSE 为 1.63155，优于表现最好的基线模型 ANN（RMSE 为 1.67988）以及次优的 RBF（RMSE 为 2.03266）。此外，在上层微电网容量优化任务中，提出的 MVO 算法求解的最佳平均年化成本（ACS）为 $54447.2，同样击败了其他所有基线元启发式算法） 。 | W67: 解决了偏远无电网地区因气象监测数据缺乏或存在大量异常值，从而导致混合微电网容量规划失真与建设成本高昂的痛点（注：作者在摘要与引言中特别强调，由于地理和经济原因，偏远地区难以获取精确的气象数据进行能源潜力评估。本研究结合智能气象预测与容量优化框架，在保证不同断电概率限制（LPSP）下，最大化提升了风能、太阳能等可再生能源的渗透率（REP），极大地助力了偏远农村低成本、高可靠性的 100% 离网供电改造） 。 | X67: 模糊系统、优化算法增强
A68: 68 | B68: 10.1016/j.energy.2014.08.064 | C68: 否 | D68: A hybrid forecasting model based on outlier detection and fuzzy time series e A case study on Hainan wind farm of China | E68: 2014年，发表于 Energy | F68: 未开源代码 | G68: 点尺度（注：文献直接选取了南海区域4个具体经纬度坐标点的气象站数据进行验证，分别为 Site 1: N17.5E110, Site 2: N17.5E107.5, Site 3: N20E110, Site 4: N20E107.5，未涉及空间网格数据 ） | H68: 日分辨率（注：原始传感器扫描频率为每天24次，数据存储的平均时间周期为2分钟。最终提取并使用的是日尺度的风速序列，模型落脚于进行提前一天的日均风速预测（one-day-ahead wind speed forecasting on a daily scale）。整体数据时间跨度为2008年1月1日至2012年12月31日 ） | I68: 75m（注：文献明确指出风速传感器的测量高度为75m（measurement height is 75 m） ） | J68: 未提及具体海拔高度（注：文中提及了宏观地理背景，即研究区域中国海南岛位于南海，北部被浅而窄的琼州海峡与广东雷州半岛隔开，但未提供任何站点的具体海拔数值或地形起伏特征 ） | K68: 仅风速（注：原文明确说明使用了中国海南省四个站点的“日平均风速（daily wind speed）”数据作为模型输入，全文未提及风向、温度、气压等其他气象变量的引入） 。 | L68: 有（注：明确使用了 WS600 型风速传感器（The type of wind speed sensor is WS600），以收集4个测风观测站的真实风速历史序列用于模型的构建、异常值检测与预测测试 ） | M68: 鲁棒回归异常值检测、三次样条插值与模糊化处理（注：模型在预处理阶段首先利用初始 ARMA1 模型提取残差，结合迭代重加权最小二乘法(WLS)的鲁棒回归算法检测异常点（判定标准为学生化残差 ti ​ >1.96），接着通过三次样条插值（cubic spline interpolation）平滑替换异常点获得修正后的风速序列。在预测阶段，再将修正后的风速序列及新 ARMA2 模型生成的残差分别进行模糊化（Fuzzify）以构建双变量模糊时间序列） 。 | N68: 未提及（注：文中仅提及数据采集自中国海南省，测风仪传感器型号为 WS600，但无论是正文、附录还是致谢部分，均未提供用于下载该真实历史数据集的开源链接或官方数据库入口） | O68: 未提及（注：文中给出了四个测风站的具体经纬度坐标（如 N17.5 E110 等）并用地图展示了海南岛的位置，但并未显式将高程DEM、地表粗糙度等空间静态地形物理特征作为数学模型的输入变量） | P68: 未提及（注：全文均未提及引入湍流动能(TKE)、局部垂直风切变或局部地形引起的尾流扰动等微尺度物理特征） | Q68: 单站点历史风速及其模型残差的滞后项（Lag variables）（注：模型为四个站点分别独立建模，未引入相邻或上游站点的空间传播连带效应；在时间序列特征上，模型将修正后的历史风速模糊序列滞后项 F(t−nk​ ) 以及 ARMA2 产生的残差模糊序列滞后项 G(t−ml) 联合作为反向传播(BP)神经网络的输入变量，具体的滞后阶数完全由 ARMA 模型的自回归与移动平均阶数 (p,q) 决定） | R68: 单点单步预测（注：最终落脚于输出每个气象观测站提前1天（one-day-ahead）的日尺度风速标量值。在输出前，采用“质心法（centroid method）”将网络输出的模糊集合去模糊化（Defuzzify）映射回具体数值） | S68: 提出结合异常值检测与双变量模糊时间序列的混合模型（注：提出的混合模型架构包含预处理部分的 ARMA1+WLS检测+三次样条插值，以及预测部分的 ARMA2+双变量模糊时间序列+BP神经网络建立模糊映射关系；实验中所采用的对比基线模型（Baseline）包括：传统的 ARMA 模型、ARIMA 模型以及单一的 BP 神经网络模型） | T68: 纯数据驱动，未涉及物理机制融合（注：全文采用完全的数据驱动架构，核心在于特征预处理与统计映射。模型仅依靠鲁棒回归（WLS）进行异常值检测、三次样条插值（Cubic spline interpolation）进行数据修补，随后结合 ARMA 模型和双变量模糊时间序列（利用 BP 神经网络求解模糊关系）进行未来风速推演。全文未引入任何气象动力学方程、未定制物理约束损失函数，属于纯粹的“黑盒”映射预测。） | U68: 加权残差平方和（预处理）与真实/输出差值（网络训练）（注：在 WLS 预处理检测异常值阶段，其目标函数明确为最小化加权残差平方和，但在 BP 神经网络的学习算法阶段，文中仅宽泛提及根据“真实值与网络输出之间的差异（difference between the real value and output）”来迭代更新权重；模型整体评价指标为 MAPE、MAE 和 RMSE，未提及在训练时加入带有物理机理的约束项） | V68: 平均 MAPE 提升超过 2.285%，但 RMSE/MAE 多数不及基线（注：原文明确给出了具体的百分比数值，指出该混合方法在平均预测精度（MAPE）上较基线模型提升了 2.285% 以上，四个站点的 MAPE 分别提升了 5.44%、0.76%、1.22% 和 1.72%（如站点1中，混合模型 MAPE 为 16.64%，而对比的基线模型最佳为 22.08%）。但必须如实指出，文献明确显示该模型在 RMSE 和 MAE 绝对误差指标上往往劣于传统模型（如站点2中，混合模型 RMSE 为 1.745，而基准 BP 神经网络的 RMSE 更优，为 1.684），其性能优势仅明确体现在 MAPE 这单一评价指标中。） | W68: 攻克了原始数据中异常值（Outliers）严重干扰预测精度的痛点，支撑风电场并网与发电储备规划（注：作者在引言与结论中强调，现有的长期风速预测方法往往直接将含有异常值的原始数据输入模型，导致参数存在偏差。本文通过显式的异常值剔除与插补，有效提高了日前（one-day-ahead）日级风速预测的可靠性，这一成果被明确指出对海南省正在筹建的海上风电场的发电引导、储能容量预留以及并网调度具有关键的业务指导价值。） | X68: 自回归 / 滑动平均类、基础基准与回归类、模糊系统、前馈神经网络
